Workbook

Sheet Resumen
A1: Backlog de contenidos – Blog Continental Media
A2: Versión 2 (calendario asignado). Fecha: 19/10/2026. Lote inicial de 8 artículos el 19/10/2026; el resto martes y jueves. Siguiente fase: validar keywords, volumen y dificultad.
E3: Calendario de publicación | F3: Valor
A4: Indicador | B4: Valor | C4: Nota | E4: Primera publicación (lote inicial) | F4: =MIN(Backlog!X2:X101) -> 46314
A5: Total de temas | B5: =COUNTA(Backlog!A2:A101) -> 100 | C5: Meta: al menos 100 | E5: Artículos en el lote inicial | F5: =COUNTIF(Backlog!X2:X101,F4) -> 8
A6: Artículos editoriales | B6: =COUNTIF(Backlog!B2:B101,"Editorial") -> 50 | C6: Meta: 50 | E6: Primera publicación del calendario regular | F6: =MIN(Backlog!X2:X101)+1 -> 46315
A7: Guías prácticas (con PDF) | B7: =COUNTIF(Backlog!B2:B101,"Guía práctica") -> 50 | C7: Meta: 50 | E7: Última publicación | F7: =MAX(Backlog!X2:X101) -> 46632
A8: Guías con entregable PDF definido | B8: =COUNTIFS(Backlog!B2:B101,"Guía práctica",Backlog!O2:O101,"?*",Backlog!O2:O101,"<>—") -> 50 | C8: Debe ser igual al número de guías | E8: Semanas de publicación | F8: =MAX(Backlog!Z2:Z101) -> 46
A9: Temas que re-redactan contenido existente | B9: =COUNTIF(Backlog!K2:K101,"Re-redacción 2026") -> 72 | C9: Tienen un artículo base en el blog actual | E9: Artículos fuera de martes/jueves (lote inicial excluido) | F9: =COUNTIFS(Backlog!AA2:AA101,"Calendario semanal",Backlog!Y2:Y101,"<>martes",Backlog!Y2:Y101,"<>jueves") -> 0
A10: Temas nuevos | B10: =COUNTIF(Backlog!K2:K101,"Nuevo") -> 28
A11: Prioridad alta | B11: =COUNTIF(Backlog!R2:R101,"Alta") -> 32
A12: Prioridad media | B12: =COUNTIF(Backlog!R2:R101,"Media") -> 52
A13: Prioridad baja | B13: =COUNTIF(Backlog!R2:R101,"Baja") -> 16
A14: Posts actuales analizados | B14: =COUNTA('Posts actuales'!A2:A1000) -> 188 | C14: Hoja "Posts actuales" (incluye el índice /blog/)
A16: Destino de los posts actuales
A17: Decisión | B17: Posts | C17: Qué significa
A18: Re-redactar v2026 | B18: =COUNTIF('Posts actuales'!D2:D1000,A18) -> 69 | C18: Reescribir con enfoque 2026 en el nuevo blog
A19: Actualizar v2026 | B19: =COUNTIF('Posts actuales'!D2:D1000,A19) -> 3 | C19: Posts de 2025 que solo necesitan actualización
A20: Consolidar | B20: =COUNTIF('Posts actuales'!D2:D1000,A20) -> 83 | C20: Se fusionan en otro artículo; la URL se redirige con 301
A21: Mantener (vigente) | B21: =COUNTIF('Posts actuales'!D2:D1000,A21) -> 3 | C21: Posts de 2026; se conservan y se enlazan con el tema relacionado
A22: Descartar | B22: =COUNTIF('Posts actuales'!D2:D1000,A22) -> 29 | C22: Sin valor SEO actual; 410 o 301 a categoría
A23: Reemplazar | B23: =COUNTIF('Posts actuales'!D2:D1000,A23) -> 1 | C23: Índice del blog
A24: Total | B24: =SUM(B18:B23) -> 188
A26: Calendario de publicación (lote inicial + martes y jueves)
A27: Mes | B27: Editoriales | C27: Guías prácticas
A28: Oct 2026 | B28: =COUNTIFS(Backlog!$T$2:$T$101,A28,Backlog!$B$2:$B$101,"Editorial") -> 6 | C28: =COUNTIFS(Backlog!$T$2:$T$101,A28,Backlog!$B$2:$B$101,"Guía práctica") -> 6
A29: Nov 2026 | B29: =COUNTIFS(Backlog!$T$2:$T$101,A29,Backlog!$B$2:$B$101,"Editorial") -> 4 | C29: =COUNTIFS(Backlog!$T$2:$T$101,A29,Backlog!$B$2:$B$101,"Guía práctica") -> 4
A30: Dic 2026 | B30: =COUNTIFS(Backlog!$T$2:$T$101,A30,Backlog!$B$2:$B$101,"Editorial") -> 5 | C30: =COUNTIFS(Backlog!$T$2:$T$101,A30,Backlog!$B$2:$B$101,"Guía práctica") -> 5
A31: Ene 2027 | B31: =COUNTIFS(Backlog!$T$2:$T$101,A31,Backlog!$B$2:$B$101,"Editorial") -> 4 | C31: =COUNTIFS(Backlog!$T$2:$T$101,A31,Backlog!$B$2:$B$101,"Guía práctica") -> 4
A32: Feb 2027 | B32: =COUNTIFS(Backlog!$T$2:$T$101,A32,Backlog!$B$2:$B$101,"Editorial") -> 4 | C32: =COUNTIFS(Backlog!$T$2:$T$101,A32,Backlog!$B$2:$B$101,"Guía práctica") -> 4
A33: Mar 2027 | B33: =COUNTIFS(Backlog!$T$2:$T$101,A33,Backlog!$B$2:$B$101,"Editorial") -> 5 | C33: =COUNTIFS(Backlog!$T$2:$T$101,A33,Backlog!$B$2:$B$101,"Guía práctica") -> 4
A34: Abr 2027 | B34: =COUNTIFS(Backlog!$T$2:$T$101,A34,Backlog!$B$2:$B$101,"Editorial") -> 4 | C34: =COUNTIFS(Backlog!$T$2:$T$101,A34,Backlog!$B$2:$B$101,"Guía práctica") -> 5
A35: May 2027 | B35: =COUNTIFS(Backlog!$T$2:$T$101,A35,Backlog!$B$2:$B$101,"Editorial") -> 4 | C35: =COUNTIFS(Backlog!$T$2:$T$101,A35,Backlog!$B$2:$B$101,"Guía práctica") -> 4
A36: Jun 2027 | B36: =COUNTIFS(Backlog!$T$2:$T$101,A36,Backlog!$B$2:$B$101,"Editorial") -> 5 | C36: =COUNTIFS(Backlog!$T$2:$T$101,A36,Backlog!$B$2:$B$101,"Guía práctica") -> 4
A37: Jul 2027 | B37: =COUNTIFS(Backlog!$T$2:$T$101,A37,Backlog!$B$2:$B$101,"Editorial") -> 4 | C37: =COUNTIFS(Backlog!$T$2:$T$101,A37,Backlog!$B$2:$B$101,"Guía práctica") -> 5
A38: Ago 2027 | B38: =COUNTIFS(Backlog!$T$2:$T$101,A38,Backlog!$B$2:$B$101,"Editorial") -> 5 | C38: =COUNTIFS(Backlog!$T$2:$T$101,A38,Backlog!$B$2:$B$101,"Guía práctica") -> 4
A39: Sep 2027 | B39: =COUNTIFS(Backlog!$T$2:$T$101,A39,Backlog!$B$2:$B$101,"Editorial") -> 0 | C39: =COUNTIFS(Backlog!$T$2:$T$101,A39,Backlog!$B$2:$B$101,"Guía práctica") -> 1
A40: Total | B40: =SUM(B28:B39) -> 50 | C40: =SUM(C28:C39) -> 50
A41: Supuestos y notas
A42: • La sección de servicios del sitio temporal (labs-publifix.github.io/continental-media) aún no tiene contenido; los 9 pilares son provisionales y deben confirmarse con la lista oficial de servicios.
A43: • Las keywords son semillas por validar: aún no tienen volumen ni dificultad (columnas amarillas). Es el objetivo de la siguiente fase.
A44: • Los títulos de los posts actuales se infirieron de sus URL (slugs); no se leyó el contenido de cada uno.
A45: • Cada tema que re-redacta contenido existente indica el post base y los posts que se consolidan; esas URLs deben redirigirse (301) al artículo nuevo. Alimenta el proyecto de redirecciones.
A46: • Cruces: cada tema enlaza con 2–4 temas relacionados (editorial ↔ guía y por clúster) para el enlazado interno. Ver hoja Cruces.
A47: • Fecha de publicación: el orden sugerido (1–100) se conserva. Los 8 primeros salen el 19/10/2026 (lote inicial: 4 editoriales y 4 guías, todos de prioridad Alta); del 9 al 100 se programan martes y jueves desde el 20/10/2026. Las fechas son editables (columna X de Backlog); Día, Semana, Lote y Mes se recalculan solos.
A48: • Fechas que caen en días de baja audiencia y se mantuvieron por instrucción: 02/11/2026 (Día de Muertos), 24/12/2026, 31/12/2026 y 25/03/2027 (Jueves Santo). Conviene confirmar si se publican o se recorren.
A49: • Posts actuales: la columna «Fecha de activación del 301» indica desde cuándo debe activarse cada redirección (el día que se publica el artículo nuevo). Aplica a Consolidar, Re-redactar y Actualizar; los posts a Mantener conservan su URL.

Sheet Backlog
A1: ID | B1: Tipo | C1: Título tentativo | D1: Pilar | E1: Keyword semilla (por validar) | F1: Intención de búsqueda | G1: Etapa del embudo | H1: Objetivo SEO | I1: Audiencia / sector | J1: Mercado | K1: Origen | L1: Artículo base a re-redactar (URL actual) | M1: Otros posts a consolidar (301) | N1: Qué actualizar / ángulo 2026 | O1: Entregable PDF (solo guías) | P1: Servicio a impulsar | Q1: Cruces (IDs) | R1: Prioridad | S1: Orden sugerido | T1: Mes de publicación | U1: Volumen de búsqueda | V1: Dificultad SEO | W1: Estado | X1: Fecha de publicación | Y1: Día | Z1: Semana | AA1: Lote
A2: E-01 | B2: Editorial | C2: IA en el marketing 2026: lo que cambió y lo que sigue siendo humano | D2: IA aplicada al marketing | E2: inteligencia artificial en el marketing | F2: Informacional | G2: TOFU | H2: Captar tráfico informacional en «inteligencia artificial en el marketing» y construir autoridad temática en ia aplicada al marketing. | I2: General | J2: México + EE.UU. | K2: Re-redacción 2026 | L2: https://www.continentalmedia.com.mx/2023/11/el-impacto-de-la-inteligencia-artificial-en-el-marketing/ | N2: Actualizar con casos 2026; postura "la IA multiplica a tu equipo" | O2: — | P2: IA aplicada a marketing y comunicación | Q2: E-02; E-07; E-09; G-18; G-19; G-22 | R2: Alta | S2: 3 | T2: =CHOOSE(MONTH(X2),"Ene","Feb","Mar","Abr","May","Jun","Jul","Ago","Sep","Oct","Nov","Dic")&" "&YEAR(X2) -> Oct 2026 | W2: Idea | X2: 46314 | Y2: =CHOOSE(WEEKDAY(X2,2),"lunes","martes","miércoles","jueves","viernes","sábado","domingo") -> lunes | Z2: =INT((X2-MIN($X$2:$X$101))/7)+1 -> 1 | AA2: =IF(X2=MIN($X$2:$X$101),"Lanzamiento","Calendario semanal") -> Lanzamiento
A3: E-02 | B3: Editorial | C3: La IA no reemplaza a tu equipo, lo multiplica: cómo trabaja una agencia en 2026 | D3: IA aplicada al marketing | E3: agencia de marketing con inteligencia artificial | F3: Informacional | G3: TOFU | H3: Captar tráfico informacional en «agencia de marketing con inteligencia artificial» y construir autoridad temática en ia aplicada al marketing. | I3: General | J3: México + EE.UU. | K3: Nuevo | N3: Artículo bandera alineado al mensaje del hero del sitio nuevo | O3: — | P3: IA aplicada a marketing y comunicación | Q3: E-01; E-04; G-21; G-23 | R3: Media | S3: 21 | T3: =CHOOSE(MONTH(X3),"Ene","Feb","Mar","Abr","May","Jun","Jul","Ago","Sep","Oct","Nov","Dic")&" "&YEAR(X3) -> Dic 2026 | W3: Idea | X3: 46357 | Y3: =CHOOSE(WEEKDAY(X3,2),"lunes","martes","miércoles","jueves","viernes","sábado","domingo") -> martes | Z3: =INT((X3-MIN($X$2:$X$101))/7)+1 -> 7 | AA3: =IF(X3=MIN($X$2:$X$101),"Lanzamiento","Calendario semanal") -> Calendario semanal
A4: E-03 | B4: Editorial | C4: SEO en la era de la búsqueda con IA: AI Overviews, GEO y qué hacer con tu marca | D4: IA aplicada al marketing | E4: SEO e inteligencia artificial | F4: Informacional | G4: TOFU | H4: Captar tráfico informacional en «SEO e inteligencia artificial» y construir autoridad temática en ia aplicada al marketing. | I4: General | J4: México + EE.UU. | K4: Nuevo | N4: Explicar GEO/AEO y cómo cambian clics y visibilidad | O4: — | P4: IA aplicada a marketing y comunicación | Q4: E-05; E-11; G-24; G-35; G-36 | R4: Alta | S4: 5 | T4: =CHOOSE(MONTH(X4),"Ene","Feb","Mar","Abr","May","Jun","Jul","Ago","Sep","Oct","Nov","Dic")&" "&YEAR(X4) -> Oct 2026 | W4: Idea | X4: 46314 | Y4: =CHOOSE(WEEKDAY(X4,2),"lunes","martes","miércoles","jueves","viernes","sábado","domingo") -> lunes | Z4: =INT((X4-MIN($X$2:$X$101))/7)+1 -> 1 | AA4: =IF(X4=MIN($X$2:$X$101),"Lanzamiento","Calendario semanal") -> Lanzamiento
A5: E-04 | B5: Editorial | C5: Agentes de IA en WhatsApp: promesas, límites y casos reales para empresas | D5: IA aplicada al marketing | E5: chatbot de WhatsApp con IA | F5: Informacional | G5: MOFU | H5: Capturar búsquedas de evaluación en «chatbot de WhatsApp con IA» y canalizarlas hacia ia aplicada a marketing y comunicación. | I5: General | J5: México + EE.UU. | K5: Re-redacción 2026 | L5: https://www.continentalmedia.com.mx/2022/06/chatbots-de-whatsapp-que-son-y-como-utilizarlos/ | N5: Pasar de chatbots de reglas a agentes con IA; riesgos y buenas prácticas | O5: — | P5: IA aplicada a marketing y comunicación | Q5: E-02; G-20; G-21 | R5: Alta | S5: 7 | T5: =CHOOSE(MONTH(X5),"Ene","Feb","Mar","Abr","May","Jun","Jul","Ago","Sep","Oct","Nov","Dic")&" "&YEAR(X5) -> Oct 2026 | W5: Idea | X5: 46314 | Y5: =CHOOSE(WEEKDAY(X5,2),"lunes","martes","miércoles","jueves","viernes","sábado","domingo") -> lunes | Z5: =INT((X5-MIN($X$2:$X$101))/7)+1 -> 1 | AA5: =IF(X5=MIN($X$2:$X$101),"Lanzamiento","Calendario semanal") -> Lanzamiento
A6: E-05 | B6: Editorial | C6: Contenido con IA sin sonar genérico: cómo conservar la voz de tu marca | D6: IA aplicada al marketing | E6: contenido generado con IA | F6: Informacional | G6: TOFU | H6: Captar tráfico informacional en «contenido generado con IA» y construir autoridad temática en ia aplicada al marketing. | I6: General | J6: México + EE.UU. | K6: Nuevo | N6: Criterios editoriales, revisión humana y señales de calidad | O6: — | P6: IA aplicada a marketing y comunicación | Q6: E-03; E-06; E-33; E-43; G-19; G-30 | R6: Alta | S6: 9 | T6: =CHOOSE(MONTH(X6),"Ene","Feb","Mar","Abr","May","Jun","Jul","Ago","Sep","Oct","Nov","Dic")&" "&YEAR(X6) -> Oct 2026 | W6: Idea | X6: 46315 | Y6: =CHOOSE(WEEKDAY(X6,2),"lunes","martes","miércoles","jueves","viernes","sábado","domingo") -> martes | Z6: =INT((X6-MIN($X$2:$X$101))/7)+1 -> 1 | AA6: =IF(X6=MIN($X$2:$X$101),"Lanzamiento","Calendario semanal") -> Calendario semanal
A7: E-06 | B7: Editorial | C7: Ética y transparencia con IA en comunicación: cuándo avisar que usaste IA | D7: IA aplicada al marketing | E7: ética de la IA en marketing | F7: Informacional | G7: TOFU | H7: Captar tráfico informacional en «ética de la IA en marketing» y construir autoridad temática en ia aplicada al marketing. | I7: General | J7: México + EE.UU. | K7: Nuevo | N7: Tendencias de regulación y confianza del consumidor | O7: — | P7: IA aplicada a marketing y comunicación | Q7: E-05; E-34; G-25 | R7: Media | S7: 23 | T7: =CHOOSE(MONTH(X7),"Ene","Feb","Mar","Abr","May","Jun","Jul","Ago","Sep","Oct","Nov","Dic")&" "&YEAR(X7) -> Dic 2026 | W7: Idea | X7: 46364 | Y7: =CHOOSE(WEEKDAY(X7,2),"lunes","martes","miércoles","jueves","viernes","sábado","domingo") -> martes | Z7: =INT((X7-MIN($X$2:$X$101))/7)+1 -> 8 | AA7: =IF(X7=MIN($X$2:$X$101),"Lanzamiento","Calendario semanal") -> Calendario semanal
A8: E-07 | B8: Editorial | C8: De ChatGPT a los asistentes de IA: cómo evolucionó el marketing asistido | D8: IA aplicada al marketing | E8: ChatGPT para marketing | F8: Informacional | G8: TOFU | H8: Captar tráfico informacional en «ChatGPT para marketing» y construir autoridad temática en ia aplicada al marketing. | I8: General | J8: México + EE.UU. | K8: Re-redacción 2026 | L8: https://www.continentalmedia.com.mx/2023/02/chatgpt-que-es-y-como-puede-ayudarte-a-crear-campanas-de-marketing/ | N8: Línea de tiempo 2023→2026 y qué sobrevivió a la moda | O8: — | P8: IA aplicada a marketing y comunicación | Q8: E-01; G-18; G-22 | R8: Media | S8: 25 | T8: =CHOOSE(MONTH(X8),"Ene","Feb","Mar","Abr","May","Jun","Jul","Ago","Sep","Oct","Nov","Dic")&" "&YEAR(X8) -> Dic 2026 | W8: Idea | X8: 46371 | Y8: =CHOOSE(WEEKDAY(X8,2),"lunes","martes","miércoles","jueves","viernes","sábado","domingo") -> martes | Z8: =INT((X8-MIN($X$2:$X$101))/7)+1 -> 9 | AA8: =IF(X8=MIN($X$2:$X$101),"Lanzamiento","Calendario semanal") -> Calendario semanal
A9: E-08 | B9: Editorial | C9: Metaverso, realidad aumentada y gaming: qué quedó de la promesa para las marcas | D9: IA aplicada al marketing | E9: metaverso para marcas | F9: Informacional | G9: TOFU | H9: Captar tráfico informacional en «metaverso para marcas» y construir autoridad temática en ia aplicada al marketing. | I9: General | J9: México + EE.UU. | K9: Re-redacción 2026 | L9: https://www.continentalmedia.com.mx/2022/05/que-es-el-metaverso-y-cuales-seran-sus-beneficios/ | M9: https://www.continentalmedia.com.mx/2013/11/realidad-aumentada-o-ciencia-ficcion/ https://www.continentalmedia.com.mx/2013/08/videojuegos-un-medio-mas-para-la-publicidad/ | N9: Balance honesto; rescatar AR y publicidad en videojuegos | O9: — | P9: IA aplicada a marketing y comunicación | Q9: E-11; E-39; E-43 | R9: Baja | S9: 79 | T9: =CHOOSE(MONTH(X9),"Ene","Feb","Mar","Abr","May","Jun","Jul","Ago","Sep","Oct","Nov","Dic")&" "&YEAR(X9) -> Jun 2027 | W9: Idea | X9: 46560 | Y9: =CHOOSE(WEEKDAY(X9,2),"lunes","martes","miércoles","jueves","viernes","sábado","domingo") -> martes | Z9: =INT((X9-MIN($X$2:$X$101))/7)+1 -> 36 | AA9: =IF(X9=MIN($X$2:$X$101),"Lanzamiento","Calendario semanal") -> Calendario semanal
A10: E-09 | B10: Editorial | C10: Tendencias de marketing 2027: lo que las marcas deben preparar desde hoy | D10: Estrategia de marketing y contenidos | E10: tendencias de marketing 2027 | F10: Informacional | G10: TOFU | H10: Captar tráfico informacional en «tendencias de marketing 2027» y construir autoridad temática en estrategia de marketing y contenidos. | I10: General | J10: México + EE.UU. | K10: Re-redacción 2026 | L10: https://www.continentalmedia.com.mx/2023/12/5-tendencias-de-marketing-para-2024/ | M10: https://www.continentalmedia.com.mx/2023/01/8-tendencias-de-marketing-para-este-2023/ https://www.continentalmedia.com.mx/2013/12/cuales-seran-las-tendencias-de-marketing-2014/ https://www.continentalmedia.com.mx/2013/01/la-forma-de-hacer-marketing-en-el-2013/ | N10: Publicar en nov-2026; mantener URL evergreen y actualizar cada año | O10: — | P10: Estrategia de marketing 360 | Q10: E-01; G-01; G-07 | R10: Alta | S10: 1 | T10: =CHOOSE(MONTH(X10),"Ene","Feb","Mar","Abr","May","Jun","Jul","Ago","Sep","Oct","Nov","Dic")&" "&YEAR(X10) -> Oct 2026 | W10: Idea | X10: 46314 | Y10: =CHOOSE(WEEKDAY(X10,2),"lunes","martes","miércoles","jueves","viernes","sábado","domingo") -> lunes | Z10: =INT((X10-MIN($X$2:$X$101))/7)+1 -> 1 | AA10: =IF(X10=MIN($X$2:$X$101),"Lanzamiento","Calendario semanal") -> Lanzamiento
A11: E-10 | B11: Editorial | C11: Alcance orgánico en redes sociales: ¿sigue valiendo la pena para tu empresa? | D11: Redes sociales y comunidad | E11: alcance orgánico en redes sociales | F11: Informacional | G11: TOFU | H11: Captar tráfico informacional en «alcance orgánico en redes sociales» y construir autoridad temática en redes sociales y comunidad. | I11: General | J11: México + EE.UU. | K11: Re-redacción 2026 | L11: https://www.continentalmedia.com.mx/2014/06/empresa-lista-redes-sociales/ | M11: https://www.continentalmedia.com.mx/2012/12/6-razones-pymes-usar-redes-sociales/ https://www.continentalmedia.com.mx/2012/12/redes-sociales-en-pymes/ https://www.continentalmedia.com.mx/2013/04/la-evolucion-de-las-redes-sociales/ | N11: Datos 2026 sobre alcance orgánico vs. pauta; cuándo conviene cada uno | O11: — | P11: Gestión de redes sociales y community management | Q11: E-11; G-09; G-17 | R11: Media | S11: 27 | T11: =CHOOSE(MONTH(X11),"Ene","Feb","Mar","Abr","May","Jun","Jul","Ago","Sep","Oct","Nov","Dic")&" "&YEAR(X11) -> Dic 2026 | W11: Idea | X11: 46378 | Y11: =CHOOSE(WEEKDAY(X11,2),"lunes","martes","miércoles","jueves","viernes","sábado","domingo") -> martes | Z11: =INT((X11-MIN($X$2:$X$101))/7)+1 -> 10 | AA11: =IF(X11=MIN($X$2:$X$101),"Lanzamiento","Calendario semanal") -> Calendario semanal
A12: E-11 | B12: Editorial | C12: Social search: por qué TikTok e Instagram ya son buscadores y cómo aparecer | D12: Redes sociales y comunidad | E12: TikTok como buscador | F12: Informacional | G12: TOFU | H12: Captar tráfico informacional en «TikTok como buscador» y construir autoridad temática en redes sociales y comunidad. | I12: General | J12: México + EE.UU. | K12: Re-redacción 2026 | L12: https://www.continentalmedia.com.mx/2022/10/tiktok-now-que-es-y-por-que-lo-comparan-con-be-real/ | M12: https://www.continentalmedia.com.mx/2013/10/google-la-red-social/ | N12: SEO social: palabras clave en captions, subtítulos y perfil | O12: — | P12: Gestión de redes sociales y community management | Q12: E-03; E-08; E-10; E-14; G-10; G-11 | R12: Media | S12: 29 | T12: =CHOOSE(MONTH(X12),"Ene","Feb","Mar","Abr","May","Jun","Jul","Ago","Sep","Oct","Nov","Dic")&" "&YEAR(X12) -> Dic 2026 | W12: Idea | X12: 46385 | Y12: =CHOOSE(WEEKDAY(X12,2),"lunes","martes","miércoles","jueves","viernes","sábado","domingo") -> martes | Z12: =INT((X12-MIN($X$2:$X$101))/7)+1 -> 11 | AA12: =IF(X12=MIN($X$2:$X$101),"Lanzamiento","Calendario semanal") -> Calendario semanal
A13: E-12 | B13: Editorial | C13: Humanizar tu marca: por qué la autenticidad le gana al contenido perfecto | D13: Redes sociales y comunidad | E13: humanizar la marca | F13: Informacional | G13: TOFU | H13: Captar tráfico informacional en «humanizar la marca» y construir autoridad temática en redes sociales y comunidad. | I13: General | J13: México + EE.UU. | K13: Re-redacción 2026 | L13: https://www.continentalmedia.com.mx/2021/11/la-importancia-de-humanizar-tu-marca-inbound-marketing/ | M13: https://www.continentalmedia.com.mx/2014/03/las-5-mejores-marcas-en-redes-sociales-en-mexico/ | N13: Ejemplos de marcas mexicanas; cómo producirlo sin improvisar | O13: — | P13: Gestión de redes sociales y community management | Q13: E-13; E-15; E-19; E-26; E-49; G-09; G-30 | R13: Alta | S13: 11 | T13: =CHOOSE(MONTH(X13),"Ene","Feb","Mar","Abr","May","Jun","Jul","Ago","Sep","Oct","Nov","Dic")&" "&YEAR(X13) -> Oct 2026 | W13: Idea | X13: 46322 | Y13: =CHOOSE(WEEKDAY(X13,2),"lunes","martes","miércoles","jueves","viernes","sábado","domingo") -> martes | Z13: =INT((X13-MIN($X$2:$X$101))/7)+1 -> 2 | AA13: =IF(X13=MIN($X$2:$X$101),"Lanzamiento","Calendario semanal") -> Calendario semanal
A14: E-13 | B14: Editorial | C14: Marketing de influencia en 2026: micro-influencers, creadores y contenido UGC | D14: Redes sociales y comunidad | E14: marketing de influencia | F14: Informacional | G14: TOFU | H14: Captar tráfico informacional en «marketing de influencia» y construir autoridad temática en redes sociales y comunidad. | I14: General | J14: México + EE.UU. | K14: Re-redacción 2026 | L14: https://www.continentalmedia.com.mx/2014/03/que-es-el-marketing-de-influencia/ | M14: https://www.continentalmedia.com.mx/2014/01/celebridades-y-marcas-se-llevan-bien/ https://www.continentalmedia.com.mx/2014/01/celebridades-marcas-y-escandalos/ | N14: Modelos de colaboración, métricas y riesgos de reputación | O14: — | P14: Gestión de redes sociales y community management | Q14: E-12; E-15; G-16 | R14: Media | S14: 31 | T14: =CHOOSE(MONTH(X14),"Ene","Feb","Mar","Abr","May","Jun","Jul","Ago","Sep","Oct","Nov","Dic")&" "&YEAR(X14) -> Ene 2027 | W14: Idea | X14: 46392 | Y14: =CHOOSE(WEEKDAY(X14,2),"lunes","martes","miércoles","jueves","viernes","sábado","domingo") -> martes | Z14: =INT((X14-MIN($X$2:$X$101))/7)+1 -> 12 | AA14: =IF(X14=MIN($X$2:$X$101),"Lanzamiento","Calendario semanal") -> Calendario semanal
A15: E-14 | B15: Editorial | C15: Más allá de X: dónde debe estar tu marca (X, Threads, Bluesky, LinkedIn) | D15: Redes sociales y comunidad | E15: redes sociales para empresas | F15: Informacional | G15: TOFU | H15: Captar tráfico informacional en «redes sociales para empresas» y construir autoridad temática en redes sociales y comunidad. | I15: General | J15: México + EE.UU. | K15: Re-redacción 2026 | L15: https://www.continentalmedia.com.mx/2022/12/en-que-ha-afectado-la-compra-de-elon-musk-a-la-publicidad-en-twitter/ | M15: https://www.continentalmedia.com.mx/2014/07/estrategias-marca-twitter/ | N15: Mapa de plataformas 2026 por objetivo y tipo de negocio | O15: — | P15: Gestión de redes sociales y community management | Q15: E-11; E-47; G-12; G-17 | R15: Baja | S15: 81 | T15: =CHOOSE(MONTH(X15),"Ene","Feb","Mar","Abr","May","Jun","Jul","Ago","Sep","Oct","Nov","Dic")&" "&YEAR(X15) -> Jun 2027 | W15: Idea | X15: 46567 | Y15: =CHOOSE(WEEKDAY(X15,2),"lunes","martes","miércoles","jueves","viernes","sábado","domingo") -> martes | Z15: =INT((X15-MIN($X$2:$X$101))/7)+1 -> 37 | AA15: =IF(X15=MIN($X$2:$X$101),"Lanzamiento","Calendario semanal") -> Calendario semanal
A16: E-15 | B16: Editorial | C16: Comunidad antes que seguidores: engagement real y contenido viral con propósito | D16: Redes sociales y comunidad | E16: engagement en redes sociales | F16: Informacional | G16: TOFU | H16: Captar tráfico informacional en «engagement en redes sociales» y construir autoridad temática en redes sociales y comunidad. | I16: General | J16: México + EE.UU. | K16: Re-redacción 2026 | L16: https://www.continentalmedia.com.mx/2015/01/conquista-clientes-engagement/ | M16: https://www.continentalmedia.com.mx/2012/12/las-4-r-s-de-las-redes-sociales/ https://www.continentalmedia.com.mx/2015/03/como-atraer-a-tu-publico-objetivo/ https://www.continentalmedia.com.mx/2012/12/marketing-viral/ https://www.continentalmedia.com.mx/2014/09/ice-bucket-challenge/ | N16: De "viralidad" a comunidad; métricas que sí importan | O16: — | P16: Gestión de redes sociales y community management | Q16: E-12; E-13; G-09; G-14 | R16: Media | S16: 33 | T16: =CHOOSE(MONTH(X16),"Ene","Feb","Mar","Abr","May","Jun","Jul","Ago","Sep","Oct","Nov","Dic")&" "&YEAR(X16) -> Ene 2027 | W16: Idea | X16: 46399 | Y16: =CHOOSE(WEEKDAY(X16,2),"lunes","martes","miércoles","jueves","viernes","sábado","domingo") -> martes | Z16: =INT((X16-MIN($X$2:$X$101))/7)+1 -> 13 | AA16: =IF(X16=MIN($X$2:$X$101),"Lanzamiento","Calendario semanal") -> Calendario semanal
A17: E-16 | B17: Editorial | C17: Marketing 360 en 2026: qué significa realmente y por qué sigue funcionando | D17: Estrategia de marketing y contenidos | E17: marketing 360 | F17: Informacional | G17: TOFU | H17: Captar tráfico informacional en «marketing 360» y construir autoridad temática en estrategia de marketing y contenidos. | I17: General | J17: México + EE.UU. | K17: Re-redacción 2026 | L17: https://www.continentalmedia.com.mx/2025/03/marketing-digital-360-como-crear-una-estrategia-integral-para-tu-marca/ | M17: https://www.continentalmedia.com.mx/2016/02/en-que-te-beneficia-el-marketing-de-360o/ https://www.continentalmedia.com.mx/2014/10/marketing-360-grados/ https://www.continentalmedia.com.mx/2016/11/la-imagen-del-marketing-en-que-te-beneficia-el-marketing-360/ | N17: Ampliar con IA, datos propios y medición omnicanal | O17: — | P17: Estrategia de marketing 360 | Q17: E-17; E-18; G-01; G-03 | R17: Alta | S17: 13 | T17: =CHOOSE(MONTH(X17),"Ene","Feb","Mar","Abr","May","Jun","Jul","Ago","Sep","Oct","Nov","Dic")&" "&YEAR(X17) -> Nov 2026 | W17: Idea | X17: 46329 | Y17: =CHOOSE(WEEKDAY(X17,2),"lunes","martes","miércoles","jueves","viernes","sábado","domingo") -> martes | Z17: =INT((X17-MIN($X$2:$X$101))/7)+1 -> 3 | AA17: =IF(X17=MIN($X$2:$X$101),"Lanzamiento","Calendario semanal") -> Calendario semanal
A18: E-17 | B18: Editorial | C18: Marketing digital vs. marketing tradicional: un debate que ya se resolvió | D18: Estrategia de marketing y contenidos | E18: marketing digital vs marketing tradicional | F18: Informacional | G18: TOFU | H18: Captar tráfico informacional en «marketing digital vs marketing tradicional» y construir autoridad temática en estrategia de marketing y contenidos. | I18: General | J18: México + EE.UU. | K18: Re-redacción 2026 | L18: https://www.continentalmedia.com.mx/2013/10/marketing-digital-vs-marketing-tradicional/ | N18: Postura: integración, no sustitución; cuándo usar cada medio | O18: — | P18: Estrategia de marketing 360 | Q18: E-16; E-21; G-05; G-38 | R18: Media | S18: 35 | T18: =CHOOSE(MONTH(X18),"Ene","Feb","Mar","Abr","May","Jun","Jul","Ago","Sep","Oct","Nov","Dic")&" "&YEAR(X18) -> Ene 2027 | W18: Idea | X18: 46406 | Y18: =CHOOSE(WEEKDAY(X18,2),"lunes","martes","miércoles","jueves","viernes","sábado","domingo") -> martes | Z18: =INT((X18-MIN($X$2:$X$101))/7)+1 -> 14 | AA18: =IF(X18=MIN($X$2:$X$101),"Lanzamiento","Calendario semanal") -> Calendario semanal
A19: E-18 | B19: Editorial | C19: Mitos del marketing que en 2026 siguen costándole dinero a las pymes | D19: Estrategia de marketing y contenidos | E19: mitos del marketing | F19: Informacional | G19: TOFU | H19: Captar tráfico informacional en «mitos del marketing» y construir autoridad temática en estrategia de marketing y contenidos. | I19: General | J19: México + EE.UU. | K19: Re-redacción 2026 | L19: https://www.continentalmedia.com.mx/2015/07/5-mitos-del-marketing-que-ya-nadie-debe-creer/ | N19: Lista actualizada: SEO muerto, viral, "más seguidores = más ventas" | O19: — | P19: Estrategia de marketing 360 | Q19: E-16; G-01; G-08 | R19: Media | S19: 37 | T19: =CHOOSE(MONTH(X19),"Ene","Feb","Mar","Abr","May","Jun","Jul","Ago","Sep","Oct","Nov","Dic")&" "&YEAR(X19) -> Ene 2027 | W19: Idea | X19: 46413 | Y19: =CHOOSE(WEEKDAY(X19,2),"lunes","martes","miércoles","jueves","viernes","sábado","domingo") -> martes | Z19: =INT((X19-MIN($X$2:$X$101))/7)+1 -> 15 | AA19: =IF(X19=MIN($X$2:$X$101),"Lanzamiento","Calendario semanal") -> Calendario semanal
A20: E-19 | B20: Editorial | C20: Storytelling de marca: por qué las historias siguen vendiendo en la era del contenido infinito | D20: Estrategia de marketing y contenidos | E20: storytelling de marca | F20: Informacional | G20: TOFU | H20: Captar tráfico informacional en «storytelling de marca» y construir autoridad temática en estrategia de marketing y contenidos. | I20: General | J20: México + EE.UU. | K20: Re-redacción 2026 | L20: https://www.continentalmedia.com.mx/2016/12/storytelling-una-tecnica-para-cautivar-a-tus-clientes/ | N20: Casos de marcas locales; estructura narrativa aplicable | O20: — | P20: Estrategia de marketing 360 | Q20: E-12; E-26; G-09; G-30 | R20: Media | S20: 39 | T20: =CHOOSE(MONTH(X20),"Ene","Feb","Mar","Abr","May","Jun","Jul","Ago","Sep","Oct","Nov","Dic")&" "&YEAR(X20) -> Feb 2027 | W20: Idea | X20: 46420 | Y20: =CHOOSE(WEEKDAY(X20,2),"lunes","martes","miércoles","jueves","viernes","sábado","domingo") -> martes | Z20: =INT((X20-MIN($X$2:$X$101))/7)+1 -> 16 | AA20: =IF(X20=MIN($X$2:$X$101),"Lanzamiento","Calendario semanal") -> Calendario semanal
A21: E-20 | B21: Editorial | C21: Neuromarketing y psicología del color: qué es ciencia y qué es mito | D21: Branding, diseño y creatividad | E21: neuromarketing | F21: Informacional | G21: TOFU | H21: Captar tráfico informacional en «neuromarketing» y construir autoridad temática en branding, diseño y creatividad. | I21: General | J21: México + EE.UU. | K21: Re-redacción 2026 | L21: https://www.continentalmedia.com.mx/2012/12/neuromarketing/ | M21: https://www.continentalmedia.com.mx/2014/04/los-6-colores-que-mas-atraen-en-publicidad/ https://www.continentalmedia.com.mx/2013/06/cual-es-tu-percepcion-del-color/ https://www.continentalmedia.com.mx/2012/08/marketing-olfativo/ https://www.continentalmedia.com.mx/2012/12/por-que-una-imagen-resulta-tan-poderosa/ | N21: Separar evidencia de mitos; color, imagen y olfato | O21: — | P21: Branding, identidad y diseño gráfico | Q21: E-23; E-29; G-40 | R21: Media | S21: 41 | T21: =CHOOSE(MONTH(X21),"Ene","Feb","Mar","Abr","May","Jun","Jul","Ago","Sep","Oct","Nov","Dic")&" "&YEAR(X21) -> Feb 2027 | W21: Idea | X21: 46427 | Y21: =CHOOSE(WEEKDAY(X21,2),"lunes","martes","miércoles","jueves","viernes","sábado","domingo") -> martes | Z21: =INT((X21-MIN($X$2:$X$101))/7)+1 -> 17 | AA21: =IF(X21=MIN($X$2:$X$101),"Lanzamiento","Calendario semanal") -> Calendario semanal
A22: E-21 | B22: Editorial | C22: Invertir en publicidad en tiempos de crisis: por qué las marcas que no recortan ganan | D22: Estrategia de marketing y contenidos | E22: publicidad en tiempos de crisis | F22: Informacional | G22: TOFU | H22: Captar tráfico informacional en «publicidad en tiempos de crisis» y construir autoridad temática en estrategia de marketing y contenidos. | I22: Pymes | J22: México + EE.UU. | K22: Re-redacción 2026 | L22: https://www.continentalmedia.com.mx/2017/01/por-que-invertir-en-publicidad-en-epoca-de-crisis/ | N22: Evidencia histórica y escenarios económicos actuales | O22: — | P22: Estrategia de marketing 360 | Q22: E-17; G-05; G-06 | R22: Media | S22: 43 | T22: =CHOOSE(MONTH(X22),"Ene","Feb","Mar","Abr","May","Jun","Jul","Ago","Sep","Oct","Nov","Dic")&" "&YEAR(X22) -> Feb 2027 | W22: Idea | X22: 46434 | Y22: =CHOOSE(WEEKDAY(X22,2),"lunes","martes","miércoles","jueves","viernes","sábado","domingo") -> martes | Z22: =INT((X22-MIN($X$2:$X$101))/7)+1 -> 18 | AA22: =IF(X22=MIN($X$2:$X$101),"Lanzamiento","Calendario semanal") -> Calendario semanal
A23: E-22 | B23: Editorial | C23: Marketing de contenidos: de producir más a producir mejor | D23: Estrategia de marketing y contenidos | E23: marketing de contenidos | F23: Informacional | G23: TOFU | H23: Captar tráfico informacional en «marketing de contenidos» y construir autoridad temática en estrategia de marketing y contenidos. | I23: General | J23: México + EE.UU. | K23: Re-redacción 2026 | L23: https://www.continentalmedia.com.mx/2017/02/los-beneficios-del-marketing-de-contenidos-para-tu-marca/ | M23: https://www.continentalmedia.com.mx/2019/01/como-hacer-mejor-marketing-de-contenidos/ https://www.continentalmedia.com.mx/2016/10/por-que-son-importantes-las-infografias-en-el-marketing-de-contenidos/ | N23: Del volumen a la calidad: infografías, formatos y reutilización | O23: — | P23: Estrategia de marketing 360 | Q23: G-09; G-36; G-41 | R23: Media | S23: 45 | T23: =CHOOSE(MONTH(X23),"Ene","Feb","Mar","Abr","May","Jun","Jul","Ago","Sep","Oct","Nov","Dic")&" "&YEAR(X23) -> Feb 2027 | W23: Idea | X23: 46441 | Y23: =CHOOSE(WEEKDAY(X23,2),"lunes","martes","miércoles","jueves","viernes","sábado","domingo") -> martes | Z23: =INT((X23-MIN($X$2:$X$101))/7)+1 -> 19 | AA23: =IF(X23=MIN($X$2:$X$101),"Lanzamiento","Calendario semanal") -> Calendario semanal
A24: E-23 | B24: Editorial | C24: Branding en 2026: identidades que funcionan en pantalla, en video y en la era de la IA | D24: Branding, diseño y creatividad | E24: branding tendencias | F24: Informacional | G24: TOFU | H24: Captar tráfico informacional en «branding tendencias» y construir autoridad temática en branding, diseño y creatividad. | I24: General | J24: México + EE.UU. | K24: Nuevo | N24: Sistemas de identidad flexibles; motion y accesibilidad | O24: — | P24: Branding, identidad y diseño gráfico | Q24: E-20; E-24; E-25; E-28; G-26; G-27; G-29; G-30 | R24: Media | S24: 47 | T24: =CHOOSE(MONTH(X24),"Ene","Feb","Mar","Abr","May","Jun","Jul","Ago","Sep","Oct","Nov","Dic")&" "&YEAR(X24) -> Mar 2027 | W24: Idea | X24: 46448 | Y24: =CHOOSE(WEEKDAY(X24,2),"lunes","martes","miércoles","jueves","viernes","sábado","domingo") -> martes | Z24: =INT((X24-MIN($X$2:$X$101))/7)+1 -> 20 | AA24: =IF(X24=MIN($X$2:$X$101),"Lanzamiento","Calendario semanal") -> Calendario semanal
A25: E-24 | B25: Editorial | C25: El logotipo hoy: logos adaptativos, animados y por qué importa tanto | D25: Branding, diseño y creatividad | E25: importancia de un logotipo | F25: Informacional | G25: TOFU | H25: Captar tráfico informacional en «importancia de un logotipo» y construir autoridad temática en branding, diseño y creatividad. | I25: General | J25: México + EE.UU. | K25: Re-redacción 2026 | L25: https://www.continentalmedia.com.mx/2014/07/la-importancia-de-un-logotipo/ | N25: Actualizar con tendencias de logos responsivos y motion | O25: — | P25: Branding, identidad y diseño gráfico | Q25: E-23; G-26; G-28 | R25: Media | S25: 49 | T25: =CHOOSE(MONTH(X25),"Ene","Feb","Mar","Abr","May","Jun","Jul","Ago","Sep","Oct","Nov","Dic")&" "&YEAR(X25) -> Mar 2027 | W25: Idea | X25: 46455 | Y25: =CHOOSE(WEEKDAY(X25,2),"lunes","martes","miércoles","jueves","viernes","sábado","domingo") -> martes | Z25: =INT((X25-MIN($X$2:$X$101))/7)+1 -> 21 | AA25: =IF(X25=MIN($X$2:$X$101),"Lanzamiento","Calendario semanal") -> Calendario semanal
A26: E-25 | B26: Editorial | C26: Branding personal y liderazgo visible: la marca del directivo en LinkedIn | D26: Branding, diseño y creatividad | E26: branding personal | F26: Informacional | G26: TOFU | H26: Captar tráfico informacional en «branding personal» y construir autoridad temática en branding, diseño y creatividad. | I26: Directivos y B2B | J26: México + EE.UU. | K26: Re-redacción 2026 | L26: https://www.continentalmedia.com.mx/2013/07/acerca-del-branding-personal/ | N26: Enfoque B2B: ejecutivos como canal de confianza | O26: — | P26: Branding, identidad y diseño gráfico | Q26: E-23; E-32; G-12 | R26: Media | S26: 51 | T26: =CHOOSE(MONTH(X26),"Ene","Feb","Mar","Abr","May","Jun","Jul","Ago","Sep","Oct","Nov","Dic")&" "&YEAR(X26) -> Mar 2027 | W26: Idea | X26: 46462 | Y26: =CHOOSE(WEEKDAY(X26,2),"lunes","martes","miércoles","jueves","viernes","sábado","domingo") -> martes | Z26: =INT((X26-MIN($X$2:$X$101))/7)+1 -> 22 | AA26: =IF(X26=MIN($X$2:$X$101),"Lanzamiento","Calendario semanal") -> Calendario semanal
A27: E-26 | B27: Editorial | C27: Lovemarks en 2026: cómo se construye una marca que la gente ama | D27: Branding, diseño y creatividad | E27: lovemarks | F27: Informacional | G27: TOFU | H27: Captar tráfico informacional en «lovemarks» y construir autoridad temática en branding, diseño y creatividad. | I27: General | J27: México + EE.UU. | K27: Re-redacción 2026 | L27: https://www.continentalmedia.com.mx/2012/12/lovemarks/ | N27: Emoción, comunidad y consistencia; ejemplos actuales | O27: — | P27: Branding, identidad y diseño gráfico | Q27: E-12; E-19; G-30 | R27: Baja | S27: 83 | T27: =CHOOSE(MONTH(X27),"Ene","Feb","Mar","Abr","May","Jun","Jul","Ago","Sep","Oct","Nov","Dic")&" "&YEAR(X27) -> Jul 2027 | W27: Idea | X27: 46574 | Y27: =CHOOSE(WEEKDAY(X27,2),"lunes","martes","miércoles","jueves","viernes","sábado","domingo") -> martes | Z27: =INT((X27-MIN($X$2:$X$101))/7)+1 -> 38 | AA27: =IF(X27=MIN($X$2:$X$101),"Lanzamiento","Calendario semanal") -> Calendario semanal
A28: E-27 | B28: Editorial | C28: Greenwashing y marketing con propósito: lo que el consumidor ya no tolera | D28: Branding, diseño y creatividad | E28: greenwashing | F28: Informacional | G28: TOFU | H28: Captar tráfico informacional en «greenwashing» y construir autoridad temática en branding, diseño y creatividad. | I28: General | J28: México + EE.UU. | K28: Re-redacción 2026 | L28: https://www.continentalmedia.com.mx/2013/11/greenwashing-el-engano-verde/ | M28: https://www.continentalmedia.com.mx/2013/07/marketing-ecologico-una-decision-responsable/ https://www.continentalmedia.com.mx/2013/10/marketing-social-filantropia-o-estrategia/ https://www.continentalmedia.com.mx/2023/03/el-poder-del-crowdfunding-para-financiar-proyectos-de-beneficencia/ | N28: Regulación y percepción actual; cómo comunicar sostenibilidad con evidencia | O28: — | P28: Branding, identidad y diseño gráfico | Q28: E-28; E-30; E-32; E-35 | R28: Media | S28: 53 | T28: =CHOOSE(MONTH(X28),"Ene","Feb","Mar","Abr","May","Jun","Jul","Ago","Sep","Oct","Nov","Dic")&" "&YEAR(X28) -> Mar 2027 | W28: Idea | X28: 46469 | Y28: =CHOOSE(WEEKDAY(X28,2),"lunes","martes","miércoles","jueves","viernes","sábado","domingo") -> martes | Z28: =INT((X28-MIN($X$2:$X$101))/7)+1 -> 23 | AA28: =IF(X28=MIN($X$2:$X$101),"Lanzamiento","Calendario semanal") -> Calendario semanal
A29: E-28 | B29: Editorial | C29: Co-branding y alianzas de marca: casos, riesgos y lecciones | D29: Branding, diseño y creatividad | E29: co-branding | F29: Informacional | G29: TOFU | H29: Captar tráfico informacional en «co-branding» y construir autoridad temática en branding, diseño y creatividad. | I29: General | J29: México + EE.UU. | K29: Re-redacción 2026 | L29: https://www.continentalmedia.com.mx/2017/03/co-branding-en-que-te-beneficia-asociar-tu-marca-a-otra/ | M29: https://www.continentalmedia.com.mx/2014/08/por-que-la-campana-comparte-una-coca-cola-con-ha-sido-tan-exitosa/ https://www.continentalmedia.com.mx/2013/09/las-marcas-en-el-cine-casualidad-o-causalidad/ | N29: Casos recientes; product placement y colaboraciones | O29: — | P29: Branding, identidad y diseño gráfico | Q29: E-23; E-27; E-46; G-48 | R29: Baja | S29: 85 | T29: =CHOOSE(MONTH(X29),"Ene","Feb","Mar","Abr","May","Jun","Jul","Ago","Sep","Oct","Nov","Dic")&" "&YEAR(X29) -> Jul 2027 | W29: Idea | X29: 46581 | Y29: =CHOOSE(WEEKDAY(X29,2),"lunes","martes","miércoles","jueves","viernes","sábado","domingo") -> martes | Z29: =INT((X29-MIN($X$2:$X$101))/7)+1 -> 39 | AA29: =IF(X29=MIN($X$2:$X$101),"Lanzamiento","Calendario semanal") -> Calendario semanal
A30: E-29 | B30: Editorial | C30: Un diseño bonito no lo es todo: diseño estratégico vs. diseño decorativo | D30: Branding, diseño y creatividad | E30: diseño estratégico | F30: Informacional | G30: TOFU | H30: Captar tráfico informacional en «diseño estratégico» y construir autoridad temática en branding, diseño y creatividad. | I30: General | J30: México + EE.UU. | K30: Re-redacción 2026 | L30: https://www.continentalmedia.com.mx/2013/03/un-diseno-bonito-no-lo-es-todo/ | M30: https://www.continentalmedia.com.mx/2013/05/leyes-gestalt/ https://www.continentalmedia.com.mx/2013/03/porque-invertir-en-imagen-corporativa/ https://www.continentalmedia.com.mx/2013/08/packaging/ | N30: Principios (Gestalt), empaque e imagen corporativa con enfoque de negocio | O30: — | P30: Branding, identidad y diseño gráfico | Q30: E-20; E-39; G-28; G-40 | R30: Media | S30: 55 | T30: =CHOOSE(MONTH(X30),"Ene","Feb","Mar","Abr","May","Jun","Jul","Ago","Sep","Oct","Nov","Dic")&" "&YEAR(X30) -> Mar 2027 | W30: Idea | X30: 46476 | Y30: =CHOOSE(WEEKDAY(X30,2),"lunes","martes","miércoles","jueves","viernes","sábado","domingo") -> martes | Z30: =INT((X30-MIN($X$2:$X$101))/7)+1 -> 24 | AA30: =IF(X30=MIN($X$2:$X$101),"Lanzamiento","Calendario semanal") -> Calendario semanal
A31: E-30 | B31: Editorial | C31: Relaciones públicas en 2026: de la nota de prensa a la reputación digital | D31: Relaciones públicas y comunicación | E31: relaciones públicas | F31: Informacional | G31: TOFU | H31: Captar tráfico informacional en «relaciones públicas» y construir autoridad temática en relaciones públicas y comunicación. | I31: General | J31: México + EE.UU. | K31: Re-redacción 2026 | L31: https://www.continentalmedia.com.mx/2012/12/relaciones-publicas/ | N31: Qué es RP hoy: medios, creadores, reputación online y IA | O31: — | P31: Relaciones públicas y comunicación corporativa | Q31: E-27; G-31; G-32; G-33 | R31: Media | S31: 57 | T31: =CHOOSE(MONTH(X31),"Ene","Feb","Mar","Abr","May","Jun","Jul","Ago","Sep","Oct","Nov","Dic")&" "&YEAR(X31) -> Abr 2027 | W31: Idea | X31: 46483 | Y31: =CHOOSE(WEEKDAY(X31,2),"lunes","martes","miércoles","jueves","viernes","sábado","domingo") -> martes | Z31: =INT((X31-MIN($X$2:$X$101))/7)+1 -> 25 | AA31: =IF(X31=MIN($X$2:$X$101),"Lanzamiento","Calendario semanal") -> Calendario semanal
A32: E-31 | B32: Editorial | C32: Crisis de reputación: lo que enseñan los casos de marcas y figuras públicas | D32: Relaciones públicas y comunicación | E32: crisis de reputación | F32: Informacional | G32: TOFU | H32: Captar tráfico informacional en «crisis de reputación» y construir autoridad temática en relaciones públicas y comunicación. | I32: General | J32: México + EE.UU. | K32: Re-redacción 2026 | L32: https://www.continentalmedia.com.mx/2013/10/crisis-de-imagen-publica-en-el-tri/ | M32: https://www.continentalmedia.com.mx/2015/07/el-gran-error-de-relaciones-publicas-de-donald-trump/ | N32: Casos clásicos y recientes; qué hacer en las primeras 24 horas | O32: — | P32: Relaciones públicas y comunicación corporativa | Q32: E-32; G-14; G-33 | R32: Media | S32: 59 | T32: =CHOOSE(MONTH(X32),"Ene","Feb","Mar","Abr","May","Jun","Jul","Ago","Sep","Oct","Nov","Dic")&" "&YEAR(X32) -> Abr 2027 | W32: Idea | X32: 46490 | Y32: =CHOOSE(WEEKDAY(X32,2),"lunes","martes","miércoles","jueves","viernes","sábado","domingo") -> martes | Z32: =INT((X32-MIN($X$2:$X$101))/7)+1 -> 26 | AA32: =IF(X32=MIN($X$2:$X$101),"Lanzamiento","Calendario semanal") -> Calendario semanal
A33: E-32 | B33: Editorial | C33: Imagen pública: cómo te ven te tratan (marcas y líderes) | D33: Relaciones públicas y comunicación | E33: imagen pública | F33: Informacional | G33: TOFU | H33: Captar tráfico informacional en «imagen pública» y construir autoridad temática en relaciones públicas y comunicación. | I33: General | J33: México + EE.UU. | K33: Re-redacción 2026 | L33: https://www.continentalmedia.com.mx/2016/02/imagen-publica-como-te-ven-te-tratan/ | M33: https://www.continentalmedia.com.mx/2013/06/en-politica-la-imagen-cuenta/ | N33: Percepción, consistencia y coherencia entre discurso y acción | O33: — | P33: Relaciones públicas y comunicación corporativa | Q33: E-25; E-27; E-31; G-34 | R33: Media | S33: 61 | T33: =CHOOSE(MONTH(X33),"Ene","Feb","Mar","Abr","May","Jun","Jul","Ago","Sep","Oct","Nov","Dic")&" "&YEAR(X33) -> Abr 2027 | W33: Idea | X33: 46497 | Y33: =CHOOSE(WEEKDAY(X33,2),"lunes","martes","miércoles","jueves","viernes","sábado","domingo") -> martes | Z33: =INT((X33-MIN($X$2:$X$101))/7)+1 -> 27 | AA33: =IF(X33=MIN($X$2:$X$101),"Lanzamiento","Calendario semanal") -> Calendario semanal
A34: E-33 | B34: Editorial | C34: El proceso creativo en la era de la IA: cómo nacen hoy las buenas ideas | D34: Branding, diseño y creatividad | E34: proceso creativo | F34: Informacional | G34: TOFU | H34: Captar tráfico informacional en «proceso creativo» y construir autoridad temática en branding, diseño y creatividad. | I34: General | J34: México + EE.UU. | K34: Re-redacción 2026 | L34: https://www.continentalmedia.com.mx/2012/12/proceso-creativo/ | M34: https://www.continentalmedia.com.mx/2013/04/10-pasos-para-conseguir-mejores-ideas-creativas/ https://www.continentalmedia.com.mx/2013/04/decalogo-del-valor-de-las-ideas/ https://www.continentalmedia.com.mx/2013/05/cuanto-valen-las-ideas/ https://www.continentalmedia.com.mx/2014/05/no-te-exprimas-el-cerebro-5-ejercicios-para-recuperar-la-creatividad/ https://www.continentalmedia.com.mx/2012/12/churros-creatividad/ | N34: Fusionar cluster de creatividad con enfoque humano + IA | O34: — | P34: Branding, identidad y diseño gráfico | Q34: E-05; E-43; G-19 | R34: Media | S34: 63 | T34: =CHOOSE(MONTH(X34),"Ene","Feb","Mar","Abr","May","Jun","Jul","Ago","Sep","Oct","Nov","Dic")&" "&YEAR(X34) -> Abr 2027 | W34: Idea | X34: 46504 | Y34: =CHOOSE(WEEKDAY(X34,2),"lunes","martes","miércoles","jueves","viernes","sábado","domingo") -> martes | Z34: =INT((X34-MIN($X$2:$X$101))/7)+1 -> 28 | AA34: =IF(X34=MIN($X$2:$X$101),"Lanzamiento","Calendario semanal") -> Calendario semanal
A35: E-34 | B35: Editorial | C35: RP y medios en la era de la IA: cómo cambia el trabajo con la prensa | D35: Relaciones públicas y comunicación | E35: relaciones públicas e inteligencia artificial | F35: Informacional | G35: TOFU | H35: Captar tráfico informacional en «relaciones públicas e inteligencia artificial» y construir autoridad temática en relaciones públicas y comunicación. | I35: General | J35: México + EE.UU. | K35: Nuevo | N35: Periodistas, sala de prensa digital y contenido generado con IA | O35: — | P35: Relaciones públicas y comunicación corporativa | Q35: E-06; E-35; G-31; G-34 | R35: Media | S35: 65 | T35: =CHOOSE(MONTH(X35),"Ene","Feb","Mar","Abr","May","Jun","Jul","Ago","Sep","Oct","Nov","Dic")&" "&YEAR(X35) -> May 2027 | W35: Idea | X35: 46511 | Y35: =CHOOSE(WEEKDAY(X35,2),"lunes","martes","miércoles","jueves","viernes","sábado","domingo") -> martes | Z35: =INT((X35-MIN($X$2:$X$101))/7)+1 -> 29 | AA35: =IF(X35=MIN($X$2:$X$101),"Lanzamiento","Calendario semanal") -> Calendario semanal
A36: E-35 | B36: Editorial | C36: Publicidad responsable: sesgos, estereotipos y mensajes que dañan a tu marca | D36: Relaciones públicas y comunicación | E36: publicidad discriminatoria | F36: Informacional | G36: TOFU | H36: Captar tráfico informacional en «publicidad discriminatoria» y construir autoridad temática en relaciones públicas y comunicación. | I36: General | J36: México + EE.UU. | K36: Re-redacción 2026 | L36: https://www.continentalmedia.com.mx/2014/01/publicidad-discriminatoria/ | M36: https://www.continentalmedia.com.mx/2014/03/por-que-es-polemica-la-publicidad-subliminal/ | N36: Cómo revisar mensajes antes de publicar; casos recientes | O36: — | P36: Relaciones públicas y comunicación corporativa | Q36: E-27; E-34; G-30 | R36: Baja | S36: 87 | T36: =CHOOSE(MONTH(X36),"Ene","Feb","Mar","Abr","May","Jun","Jul","Ago","Sep","Oct","Nov","Dic")&" "&YEAR(X36) -> Jul 2027 | W36: Idea | X36: 46588 | Y36: =CHOOSE(WEEKDAY(X36,2),"lunes","martes","miércoles","jueves","viernes","sábado","domingo") -> martes | Z36: =INT((X36-MIN($X$2:$X$101))/7)+1 -> 40 | AA36: =IF(X36=MIN($X$2:$X$101),"Lanzamiento","Calendario semanal") -> Calendario semanal
A37: E-36 | B37: Editorial | C37: Meta Ads, Google Ads o TikTok Ads: dónde conviene invertir en 2026 | D37: Web, SEO y publicidad digital | E37: diferencias entre Facebook Ads y Google Ads | F37: Comercial | G37: MOFU | H37: Capturar búsquedas de evaluación en «diferencias entre Facebook Ads y Google Ads» y canalizarlas hacia diseño y desarrollo web, seo y publicidad digital. | I37: General | J37: México + EE.UU. | K37: Re-redacción 2026 | L37: https://www.continentalmedia.com.mx/2021/10/diferencias-entre-facebook-ads-y-google-ads/ | N37: Comparativa por objetivo, presupuesto y tipo de negocio | O37: — | P37: Diseño y desarrollo web, SEO y publicidad digital | Q37: G-38; G-39; G-43 | R37: Alta | S37: 15 | T37: =CHOOSE(MONTH(X37),"Ene","Feb","Mar","Abr","May","Jun","Jul","Ago","Sep","Oct","Nov","Dic")&" "&YEAR(X37) -> Nov 2026 | W37: Idea | X37: 46336 | Y37: =CHOOSE(WEEKDAY(X37,2),"lunes","martes","miércoles","jueves","viernes","sábado","domingo") -> martes | Z37: =INT((X37-MIN($X$2:$X$101))/7)+1 -> 4 | AA37: =IF(X37=MIN($X$2:$X$101),"Lanzamiento","Calendario semanal") -> Calendario semanal
A38: E-37 | B38: Editorial | C38: Fin de las cookies y datos propios: cómo medir y vender sin rastreo de terceros | D38: Web, SEO y publicidad digital | E38: first-party data | F38: Informacional | G38: TOFU | H38: Captar tráfico informacional en «first-party data» y construir autoridad temática en web, seo y publicidad digital. | I38: General | J38: México + EE.UU. | K38: Nuevo | N38: Privacidad, consentimiento y estrategia de datos propios | O38: — | P38: Diseño y desarrollo web, SEO y publicidad digital | Q38: G-23; G-42; G-43 | R38: Media | S38: 67 | T38: =CHOOSE(MONTH(X38),"Ene","Feb","Mar","Abr","May","Jun","Jul","Ago","Sep","Oct","Nov","Dic")&" "&YEAR(X38) -> May 2027 | W38: Idea | X38: 46518 | Y38: =CHOOSE(WEEKDAY(X38,2),"lunes","martes","miércoles","jueves","viernes","sábado","domingo") -> martes | Z38: =INT((X38-MIN($X$2:$X$101))/7)+1 -> 30 | AA38: =IF(X38=MIN($X$2:$X$101),"Lanzamiento","Calendario semanal") -> Calendario semanal
A39: E-38 | B39: Editorial | C39: ¿Página de Facebook o sitio web? Por qué tu web sigue siendo tu activo principal | D39: Web, SEO y publicidad digital | E39: página web vs redes sociales | F39: Comercial | G39: MOFU | H39: Capturar búsquedas de evaluación en «página web vs redes sociales» y canalizarlas hacia diseño y desarrollo web, seo y publicidad digital. | I39: General | J39: México + EE.UU. | K39: Re-redacción 2026 | L39: https://www.continentalmedia.com.mx/2014/08/que-es-mejor-para-tu-empresa-una-pagina-de-facebook-o-un-sitio-web/ | M39: https://www.continentalmedia.com.mx/2016/09/la-imagen-del-marketing-sitio-web-o-red-social/ | N39: Argumentos 2026: propiedad de la audiencia, SEO y conversión | O39: — | P39: Diseño y desarrollo web, SEO y publicidad digital | Q39: G-35; G-37; G-40 | R39: Alta | S39: 17 | T39: =CHOOSE(MONTH(X39),"Ene","Feb","Mar","Abr","May","Jun","Jul","Ago","Sep","Oct","Nov","Dic")&" "&YEAR(X39) -> Nov 2026 | W39: Idea | X39: 46343 | Y39: =CHOOSE(WEEKDAY(X39,2),"lunes","martes","miércoles","jueves","viernes","sábado","domingo") -> martes | Z39: =INT((X39-MIN($X$2:$X$101))/7)+1 -> 5 | AA39: =IF(X39=MIN($X$2:$X$101),"Lanzamiento","Calendario semanal") -> Calendario semanal
A40: E-39 | B40: Editorial | C40: Diseño web 2026: tendencias que sí importan (velocidad, accesibilidad, motion, IA) | D40: Web, SEO y publicidad digital | E40: tendencias diseño web | F40: Informacional | G40: TOFU | H40: Captar tráfico informacional en «tendencias diseño web» y construir autoridad temática en web, seo y publicidad digital. | I40: General | J40: México + EE.UU. | K40: Re-redacción 2026 | L40: https://www.continentalmedia.com.mx/2013/03/tendencias-en-diseno-web-2013/ | M40: https://www.continentalmedia.com.mx/2014/04/adaptate-llego-el-diseno-responsivo/ | N40: Reemplaza diseño responsivo 2014 y tendencias 2013 | O40: — | P40: Diseño y desarrollo web, SEO y publicidad digital | Q40: E-08; E-29; E-40; G-35; G-40 | R40: Media | S40: 69 | T40: =CHOOSE(MONTH(X40),"Ene","Feb","Mar","Abr","May","Jun","Jul","Ago","Sep","Oct","Nov","Dic")&" "&YEAR(X40) -> May 2027 | W40: Idea | X40: 46525 | Y40: =CHOOSE(WEEKDAY(X40,2),"lunes","martes","miércoles","jueves","viernes","sábado","domingo") -> martes | Z40: =INT((X40-MIN($X$2:$X$101))/7)+1 -> 31 | AA40: =IF(X40=MIN($X$2:$X$101),"Lanzamiento","Calendario semanal") -> Calendario semanal
A41: E-40 | B41: Editorial | C41: ¿App móvil o web progresiva? Cómo decidir sin tirar dinero | D41: Web, SEO y publicidad digital | E41: app móvil para mi empresa | F41: Comercial | G41: MOFU | H41: Capturar búsquedas de evaluación en «app móvil para mi empresa» y canalizarlas hacia diseño y desarrollo web, seo y publicidad digital. | I41: General | J41: México + EE.UU. | K41: Re-redacción 2026 | L41: https://www.continentalmedia.com.mx/2016/04/mi-empresa-necesita-una-aplicacion-movil/ | N41: Criterios de decisión, costos y alternativas (PWA) | O41: — | P41: Diseño y desarrollo web, SEO y publicidad digital | Q41: E-39; G-35; G-40 | R41: Baja | S41: 89 | T41: =CHOOSE(MONTH(X41),"Ene","Feb","Mar","Abr","May","Jun","Jul","Ago","Sep","Oct","Nov","Dic")&" "&YEAR(X41) -> Jul 2027 | W41: Idea | X41: 46595 | Y41: =CHOOSE(WEEKDAY(X41,2),"lunes","martes","miércoles","jueves","viernes","sábado","domingo") -> martes | Z41: =INT((X41-MIN($X$2:$X$101))/7)+1 -> 41 | AA41: =IF(X41=MIN($X$2:$X$101),"Lanzamiento","Calendario semanal") -> Calendario semanal
A42: E-41 | B42: Editorial | C42: Video corto vs. video largo: qué formato necesita cada etapa del embudo | D42: Video y fotografía | E42: video marketing | F42: Informacional | G42: TOFU | H42: Captar tráfico informacional en «video marketing» y construir autoridad temática en video y fotografía. | I42: General | J42: México + EE.UU. | K42: Re-redacción 2026 | L42: https://www.continentalmedia.com.mx/2017/06/que-tipo-de-video-funciona-para-redes-sociales/ | N42: Formatos 2026: Reels, Shorts, video largo y verticales | O42: — | P42: Producción de video y fotografía | Q42: E-42; G-45; G-46 | R42: Media | S42: 71 | T42: =CHOOSE(MONTH(X42),"Ene","Feb","Mar","Abr","May","Jun","Jul","Ago","Sep","Oct","Nov","Dic")&" "&YEAR(X42) -> May 2027 | W42: Idea | X42: 46532 | Y42: =CHOOSE(WEEKDAY(X42,2),"lunes","martes","miércoles","jueves","viernes","sábado","domingo") -> martes | Z42: =INT((X42-MIN($X$2:$X$101))/7)+1 -> 32 | AA42: =IF(X42=MIN($X$2:$X$101),"Lanzamiento","Calendario semanal") -> Calendario semanal
A43: E-42 | B43: Editorial | C43: Podcast y video-podcast: ¿conviene a tu marca B2B en 2026? | D43: Video y fotografía | E43: podcast para empresas | F43: Informacional | G43: TOFU | H43: Captar tráfico informacional en «podcast para empresas» y construir autoridad temática en video y fotografía. | I43: B2B | J43: México + EE.UU. | K43: Re-redacción 2026 | L43: https://www.continentalmedia.com.mx/2022/06/6-razones-para-hacer-un-podcast/ | M43: https://www.continentalmedia.com.mx/2022/07/twitch-que-es-y-por-que-es-importante-en-el-marketing/ | N43: Costo-beneficio y formatos; Twitch y streaming como complemento | O43: — | P43: Producción de video y fotografía | Q43: E-41; G-45; G-46 | R43: Baja | S43: 91 | T43: =CHOOSE(MONTH(X43),"Ene","Feb","Mar","Abr","May","Jun","Jul","Ago","Sep","Oct","Nov","Dic")&" "&YEAR(X43) -> Ago 2027 | W43: Idea | X43: 46602 | Y43: =CHOOSE(WEEKDAY(X43,2),"lunes","martes","miércoles","jueves","viernes","sábado","domingo") -> martes | Z43: =INT((X43-MIN($X$2:$X$101))/7)+1 -> 42 | AA43: =IF(X43=MIN($X$2:$X$101),"Lanzamiento","Calendario semanal") -> Calendario semanal
A44: E-43 | B44: Editorial | C44: Producción visual con IA vs. producción real: cuándo usar cada una | D44: Video y fotografía | E44: fotografía con IA | F44: Informacional | G44: TOFU | H44: Captar tráfico informacional en «fotografía con IA» y construir autoridad temática en video y fotografía. | I44: Hoteles, restaurantes y retail | J44: México + EE.UU. | K44: Nuevo | N44: Criterios de calidad, costos y confianza; hoteles y gastronomía | O44: — | P44: Producción de video y fotografía | Q44: E-05; E-08; E-33; G-47 | R44: Media | S44: 73 | T44: =CHOOSE(MONTH(X44),"Ene","Feb","Mar","Abr","May","Jun","Jul","Ago","Sep","Oct","Nov","Dic")&" "&YEAR(X44) -> Jun 2027 | W44: Idea | X44: 46539 | Y44: =CHOOSE(WEEKDAY(X44,2),"lunes","martes","miércoles","jueves","viernes","sábado","domingo") -> martes | Z44: =INT((X44-MIN($X$2:$X$101))/7)+1 -> 33 | AA44: =IF(X44=MIN($X$2:$X$101),"Lanzamiento","Calendario semanal") -> Calendario semanal
A45: E-44 | B45: Editorial | C45: BTL, guerrilla y experiencias de marca: ideas que funcionan en 2026 | D45: Eventos, medios y publicidad exterior | E45: marketing de guerrilla | F45: Informacional | G45: TOFU | H45: Captar tráfico informacional en «marketing de guerrilla» y construir autoridad temática en eventos, medios y publicidad exterior. | I45: General | J45: México + EE.UU. | K45: Re-redacción 2026 | L45: https://www.continentalmedia.com.mx/2012/12/publicidad-btl/ | M45: https://www.continentalmedia.com.mx/2012/12/marketing-de-guerrilla/ https://www.continentalmedia.com.mx/2013/05/codigos-qr-una-herramienta-muy-poderosa-para-tu-empresa/ https://www.continentalmedia.com.mx/2022/06/5-estrategias-con-codigos-qr-para-tu-negocio/ | N45: Activaciones, QR y marketing de experiencias con medición | O45: — | P45: Eventos, patrocinios y medios | Q45: E-45; E-46; G-48 | R45: Baja | S45: 93 | T45: =CHOOSE(MONTH(X45),"Ene","Feb","Mar","Abr","May","Jun","Jul","Ago","Sep","Oct","Nov","Dic")&" "&YEAR(X45) -> Ago 2027 | W45: Idea | X45: 46609 | Y45: =CHOOSE(WEEKDAY(X45,2),"lunes","martes","miércoles","jueves","viernes","sábado","domingo") -> martes | Z45: =INT((X45-MIN($X$2:$X$101))/7)+1 -> 43 | AA45: =IF(X45=MIN($X$2:$X$101),"Lanzamiento","Calendario semanal") -> Calendario semanal
A46: E-45 | B46: Editorial | C46: Radio, TV y medios masivos en un plan de medios omnicanal 2026 | D46: Eventos, medios y publicidad exterior | E46: plan de medios | F46: Informacional | G46: TOFU | H46: Captar tráfico informacional en «plan de medios» y construir autoridad temática en eventos, medios y publicidad exterior. | I46: General | J46: México + EE.UU. | K46: Re-redacción 2026 | L46: https://www.continentalmedia.com.mx/2016/11/el-poder-de-la-radio-como-medio-de-comunicacion-publicitaria/ | M46: https://www.continentalmedia.com.mx/2017/08/por-que-debo-anunciarme-en-television/ https://www.continentalmedia.com.mx/2012/12/plan-de-medios/ https://www.continentalmedia.com.mx/2014/10/clientes-radio-en-el-cine/ https://www.continentalmedia.com.mx/2012/12/inversion-publicitaria-en-medios-online/ | N46: Papel de medios masivos hoy, DOOH y medición cruzada | O46: — | P46: Eventos, patrocinios y medios | Q46: E-44; G-05; G-06 | R46: Baja | S46: 95 | T46: =CHOOSE(MONTH(X46),"Ene","Feb","Mar","Abr","May","Jun","Jul","Ago","Sep","Oct","Nov","Dic")&" "&YEAR(X46) -> Ago 2027 | W46: Idea | X46: 46616 | Y46: =CHOOSE(WEEKDAY(X46,2),"lunes","martes","miércoles","jueves","viernes","sábado","domingo") -> martes | Z46: =INT((X46-MIN($X$2:$X$101))/7)+1 -> 44 | AA46: =IF(X46=MIN($X$2:$X$101),"Lanzamiento","Calendario semanal") -> Calendario semanal
A47: E-46 | B47: Editorial | C47: Patrocinio de eventos: cómo medir el retorno y elegir bien | D47: Eventos, medios y publicidad exterior | E47: patrocinio de eventos | F47: Informacional | G47: TOFU | H47: Captar tráfico informacional en «patrocinio de eventos» y construir autoridad temática en eventos, medios y publicidad exterior. | I47: General | J47: México + EE.UU. | K47: Re-redacción 2026 | L47: https://www.continentalmedia.com.mx/2016/12/el-patrocinio-de-eventos-una-estrategia-clave-para-tu-marca/ | M47: https://www.continentalmedia.com.mx/2012/12/marketing-deportivo/ | N47: Marketing deportivo y patrocinio con métricas | O47: — | P47: Eventos, patrocinios y medios | Q47: E-28; E-44; G-05; G-48 | R47: Baja | S47: 97 | T47: =CHOOSE(MONTH(X47),"Ene","Feb","Mar","Abr","May","Jun","Jul","Ago","Sep","Oct","Nov","Dic")&" "&YEAR(X47) -> Ago 2027 | W47: Idea | X47: 46623 | Y47: =CHOOSE(WEEKDAY(X47,2),"lunes","martes","miércoles","jueves","viernes","sábado","domingo") -> martes | Z47: =INT((X47-MIN($X$2:$X$101))/7)+1 -> 45 | AA47: =IF(X47=MIN($X$2:$X$101),"Lanzamiento","Calendario semanal") -> Calendario semanal
A48: E-47 | B48: Editorial | C48: El consumidor hispano en EE.UU. en 2026: quién es y cómo comunicarle | D48: Marketing por industria y mercado | E48: marketing para público hispano en EE.UU. | F48: Informacional | G48: TOFU | H48: Captar tráfico informacional en «marketing para público hispano en EE.UU.» y construir autoridad temática en marketing por industria y mercado. | I48: Empresas que venden a hispanos en EE.UU. | J48: EE.UU. hispano | K48: Re-redacción 2026 | L48: https://www.continentalmedia.com.mx/2022/01/marketing-para-publico-hispano-en-eeuu/ | N48: Datos recientes de población hispana; cultura, idioma y canales | O48: — | P48: Marketing por industria y mercado hispano | Q48: E-14; E-49; G-50 | R48: Alta | S48: 19 | T48: =CHOOSE(MONTH(X48),"Ene","Feb","Mar","Abr","May","Jun","Jul","Ago","Sep","Oct","Nov","Dic")&" "&YEAR(X48) -> Nov 2026 | W48: Idea | X48: 46350 | Y48: =CHOOSE(WEEKDAY(X48,2),"lunes","martes","miércoles","jueves","viernes","sábado","domingo") -> martes | Z48: =INT((X48-MIN($X$2:$X$101))/7)+1 -> 6 | AA48: =IF(X48=MIN($X$2:$X$101),"Lanzamiento","Calendario semanal") -> Calendario semanal
A49: E-48 | B49: Editorial | C49: Marketing hotelero: cómo ganar reservas directas sin depender de las OTA | D49: Marketing por industria y mercado | E49: marketing para hoteles | F49: Comercial | G49: MOFU | H49: Capturar búsquedas de evaluación en «marketing para hoteles» y canalizarlas hacia marketing por industria y mercado hispano. | I49: Hoteles y hospitalidad | J49: México | K49: Re-redacción 2026 | L49: https://www.continentalmedia.com.mx/2015/03/marketing-para-hoteles/ | N49: Reservas directas, contenido y reputación | O49: — | P49: Marketing por industria y mercado hispano | Q49: E-50; G-37; G-47; G-49 | R49: Media | S49: 75 | T49: =CHOOSE(MONTH(X49),"Ene","Feb","Mar","Abr","May","Jun","Jul","Ago","Sep","Oct","Nov","Dic")&" "&YEAR(X49) -> Jun 2027 | W49: Idea | X49: 46546 | Y49: =CHOOSE(WEEKDAY(X49,2),"lunes","martes","miércoles","jueves","viernes","sábado","domingo") -> martes | Z49: =INT((X49-MIN($X$2:$X$101))/7)+1 -> 34 | AA49: =IF(X49=MIN($X$2:$X$101),"Lanzamiento","Calendario semanal") -> Calendario semanal
A50: E-49 | B50: Editorial | C50: Millennials, Gen Z y el nicho 50+: cómo cambió el consumidor al que le vendes | D50: Marketing por industria y mercado | E50: marketing generacional | F50: Informacional | G50: TOFU | H50: Captar tráfico informacional en «marketing generacional» y construir autoridad temática en marketing por industria y mercado. | I50: General | J50: México + EE.UU. | K50: Re-redacción 2026 | L50: https://www.continentalmedia.com.mx/2017/11/marketing-para-millenials-como-venderle-a-los-millenials/ | M50: https://www.continentalmedia.com.mx/2015/09/la-tercera-edad-el-nicho-de-mercado-inesperado/ | N50: Fusionar millennials y nicho de adultos mayores en una visión generacional | O50: — | P50: Marketing por industria y mercado hispano | Q50: E-12; E-47; G-02 | R50: Baja | S50: 99 | T50: =CHOOSE(MONTH(X50),"Ene","Feb","Mar","Abr","May","Jun","Jul","Ago","Sep","Oct","Nov","Dic")&" "&YEAR(X50) -> Ago 2027 | W50: Idea | X50: 46630 | Y50: =CHOOSE(WEEKDAY(X50,2),"lunes","martes","miércoles","jueves","viernes","sábado","domingo") -> martes | Z50: =INT((X50-MIN($X$2:$X$101))/7)+1 -> 46 | AA50: =IF(X50=MIN($X$2:$X$101),"Lanzamiento","Calendario semanal") -> Calendario semanal
A51: E-50 | B51: Editorial | C51: Marketing inmobiliario en 2026: cómo cambió el comprador de vivienda | D51: Marketing por industria y mercado | E51: marketing inmobiliario | F51: Informacional | G51: TOFU | H51: Captar tráfico informacional en «marketing inmobiliario» y construir autoridad temática en marketing por industria y mercado. | I51: Inmobiliario y desarrolladoras | J51: México | K51: Re-redacción 2026 | L51: https://www.continentalmedia.com.mx/2021/11/las-herramientas-mas-poderosas-para-marketing-de-inmobiliarias/ | N51: Recorrido digital del comprador; recorridos virtuales y WhatsApp | O51: — | P51: Marketing por industria y mercado hispano | Q51: E-48; G-37; G-40 | R51: Media | S51: 77 | T51: =CHOOSE(MONTH(X51),"Ene","Feb","Mar","Abr","May","Jun","Jul","Ago","Sep","Oct","Nov","Dic")&" "&YEAR(X51) -> Jun 2027 | W51: Idea | X51: 46553 | Y51: =CHOOSE(WEEKDAY(X51,2),"lunes","martes","miércoles","jueves","viernes","sábado","domingo") -> martes | Z51: =INT((X51-MIN($X$2:$X$101))/7)+1 -> 35 | AA51: =IF(X51=MIN($X$2:$X$101),"Lanzamiento","Calendario semanal") -> Calendario semanal
A52: G-01 | B52: Guía práctica | C52: Cómo crear tu plan de marketing 2027 paso a paso | D52: Estrategia de marketing y contenidos | E52: cómo hacer un plan de marketing | F52: Informacional | G52: MOFU | H52: Posicionar «cómo hacer un plan de marketing» (búsqueda "cómo hacerlo") y convertir visitas en leads con el PDF descargable. | I52: Pymes y direcciones de marketing | J52: México + EE.UU. | K52: Re-redacción 2026 | L52: https://www.continentalmedia.com.mx/2013/06/la-necesidad-de-contar-con-un-buen-plan-de-marketing/ | M52: https://www.continentalmedia.com.mx/2014/09/que-le-falta-a-tu-plan-de-negocios/ | N52: Metodología en 7 pasos + ejemplo para pyme | O52: Plantilla editable de plan de marketing 2027 | P52: Estrategia de marketing 360 | Q52: E-09; E-16; E-18; G-02; G-03; G-04; G-06; G-08 | R52: Alta | S52: 2 | T52: =CHOOSE(MONTH(X52),"Ene","Feb","Mar","Abr","May","Jun","Jul","Ago","Sep","Oct","Nov","Dic")&" "&YEAR(X52) -> Oct 2026 | W52: Idea | X52: 46314 | Y52: =CHOOSE(WEEKDAY(X52,2),"lunes","martes","miércoles","jueves","viernes","sábado","domingo") -> lunes | Z52: =INT((X52-MIN($X$2:$X$101))/7)+1 -> 1 | AA52: =IF(X52=MIN($X$2:$X$101),"Lanzamiento","Calendario semanal") -> Lanzamiento
A53: G-02 | B53: Guía práctica | C53: Cómo definir tu buyer persona (con ejemplos) | D53: Estrategia de marketing y contenidos | E53: buyer persona | F53: Informacional | G53: MOFU | H53: Posicionar «buyer persona» (búsqueda "cómo hacerlo") y convertir visitas en leads con el PDF descargable. | I53: General | J53: México + EE.UU. | K53: Re-redacción 2026 | L53: https://www.continentalmedia.com.mx/2017/06/el-buyer-persona-la-nueva-manera-de-segmentar-a-tu-mercado/ | N53: Ejemplos por sector; entrevista a clientes | O53: Plantilla de buyer persona | P53: Estrategia de marketing 360 | Q53: E-49; G-01; G-03; G-08 | R53: Media | S53: 46 | T53: =CHOOSE(MONTH(X53),"Ene","Feb","Mar","Abr","May","Jun","Jul","Ago","Sep","Oct","Nov","Dic")&" "&YEAR(X53) -> Feb 2027 | W53: Idea | X53: 46443 | Y53: =CHOOSE(WEEKDAY(X53,2),"lunes","martes","miércoles","jueves","viernes","sábado","domingo") -> jueves | Z53: =INT((X53-MIN($X$2:$X$101))/7)+1 -> 19 | AA53: =IF(X53=MIN($X$2:$X$101),"Lanzamiento","Calendario semanal") -> Calendario semanal
A54: G-03 | B54: Guía práctica | C54: Embudo de ventas: cómo diseñar el tuyo, etapa por etapa | D54: Estrategia de marketing y contenidos | E54: funnel de ventas | F54: Informacional | G54: MOFU | H54: Posicionar «funnel de ventas» (búsqueda "cómo hacerlo") y convertir visitas en leads con el PDF descargable. | I54: General | J54: México + EE.UU. | K54: Re-redacción 2026 | L54: https://www.continentalmedia.com.mx/2021/10/funnel-de-ventas-que-es-y-para-que-sirve/ | N54: Embudo + métricas por etapa + automatizaciones | O54: Mapa de embudo de ventas (editable) | P54: Estrategia de marketing 360 | Q54: E-16; G-01; G-02; G-40; G-41; G-42 | R54: Media | S54: 48 | T54: =CHOOSE(MONTH(X54),"Ene","Feb","Mar","Abr","May","Jun","Jul","Ago","Sep","Oct","Nov","Dic")&" "&YEAR(X54) -> Mar 2027 | W54: Idea | X54: 46450 | Y54: =CHOOSE(WEEKDAY(X54,2),"lunes","martes","miércoles","jueves","viernes","sábado","domingo") -> jueves | Z54: =INT((X54-MIN($X$2:$X$101))/7)+1 -> 20 | AA54: =IF(X54=MIN($X$2:$X$101),"Lanzamiento","Calendario semanal") -> Calendario semanal
A55: G-04 | B55: Guía práctica | C55: Cómo hacer un brief de marketing para tu agencia | D55: Estrategia de marketing y contenidos | E55: brief de marketing | F55: Informacional | G55: MOFU | H55: Posicionar «brief de marketing» (búsqueda "cómo hacerlo") y convertir visitas en leads con el PDF descargable. | I55: General | J55: México + EE.UU. | K55: Re-redacción 2026 | L55: https://www.continentalmedia.com.mx/2020/01/10-pasos-para-hacer-un-brief-de-redes-sociales/ | M55: https://www.continentalmedia.com.mx/2013/06/10-sencillos-pasos-para-una-campana-publicitaria/ | N55: Ampliar de brief de redes a brief integral | O55: Formato de brief de marketing | P55: Estrategia de marketing 360 | Q55: G-01; G-26 | R55: Media | S55: 50 | T55: =CHOOSE(MONTH(X55),"Ene","Feb","Mar","Abr","May","Jun","Jul","Ago","Sep","Oct","Nov","Dic")&" "&YEAR(X55) -> Mar 2027 | W55: Idea | X55: 46457 | Y55: =CHOOSE(WEEKDAY(X55,2),"lunes","martes","miércoles","jueves","viernes","sábado","domingo") -> jueves | Z55: =INT((X55-MIN($X$2:$X$101))/7)+1 -> 21 | AA55: =IF(X55=MIN($X$2:$X$101),"Lanzamiento","Calendario semanal") -> Calendario semanal
A56: G-05 | B56: Guía práctica | C56: Cómo calcular el ROI de tu publicidad (y qué KPIs reportar) | D56: Estrategia de marketing y contenidos | E56: retorno de inversión publicitaria | F56: Informacional | G56: MOFU | H56: Posicionar «retorno de inversión publicitaria» (búsqueda "cómo hacerlo") y convertir visitas en leads con el PDF descargable. | I56: General | J56: México + EE.UU. | K56: Re-redacción 2026 | L56: https://www.continentalmedia.com.mx/2015/05/retorno-inversion-publicitaria/ | N56: Fórmulas, ROAS, CAC y ejemplos | O56: Hoja de cálculo de ROI y KPIs | P56: Estrategia de marketing 360 | Q56: E-17; E-21; E-45; E-46; G-06; G-43 | R56: Media | S56: 52 | T56: =CHOOSE(MONTH(X56),"Ene","Feb","Mar","Abr","May","Jun","Jul","Ago","Sep","Oct","Nov","Dic")&" "&YEAR(X56) -> Mar 2027 | W56: Idea | X56: 46464 | Y56: =CHOOSE(WEEKDAY(X56,2),"lunes","martes","miércoles","jueves","viernes","sábado","domingo") -> jueves | Z56: =INT((X56-MIN($X$2:$X$101))/7)+1 -> 22 | AA56: =IF(X56=MIN($X$2:$X$101),"Lanzamiento","Calendario semanal") -> Calendario semanal
A57: G-06 | B57: Guía práctica | C57: Cómo armar tu presupuesto de marketing anual | D57: Estrategia de marketing y contenidos | E57: presupuesto de marketing | F57: Informacional | G57: MOFU | H57: Posicionar «presupuesto de marketing» (búsqueda "cómo hacerlo") y convertir visitas en leads con el PDF descargable. | I57: General | J57: México + EE.UU. | K57: Re-redacción 2026 | L57: https://www.continentalmedia.com.mx/2014/12/presupuesto-publicitario/ | N57: Porcentajes por industria y distribución por canal | O57: Plantilla de presupuesto de marketing | P57: Estrategia de marketing 360 | Q57: E-21; E-45; G-01; G-05 | R57: Media | S57: 54 | T57: =CHOOSE(MONTH(X57),"Ene","Feb","Mar","Abr","May","Jun","Jul","Ago","Sep","Oct","Nov","Dic")&" "&YEAR(X57) -> Mar 2027 | W57: Idea | X57: 46471 | Y57: =CHOOSE(WEEKDAY(X57,2),"lunes","martes","miércoles","jueves","viernes","sábado","domingo") -> jueves | Z57: =INT((X57-MIN($X$2:$X$101))/7)+1 -> 23 | AA57: =IF(X57=MIN($X$2:$X$101),"Lanzamiento","Calendario semanal") -> Calendario semanal
A58: G-07 | B58: Guía práctica | C58: Calendario comercial México 2027 y cómo planear campañas estacionales | D58: Estrategia de marketing y contenidos | E58: calendario de marketing 2027 | F58: Informacional | G58: MOFU | H58: Posicionar «calendario de marketing 2027» (búsqueda "cómo hacerlo") y convertir visitas en leads con el PDF descargable. | I58: General | J58: México | K58: Re-redacción 2026 | L58: https://www.continentalmedia.com.mx/2023/01/como-aplicar-una-campana-de-marketing-estacional-en-5-pasos/ | M58: https://www.continentalmedia.com.mx/2023/12/guia-de-publicidad-para-fin-de-ano/ https://www.continentalmedia.com.mx/2016/11/como-aprovechar-mejor-la-inercia-del-buen-fin/ https://www.continentalmedia.com.mx/2013/11/no-te-pierdas-dentro-del-buen-fin/ https://www.continentalmedia.com.mx/2013/12/publicidad-con-aroma-navideno/ | N58: Buen Fin, fin de año y fechas clave; campaña estacional en 5 pasos | O58: Calendario comercial 2027 (México y EE.UU.) | P58: Estrategia de marketing 360 | Q58: E-09; G-09; G-39 | R58: Alta | S58: 4 | T58: =CHOOSE(MONTH(X58),"Ene","Feb","Mar","Abr","May","Jun","Jul","Ago","Sep","Oct","Nov","Dic")&" "&YEAR(X58) -> Oct 2026 | W58: Idea | X58: 46314 | Y58: =CHOOSE(WEEKDAY(X58,2),"lunes","martes","miércoles","jueves","viernes","sábado","domingo") -> lunes | Z58: =INT((X58-MIN($X$2:$X$101))/7)+1 -> 1 | AA58: =IF(X58=MIN($X$2:$X$101),"Lanzamiento","Calendario semanal") -> Lanzamiento
A59: G-08 | B59: Guía práctica | C59: Cómo hacer un estudio de mercado y analizar a tu competencia | D59: Estrategia de marketing y contenidos | E59: estudio de mercado | F59: Informacional | G59: MOFU | H59: Posicionar «estudio de mercado» (búsqueda "cómo hacerlo") y convertir visitas en leads con el PDF descargable. | I59: Pymes y emprendedores | J59: México + EE.UU. | K59: Re-redacción 2026 | L59: https://www.continentalmedia.com.mx/2013/05/por-que-realizar-una-investigacion-de-mercados/ | M59: https://www.continentalmedia.com.mx/2014/02/estudio-de-mercado-la-clave-del-exito-de-tu-producto/ https://www.continentalmedia.com.mx/2014/02/por-que-algunos-productos-fracasaron-en-el-mercado/ | N59: Fuentes gratuitas, análisis FODA y de competencia | O59: Plantilla de análisis de competencia | P59: Estrategia de marketing 360 | Q59: E-18; G-01; G-02 | R59: Media | S59: 56 | T59: =CHOOSE(MONTH(X59),"Ene","Feb","Mar","Abr","May","Jun","Jul","Ago","Sep","Oct","Nov","Dic")&" "&YEAR(X59) -> Abr 2027 | W59: Idea | X59: 46478 | Y59: =CHOOSE(WEEKDAY(X59,2),"lunes","martes","miércoles","jueves","viernes","sábado","domingo") -> jueves | Z59: =INT((X59-MIN($X$2:$X$101))/7)+1 -> 24 | AA59: =IF(X59=MIN($X$2:$X$101),"Lanzamiento","Calendario semanal") -> Calendario semanal
A60: G-09 | B60: Guía práctica | C60: Cómo crear un calendario de contenido para redes sociales | D60: Redes sociales y comunidad | E60: calendario de contenido redes sociales | F60: Informacional | G60: MOFU | H60: Posicionar «calendario de contenido redes sociales» (búsqueda "cómo hacerlo") y convertir visitas en leads con el PDF descargable. | I60: General | J60: México + EE.UU. | K60: Nuevo | N60: Complementa el artículo 2026/08 de contenido | O60: Calendario de contenido editable (12 meses) | P60: Gestión de redes sociales y community management | Q60: E-10; E-12; E-15; E-19; E-22; G-07; G-10; G-17; G-49; G-50 | R60: Alta | S60: 6 | T60: =CHOOSE(MONTH(X60),"Ene","Feb","Mar","Abr","May","Jun","Jul","Ago","Sep","Oct","Nov","Dic")&" "&YEAR(X60) -> Oct 2026 | W60: Idea | X60: 46314 | Y60: =CHOOSE(WEEKDAY(X60,2),"lunes","martes","miércoles","jueves","viernes","sábado","domingo") -> lunes | Z60: =INT((X60-MIN($X$2:$X$101))/7)+1 -> 1 | AA60: =IF(X60=MIN($X$2:$X$101),"Lanzamiento","Calendario semanal") -> Lanzamiento
A61: G-10 | B61: Guía práctica | C61: Guía de Instagram para empresas 2026: perfil, Reels, SEO y métricas | D61: Redes sociales y comunidad | E61: Instagram para empresas | F61: Informacional | G61: MOFU | H61: Posicionar «Instagram para empresas» (búsqueda "cómo hacerlo") y convertir visitas en leads con el PDF descargable. | I61: General | J61: México + EE.UU. | K61: Re-redacción 2026 | L61: https://www.continentalmedia.com.mx/2023/04/7-tips-clave-para-crecer-en-instagram-en-2023/ | M61: https://www.continentalmedia.com.mx/2023/02/5-estrategias-de-instagram-reels-para-tu-marca/ https://www.continentalmedia.com.mx/2021/12/instagram-como-herramienta-para-llegar-a-tu-cliente/ | N61: Consolida 3 posts de Instagram; añadir SEO social | O61: Checklist de Instagram para empresas | P61: Gestión de redes sociales y community management | Q61: E-11; G-09; G-11; G-13; G-16 | R61: Alta | S61: 8 | T61: =CHOOSE(MONTH(X61),"Ene","Feb","Mar","Abr","May","Jun","Jul","Ago","Sep","Oct","Nov","Dic")&" "&YEAR(X61) -> Oct 2026 | W61: Idea | X61: 46314 | Y61: =CHOOSE(WEEKDAY(X61,2),"lunes","martes","miércoles","jueves","viernes","sábado","domingo") -> lunes | Z61: =INT((X61-MIN($X$2:$X$101))/7)+1 -> 1 | AA61: =IF(X61=MIN($X$2:$X$101),"Lanzamiento","Calendario semanal") -> Lanzamiento
A62: G-11 | B62: Guía práctica | C62: Cómo vender en TikTok y TikTok Shop para tu negocio | D62: Redes sociales y comunidad | E62: TikTok para empresas | F62: Informacional | G62: MOFU | H62: Posicionar «TikTok para empresas» (búsqueda "cómo hacerlo") y convertir visitas en leads con el PDF descargable. | I62: General | J62: México + EE.UU. | K62: Re-redacción 2026 | L62: https://www.continentalmedia.com.mx/2022/05/como-y-por-que-deberias-llevar-tu-empresa-a-tiktok/ | N62: Actualizar con TikTok Shop y publicidad | O62: Guía de arranque en TikTok | P62: Gestión de redes sociales y community management | Q62: E-11; G-10 | R62: Media | S62: 58 | T62: =CHOOSE(MONTH(X62),"Ene","Feb","Mar","Abr","May","Jun","Jul","Ago","Sep","Oct","Nov","Dic")&" "&YEAR(X62) -> Abr 2027 | W62: Idea | X62: 46485 | Y62: =CHOOSE(WEEKDAY(X62,2),"lunes","martes","miércoles","jueves","viernes","sábado","domingo") -> jueves | Z62: =INT((X62-MIN($X$2:$X$101))/7)+1 -> 25 | AA62: =IF(X62=MIN($X$2:$X$101),"Lanzamiento","Calendario semanal") -> Calendario semanal
A63: G-12 | B63: Guía práctica | C63: LinkedIn para empresas: cómo generar leads B2B y posicionar tu marca | D63: Redes sociales y comunidad | E63: LinkedIn para empresas | F63: Informacional | G63: MOFU | H63: Posicionar «LinkedIn para empresas» (búsqueda "cómo hacerlo") y convertir visitas en leads con el PDF descargable. | I63: B2B | J63: México + EE.UU. | K63: Re-redacción 2026 | L63: https://www.continentalmedia.com.mx/2022/04/como-gestionar-exitosamente-tu-cuenta-empresarial-de-linkedin/ | M63: https://www.continentalmedia.com.mx/2022/05/como-gestionar-exitosamente-tu-cuenta-empresarial-de-linkedin-parte-ii/ | N63: Unificar partes I y II; añadir newsletters y ads | O63: Checklist de LinkedIn para empresas | P63: Gestión de redes sociales y community management | Q63: E-14; E-25; G-17 | R63: Media | S63: 60 | T63: =CHOOSE(MONTH(X63),"Ene","Feb","Mar","Abr","May","Jun","Jul","Ago","Sep","Oct","Nov","Dic")&" "&YEAR(X63) -> Abr 2027 | W63: Idea | X63: 46492 | Y63: =CHOOSE(WEEKDAY(X63,2),"lunes","martes","miércoles","jueves","viernes","sábado","domingo") -> jueves | Z63: =INT((X63-MIN($X$2:$X$101))/7)+1 -> 26 | AA63: =IF(X63=MIN($X$2:$X$101),"Lanzamiento","Calendario semanal") -> Calendario semanal
A64: G-13 | B64: Guía práctica | C64: Cómo hacer un giveaway o sorteo en redes sin meterte en problemas | D64: Redes sociales y comunidad | E64: cómo hacer un sorteo en Instagram | F64: Informacional | G64: MOFU | H64: Posicionar «cómo hacer un sorteo en Instagram» (búsqueda "cómo hacerlo") y convertir visitas en leads con el PDF descargable. | I64: General | J64: México | K64: Re-redacción 2026 | L64: https://www.continentalmedia.com.mx/2018/03/como-hacer-un-giveaway-en-5-sencillos-pasos/ | N64: Reglas de plataformas y legales en México | O64: Checklist de sorteos en redes | P64: Gestión de redes sociales y community management | Q64: G-10; G-17 | R64: Baja | S64: 92 | T64: =CHOOSE(MONTH(X64),"Ene","Feb","Mar","Abr","May","Jun","Jul","Ago","Sep","Oct","Nov","Dic")&" "&YEAR(X64) -> Ago 2027 | W64: Idea | X64: 46604 | Y64: =CHOOSE(WEEKDAY(X64,2),"lunes","martes","miércoles","jueves","viernes","sábado","domingo") -> jueves | Z64: =INT((X64-MIN($X$2:$X$101))/7)+1 -> 42 | AA64: =IF(X64=MIN($X$2:$X$101),"Lanzamiento","Calendario semanal") -> Calendario semanal
A65: G-14 | B65: Guía práctica | C65: Cómo responder comentarios negativos y atender clientes en redes sociales | D65: Redes sociales y comunidad | E65: atención al cliente en redes sociales | F65: Informacional | G65: MOFU | H65: Posicionar «atención al cliente en redes sociales» (búsqueda "cómo hacerlo") y convertir visitas en leads con el PDF descargable. | I65: General | J65: México + EE.UU. | K65: Re-redacción 2026 | L65: https://www.continentalmedia.com.mx/2012/12/es-necesario-ofrecer-una-buena-atencion-al-cliente-en-las-redes-sociales/ | M65: https://www.continentalmedia.com.mx/2014/04/no-ahuyentes-a-tus-clientes/ https://www.continentalmedia.com.mx/2014/06/recuperar-clientes/ | N65: Protocolos de respuesta y tiempos | O65: Protocolo de atención en redes sociales | P65: Gestión de redes sociales y community management | Q65: E-15; E-31; G-17 | R65: Media | S65: 62 | T65: =CHOOSE(MONTH(X65),"Ene","Feb","Mar","Abr","May","Jun","Jul","Ago","Sep","Oct","Nov","Dic")&" "&YEAR(X65) -> Abr 2027 | W65: Idea | X65: 46499 | Y65: =CHOOSE(WEEKDAY(X65,2),"lunes","martes","miércoles","jueves","viernes","sábado","domingo") -> jueves | Z65: =INT((X65-MIN($X$2:$X$101))/7)+1 -> 27 | AA65: =IF(X65=MIN($X$2:$X$101),"Lanzamiento","Calendario semanal") -> Calendario semanal
A66: G-15 | B66: Guía práctica | C66: Meta Business Suite: cómo administrar Facebook e Instagram en un solo lugar | D66: Redes sociales y comunidad | E66: Meta Business Suite | F66: Informacional | G66: MOFU | H66: Posicionar «Meta Business Suite» (búsqueda "cómo hacerlo") y convertir visitas en leads con el PDF descargable. | I66: General | J66: México + EE.UU. | K66: Re-redacción 2026 | L66: https://www.continentalmedia.com.mx/2022/07/que-es-meta-business-suite-y-como-utilizarlo/ | M66: https://www.continentalmedia.com.mx/2022/05/no-pierdas-tu-cuenta-empresarial-conoce-las-nueva-normas-y-politicas-de-facebook/ https://www.continentalmedia.com.mx/2016/03/porque-es-importante-verificar-mi-cuenta-de-facebook/ https://www.continentalmedia.com.mx/2016/09/como-afecta-a-tu-fanpage-el-nuevo-algoritmo-de-facebook/ | N66: Actualizar con cambios 2026, verificación y políticas | O66: Checklist de configuración de Meta Business | P66: Gestión de redes sociales y community management | Q66: G-17; G-21; G-39 | R66: Alta | S66: 10 | T66: =CHOOSE(MONTH(X66),"Ene","Feb","Mar","Abr","May","Jun","Jul","Ago","Sep","Oct","Nov","Dic")&" "&YEAR(X66) -> Oct 2026 | W66: Idea | X66: 46317 | Y66: =CHOOSE(WEEKDAY(X66,2),"lunes","martes","miércoles","jueves","viernes","sábado","domingo") -> jueves | Z66: =INT((X66-MIN($X$2:$X$101))/7)+1 -> 1 | AA66: =IF(X66=MIN($X$2:$X$101),"Lanzamiento","Calendario semanal") -> Calendario semanal
A67: G-16 | B67: Guía práctica | C67: Cómo trabajar con influencers y creadores: brief, contrato y medición | D67: Redes sociales y comunidad | E67: cómo trabajar con influencers | F67: Informacional | G67: MOFU | H67: Posicionar «cómo trabajar con influencers» (búsqueda "cómo hacerlo") y convertir visitas en leads con el PDF descargable. | I67: General | J67: México + EE.UU. | K67: Nuevo | N67: Operativo del tema E-13 | O67: Brief y checklist de colaboración con creadores | P67: Gestión de redes sociales y community management | Q67: E-13; G-10; G-17 | R67: Media | S67: 64 | T67: =CHOOSE(MONTH(X67),"Ene","Feb","Mar","Abr","May","Jun","Jul","Ago","Sep","Oct","Nov","Dic")&" "&YEAR(X67) -> Abr 2027 | W67: Idea | X67: 46506 | Y67: =CHOOSE(WEEKDAY(X67,2),"lunes","martes","miércoles","jueves","viernes","sábado","domingo") -> jueves | Z67: =INT((X67-MIN($X$2:$X$101))/7)+1 -> 28 | AA67: =IF(X67=MIN($X$2:$X$101),"Lanzamiento","Calendario semanal") -> Calendario semanal
A68: G-17 | B68: Guía práctica | C68: Qué métricas de redes sociales importan: reporte mensual paso a paso | D68: Redes sociales y comunidad | E68: métricas de redes sociales | F68: Informacional | G68: MOFU | H68: Posicionar «métricas de redes sociales» (búsqueda "cómo hacerlo") y convertir visitas en leads con el PDF descargable. | I68: General | J68: México + EE.UU. | K68: Nuevo | N68: KPIs por objetivo y plantilla de reporte | O68: Plantilla de reporte mensual de redes | P68: Gestión de redes sociales y community management | Q68: E-10; E-14; G-09; G-12; G-13; G-14; G-15; G-16 | R68: Alta | S68: 12 | T68: =CHOOSE(MONTH(X68),"Ene","Feb","Mar","Abr","May","Jun","Jul","Ago","Sep","Oct","Nov","Dic")&" "&YEAR(X68) -> Oct 2026 | W68: Idea | X68: 46324 | Y68: =CHOOSE(WEEKDAY(X68,2),"lunes","martes","miércoles","jueves","viernes","sábado","domingo") -> jueves | Z68: =INT((X68-MIN($X$2:$X$101))/7)+1 -> 2 | AA68: =IF(X68=MIN($X$2:$X$101),"Lanzamiento","Calendario semanal") -> Calendario semanal
A69: G-18 | B69: Guía práctica | C69: 50 prompts de IA para marketing que sí funcionan | D69: IA aplicada al marketing | E69: prompts de ChatGPT para marketing | F69: Informacional | G69: MOFU | H69: Posicionar «prompts de ChatGPT para marketing» (búsqueda "cómo hacerlo") y convertir visitas en leads con el PDF descargable. | I69: General | J69: México + EE.UU. | K69: Nuevo | N69: Biblioteca por tarea: SEO, redes, email, anuncios, RP | O69: Biblioteca de 50 prompts de marketing | P69: IA aplicada a marketing y comunicación | Q69: E-01; E-07; G-19; G-22 | R69: Alta | S69: 14 | T69: =CHOOSE(MONTH(X69),"Ene","Feb","Mar","Abr","May","Jun","Jul","Ago","Sep","Oct","Nov","Dic")&" "&YEAR(X69) -> Nov 2026 | W69: Idea | X69: 46331 | Y69: =CHOOSE(WEEKDAY(X69,2),"lunes","martes","miércoles","jueves","viernes","sábado","domingo") -> jueves | Z69: =INT((X69-MIN($X$2:$X$101))/7)+1 -> 3 | AA69: =IF(X69=MIN($X$2:$X$101),"Lanzamiento","Calendario semanal") -> Calendario semanal
A70: G-19 | B70: Guía práctica | C70: Cómo usar IA para crear contenido sin perder tu voz de marca | D70: IA aplicada al marketing | E70: cómo usar IA para crear contenido | F70: Informacional | G70: MOFU | H70: Posicionar «cómo usar IA para crear contenido» (búsqueda "cómo hacerlo") y convertir visitas en leads con el PDF descargable. | I70: General | J70: México + EE.UU. | K70: Nuevo | N70: Flujo con guía de estilo y revisión humana | O70: Guía de estilo para trabajar con IA | P70: IA aplicada a marketing y comunicación | Q70: E-01; E-05; E-33; G-18; G-24; G-25; G-30 | R70: Alta | S70: 16 | T70: =CHOOSE(MONTH(X70),"Ene","Feb","Mar","Abr","May","Jun","Jul","Ago","Sep","Oct","Nov","Dic")&" "&YEAR(X70) -> Nov 2026 | W70: Idea | X70: 46338 | Y70: =CHOOSE(WEEKDAY(X70,2),"lunes","martes","miércoles","jueves","viernes","sábado","domingo") -> jueves | Z70: =INT((X70-MIN($X$2:$X$101))/7)+1 -> 4 | AA70: =IF(X70=MIN($X$2:$X$101),"Lanzamiento","Calendario semanal") -> Calendario semanal
A71: G-20 | B71: Guía práctica | C71: Cómo dar seguimiento a tus leads con IA y automatización | D71: IA aplicada al marketing | E71: seguimiento de leads con IA | F71: Informacional | G71: MOFU | H71: Posicionar «seguimiento de leads con IA» (búsqueda "cómo hacerlo") y convertir visitas en leads con el PDF descargable. | I71: General | J71: México + EE.UU. | K71: Re-redacción 2026 | L71: https://www.continentalmedia.com.mx/2025/08/como-dar-seguimiento-a-leads-mediante-inteligencia-artificial/ | N71: Actualizar con agentes de IA y CRM | O71: Flujo de seguimiento de leads (diagrama editable) | P71: IA aplicada a marketing y comunicación | Q71: E-04; G-21; G-23; G-42 | R71: Alta | S71: 18 | T71: =CHOOSE(MONTH(X71),"Ene","Feb","Mar","Abr","May","Jun","Jul","Ago","Sep","Oct","Nov","Dic")&" "&YEAR(X71) -> Nov 2026 | W71: Idea | X71: 46345 | Y71: =CHOOSE(WEEKDAY(X71,2),"lunes","martes","miércoles","jueves","viernes","sábado","domingo") -> jueves | Z71: =INT((X71-MIN($X$2:$X$101))/7)+1 -> 5 | AA71: =IF(X71=MIN($X$2:$X$101),"Lanzamiento","Calendario semanal") -> Calendario semanal
A72: G-21 | B72: Guía práctica | C72: Cómo implementar un asistente de IA en WhatsApp Business paso a paso | D72: IA aplicada al marketing | E72: WhatsApp Business API | F72: Comercial | G72: MOFU | H72: Capturar demanda de evaluación en «WhatsApp Business API», generar leads con el PDF y empujar ia aplicada a marketing y comunicación. | I72: General | J72: México + EE.UU. | K72: Nuevo | N72: Operativo del tema E-04: alcance, guion y métricas | O72: Checklist de implementación de asistente en WhatsApp | P72: IA aplicada a marketing y comunicación | Q72: E-02; E-04; G-15; G-20; G-23 | R72: Alta | S72: 20 | T72: =CHOOSE(MONTH(X72),"Ene","Feb","Mar","Abr","May","Jun","Jul","Ago","Sep","Oct","Nov","Dic")&" "&YEAR(X72) -> Nov 2026 | W72: Idea | X72: 46352 | Y72: =CHOOSE(WEEKDAY(X72,2),"lunes","martes","miércoles","jueves","viernes","sábado","domingo") -> jueves | Z72: =INT((X72-MIN($X$2:$X$101))/7)+1 -> 6 | AA72: =IF(X72=MIN($X$2:$X$101),"Lanzamiento","Calendario semanal") -> Calendario semanal
A73: G-22 | B73: Guía práctica | C73: Herramientas de IA para marketing: cómo elegir y armar tu stack | D73: IA aplicada al marketing | E73: herramientas de IA para marketing | F73: Informacional | G73: MOFU | H73: Posicionar «herramientas de IA para marketing» (búsqueda "cómo hacerlo") y convertir visitas en leads con el PDF descargable. | I73: General | J73: México + EE.UU. | K73: Re-redacción 2026 | L73: https://www.continentalmedia.com.mx/2025/07/como-aprovechar-la-inteligencia-artificial-en-el-marketing-6-herramientas-que-transformaran-tu-negocio/ | M73: https://www.continentalmedia.com.mx/2014/10/herramientas-marketing-digital/ | N73: Actualizar el listado de 6 herramientas de 2025 | O73: Matriz comparativa de herramientas de IA | P73: IA aplicada a marketing y comunicación | Q73: E-01; E-07; G-18 | R73: Media | S73: 66 | T73: =CHOOSE(MONTH(X73),"Ene","Feb","Mar","Abr","May","Jun","Jul","Ago","Sep","Oct","Nov","Dic")&" "&YEAR(X73) -> May 2027 | W73: Idea | X73: 46513 | Y73: =CHOOSE(WEEKDAY(X73,2),"lunes","martes","miércoles","jueves","viernes","sábado","domingo") -> jueves | Z73: =INT((X73-MIN($X$2:$X$101))/7)+1 -> 29 | AA73: =IF(X73=MIN($X$2:$X$101),"Lanzamiento","Calendario semanal") -> Calendario semanal
A74: G-23 | B74: Guía práctica | C74: Cómo combinar CRM, automatización y lealtad sin perder el trato humano | D74: IA aplicada al marketing | E74: CRM para pymes | F74: Informacional | G74: MOFU | H74: Posicionar «CRM para pymes» (búsqueda "cómo hacerlo") y convertir visitas en leads con el PDF descargable. | I74: General | J74: México + EE.UU. | K74: Re-redacción 2026 | L74: https://www.continentalmedia.com.mx/2013/07/sabes-lo-que-significa-crm/ | M74: https://www.continentalmedia.com.mx/2015/04/estrategias-programa-de-lealtad/ | N74: Actualizar CRM, programas de lealtad y automatización | O74: Guía de arranque de CRM para pymes | P74: IA aplicada a marketing y comunicación | Q74: E-02; E-37; G-20; G-21 | R74: Baja | S74: 94 | T74: =CHOOSE(MONTH(X74),"Ene","Feb","Mar","Abr","May","Jun","Jul","Ago","Sep","Oct","Nov","Dic")&" "&YEAR(X74) -> Ago 2027 | W74: Idea | X74: 46611 | Y74: =CHOOSE(WEEKDAY(X74,2),"lunes","martes","miércoles","jueves","viernes","sábado","domingo") -> jueves | Z74: =INT((X74-MIN($X$2:$X$101))/7)+1 -> 43 | AA74: =IF(X74=MIN($X$2:$X$101),"Lanzamiento","Calendario semanal") -> Calendario semanal
A75: G-24 | B75: Guía práctica | C75: Cómo optimizar tu contenido para buscadores con IA (GEO) | D75: IA aplicada al marketing | E75: optimización para motores generativos | F75: Informacional | G75: MOFU | H75: Posicionar «optimización para motores generativos» (búsqueda "cómo hacerlo") y convertir visitas en leads con el PDF descargable. | I75: General | J75: México + EE.UU. | K75: Nuevo | N75: Checklist práctico de E-03 | O75: Checklist de optimización GEO/SEO | P75: IA aplicada a marketing y comunicación | Q75: E-03; G-19; G-35; G-36 | R75: Alta | S75: 22 | T75: =CHOOSE(MONTH(X75),"Ene","Feb","Mar","Abr","May","Jun","Jul","Ago","Sep","Oct","Nov","Dic")&" "&YEAR(X75) -> Dic 2026 | W75: Idea | X75: 46359 | Y75: =CHOOSE(WEEKDAY(X75,2),"lunes","martes","miércoles","jueves","viernes","sábado","domingo") -> jueves | Z75: =INT((X75-MIN($X$2:$X$101))/7)+1 -> 7 | AA75: =IF(X75=MIN($X$2:$X$101),"Lanzamiento","Calendario semanal") -> Calendario semanal
A76: G-25 | B76: Guía práctica | C76: Cómo crear una política de uso de IA para tu empresa | D76: IA aplicada al marketing | E76: política de uso de inteligencia artificial | F76: Informacional | G76: MOFU | H76: Posicionar «política de uso de inteligencia artificial» (búsqueda "cómo hacerlo") y convertir visitas en leads con el PDF descargable. | I76: General | J76: México + EE.UU. | K76: Nuevo | N76: Plantilla práctica de E-06 | O76: Plantilla de política de uso de IA | P76: IA aplicada a marketing y comunicación | Q76: E-06; G-19 | R76: Media | S76: 68 | T76: =CHOOSE(MONTH(X76),"Ene","Feb","Mar","Abr","May","Jun","Jul","Ago","Sep","Oct","Nov","Dic")&" "&YEAR(X76) -> May 2027 | W76: Idea | X76: 46520 | Y76: =CHOOSE(WEEKDAY(X76,2),"lunes","martes","miércoles","jueves","viernes","sábado","domingo") -> jueves | Z76: =INT((X76-MIN($X$2:$X$101))/7)+1 -> 30 | AA76: =IF(X76=MIN($X$2:$X$101),"Lanzamiento","Calendario semanal") -> Calendario semanal
A77: G-26 | B77: Guía práctica | C77: Cómo crear el manual de identidad de tu marca | D77: Branding, diseño y creatividad | E77: manual de identidad de marca | F77: Comercial | G77: MOFU | H77: Capturar demanda de evaluación en «manual de identidad de marca», generar leads con el PDF y empujar branding, identidad y diseño gráfico. | I77: General | J77: México + EE.UU. | K77: Nuevo | N77: Qué incluye un manual y cómo usarlo | O77: Checklist de manual de identidad de marca | P77: Branding, identidad y diseño gráfico | Q77: E-23; E-24; G-04; G-27; G-28; G-29; G-30 | R77: Alta | S77: 24 | T77: =CHOOSE(MONTH(X77),"Ene","Feb","Mar","Abr","May","Jun","Jul","Ago","Sep","Oct","Nov","Dic")&" "&YEAR(X77) -> Dic 2026 | W77: Idea | X77: 46366 | Y77: =CHOOSE(WEEKDAY(X77,2),"lunes","martes","miércoles","jueves","viernes","sábado","domingo") -> jueves | Z77: =INT((X77-MIN($X$2:$X$101))/7)+1 -> 8 | AA77: =IF(X77=MIN($X$2:$X$101),"Lanzamiento","Calendario semanal") -> Calendario semanal
A78: G-27 | B78: Guía práctica | C78: Cómo nombrar tu marca: método y errores a evitar | D78: Branding, diseño y creatividad | E78: cómo nombrar una marca | F78: Informacional | G78: MOFU | H78: Posicionar «cómo nombrar una marca» (búsqueda "cómo hacerlo") y convertir visitas en leads con el PDF descargable. | I78: Emprendedores y pymes | J78: México | K78: Re-redacción 2026 | L78: https://www.continentalmedia.com.mx/2016/08/7-tips-para-nombrar-tu-marca/ | N78: Registro de marca en México (IMPI) y dominios | O78: Hoja de evaluación de nombres de marca | P78: Branding, identidad y diseño gráfico | Q78: E-23; G-26; G-28 | R78: Baja | S78: 96 | T78: =CHOOSE(MONTH(X78),"Ene","Feb","Mar","Abr","May","Jun","Jul","Ago","Sep","Oct","Nov","Dic")&" "&YEAR(X78) -> Ago 2027 | W78: Idea | X78: 46618 | Y78: =CHOOSE(WEEKDAY(X78,2),"lunes","martes","miércoles","jueves","viernes","sábado","domingo") -> jueves | Z78: =INT((X78-MIN($X$2:$X$101))/7)+1 -> 44 | AA78: =IF(X78=MIN($X$2:$X$101),"Lanzamiento","Calendario semanal") -> Calendario semanal
A79: G-28 | B79: Guía práctica | C79: Cómo diseñar un logotipo que funcione: brief y errores comunes | D79: Branding, diseño y creatividad | E79: cómo diseñar un logotipo | F79: Comercial | G79: MOFU | H79: Capturar demanda de evaluación en «cómo diseñar un logotipo», generar leads con el PDF y empujar branding, identidad y diseño gráfico. | I79: General | J79: México + EE.UU. | K79: Re-redacción 2026 | L79: https://www.continentalmedia.com.mx/2015/08/6-secretos-para-diseñar-un-logotipo-exitoso/ | N79: Archivos, versiones y usos | O79: Brief de logotipo y checklist de entregables | P79: Branding, identidad y diseño gráfico | Q79: E-24; E-29; G-26; G-27 | R79: Media | S79: 70 | T79: =CHOOSE(MONTH(X79),"Ene","Feb","Mar","Abr","May","Jun","Jul","Ago","Sep","Oct","Nov","Dic")&" "&YEAR(X79) -> May 2027 | W79: Idea | X79: 46527 | Y79: =CHOOSE(WEEKDAY(X79,2),"lunes","martes","miércoles","jueves","viernes","sábado","domingo") -> jueves | Z79: =INT((X79-MIN($X$2:$X$101))/7)+1 -> 31 | AA79: =IF(X79=MIN($X$2:$X$101),"Lanzamiento","Calendario semanal") -> Calendario semanal
A80: G-29 | B80: Guía práctica | C80: Rebranding: checklist para decidir y ejecutar el cambio | D80: Branding, diseño y creatividad | E80: rebranding checklist | F80: Informacional | G80: MOFU | H80: Posicionar «rebranding checklist» (búsqueda "cómo hacerlo") y convertir visitas en leads con el PDF descargable. | I80: General | J80: México + EE.UU. | K80: Nuevo | N80: Complementa el artículo 2026/08 sobre cuándo hacer rebranding | O80: Checklist de rebranding | P80: Branding, identidad y diseño gráfico | Q80: E-23; G-26; G-30 | R80: Media | S80: 72 | T80: =CHOOSE(MONTH(X80),"Ene","Feb","Mar","Abr","May","Jun","Jul","Ago","Sep","Oct","Nov","Dic")&" "&YEAR(X80) -> May 2027 | W80: Idea | X80: 46534 | Y80: =CHOOSE(WEEKDAY(X80,2),"lunes","martes","miércoles","jueves","viernes","sábado","domingo") -> jueves | Z80: =INT((X80-MIN($X$2:$X$101))/7)+1 -> 32 | AA80: =IF(X80=MIN($X$2:$X$101),"Lanzamiento","Calendario semanal") -> Calendario semanal
A81: G-30 | B81: Guía práctica | C81: Cómo definir el tono de voz y los mensajes clave de tu marca | D81: Branding, diseño y creatividad | E81: tono de voz de marca | F81: Informacional | G81: MOFU | H81: Posicionar «tono de voz de marca» (búsqueda "cómo hacerlo") y convertir visitas en leads con el PDF descargable. | I81: General | J81: México + EE.UU. | K81: Nuevo | N81: Ejemplos de tono y documento de mensajes | O81: Plantilla de tono de voz y mensajes clave | P81: Branding, identidad y diseño gráfico | Q81: E-05; E-12; E-19; E-23; E-26; E-35; G-19; G-26; G-29 | R81: Media | S81: 74 | T81: =CHOOSE(MONTH(X81),"Ene","Feb","Mar","Abr","May","Jun","Jul","Ago","Sep","Oct","Nov","Dic")&" "&YEAR(X81) -> Jun 2027 | W81: Idea | X81: 46541 | Y81: =CHOOSE(WEEKDAY(X81,2),"lunes","martes","miércoles","jueves","viernes","sábado","domingo") -> jueves | Z81: =INT((X81-MIN($X$2:$X$101))/7)+1 -> 33 | AA81: =IF(X81=MIN($X$2:$X$101),"Lanzamiento","Calendario semanal") -> Calendario semanal
A82: G-31 | B82: Guía práctica | C82: Cómo escribir un comunicado de prensa que sí se publica | D82: Relaciones públicas y comunicación | E82: cómo hacer un comunicado de prensa | F82: Comercial | G82: MOFU | H82: Capturar demanda de evaluación en «cómo hacer un comunicado de prensa», generar leads con el PDF y empujar relaciones públicas y comunicación corporativa. | I82: General | J82: México + EE.UU. | K82: Nuevo | N82: Estructura, distribución y seguimiento a medios | O82: Plantilla de comunicado de prensa | P82: Relaciones públicas y comunicación corporativa | Q82: E-30; E-34; G-32; G-34 | R82: Alta | S82: 26 | T82: =CHOOSE(MONTH(X82),"Ene","Feb","Mar","Abr","May","Jun","Jul","Ago","Sep","Oct","Nov","Dic")&" "&YEAR(X82) -> Dic 2026 | W82: Idea | X82: 46373 | Y82: =CHOOSE(WEEKDAY(X82,2),"lunes","martes","miércoles","jueves","viernes","sábado","domingo") -> jueves | Z82: =INT((X82-MIN($X$2:$X$101))/7)+1 -> 9 | AA82: =IF(X82=MIN($X$2:$X$101),"Lanzamiento","Calendario semanal") -> Calendario semanal
A83: G-32 | B83: Guía práctica | C83: Cómo armar un plan de relaciones públicas paso a paso | D83: Relaciones públicas y comunicación | E83: plan de relaciones públicas | F83: Informacional | G83: MOFU | H83: Posicionar «plan de relaciones públicas» (búsqueda "cómo hacerlo") y convertir visitas en leads con el PDF descargable. | I83: General | J83: México + EE.UU. | K83: Re-redacción 2026 | L83: https://www.continentalmedia.com.mx/2014/08/plan-de-relaciones-publicas/ | N83: Actualizar con digital PR y medición | O83: Plantilla de plan de relaciones públicas | P83: Relaciones públicas y comunicación corporativa | Q83: E-30; G-31; G-33 | R83: Media | S83: 76 | T83: =CHOOSE(MONTH(X83),"Ene","Feb","Mar","Abr","May","Jun","Jul","Ago","Sep","Oct","Nov","Dic")&" "&YEAR(X83) -> Jun 2027 | W83: Idea | X83: 46548 | Y83: =CHOOSE(WEEKDAY(X83,2),"lunes","martes","miércoles","jueves","viernes","sábado","domingo") -> jueves | Z83: =INT((X83-MIN($X$2:$X$101))/7)+1 -> 34 | AA83: =IF(X83=MIN($X$2:$X$101),"Lanzamiento","Calendario semanal") -> Calendario semanal
A84: G-33 | B84: Guía práctica | C84: Protocolo de comunicación de crisis: qué hacer en las primeras 24 horas | D84: Relaciones públicas y comunicación | E84: plan de comunicación de crisis | F84: Comercial | G84: MOFU | H84: Capturar demanda de evaluación en «plan de comunicación de crisis», generar leads con el PDF y empujar relaciones públicas y comunicación corporativa. | I84: General | J84: México + EE.UU. | K84: Nuevo | N84: Roles, mensajes y comités | O84: Manual de crisis (protocolo editable) | P84: Relaciones públicas y comunicación corporativa | Q84: E-30; E-31; G-32; G-34 | R84: Alta | S84: 28 | T84: =CHOOSE(MONTH(X84),"Ene","Feb","Mar","Abr","May","Jun","Jul","Ago","Sep","Oct","Nov","Dic")&" "&YEAR(X84) -> Dic 2026 | W84: Idea | X84: 46380 | Y84: =CHOOSE(WEEKDAY(X84,2),"lunes","martes","miércoles","jueves","viernes","sábado","domingo") -> jueves | Z84: =INT((X84-MIN($X$2:$X$101))/7)+1 -> 10 | AA84: =IF(X84=MIN($X$2:$X$101),"Lanzamiento","Calendario semanal") -> Calendario semanal
A85: G-34 | B85: Guía práctica | C85: Cómo preparar a un vocero para entrevistas y presentaciones | D85: Relaciones públicas y comunicación | E85: vocero media training | F85: Informacional | G85: MOFU | H85: Posicionar «vocero media training» (búsqueda "cómo hacerlo") y convertir visitas en leads con el PDF descargable. | I85: Directivos y voceros | J85: México + EE.UU. | K85: Re-redacción 2026 | L85: https://www.continentalmedia.com.mx/2014/05/10-errores-al-hablar-en-publico/ | M85: https://www.continentalmedia.com.mx/2014/05/que-hacer-durante-una-reunion-con-un-cliente/ https://www.continentalmedia.com.mx/2015/10/5-tips-para-convencer-a-tus-clientes/ | N85: Reunir contenidos de hablar en público y reuniones con clientes | O85: Guía de preparación de vocero | P85: Relaciones públicas y comunicación corporativa | Q85: E-32; E-34; G-31; G-33 | R85: Media | S85: 78 | T85: =CHOOSE(MONTH(X85),"Ene","Feb","Mar","Abr","May","Jun","Jul","Ago","Sep","Oct","Nov","Dic")&" "&YEAR(X85) -> Jun 2027 | W85: Idea | X85: 46555 | Y85: =CHOOSE(WEEKDAY(X85,2),"lunes","martes","miércoles","jueves","viernes","sábado","domingo") -> jueves | Z85: =INT((X85-MIN($X$2:$X$101))/7)+1 -> 35 | AA85: =IF(X85=MIN($X$2:$X$101),"Lanzamiento","Calendario semanal") -> Calendario semanal
A86: G-35 | B86: Guía práctica | C86: Checklist SEO para migrar o lanzar un sitio web sin perder posicionamiento | D86: Web, SEO y publicidad digital | E86: migración de sitio web SEO | F86: Comercial | G86: MOFU | H86: Capturar demanda de evaluación en «migración de sitio web SEO», generar leads con el PDF y empujar diseño y desarrollo web, seo y publicidad digital. | I86: General | J86: México + EE.UU. | K86: Nuevo | N86: Conecta con el proyecto de redirecciones; caso real | O86: Checklist SEO de migración de sitio | P86: Diseño y desarrollo web, SEO y publicidad digital | Q86: E-03; E-38; E-39; E-40; G-24; G-36; G-37; G-40; G-43 | R86: Alta | S86: 30 | T86: =CHOOSE(MONTH(X86),"Ene","Feb","Mar","Abr","May","Jun","Jul","Ago","Sep","Oct","Nov","Dic")&" "&YEAR(X86) -> Dic 2026 | W86: Idea | X86: 46387 | Y86: =CHOOSE(WEEKDAY(X86,2),"lunes","martes","miércoles","jueves","viernes","sábado","domingo") -> jueves | Z86: =INT((X86-MIN($X$2:$X$101))/7)+1 -> 11 | AA86: =IF(X86=MIN($X$2:$X$101),"Lanzamiento","Calendario semanal") -> Calendario semanal
A87: G-36 | B87: Guía práctica | C87: SEO para tu blog: guía práctica 2026 | D87: Web, SEO y publicidad digital | E87: SEO para blog | F87: Informacional | G87: MOFU | H87: Posicionar «SEO para blog» (búsqueda "cómo hacerlo") y convertir visitas en leads con el PDF descargable. | I87: General | J87: México + EE.UU. | K87: Re-redacción 2026 | L87: https://www.continentalmedia.com.mx/2022/08/estrategias-basicas-de-seo-para-tu-blog/ | N87: Actualizar estrategia básica; añadir clusters e IA | O87: Plantilla de plan de contenidos SEO | P87: Diseño y desarrollo web, SEO y publicidad digital | Q87: E-03; E-22; G-24; G-35 | R87: Alta | S87: 32 | T87: =CHOOSE(MONTH(X87),"Ene","Feb","Mar","Abr","May","Jun","Jul","Ago","Sep","Oct","Nov","Dic")&" "&YEAR(X87) -> Ene 2027 | W87: Idea | X87: 46394 | Y87: =CHOOSE(WEEKDAY(X87,2),"lunes","martes","miércoles","jueves","viernes","sábado","domingo") -> jueves | Z87: =INT((X87-MIN($X$2:$X$101))/7)+1 -> 12 | AA87: =IF(X87=MIN($X$2:$X$101),"Lanzamiento","Calendario semanal") -> Calendario semanal
A88: G-37 | B88: Guía práctica | C88: SEO local: cómo aparecer en Google Maps y búsquedas "cerca de mí" | D88: Web, SEO y publicidad digital | E88: SEO local | F88: Comercial | G88: BOFU | H88: Capturar demanda de evaluación en «SEO local», generar leads con el PDF y empujar diseño y desarrollo web, seo y publicidad digital. | I88: Negocios locales | J88: México | K88: Re-redacción 2026 | L88: https://www.continentalmedia.com.mx/2013/07/sabes-lo-que-es-geomarketing-y-lo-que-puedes-hacer-con-el/ | N88: Google Business Profile, reseñas y geomarketing | O88: Checklist de Google Business Profile | P88: Diseño y desarrollo web, SEO y publicidad digital | Q88: E-38; E-48; E-50; G-35; G-38; G-49; G-50 | R88: Alta | S88: 34 | T88: =CHOOSE(MONTH(X88),"Ene","Feb","Mar","Abr","May","Jun","Jul","Ago","Sep","Oct","Nov","Dic")&" "&YEAR(X88) -> Ene 2027 | W88: Idea | X88: 46401 | Y88: =CHOOSE(WEEKDAY(X88,2),"lunes","martes","miércoles","jueves","viernes","sábado","domingo") -> jueves | Z88: =INT((X88-MIN($X$2:$X$101))/7)+1 -> 13 | AA88: =IF(X88=MIN($X$2:$X$101),"Lanzamiento","Calendario semanal") -> Calendario semanal
A89: G-38 | B89: Guía práctica | C89: Cómo anunciarte en Google Ads desde cero | D89: Web, SEO y publicidad digital | E89: cómo anunciarse en Google Ads | F89: Comercial | G89: MOFU | H89: Capturar demanda de evaluación en «cómo anunciarse en Google Ads», generar leads con el PDF y empujar diseño y desarrollo web, seo y publicidad digital. | I89: General | J89: México + EE.UU. | K89: Re-redacción 2026 | L89: https://www.continentalmedia.com.mx/2014/07/conoces-la-manera-de-anunciarte-a-traves-de-google/ | M89: https://www.continentalmedia.com.mx/2016/04/10-alternativas-de-publicidad-de-paga-en-internet/ | N89: Estructura de cuenta, presupuesto y alternativas de pago | O89: Guía de arranque en Google Ads | P89: Diseño y desarrollo web, SEO y publicidad digital | Q89: E-17; E-36; G-37; G-39; G-43 | R89: Alta | S89: 36 | T89: =CHOOSE(MONTH(X89),"Ene","Feb","Mar","Abr","May","Jun","Jul","Ago","Sep","Oct","Nov","Dic")&" "&YEAR(X89) -> Ene 2027 | W89: Idea | X89: 46408 | Y89: =CHOOSE(WEEKDAY(X89,2),"lunes","martes","miércoles","jueves","viernes","sábado","domingo") -> jueves | Z89: =INT((X89-MIN($X$2:$X$101))/7)+1 -> 14 | AA89: =IF(X89=MIN($X$2:$X$101),"Lanzamiento","Calendario semanal") -> Calendario semanal
A90: G-39 | B90: Guía práctica | C90: Cómo optimizar tus anuncios de Meta Ads en 2026 | D90: Web, SEO y publicidad digital | E90: optimizar anuncios de Facebook | F90: Informacional | G90: MOFU | H90: Posicionar «optimizar anuncios de Facebook» (búsqueda "cómo hacerlo") y convertir visitas en leads con el PDF descargable. | I90: General | J90: México + EE.UU. | K90: Re-redacción 2026 | L90: https://www.continentalmedia.com.mx/2024/01/10-tips-para-optimizar-tus-ads-de-facebook-en-2024/ | N90: Actualizar Advantage+, creativos y medición | O90: Checklist de optimización de Meta Ads | P90: Diseño y desarrollo web, SEO y publicidad digital | Q90: E-36; G-07; G-15; G-38; G-40; G-43 | R90: Alta | S90: 38 | T90: =CHOOSE(MONTH(X90),"Ene","Feb","Mar","Abr","May","Jun","Jul","Ago","Sep","Oct","Nov","Dic")&" "&YEAR(X90) -> Ene 2027 | W90: Idea | X90: 46415 | Y90: =CHOOSE(WEEKDAY(X90,2),"lunes","martes","miércoles","jueves","viernes","sábado","domingo") -> jueves | Z90: =INT((X90-MIN($X$2:$X$101))/7)+1 -> 15 | AA90: =IF(X90=MIN($X$2:$X$101),"Lanzamiento","Calendario semanal") -> Calendario semanal
A91: G-40 | B91: Guía práctica | C91: Cómo crear una landing page que convierte | D91: Web, SEO y publicidad digital | E91: landing page | F91: Informacional | G91: MOFU | H91: Posicionar «landing page» (búsqueda "cómo hacerlo") y convertir visitas en leads con el PDF descargable. | I91: General | J91: México + EE.UU. | K91: Nuevo | N91: Estructura, copy y pruebas A/B | O91: Checklist de landing page | P91: Diseño y desarrollo web, SEO y publicidad digital | Q91: E-20; E-29; E-38; E-39; E-40; E-50; G-03; G-35; G-39; G-44 | R91: Alta | S91: 40 | T91: =CHOOSE(MONTH(X91),"Ene","Feb","Mar","Abr","May","Jun","Jul","Ago","Sep","Oct","Nov","Dic")&" "&YEAR(X91) -> Feb 2027 | W91: Idea | X91: 46422 | Y91: =CHOOSE(WEEKDAY(X91,2),"lunes","martes","miércoles","jueves","viernes","sábado","domingo") -> jueves | Z91: =INT((X91-MIN($X$2:$X$101))/7)+1 -> 16 | AA91: =IF(X91=MIN($X$2:$X$101),"Lanzamiento","Calendario semanal") -> Calendario semanal
A92: G-41 | B92: Guía práctica | C92: Lead magnets: ideas y cómo crear uno que sí capte clientes | D92: Web, SEO y publicidad digital | E92: lead magnet | F92: Informacional | G92: MOFU | H92: Posicionar «lead magnet» (búsqueda "cómo hacerlo") y convertir visitas en leads con el PDF descargable. | I92: General | J92: México + EE.UU. | K92: Re-redacción 2026 | L92: https://www.continentalmedia.com.mx/2023/03/atrae-a-mas-clientes-con-estas-5-ideas-de-lead-magnets/ | N92: Actualizar ejemplos; formatos PDF, calculadora, plantilla | O92: Plantilla de lead magnet | P92: Diseño y desarrollo web, SEO y publicidad digital | Q92: E-22; G-03; G-42; G-46 | R92: Media | S92: 80 | T92: =CHOOSE(MONTH(X92),"Ene","Feb","Mar","Abr","May","Jun","Jul","Ago","Sep","Oct","Nov","Dic")&" "&YEAR(X92) -> Jun 2027 | W92: Idea | X92: 46562 | Y92: =CHOOSE(WEEKDAY(X92,2),"lunes","martes","miércoles","jueves","viernes","sábado","domingo") -> jueves | Z92: =INT((X92-MIN($X$2:$X$101))/7)+1 -> 36 | AA92: =IF(X92=MIN($X$2:$X$101),"Lanzamiento","Calendario semanal") -> Calendario semanal
A93: G-42 | B93: Guía práctica | C93: Email marketing 2026: estrategia, automatizaciones y entregabilidad | D93: Web, SEO y publicidad digital | E93: email marketing | F93: Informacional | G93: MOFU | H93: Posicionar «email marketing» (búsqueda "cómo hacerlo") y convertir visitas en leads con el PDF descargable. | I93: General | J93: México + EE.UU. | K93: Re-redacción 2026 | L93: https://www.continentalmedia.com.mx/2012/12/conoce-el-funcionamiento-del-e-mail-marketing/ | M93: https://www.continentalmedia.com.mx/2014/11/mailing-mensajeria-negocio/ | N93: Fusionar posts de email y mailing; añadir automatización | O93: Calendario y flujos de email marketing | P93: Diseño y desarrollo web, SEO y publicidad digital | Q93: E-37; G-03; G-20; G-41 | R93: Media | S93: 82 | T93: =CHOOSE(MONTH(X93),"Ene","Feb","Mar","Abr","May","Jun","Jul","Ago","Sep","Oct","Nov","Dic")&" "&YEAR(X93) -> Jul 2027 | W93: Idea | X93: 46569 | Y93: =CHOOSE(WEEKDAY(X93,2),"lunes","martes","miércoles","jueves","viernes","sábado","domingo") -> jueves | Z93: =INT((X93-MIN($X$2:$X$101))/7)+1 -> 37 | AA93: =IF(X93=MIN($X$2:$X$101),"Lanzamiento","Calendario semanal") -> Calendario semanal
A94: G-43 | B94: Guía práctica | C94: Cómo configurar Google Analytics 4 y medir lo que importa | D94: Web, SEO y publicidad digital | E94: Google Analytics 4 | F94: Informacional | G94: MOFU | H94: Posicionar «Google Analytics 4» (búsqueda "cómo hacerlo") y convertir visitas en leads con el PDF descargable. | I94: General | J94: México + EE.UU. | K94: Nuevo | N94: Eventos, conversiones y reportes | O94: Checklist de configuración de GA4 | P94: Diseño y desarrollo web, SEO y publicidad digital | Q94: E-36; E-37; G-05; G-35; G-38; G-39; G-44 | R94: Alta | S94: 42 | T94: =CHOOSE(MONTH(X94),"Ene","Feb","Mar","Abr","May","Jun","Jul","Ago","Sep","Oct","Nov","Dic")&" "&YEAR(X94) -> Feb 2027 | W94: Idea | X94: 46429 | Y94: =CHOOSE(WEEKDAY(X94,2),"lunes","martes","miércoles","jueves","viernes","sábado","domingo") -> jueves | Z94: =INT((X94-MIN($X$2:$X$101))/7)+1 -> 17 | AA94: =IF(X94=MIN($X$2:$X$101),"Lanzamiento","Calendario semanal") -> Calendario semanal
A95: G-44 | B95: Guía práctica | C95: Cómo vender en Amazon y Mercado Libre desde México | D95: Web, SEO y publicidad digital | E95: cómo vender en Amazon México | F95: Informacional | G95: MOFU | H95: Posicionar «cómo vender en Amazon México» (búsqueda "cómo hacerlo") y convertir visitas en leads con el PDF descargable. | I95: E-commerce y retail | J95: México | K95: Re-redacción 2026 | L95: https://www.continentalmedia.com.mx/2023/04/guia-rapida-para-vender-tus-productos-en-amazon/ | M95: https://www.continentalmedia.com.mx/2021/11/marketplace-que-es-y-como-puedo-adaptarlo-a-mi-negocio/ https://www.continentalmedia.com.mx/2023/02/live-shopping-la-nueva-forma-de-vender-en-internet/ https://www.continentalmedia.com.mx/2013/11/el-web-y-showrooming-amigos-o-enemigos-de-tu-negocio/ | N95: Marketplaces, live shopping y estrategia omnicanal | O95: Checklist de lanzamiento en marketplaces | P95: Diseño y desarrollo web, SEO y publicidad digital | Q95: G-40; G-43 | R95: Baja | S95: 98 | T95: =CHOOSE(MONTH(X95),"Ene","Feb","Mar","Abr","May","Jun","Jul","Ago","Sep","Oct","Nov","Dic")&" "&YEAR(X95) -> Ago 2027 | W95: Idea | X95: 46625 | Y95: =CHOOSE(WEEKDAY(X95,2),"lunes","martes","miércoles","jueves","viernes","sábado","domingo") -> jueves | Z95: =INT((X95-MIN($X$2:$X$101))/7)+1 -> 45 | AA95: =IF(X95=MIN($X$2:$X$101),"Lanzamiento","Calendario semanal") -> Calendario semanal
A96: G-45 | B96: Guía práctica | C96: Cómo grabar videos profesionales con tu celular | D96: Video y fotografía | E96: grabar video con celular | F96: Informacional | G96: MOFU | H96: Posicionar «grabar video con celular» (búsqueda "cómo hacerlo") y convertir visitas en leads con el PDF descargable. | I96: General | J96: México + EE.UU. | K96: Re-redacción 2026 | L96: https://www.continentalmedia.com.mx/2020/09/grabar-videos-profesionales-desde-casa/ | N96: Equipo, luz, audio y edición con IA | O96: Checklist de producción de video con celular | P96: Producción de video y fotografía | Q96: E-41; E-42; G-46; G-47 | R96: Media | S96: 84 | T96: =CHOOSE(MONTH(X96),"Ene","Feb","Mar","Abr","May","Jun","Jul","Ago","Sep","Oct","Nov","Dic")&" "&YEAR(X96) -> Jul 2027 | W96: Idea | X96: 46576 | Y96: =CHOOSE(WEEKDAY(X96,2),"lunes","martes","miércoles","jueves","viernes","sábado","domingo") -> jueves | Z96: =INT((X96-MIN($X$2:$X$101))/7)+1 -> 38 | AA96: =IF(X96=MIN($X$2:$X$101),"Lanzamiento","Calendario semanal") -> Calendario semanal
A97: G-46 | B97: Guía práctica | C97: Cómo hacer un webinar o transmisión en vivo que convierta | D97: Video y fotografía | E97: cómo hacer un webinar | F97: Informacional | G97: MOFU | H97: Posicionar «cómo hacer un webinar» (búsqueda "cómo hacerlo") y convertir visitas en leads con el PDF descargable. | I97: General | J97: México + EE.UU. | K97: Re-redacción 2026 | L97: https://www.continentalmedia.com.mx/2022/07/10-pasos-para-crear-un-webinar/ | M97: https://www.continentalmedia.com.mx/2018/03/como-transmitir-un-evento-en-vivo-en-8-sencillos-pasos/ https://www.continentalmedia.com.mx/2018/12/como-convertir-en-compradores-a-los-leads-de-un-seminario-web/ https://www.continentalmedia.com.mx/2021/10/como-crear-un-curso-online-de-exito-parte-1/ https://www.continentalmedia.com.mx/2021/10/como-crear-un-curso-online-de-exito-parte-2/ | N97: Unifica webinar, transmisión en vivo y cursos online | O97: Guion y checklist de webinar | P97: Producción de video y fotografía | Q97: E-41; E-42; G-41; G-45 | R97: Media | S97: 86 | T97: =CHOOSE(MONTH(X97),"Ene","Feb","Mar","Abr","May","Jun","Jul","Ago","Sep","Oct","Nov","Dic")&" "&YEAR(X97) -> Jul 2027 | W97: Idea | X97: 46583 | Y97: =CHOOSE(WEEKDAY(X97,2),"lunes","martes","miércoles","jueves","viernes","sábado","domingo") -> jueves | Z97: =INT((X97-MIN($X$2:$X$101))/7)+1 -> 39 | AA97: =IF(X97=MIN($X$2:$X$101),"Lanzamiento","Calendario semanal") -> Calendario semanal
A98: G-47 | B98: Guía práctica | C98: Cómo planear una sesión de fotos de producto o gastronómica | D98: Video y fotografía | E98: sesión de fotos para restaurante | F98: Informacional | G98: MOFU | H98: Posicionar «sesión de fotos para restaurante» (búsqueda "cómo hacerlo") y convertir visitas en leads con el PDF descargable. | I98: Hoteles, restaurantes y retail | J98: México + EE.UU. | K98: Nuevo | N98: Shot list y preparación (hoteles, restaurantes) | O98: Shot list editable para sesión de fotos | P98: Producción de video y fotografía | Q98: E-43; E-48; G-45; G-49 | R98: Media | S98: 88 | T98: =CHOOSE(MONTH(X98),"Ene","Feb","Mar","Abr","May","Jun","Jul","Ago","Sep","Oct","Nov","Dic")&" "&YEAR(X98) -> Jul 2027 | W98: Idea | X98: 46590 | Y98: =CHOOSE(WEEKDAY(X98,2),"lunes","martes","miércoles","jueves","viernes","sábado","domingo") -> jueves | Z98: =INT((X98-MIN($X$2:$X$101))/7)+1 -> 40 | AA98: =IF(X98=MIN($X$2:$X$101),"Lanzamiento","Calendario semanal") -> Calendario semanal
A99: G-48 | B99: Guía práctica | C99: Cómo organizar un evento de lanzamiento de marca | D99: Eventos, medios y publicidad exterior | E99: cómo organizar un evento de lanzamiento | F99: Informacional | G99: MOFU | H99: Posicionar «cómo organizar un evento de lanzamiento» (búsqueda "cómo hacerlo") y convertir visitas en leads con el PDF descargable. | I99: General | J99: México + EE.UU. | K99: Nuevo | N99: Cronograma, proveedores y presupuesto | O99: Checklist y cronograma de evento | P99: Eventos, patrocinios y medios | Q99: E-28; E-44; E-46 | R99: Baja | S99: 100 | T99: =CHOOSE(MONTH(X99),"Ene","Feb","Mar","Abr","May","Jun","Jul","Ago","Sep","Oct","Nov","Dic")&" "&YEAR(X99) -> Sep 2027 | W99: Idea | X99: 46632 | Y99: =CHOOSE(WEEKDAY(X99,2),"lunes","martes","miércoles","jueves","viernes","sábado","domingo") -> jueves | Z99: =INT((X99-MIN($X$2:$X$101))/7)+1 -> 46 | AA99: =IF(X99=MIN($X$2:$X$101),"Lanzamiento","Calendario semanal") -> Calendario semanal
A100: G-49 | B100: Guía práctica | C100: Marketing para restaurantes: redes, menú, reservaciones y reseñas | D100: Marketing por industria y mercado | E100: marketing para restaurantes | F100: Informacional | G100: MOFU | H100: Posicionar «marketing para restaurantes» (búsqueda "cómo hacerlo") y convertir visitas en leads con el PDF descargable. | I100: Restaurantes | J100: México | K100: Nuevo | N100: Diseño de menú, contenido y SEO local | O100: Guía de marketing para restaurantes | P100: Marketing por industria y mercado hispano | Q100: E-48; G-09; G-37; G-47 | R100: Media | S100: 90 | T100: =CHOOSE(MONTH(X100),"Ene","Feb","Mar","Abr","May","Jun","Jul","Ago","Sep","Oct","Nov","Dic")&" "&YEAR(X100) -> Jul 2027 | W100: Idea | X100: 46597 | Y100: =CHOOSE(WEEKDAY(X100,2),"lunes","martes","miércoles","jueves","viernes","sábado","domingo") -> jueves | Z100: =INT((X100-MIN($X$2:$X$101))/7)+1 -> 41 | AA100: =IF(X100=MIN($X$2:$X$101),"Lanzamiento","Calendario semanal") -> Calendario semanal
...

Sheet Posts actuales
A1: URL actual | B1: Año | C1: Última modificación | D1: Decisión | E1: ID del tema destino | F1: Tema destino | G1: Qué hacer con la URL | H1: Motivo / nota | I1: Fecha de activación del 301
A2: https://www.continentalmedia.com.mx/2012/08/creative-interior-design/ | B2: 2012 | C2: 2019-10-29 | D2: Descartar | F2: =IF(E2="","",IFERROR(INDEX(Backlog!$C$2:$C$101,MATCH(E2,Backlog!$A$2:$A$101,0)),"")) | G2: 410, o 301 a /blog/ o a la categoría más cercana | H2: Contenido de coyuntura/curiosidad o fuera de los servicios actuales | I2: =IF(OR(D2="Consolidar",D2="Re-redactar v2026",D2="Actualizar v2026"),IFERROR(INDEX(Backlog!$X$2:$X$101,MATCH(E2,Backlog!$A$2:$A$101,0)),""),"")
A3: https://www.continentalmedia.com.mx/2012/08/marketing-olfativo/ | B3: 2012 | C3: 2019-10-29 | D3: Consolidar | E3: E-20 | F3: =IF(E3="","",IFERROR(INDEX(Backlog!$C$2:$C$101,MATCH(E3,Backlog!$A$2:$A$101,0)),"")) -> Neuromarketing y psicología del color: qué es ciencia y qué es mito | G3: 301 al nuevo artículo E-20 | H3: Contenido fusionado dentro del tema destino | I3: =IF(OR(D3="Consolidar",D3="Re-redactar v2026",D3="Actualizar v2026"),IFERROR(INDEX(Backlog!$X$2:$X$101,MATCH(E3,Backlog!$A$2:$A$101,0)),""),"") -> 46427
A4: https://www.continentalmedia.com.mx/2012/12/6-razones-pymes-usar-redes-sociales/ | B4: 2012 | C4: 2019-10-22 | D4: Consolidar | E4: E-10 | F4: =IF(E4="","",IFERROR(INDEX(Backlog!$C$2:$C$101,MATCH(E4,Backlog!$A$2:$A$101,0)),"")) -> Alcance orgánico en redes sociales: ¿sigue valiendo la pena para tu empresa? | G4: 301 al nuevo artículo E-10 | H4: Contenido fusionado dentro del tema destino | I4: =IF(OR(D4="Consolidar",D4="Re-redactar v2026",D4="Actualizar v2026"),IFERROR(INDEX(Backlog!$X$2:$X$101,MATCH(E4,Backlog!$A$2:$A$101,0)),""),"") -> 46378
A5: https://www.continentalmedia.com.mx/2012/12/campanas-exitosas-del-2012/ | B5: 2012 | C5: 2019-10-21 | D5: Descartar | F5: =IF(E5="","",IFERROR(INDEX(Backlog!$C$2:$C$101,MATCH(E5,Backlog!$A$2:$A$101,0)),"")) | G5: 410, o 301 a /blog/ o a la categoría más cercana | H5: Contenido de coyuntura/curiosidad o fuera de los servicios actuales | I5: =IF(OR(D5="Consolidar",D5="Re-redactar v2026",D5="Actualizar v2026"),IFERROR(INDEX(Backlog!$X$2:$X$101,MATCH(E5,Backlog!$A$2:$A$101,0)),""),"")
A6: https://www.continentalmedia.com.mx/2012/12/churros-creatividad/ | B6: 2012 | C6: 2019-10-21 | D6: Consolidar | E6: E-33 | F6: =IF(E6="","",IFERROR(INDEX(Backlog!$C$2:$C$101,MATCH(E6,Backlog!$A$2:$A$101,0)),"")) -> El proceso creativo en la era de la IA: cómo nacen hoy las buenas ideas | G6: 301 al nuevo artículo E-33 | H6: Contenido fusionado dentro del tema destino | I6: =IF(OR(D6="Consolidar",D6="Re-redactar v2026",D6="Actualizar v2026"),IFERROR(INDEX(Backlog!$X$2:$X$101,MATCH(E6,Backlog!$A$2:$A$101,0)),""),"") -> 46504
A7: https://www.continentalmedia.com.mx/2012/12/conoce-el-funcionamiento-del-e-mail-marketing/ | B7: 2012 | C7: 2019-10-22 | D7: Re-redactar v2026 | E7: G-42 | F7: =IF(E7="","",IFERROR(INDEX(Backlog!$C$2:$C$101,MATCH(E7,Backlog!$A$2:$A$101,0)),"")) -> Email marketing 2026: estrategia, automatizaciones y entregabilidad | G7: Publicar versión 2026; 301 de la URL antigua a la nueva (o conservar slug) | H7: Fusionar posts de email y mailing; añadir automatización | I7: =IF(OR(D7="Consolidar",D7="Re-redactar v2026",D7="Actualizar v2026"),IFERROR(INDEX(Backlog!$X$2:$X$101,MATCH(E7,Backlog!$A$2:$A$101,0)),""),"") -> 46569
A8: https://www.continentalmedia.com.mx/2012/12/es-necesario-ofrecer-una-buena-atencion-al-cliente-en-las-redes-sociales/ | B8: 2012 | C8: 2019-10-22 | D8: Re-redactar v2026 | E8: G-14 | F8: =IF(E8="","",IFERROR(INDEX(Backlog!$C$2:$C$101,MATCH(E8,Backlog!$A$2:$A$101,0)),"")) -> Cómo responder comentarios negativos y atender clientes en redes sociales | G8: Publicar versión 2026; 301 de la URL antigua a la nueva (o conservar slug) | H8: Protocolos de respuesta y tiempos | I8: =IF(OR(D8="Consolidar",D8="Re-redactar v2026",D8="Actualizar v2026"),IFERROR(INDEX(Backlog!$X$2:$X$101,MATCH(E8,Backlog!$A$2:$A$101,0)),""),"") -> 46499
A9: https://www.continentalmedia.com.mx/2012/12/inversion-publicitaria-en-medios-online/ | B9: 2012 | C9: 2019-10-21 | D9: Consolidar | E9: E-45 | F9: =IF(E9="","",IFERROR(INDEX(Backlog!$C$2:$C$101,MATCH(E9,Backlog!$A$2:$A$101,0)),"")) -> Radio, TV y medios masivos en un plan de medios omnicanal 2026 | G9: 301 al nuevo artículo E-45 | H9: Contenido fusionado dentro del tema destino | I9: =IF(OR(D9="Consolidar",D9="Re-redactar v2026",D9="Actualizar v2026"),IFERROR(INDEX(Backlog!$X$2:$X$101,MATCH(E9,Backlog!$A$2:$A$101,0)),""),"") -> 46616
A10: https://www.continentalmedia.com.mx/2012/12/las-4-r-s-de-las-redes-sociales/ | B10: 2012 | C10: 2019-10-21 | D10: Consolidar | E10: E-15 | F10: =IF(E10="","",IFERROR(INDEX(Backlog!$C$2:$C$101,MATCH(E10,Backlog!$A$2:$A$101,0)),"")) -> Comunidad antes que seguidores: engagement real y contenido viral con propósito | G10: 301 al nuevo artículo E-15 | H10: Contenido fusionado dentro del tema destino | I10: =IF(OR(D10="Consolidar",D10="Re-redactar v2026",D10="Actualizar v2026"),IFERROR(INDEX(Backlog!$X$2:$X$101,MATCH(E10,Backlog!$A$2:$A$101,0)),""),"") -> 46399
A11: https://www.continentalmedia.com.mx/2012/12/lovemarks/ | B11: 2012 | C11: 2019-10-21 | D11: Re-redactar v2026 | E11: E-26 | F11: =IF(E11="","",IFERROR(INDEX(Backlog!$C$2:$C$101,MATCH(E11,Backlog!$A$2:$A$101,0)),"")) -> Lovemarks en 2026: cómo se construye una marca que la gente ama | G11: Publicar versión 2026; 301 de la URL antigua a la nueva (o conservar slug) | H11: Emoción, comunidad y consistencia; ejemplos actuales | I11: =IF(OR(D11="Consolidar",D11="Re-redactar v2026",D11="Actualizar v2026"),IFERROR(INDEX(Backlog!$X$2:$X$101,MATCH(E11,Backlog!$A$2:$A$101,0)),""),"") -> 46574
A12: https://www.continentalmedia.com.mx/2012/12/marketing-de-guerrilla/ | B12: 2012 | C12: 2019-10-21 | D12: Consolidar | E12: E-44 | F12: =IF(E12="","",IFERROR(INDEX(Backlog!$C$2:$C$101,MATCH(E12,Backlog!$A$2:$A$101,0)),"")) -> BTL, guerrilla y experiencias de marca: ideas que funcionan en 2026 | G12: 301 al nuevo artículo E-44 | H12: Contenido fusionado dentro del tema destino | I12: =IF(OR(D12="Consolidar",D12="Re-redactar v2026",D12="Actualizar v2026"),IFERROR(INDEX(Backlog!$X$2:$X$101,MATCH(E12,Backlog!$A$2:$A$101,0)),""),"") -> 46609
A13: https://www.continentalmedia.com.mx/2012/12/marketing-deportivo/ | B13: 2012 | C13: 2019-10-21 | D13: Consolidar | E13: E-46 | F13: =IF(E13="","",IFERROR(INDEX(Backlog!$C$2:$C$101,MATCH(E13,Backlog!$A$2:$A$101,0)),"")) -> Patrocinio de eventos: cómo medir el retorno y elegir bien | G13: 301 al nuevo artículo E-46 | H13: Contenido fusionado dentro del tema destino | I13: =IF(OR(D13="Consolidar",D13="Re-redactar v2026",D13="Actualizar v2026"),IFERROR(INDEX(Backlog!$X$2:$X$101,MATCH(E13,Backlog!$A$2:$A$101,0)),""),"") -> 46623
A14: https://www.continentalmedia.com.mx/2012/12/marketing-viral/ | B14: 2012 | C14: 2019-10-21 | D14: Consolidar | E14: E-15 | F14: =IF(E14="","",IFERROR(INDEX(Backlog!$C$2:$C$101,MATCH(E14,Backlog!$A$2:$A$101,0)),"")) -> Comunidad antes que seguidores: engagement real y contenido viral con propósito | G14: 301 al nuevo artículo E-15 | H14: Contenido fusionado dentro del tema destino | I14: =IF(OR(D14="Consolidar",D14="Re-redactar v2026",D14="Actualizar v2026"),IFERROR(INDEX(Backlog!$X$2:$X$101,MATCH(E14,Backlog!$A$2:$A$101,0)),""),"") -> 46399
A15: https://www.continentalmedia.com.mx/2012/12/neuromarketing/ | B15: 2012 | C15: 2019-10-21 | D15: Re-redactar v2026 | E15: E-20 | F15: =IF(E15="","",IFERROR(INDEX(Backlog!$C$2:$C$101,MATCH(E15,Backlog!$A$2:$A$101,0)),"")) -> Neuromarketing y psicología del color: qué es ciencia y qué es mito | G15: Publicar versión 2026; 301 de la URL antigua a la nueva (o conservar slug) | H15: Separar evidencia de mitos; color, imagen y olfato | I15: =IF(OR(D15="Consolidar",D15="Re-redactar v2026",D15="Actualizar v2026"),IFERROR(INDEX(Backlog!$X$2:$X$101,MATCH(E15,Backlog!$A$2:$A$101,0)),""),"") -> 46427
A16: https://www.continentalmedia.com.mx/2012/12/plan-de-medios/ | B16: 2012 | C16: 2019-10-21 | D16: Consolidar | E16: E-45 | F16: =IF(E16="","",IFERROR(INDEX(Backlog!$C$2:$C$101,MATCH(E16,Backlog!$A$2:$A$101,0)),"")) -> Radio, TV y medios masivos en un plan de medios omnicanal 2026 | G16: 301 al nuevo artículo E-45 | H16: Contenido fusionado dentro del tema destino | I16: =IF(OR(D16="Consolidar",D16="Re-redactar v2026",D16="Actualizar v2026"),IFERROR(INDEX(Backlog!$X$2:$X$101,MATCH(E16,Backlog!$A$2:$A$101,0)),""),"") -> 46616
A17: https://www.continentalmedia.com.mx/2012/12/por-que-una-imagen-resulta-tan-poderosa/ | B17: 2012 | C17: 2019-10-21 | D17: Consolidar | E17: E-20 | F17: =IF(E17="","",IFERROR(INDEX(Backlog!$C$2:$C$101,MATCH(E17,Backlog!$A$2:$A$101,0)),"")) -> Neuromarketing y psicología del color: qué es ciencia y qué es mito | G17: 301 al nuevo artículo E-20 | H17: Contenido fusionado dentro del tema destino | I17: =IF(OR(D17="Consolidar",D17="Re-redactar v2026",D17="Actualizar v2026"),IFERROR(INDEX(Backlog!$X$2:$X$101,MATCH(E17,Backlog!$A$2:$A$101,0)),""),"") -> 46427
... A21: https://www.continentalmedia.com.mx/2012/12/relaciones-publicas/ | B21: 2012 | C21: 2019-10-21 | D21: Re-redactar v2026 | E21: E-30 | F21: =IF(E21="","",IFERROR(INDEX(Backlog!$C$2:$C$101,MATCH(E21,Backlog!$A$2:$A$101,0)),"")) -> Relaciones públicas en 2026: de la nota de prensa a la reputación digital | G21: Publicar versión 2026; 301 de la URL antigua a la nueva (o conservar slug) | H21: Qué es RP hoy: medios, creadores, reputación online y IA | I21: =IF(OR(D21="Consolidar",D21="Re-redactar v2026",D21="Actualizar v2026"),IFERROR(INDEX(Backlog!$X$2:$X$101,MATCH(E21,Backlog!$A$2:$A$101,0)),""),"") -> 46483
A22: https://www.continentalmedia.com.mx/2013/01/el-social-media-no-es-una-labor-mas-de-tu-secretaria/ | B22: 2013 | C22: 2019-10-21 | D22: Descartar | F22: =IF(E22="","",IFERROR(INDEX(Backlog!$C$2:$C$101,MATCH(E22,Backlog!$A$2:$A$101,0)),"")) | G22: 410, o 301 a /blog/ o a la categoría más cercana | H22: Contenido de coyuntura/curiosidad o fuera de los servicios actuales | I22: =IF(OR(D22="Consolidar",D22="Re-redactar v2026",D22="Actualizar v2026"),IFERROR(INDEX(Backlog!$X$2:$X$101,MATCH(E22,Backlog!$A$2:$A$101,0)),""),"")
A23: https://www.continentalmedia.com.mx/2013/01/la-forma-de-hacer-marketing-en-el-2013/ | B23: 2013 | C23: 2019-10-21 | D23: Consolidar | E23: E-09 | F23: =IF(E23="","",IFERROR(INDEX(Backlog!$C$2:$C$101,MATCH(E23,Backlog!$A$2:$A$101,0)),"")) -> Tendencias de marketing 2027: lo que las marcas deben preparar desde hoy | G23: 301 al nuevo artículo E-09 | H23: Contenido fusionado dentro del tema destino | I23: =IF(OR(D23="Consolidar",D23="Re-redactar v2026",D23="Actualizar v2026"),IFERROR(INDEX(Backlog!$X$2:$X$101,MATCH(E23,Backlog!$A$2:$A$101,0)),""),"") -> 46314
A24: https://www.continentalmedia.com.mx/2013/02/insight-un-concepto-que-muchos-manejan-pero-no-todos-comprenden/ | B24: 2013 | C24: 2019-10-21 | D24: Descartar | F24: =IF(E24="","",IFERROR(INDEX(Backlog!$C$2:$C$101,MATCH(E24,Backlog!$A$2:$A$101,0)),"")) | G24: 410, o 301 a /blog/ o a la categoría más cercana | H24: Contenido de coyuntura/curiosidad o fuera de los servicios actuales | I24: =IF(OR(D24="Consolidar",D24="Re-redactar v2026",D24="Actualizar v2026"),IFERROR(INDEX(Backlog!$X$2:$X$101,MATCH(E24,Backlog!$A$2:$A$101,0)),""),"")
A25: https://www.continentalmedia.com.mx/2013/03/la-publicidad-en-retrospectiva/ | B25: 2013 | C25: 2019-10-21 | D25: Descartar | F25: =IF(E25="","",IFERROR(INDEX(Backlog!$C$2:$C$101,MATCH(E25,Backlog!$A$2:$A$101,0)),"")) | G25: 410, o 301 a /blog/ o a la categoría más cercana | H25: Contenido de coyuntura/curiosidad o fuera de los servicios actuales | I25: =IF(OR(D25="Consolidar",D25="Re-redactar v2026",D25="Actualizar v2026"),IFERROR(INDEX(Backlog!$X$2:$X$101,MATCH(E25,Backlog!$A$2:$A$101,0)),""),"")
A26: https://www.continentalmedia.com.mx/2013/03/porque-invertir-en-imagen-corporativa/ | B26: 2013 | C26: 2019-10-21 | D26: Consolidar | E26: E-29 | F26: =IF(E26="","",IFERROR(INDEX(Backlog!$C$2:$C$101,MATCH(E26,Backlog!$A$2:$A$101,0)),"")) -> Un diseño bonito no lo es todo: diseño estratégico vs. diseño decorativo | G26: 301 al nuevo artículo E-29 | H26: Contenido fusionado dentro del tema destino | I26: =IF(OR(D26="Consolidar",D26="Re-redactar v2026",D26="Actualizar v2026"),IFERROR(INDEX(Backlog!$X$2:$X$101,MATCH(E26,Backlog!$A$2:$A$101,0)),""),"") -> 46476
A27: https://www.continentalmedia.com.mx/2013/03/tendencias-en-diseno-web-2013/ | B27: 2013 | C27: 2019-10-21 | D27: Re-redactar v2026 | E27: E-39 | F27: =IF(E27="","",IFERROR(INDEX(Backlog!$C$2:$C$101,MATCH(E27,Backlog!$A$2:$A$101,0)),"")) -> Diseño web 2026: tendencias que sí importan (velocidad, accesibilidad, motion, IA) | G27: Publicar versión 2026; 301 de la URL antigua a la nueva (o conservar slug) | H27: Reemplaza diseño responsivo 2014 y tendencias 2013 | I27: =IF(OR(D27="Consolidar",D27="Re-redactar v2026",D27="Actualizar v2026"),IFERROR(INDEX(Backlog!$X$2:$X$101,MATCH(E27,Backlog!$A$2:$A$101,0)),""),"") -> 46525
A28: https://www.continentalmedia.com.mx/2013/03/un-diseno-bonito-no-lo-es-todo/ | B28: 2013 | C28: 2019-10-21 | D28: Re-redactar v2026 | E28: E-29 | F28: =IF(E28="","",IFERROR(INDEX(Backlog!$C$2:$C$101,MATCH(E28,Backlog!$A$2:$A$101,0)),"")) -> Un diseño bonito no lo es todo: diseño estratégico vs. diseño decorativo | G28: Publicar versión 2026; 301 de la URL antigua a la nueva (o conservar slug) | H28: Principios (Gestalt), empaque e imagen corporativa con enfoque de negocio | I28: =IF(OR(D28="Consolidar",D28="Re-redactar v2026",D28="Actualizar v2026"),IFERROR(INDEX(Backlog!$X$2:$X$101,MATCH(E28,Backlog!$A$2:$A$101,0)),""),"") -> 46476
A29: https://www.continentalmedia.com.mx/2013/04/10-pasos-para-conseguir-mejores-ideas-creativas/ | B29: 2013 | C29: 2019-10-22 | D29: Consolidar | E29: E-33 | F29: =IF(E29="","",IFERROR(INDEX(Backlog!$C$2:$C$101,MATCH(E29,Backlog!$A$2:$A$101,0)),"")) -> El proceso creativo en la era de la IA: cómo nacen hoy las buenas ideas | G29: 301 al nuevo artículo E-33 | H29: Contenido fusionado dentro del tema destino | I29: =IF(OR(D29="Consolidar",D29="Re-redactar v2026",D29="Actualizar v2026"),IFERROR(INDEX(Backlog!$X$2:$X$101,MATCH(E29,Backlog!$A$2:$A$101,0)),""),"") -> 46504
A30: https://www.continentalmedia.com.mx/2013/04/decalogo-del-valor-de-las-ideas/ | B30: 2013 | C30: 2019-10-21 | D30: Consolidar | E30: E-33 | F30: =IF(E30="","",IFERROR(INDEX(Backlog!$C$2:$C$101,MATCH(E30,Backlog!$A$2:$A$101,0)),"")) -> El proceso creativo en la era de la IA: cómo nacen hoy las buenas ideas | G30: 301 al nuevo artículo E-33 | H30: Contenido fusionado dentro del tema destino | I30: =IF(OR(D30="Consolidar",D30="Re-redactar v2026",D30="Actualizar v2026"),IFERROR(INDEX(Backlog!$X$2:$X$101,MATCH(E30,Backlog!$A$2:$A$101,0)),""),"") -> 46504
A31: https://www.continentalmedia.com.mx/2013/04/historia-de-la-publicidad-en-mexico/ | B31: 2013 | C31: 2019-10-22 | D31: Descartar | F31: =IF(E31="","",IFERROR(INDEX(Backlog!$C$2:$C$101,MATCH(E31,Backlog!$A$2:$A$101,0)),"")) | G31: 410, o 301 a /blog/ o a la categoría más cercana | H31: Contenido de coyuntura/curiosidad o fuera de los servicios actuales | I31: =IF(OR(D31="Consolidar",D31="Re-redactar v2026",D31="Actualizar v2026"),IFERROR(INDEX(Backlog!$X$2:$X$101,MATCH(E31,Backlog!$A$2:$A$101,0)),""),"")
A32: https://www.continentalmedia.com.mx/2013/04/la-evolucion-de-las-redes-sociales/ | B32: 2013 | C32: 2019-10-22 | D32: Consolidar | E32: E-10 | F32: =IF(E32="","",IFERROR(INDEX(Backlog!$C$2:$C$101,MATCH(E32,Backlog!$A$2:$A$101,0)),"")) -> Alcance orgánico en redes sociales: ¿sigue valiendo la pena para tu empresa? | G32: 301 al nuevo artículo E-10 | H32: Contenido fusionado dentro del tema destino | I32: =IF(OR(D32="Consolidar",D32="Re-redactar v2026",D32="Actualizar v2026"),IFERROR(INDEX(Backlog!$X$2:$X$101,MATCH(E32,Backlog!$A$2:$A$101,0)),""),"") -> 46378
A33: https://www.continentalmedia.com.mx/2013/05/codigos-qr-una-herramienta-muy-poderosa-para-tu-empresa/ | B33: 2013 | C33: 2019-10-21 | D33: Consolidar | E33: E-44 | F33: =IF(E33="","",IFERROR(INDEX(Backlog!$C$2:$C$101,MATCH(E33,Backlog!$A$2:$A$101,0)),"")) -> BTL, guerrilla y experiencias de marca: ideas que funcionan en 2026 | G33: 301 al nuevo artículo E-44 | H33: Contenido fusionado dentro del tema destino | I33: =IF(OR(D33="Consolidar",D33="Re-redactar v2026",D33="Actualizar v2026"),IFERROR(INDEX(Backlog!$X$2:$X$101,MATCH(E33,Backlog!$A$2:$A$101,0)),""),"") -> 46609
A34: https://www.continentalmedia.com.mx/2013/05/cuanto-valen-las-ideas/ | B34: 2013 | C34: 2019-10-22 | D34: Consolidar | E34: E-33 | F34: =IF(E34="","",IFERROR(INDEX(Backlog!$C$2:$C$101,MATCH(E34,Backlog!$A$2:$A$101,0)),"")) -> El proceso creativo en la era de la IA: cómo nacen hoy las buenas ideas | G34: 301 al nuevo artículo E-33 | H34: Contenido fusionado dentro del tema destino | I34: =IF(OR(D34="Consolidar",D34="Re-redactar v2026",D34="Actualizar v2026"),IFERROR(INDEX(Backlog!$X$2:$X$101,MATCH(E34,Backlog!$A$2:$A$101,0)),""),"") -> 46504
A35: https://www.continentalmedia.com.mx/2013/05/leyes-gestalt/ | B35: 2013 | C35: 2019-10-21 | D35: Consolidar | E35: E-29 | F35: =IF(E35="","",IFERROR(INDEX(Backlog!$C$2:$C$101,MATCH(E35,Backlog!$A$2:$A$101,0)),"")) -> Un diseño bonito no lo es todo: diseño estratégico vs. diseño decorativo | G35: 301 al nuevo artículo E-29 | H35: Contenido fusionado dentro del tema destino | I35: =IF(OR(D35="Consolidar",D35="Re-redactar v2026",D35="Actualizar v2026"),IFERROR(INDEX(Backlog!$X$2:$X$101,MATCH(E35,Backlog!$A$2:$A$101,0)),""),"") -> 46476
A36: https://www.continentalmedia.com.mx/2013/05/por-que-realizar-una-investigacion-de-mercados/ | B36: 2013 | C36: 2019-10-21 | D36: Re-redactar v2026 | E36: G-08 | F36: =IF(E36="","",IFERROR(INDEX(Backlog!$C$2:$C$101,MATCH(E36,Backlog!$A$2:$A$101,0)),"")) -> Cómo hacer un estudio de mercado y analizar a tu competencia | G36: Publicar versión 2026; 301 de la URL antigua a la nueva (o conservar slug) | H36: Fuentes gratuitas, análisis FODA y de competencia | I36: =IF(OR(D36="Consolidar",D36="Re-redactar v2026",D36="Actualizar v2026"),IFERROR(INDEX(Backlog!$X$2:$X$101,MATCH(E36,Backlog!$A$2:$A$101,0)),""),"") -> 46478
A37: https://www.continentalmedia.com.mx/2013/06/10-sencillos-pasos-para-una-campana-publicitaria/ | B37: 2013 | C37: 2019-10-22 | D37: Consolidar | E37: G-04 | F37: =IF(E37="","",IFERROR(INDEX(Backlog!$C$2:$C$101,MATCH(E37,Backlog!$A$2:$A$101,0)),"")) -> Cómo hacer un brief de marketing para tu agencia | G37: 301 al nuevo artículo G-04 | H37: Contenido fusionado dentro del tema destino | I37: =IF(OR(D37="Consolidar",D37="Re-redactar v2026",D37="Actualizar v2026"),IFERROR(INDEX(Backlog!$X$2:$X$101,MATCH(E37,Backlog!$A$2:$A$101,0)),""),"") -> 46457
A38: https://www.continentalmedia.com.mx/2013/06/cual-es-tu-percepcion-del-color/ | B38: 2013 | C38: 2019-10-22 | D38: Consolidar | E38: E-20 | F38: =IF(E38="","",IFERROR(INDEX(Backlog!$C$2:$C$101,MATCH(E38,Backlog!$A$2:$A$101,0)),"")) -> Neuromarketing y psicología del color: qué es ciencia y qué es mito | G38: 301 al nuevo artículo E-20 | H38: Contenido fusionado dentro del tema destino | I38: =IF(OR(D38="Consolidar",D38="Re-redactar v2026",D38="Actualizar v2026"),IFERROR(INDEX(Backlog!$X$2:$X$101,MATCH(E38,Backlog!$A$2:$A$101,0)),""),"") -> 46427
A39: https://www.continentalmedia.com.mx/2013/06/en-politica-la-imagen-cuenta/ | B39: 2013 | C39: 2019-10-22 | D39: Consolidar | E39: E-32 | F39: =IF(E39="","",IFERROR(INDEX(Backlog!$C$2:$C$101,MATCH(E39,Backlog!$A$2:$A$101,0)),"")) -> Imagen pública: cómo te ven te tratan (marcas y líderes) | G39: 301 al nuevo artículo E-32 | H39: Contenido fusionado dentro del tema destino | I39: =IF(OR(D39="Consolidar",D39="Re-redactar v2026",D39="Actualizar v2026"),IFERROR(INDEX(Backlog!$X$2:$X$101,MATCH(E39,Backlog!$A$2:$A$101,0)),""),"") -> 46497
A40: https://www.continentalmedia.com.mx/2013/06/la-necesidad-de-contar-con-un-buen-plan-de-marketing/ | B40: 2013 | C40: 2019-10-21 | D40: Re-redactar v2026 | E40: G-01 | F40: =IF(E40="","",IFERROR(INDEX(Backlog!$C$2:$C$101,MATCH(E40,Backlog!$A$2:$A$101,0)),"")) -> Cómo crear tu plan de marketing 2027 paso a paso | G40: Publicar versión 2026; 301 de la URL antigua a la nueva (o conservar slug) | H40: Metodología en 7 pasos + ejemplo para pyme | I40: =IF(OR(D40="Consolidar",D40="Re-redactar v2026",D40="Actualizar v2026"),IFERROR(INDEX(Backlog!$X$2:$X$101,MATCH(E40,Backlog!$A$2:$A$101,0)),""),"") -> 46314
A41: https://www.continentalmedia.com.mx/2013/07/acerca-del-branding-personal/ | B41: 2013 | C41: 2019-10-22 | D41: Re-redactar v2026 | E41: E-25 | F41: =IF(E41="","",IFERROR(INDEX(Backlog!$C$2:$C$101,MATCH(E41,Backlog!$A$2:$A$101,0)),"")) -> Branding personal y liderazgo visible: la marca del directivo en LinkedIn | G41: Publicar versión 2026; 301 de la URL antigua a la nueva (o conservar slug) | H41: Enfoque B2B: ejecutivos como canal de confianza | I41: =IF(OR(D41="Consolidar",D41="Re-redactar v2026",D41="Actualizar v2026"),IFERROR(INDEX(Backlog!$X$2:$X$101,MATCH(E41,Backlog!$A$2:$A$101,0)),""),"") -> 46462
A42: https://www.continentalmedia.com.mx/2013/07/marketing-ecologico-una-decision-responsable/ | B42: 2013 | C42: 2019-10-21 | D42: Consolidar | E42: E-27 | F42: =IF(E42="","",IFERROR(INDEX(Backlog!$C$2:$C$101,MATCH(E42,Backlog!$A$2:$A$101,0)),"")) -> Greenwashing y marketing con propósito: lo que el consumidor ya no tolera | G42: 301 al nuevo artículo E-27 | H42: Contenido fusionado dentro del tema destino | I42: =IF(OR(D42="Consolidar",D42="Re-redactar v2026",D42="Actualizar v2026"),IFERROR(INDEX(Backlog!$X$2:$X$101,MATCH(E42,Backlog!$A$2:$A$101,0)),""),"") -> 46469
A43: https://www.continentalmedia.com.mx/2013/07/sabes-lo-que-es-geomarketing-y-lo-que-puedes-hacer-con-el/ | B43: 2013 | C43: 2019-10-21 | D43: Re-redactar v2026 | E43: G-37 | F43: =IF(E43="","",IFERROR(INDEX(Backlog!$C$2:$C$101,MATCH(E43,Backlog!$A$2:$A$101,0)),"")) -> SEO local: cómo aparecer en Google Maps y búsquedas "cerca de mí" | G43: Publicar versión 2026; 301 de la URL antigua a la nueva (o conservar slug) | H43: Google Business Profile, reseñas y geomarketing | I43: =IF(OR(D43="Consolidar",D43="Re-redactar v2026",D43="Actualizar v2026"),IFERROR(INDEX(Backlog!$X$2:$X$101,MATCH(E43,Backlog!$A$2:$A$101,0)),""),"") -> 46401
A44: https://www.continentalmedia.com.mx/2013/07/sabes-lo-que-significa-crm/ | B44: 2013 | C44: 2019-10-21 | D44: Re-redactar v2026 | E44: G-23 | F44: =IF(E44="","",IFERROR(INDEX(Backlog!$C$2:$C$101,MATCH(E44,Backlog!$A$2:$A$101,0)),"")) -> Cómo combinar CRM, automatización y lealtad sin perder el trato humano | G44: Publicar versión 2026; 301 de la URL antigua a la nueva (o conservar slug) | H44: Actualizar CRM, programas de lealtad y automatización | I44: =IF(OR(D44="Consolidar",D44="Re-redactar v2026",D44="Actualizar v2026"),IFERROR(INDEX(Backlog!$X$2:$X$101,MATCH(E44,Backlog!$A$2:$A$101,0)),""),"") -> 46611
A45: https://www.continentalmedia.com.mx/2013/08/el-mundo-del-marketing-alrededor-del-vino/ | B45: 2013 | C45: 2019-10-22 | D45: Descartar | F45: =IF(E45="","",IFERROR(INDEX(Backlog!$C$2:$C$101,MATCH(E45,Backlog!$A$2:$A$101,0)),"")) | G45: 410, o 301 a /blog/ o a la categoría más cercana | H45: Contenido de coyuntura/curiosidad o fuera de los servicios actuales | I45: =IF(OR(D45="Consolidar",D45="Re-redactar v2026",D45="Actualizar v2026"),IFERROR(INDEX(Backlog!$X$2:$X$101,MATCH(E45,Backlog!$A$2:$A$101,0)),""),"")
A46: https://www.continentalmedia.com.mx/2013/08/packaging/ | B46: 2013 | C46: 2019-10-22 | D46: Consolidar | E46: E-29 | F46: =IF(E46="","",IFERROR(INDEX(Backlog!$C$2:$C$101,MATCH(E46,Backlog!$A$2:$A$101,0)),"")) -> Un diseño bonito no lo es todo: diseño estratégico vs. diseño decorativo | G46: 301 al nuevo artículo E-29 | H46: Contenido fusionado dentro del tema destino | I46: =IF(OR(D46="Consolidar",D46="Re-redactar v2026",D46="Actualizar v2026"),IFERROR(INDEX(Backlog!$X$2:$X$101,MATCH(E46,Backlog!$A$2:$A$101,0)),""),"") -> 46476
A47: https://www.continentalmedia.com.mx/2013/08/videojuegos-un-medio-mas-para-la-publicidad/ | B47: 2013 | C47: 2019-10-21 | D47: Consolidar | E47: E-08 | F47: =IF(E47="","",IFERROR(INDEX(Backlog!$C$2:$C$101,MATCH(E47,Backlog!$A$2:$A$101,0)),"")) -> Metaverso, realidad aumentada y gaming: qué quedó de la promesa para las marcas | G47: 301 al nuevo artículo E-08 | H47: Contenido fusionado dentro del tema destino | I47: =IF(OR(D47="Consolidar",D47="Re-redactar v2026",D47="Actualizar v2026"),IFERROR(INDEX(Backlog!$X$2:$X$101,MATCH(E47,Backlog!$A$2:$A$101,0)),""),"") -> 46560
A48: https://www.continentalmedia.com.mx/2013/09/eres-fan-de-los-gadgets-y-te-gusta-estar-conectado-a-internet-a-donde-quiera-que-vas/ | B48: 2013 | C48: 2019-10-21 | D48: Descartar | F48: =IF(E48="","",IFERROR(INDEX(Backlog!$C$2:$C$101,MATCH(E48,Backlog!$A$2:$A$101,0)),"")) | G48: 410, o 301 a /blog/ o a la categoría más cercana | H48: Contenido de coyuntura/curiosidad o fuera de los servicios actuales | I48: =IF(OR(D48="Consolidar",D48="Re-redactar v2026",D48="Actualizar v2026"),IFERROR(INDEX(Backlog!$X$2:$X$101,MATCH(E48,Backlog!$A$2:$A$101,0)),""),"")
A49: https://www.continentalmedia.com.mx/2013/09/las-marcas-en-el-cine-casualidad-o-causalidad/ | B49: 2013 | C49: 2019-10-21 | D49: Consolidar | E49: E-28 | F49: =IF(E49="","",IFERROR(INDEX(Backlog!$C$2:$C$101,MATCH(E49,Backlog!$A$2:$A$101,0)),"")) -> Co-branding y alianzas de marca: casos, riesgos y lecciones | G49: 301 al nuevo artículo E-28 | H49: Contenido fusionado dentro del tema destino | I49: =IF(OR(D49="Consolidar",D49="Re-redactar v2026",D49="Actualizar v2026"),IFERROR(INDEX(Backlog!$X$2:$X$101,MATCH(E49,Backlog!$A$2:$A$101,0)),""),"") -> 46581
A50: https://www.continentalmedia.com.mx/2013/09/no-uses-mi-marca-en-publico/ | B50: 2013 | C50: 2019-10-21 | D50: Descartar | F50: =IF(E50="","",IFERROR(INDEX(Backlog!$C$2:$C$101,MATCH(E50,Backlog!$A$2:$A$101,0)),"")) | G50: 410, o 301 a /blog/ o a la categoría más cercana | H50: Contenido de coyuntura/curiosidad o fuera de los servicios actuales | I50: =IF(OR(D50="Consolidar",D50="Re-redactar v2026",D50="Actualizar v2026"),IFERROR(INDEX(Backlog!$X$2:$X$101,MATCH(E50,Backlog!$A$2:$A$101,0)),""),"")
A51: https://www.continentalmedia.com.mx/2013/10/campanas-de-terror/ | B51: 2013 | C51: 2019-10-22 | D51: Descartar | F51: =IF(E51="","",IFERROR(INDEX(Backlog!$C$2:$C$101,MATCH(E51,Backlog!$A$2:$A$101,0)),"")) | G51: 410, o 301 a /blog/ o a la categoría más cercana | H51: Contenido de coyuntura/curiosidad o fuera de los servicios actuales | I51: =IF(OR(D51="Consolidar",D51="Re-redactar v2026",D51="Actualizar v2026"),IFERROR(INDEX(Backlog!$X$2:$X$101,MATCH(E51,Backlog!$A$2:$A$101,0)),""),"")
A52: https://www.continentalmedia.com.mx/2013/10/crisis-de-imagen-publica-en-el-tri/ | B52: 2013 | C52: 2019-10-22 | D52: Re-redactar v2026 | E52: E-31 | F52: =IF(E52="","",IFERROR(INDEX(Backlog!$C$2:$C$101,MATCH(E52,Backlog!$A$2:$A$101,0)),"")) -> Crisis de reputación: lo que enseñan los casos de marcas y figuras públicas | G52: Publicar versión 2026; 301 de la URL antigua a la nueva (o conservar slug) | H52: Casos clásicos y recientes; qué hacer en las primeras 24 horas | I52: =IF(OR(D52="Consolidar",D52="Re-redactar v2026",D52="Actualizar v2026"),IFERROR(INDEX(Backlog!$X$2:$X$101,MATCH(E52,Backlog!$A$2:$A$101,0)),""),"") -> 46490
A53: https://www.continentalmedia.com.mx/2013/10/google-la-red-social/ | B53: 2013 | C53: 2019-10-21 | D53: Consolidar | E53: E-11 | F53: =IF(E53="","",IFERROR(INDEX(Backlog!$C$2:$C$101,MATCH(E53,Backlog!$A$2:$A$101,0)),"")) -> Social search: por qué TikTok e Instagram ya son buscadores y cómo aparecer | G53: 301 al nuevo artículo E-11 | H53: Contenido fusionado dentro del tema destino | I53: =IF(OR(D53="Consolidar",D53="Re-redactar v2026",D53="Actualizar v2026"),IFERROR(INDEX(Backlog!$X$2:$X$101,MATCH(E53,Backlog!$A$2:$A$101,0)),""),"") -> 46385
A54: https://www.continentalmedia.com.mx/2013/10/marketing-digital-vs-marketing-tradicional/ | B54: 2013 | C54: 2019-10-21 | D54: Re-redactar v2026 | E54: E-17 | F54: =IF(E54="","",IFERROR(INDEX(Backlog!$C$2:$C$101,MATCH(E54,Backlog!$A$2:$A$101,0)),"")) -> Marketing digital vs. marketing tradicional: un debate que ya se resolvió | G54: Publicar versión 2026; 301 de la URL antigua a la nueva (o conservar slug) | H54: Postura: integración, no sustitución; cuándo usar cada medio | I54: =IF(OR(D54="Consolidar",D54="Re-redactar v2026",D54="Actualizar v2026"),IFERROR(INDEX(Backlog!$X$2:$X$101,MATCH(E54,Backlog!$A$2:$A$101,0)),""),"") -> 46406
A55: https://www.continentalmedia.com.mx/2013/10/marketing-social-filantropia-o-estrategia/ | B55: 2013 | C55: 2019-10-21 | D55: Consolidar | E55: E-27 | F55: =IF(E55="","",IFERROR(INDEX(Backlog!$C$2:$C$101,MATCH(E55,Backlog!$A$2:$A$101,0)),"")) -> Greenwashing y marketing con propósito: lo que el consumidor ya no tolera | G55: 301 al nuevo artículo E-27 | H55: Contenido fusionado dentro del tema destino | I55: =IF(OR(D55="Consolidar",D55="Re-redactar v2026",D55="Actualizar v2026"),IFERROR(INDEX(Backlog!$X$2:$X$101,MATCH(E55,Backlog!$A$2:$A$101,0)),""),"") -> 46469
A56: https://www.continentalmedia.com.mx/2013/11/calaverita-continental-media/ | B56: 2013 | C56: 2019-10-21 | D56: Descartar | F56: =IF(E56="","",IFERROR(INDEX(Backlog!$C$2:$C$101,MATCH(E56,Backlog!$A$2:$A$101,0)),"")) | G56: 410, o 301 a /blog/ o a la categoría más cercana | H56: Contenido de coyuntura/curiosidad o fuera de los servicios actuales | I56: =IF(OR(D56="Consolidar",D56="Re-redactar v2026",D56="Actualizar v2026"),IFERROR(INDEX(Backlog!$X$2:$X$101,MATCH(E56,Backlog!$A$2:$A$101,0)),""),"")
A57: https://www.continentalmedia.com.mx/2013/11/el-web-y-showrooming-amigos-o-enemigos-de-tu-negocio/ | B57: 2013 | C57: 2019-10-21 | D57: Consolidar | E57: G-44 | F57: =IF(E57="","",IFERROR(INDEX(Backlog!$C$2:$C$101,MATCH(E57,Backlog!$A$2:$A$101,0)),"")) -> Cómo vender en Amazon y Mercado Libre desde México | G57: 301 al nuevo artículo G-44 | H57: Contenido fusionado dentro del tema destino | I57: =IF(OR(D57="Consolidar",D57="Re-redactar v2026",D57="Actualizar v2026"),IFERROR(INDEX(Backlog!$X$2:$X$101,MATCH(E57,Backlog!$A$2:$A$101,0)),""),"") -> 46625
A58: https://www.continentalmedia.com.mx/2013/11/greenwashing-el-engano-verde/ | B58: 2013 | C58: 2019-10-21 | D58: Re-redactar v2026 | E58: E-27 | F58: =IF(E58="","",IFERROR(INDEX(Backlog!$C$2:$C$101,MATCH(E58,Backlog!$A$2:$A$101,0)),"")) -> Greenwashing y marketing con propósito: lo que el consumidor ya no tolera | G58: Publicar versión 2026; 301 de la URL antigua a la nueva (o conservar slug) | H58: Regulación y percepción actual; cómo comunicar sostenibilidad con evidencia | I58: =IF(OR(D58="Consolidar",D58="Re-redactar v2026",D58="Actualizar v2026"),IFERROR(INDEX(Backlog!$X$2:$X$101,MATCH(E58,Backlog!$A$2:$A$101,0)),""),"") -> 46469
A59: https://www.continentalmedia.com.mx/2013/11/no-te-pierdas-dentro-del-buen-fin/ | B59: 2013 | C59: 2019-10-21 | D59: Consolidar | E59: G-07 | F59: =IF(E59="","",IFERROR(INDEX(Backlog!$C$2:$C$101,MATCH(E59,Backlog!$A$2:$A$101,0)),"")) -> Calendario comercial México 2027 y cómo planear campañas estacionales | G59: 301 al nuevo artículo G-07 | H59: Contenido fusionado dentro del tema destino | I59: =IF(OR(D59="Consolidar",D59="Re-redactar v2026",D59="Actualizar v2026"),IFERROR(INDEX(Backlog!$X$2:$X$101,MATCH(E59,Backlog!$A$2:$A$101,0)),""),"") -> 46314
A60: https://www.continentalmedia.com.mx/2013/11/realidad-aumentada-o-ciencia-ficcion/ | B60: 2013 | C60: 2019-10-21 | D60: Consolidar | E60: E-08 | F60: =IF(E60="","",IFERROR(INDEX(Backlog!$C$2:$C$101,MATCH(E60,Backlog!$A$2:$A$101,0)),"")) -> Metaverso, realidad aumentada y gaming: qué quedó de la promesa para las marcas | G60: 301 al nuevo artículo E-08 | H60: Contenido fusionado dentro del tema destino | I60: =IF(OR(D60="Consolidar",D60="Re-redactar v2026",D60="Actualizar v2026"),IFERROR(INDEX(Backlog!$X$2:$X$101,MATCH(E60,Backlog!$A$2:$A$101,0)),""),"") -> 46560
A61: https://www.continentalmedia.com.mx/2013/12/cuales-seran-las-tendencias-de-marketing-2014/ | B61: 2013 | C61: 2019-10-21 | D61: Consolidar | E61: E-09 | F61: =IF(E61="","",IFERROR(INDEX(Backlog!$C$2:$C$101,MATCH(E61,Backlog!$A$2:$A$101,0)),"")) -> Tendencias de marketing 2027: lo que las marcas deben preparar desde hoy | G61: 301 al nuevo artículo E-09 | H61: Contenido fusionado dentro del tema destino | I61: =IF(OR(D61="Consolidar",D61="Re-redactar v2026",D61="Actualizar v2026"),IFERROR(INDEX(Backlog!$X$2:$X$101,MATCH(E61,Backlog!$A$2:$A$101,0)),""),"") -> 46314
A62: https://www.continentalmedia.com.mx/2013/12/las-campanas-mexicanas-mas-premiadas-de-2013/ | B62: 2013 | C62: 2019-10-21 | D62: Descartar | F62: =IF(E62="","",IFERROR(INDEX(Backlog!$C$2:$C$101,MATCH(E62,Backlog!$A$2:$A$101,0)),"")) | G62: 410, o 301 a /blog/ o a la categoría más cercana | H62: Contenido de coyuntura/curiosidad o fuera de los servicios actuales | I62: =IF(OR(D62="Consolidar",D62="Re-redactar v2026",D62="Actualizar v2026"),IFERROR(INDEX(Backlog!$X$2:$X$101,MATCH(E62,Backlog!$A$2:$A$101,0)),""),"")
A63: https://www.continentalmedia.com.mx/2013/12/publicidad-con-aroma-navideno/ | B63: 2013 | C63: 2019-10-22 | D63: Consolidar | E63: G-07 | F63: =IF(E63="","",IFERROR(INDEX(Backlog!$C$2:$C$101,MATCH(E63,Backlog!$A$2:$A$101,0)),"")) -> Calendario comercial México 2027 y cómo planear campañas estacionales | G63: 301 al nuevo artículo G-07 | H63: Contenido fusionado dentro del tema destino | I63: =IF(OR(D63="Consolidar",D63="Re-redactar v2026",D63="Actualizar v2026"),IFERROR(INDEX(Backlog!$X$2:$X$101,MATCH(E63,Backlog!$A$2:$A$101,0)),""),"") -> 46314
A64: https://www.continentalmedia.com.mx/2014/01/branding-para-pymes/ | B64: 2014 | C64: 2019-10-21 | D64: Descartar | F64: =IF(E64="","",IFERROR(INDEX(Backlog!$C$2:$C$101,MATCH(E64,Backlog!$A$2:$A$101,0)),"")) | G64: 410, o 301 a /blog/ o a la categoría más cercana | H64: Contenido de coyuntura/curiosidad o fuera de los servicios actuales | I64: =IF(OR(D64="Consolidar",D64="Re-redactar v2026",D64="Actualizar v2026"),IFERROR(INDEX(Backlog!$X$2:$X$101,MATCH(E64,Backlog!$A$2:$A$101,0)),""),"")
A65: https://www.continentalmedia.com.mx/2014/01/celebridades-marcas-y-escandalos/ | B65: 2014 | C65: 2019-10-22 | D65: Consolidar | E65: E-13 | F65: =IF(E65="","",IFERROR(INDEX(Backlog!$C$2:$C$101,MATCH(E65,Backlog!$A$2:$A$101,0)),"")) -> Marketing de influencia en 2026: micro-influencers, creadores y contenido UGC | G65: 301 al nuevo artículo E-13 | H65: Contenido fusionado dentro del tema destino | I65: =IF(OR(D65="Consolidar",D65="Re-redactar v2026",D65="Actualizar v2026"),IFERROR(INDEX(Backlog!$X$2:$X$101,MATCH(E65,Backlog!$A$2:$A$101,0)),""),"") -> 46392
A66: https://www.continentalmedia.com.mx/2014/01/celebridades-y-marcas-se-llevan-bien/ | B66: 2014 | C66: 2019-10-22 | D66: Consolidar | E66: E-13 | F66: =IF(E66="","",IFERROR(INDEX(Backlog!$C$2:$C$101,MATCH(E66,Backlog!$A$2:$A$101,0)),"")) -> Marketing de influencia en 2026: micro-influencers, creadores y contenido UGC | G66: 301 al nuevo artículo E-13 | H66: Contenido fusionado dentro del tema destino | I66: =IF(OR(D66="Consolidar",D66="Re-redactar v2026",D66="Actualizar v2026"),IFERROR(INDEX(Backlog!$X$2:$X$101,MATCH(E66,Backlog!$A$2:$A$101,0)),""),"") -> 46392
A67: https://www.continentalmedia.com.mx/2014/01/publicidad-discriminatoria/ | B67: 2014 | C67: 2019-10-21 | D67: Re-redactar v2026 | E67: E-35 | F67: =IF(E67="","",IFERROR(INDEX(Backlog!$C$2:$C$101,MATCH(E67,Backlog!$A$2:$A$101,0)),"")) -> Publicidad responsable: sesgos, estereotipos y mensajes que dañan a tu marca | G67: Publicar versión 2026; 301 de la URL antigua a la nueva (o conservar slug) | H67: Cómo revisar mensajes antes de publicar; casos recientes | I67: =IF(OR(D67="Consolidar",D67="Re-redactar v2026",D67="Actualizar v2026"),IFERROR(INDEX(Backlog!$X$2:$X$101,MATCH(E67,Backlog!$A$2:$A$101,0)),""),"") -> 46588
A68: https://www.continentalmedia.com.mx/2014/02/el-top-5-mejores-agencias-de-publicidad-en-mexico/ | B68: 2014 | C68: 2019-10-21 | D68: Descartar | F68: =IF(E68="","",IFERROR(INDEX(Backlog!$C$2:$C$101,MATCH(E68,Backlog!$A$2:$A$101,0)),"")) | G68: 410, o 301 a /blog/ o a la categoría más cercana | H68: Contenido de coyuntura/curiosidad o fuera de los servicios actuales | I68: =IF(OR(D68="Consolidar",D68="Re-redactar v2026",D68="Actualizar v2026"),IFERROR(INDEX(Backlog!$X$2:$X$101,MATCH(E68,Backlog!$A$2:$A$101,0)),""),"")
A69: https://www.continentalmedia.com.mx/2014/02/estudio-de-mercado-la-clave-del-exito-de-tu-producto/ | B69: 2014 | C69: 2019-10-21 | D69: Consolidar | E69: G-08 | F69: =IF(E69="","",IFERROR(INDEX(Backlog!$C$2:$C$101,MATCH(E69,Backlog!$A$2:$A$101,0)),"")) -> Cómo hacer un estudio de mercado y analizar a tu competencia | G69: 301 al nuevo artículo G-08 | H69: Contenido fusionado dentro del tema destino | I69: =IF(OR(D69="Consolidar",D69="Re-redactar v2026",D69="Actualizar v2026"),IFERROR(INDEX(Backlog!$X$2:$X$101,MATCH(E69,Backlog!$A$2:$A$101,0)),""),"") -> 46478
A70: https://www.continentalmedia.com.mx/2014/02/pioneros-de-la-publicidad-en-mexico/ | B70: 2014 | C70: 2019-10-21 | D70: Descartar | F70: =IF(E70="","",IFERROR(INDEX(Backlog!$C$2:$C$101,MATCH(E70,Backlog!$A$2:$A$101,0)),"")) | G70: 410, o 301 a /blog/ o a la categoría más cercana | H70: Contenido de coyuntura/curiosidad o fuera de los servicios actuales | I70: =IF(OR(D70="Consolidar",D70="Re-redactar v2026",D70="Actualizar v2026"),IFERROR(INDEX(Backlog!$X$2:$X$101,MATCH(E70,Backlog!$A$2:$A$101,0)),""),"")
A71: https://www.continentalmedia.com.mx/2014/02/por-que-algunos-productos-fracasaron-en-el-mercado/ | B71: 2014 | C71: 2019-10-21 | D71: Consolidar | E71: G-08 | F71: =IF(E71="","",IFERROR(INDEX(Backlog!$C$2:$C$101,MATCH(E71,Backlog!$A$2:$A$101,0)),"")) -> Cómo hacer un estudio de mercado y analizar a tu competencia | G71: 301 al nuevo artículo G-08 | H71: Contenido fusionado dentro del tema destino | I71: =IF(OR(D71="Consolidar",D71="Re-redactar v2026",D71="Actualizar v2026"),IFERROR(INDEX(Backlog!$X$2:$X$101,MATCH(E71,Backlog!$A$2:$A$101,0)),""),"") -> 46478
A72: https://www.continentalmedia.com.mx/2014/03/las-5-mejores-marcas-en-redes-sociales-en-mexico/ | B72: 2014 | C72: 2019-10-21 | D72: Consolidar | E72: E-12 | F72: =IF(E72="","",IFERROR(INDEX(Backlog!$C$2:$C$101,MATCH(E72,Backlog!$A$2:$A$101,0)),"")) -> Humanizar tu marca: por qué la autenticidad le gana al contenido perfecto | G72: 301 al nuevo artículo E-12 | H72: Contenido fusionado dentro del tema destino | I72: =IF(OR(D72="Consolidar",D72="Re-redactar v2026",D72="Actualizar v2026"),IFERROR(INDEX(Backlog!$X$2:$X$101,MATCH(E72,Backlog!$A$2:$A$101,0)),""),"") -> 46322
A73: https://www.continentalmedia.com.mx/2014/03/por-que-es-polemica-la-publicidad-subliminal/ | B73: 2014 | C73: 2019-10-21 | D73: Consolidar | E73: E-35 | F73: =IF(E73="","",IFERROR(INDEX(Backlog!$C$2:$C$101,MATCH(E73,Backlog!$A$2:$A$101,0)),"")) -> Publicidad responsable: sesgos, estereotipos y mensajes que dañan a tu marca | G73: 301 al nuevo artículo E-35 | H73: Contenido fusionado dentro del tema destino | I73: =IF(OR(D73="Consolidar",D73="Re-redactar v2026",D73="Actualizar v2026"),IFERROR(INDEX(Backlog!$X$2:$X$101,MATCH(E73,Backlog!$A$2:$A$101,0)),""),"") -> 46588
A74: https://www.continentalmedia.com.mx/2014/03/que-es-el-marketing-de-influencia/ | B74: 2014 | C74: 2019-10-21 | D74: Re-redactar v2026 | E74: E-13 | F74: =IF(E74="","",IFERROR(INDEX(Backlog!$C$2:$C$101,MATCH(E74,Backlog!$A$2:$A$101,0)),"")) -> Marketing de influencia en 2026: micro-influencers, creadores y contenido UGC | G74: Publicar versión 2026; 301 de la URL antigua a la nueva (o conservar slug) | H74: Modelos de colaboración, métricas y riesgos de reputación | I74: =IF(OR(D74="Consolidar",D74="Re-redactar v2026",D74="Actualizar v2026"),IFERROR(INDEX(Backlog!$X$2:$X$101,MATCH(E74,Backlog!$A$2:$A$101,0)),""),"") -> 46392
A75: https://www.continentalmedia.com.mx/2014/04/10-consejos-para-el-correcto-uso-de-tu-celular/ | B75: 2014 | C75: 2019-10-21 | D75: Descartar | F75: =IF(E75="","",IFERROR(INDEX(Backlog!$C$2:$C$101,MATCH(E75,Backlog!$A$2:$A$101,0)),"")) | G75: 410, o 301 a /blog/ o a la categoría más cercana | H75: Contenido de coyuntura/curiosidad o fuera de los servicios actuales | I75: =IF(OR(D75="Consolidar",D75="Re-redactar v2026",D75="Actualizar v2026"),IFERROR(INDEX(Backlog!$X$2:$X$101,MATCH(E75,Backlog!$A$2:$A$101,0)),""),"")
A76: https://www.continentalmedia.com.mx/2014/04/adaptate-llego-el-diseno-responsivo/ | B76: 2014 | C76: 2019-10-21 | D76: Consolidar | E76: E-39 | F76: =IF(E76="","",IFERROR(INDEX(Backlog!$C$2:$C$101,MATCH(E76,Backlog!$A$2:$A$101,0)),"")) -> Diseño web 2026: tendencias que sí importan (velocidad, accesibilidad, motion, IA) | G76: 301 al nuevo artículo E-39 | H76: Contenido fusionado dentro del tema destino | I76: =IF(OR(D76="Consolidar",D76="Re-redactar v2026",D76="Actualizar v2026"),IFERROR(INDEX(Backlog!$X$2:$X$101,MATCH(E76,Backlog!$A$2:$A$101,0)),""),"") -> 46525
A77: https://www.continentalmedia.com.mx/2014/04/los-6-colores-que-mas-atraen-en-publicidad/ | B77: 2014 | C77: 2019-10-24 | D77: Consolidar | E77: E-20 | F77: =IF(E77="","",IFERROR(INDEX(Backlog!$C$2:$C$101,MATCH(E77,Backlog!$A$2:$A$101,0)),"")) -> Neuromarketing y psicología del color: qué es ciencia y qué es mito | G77: 301 al nuevo artículo E-20 | H77: Contenido fusionado dentro del tema destino | I77: =IF(OR(D77="Consolidar",D77="Re-redactar v2026",D77="Actualizar v2026"),IFERROR(INDEX(Backlog!$X$2:$X$101,MATCH(E77,Backlog!$A$2:$A$101,0)),""),"") -> 46427
A78: https://www.continentalmedia.com.mx/2014/04/marketing-de-peluche/ | B78: 2014 | C78: 2019-10-21 | D78: Descartar | F78: =IF(E78="","",IFERROR(INDEX(Backlog!$C$2:$C$101,MATCH(E78,Backlog!$A$2:$A$101,0)),"")) | G78: 410, o 301 a /blog/ o a la categoría más cercana | H78: Contenido de coyuntura/curiosidad o fuera de los servicios actuales | I78: =IF(OR(D78="Consolidar",D78="Re-redactar v2026",D78="Actualizar v2026"),IFERROR(INDEX(Backlog!$X$2:$X$101,MATCH(E78,Backlog!$A$2:$A$101,0)),""),"")
A79: https://www.continentalmedia.com.mx/2014/04/no-ahuyentes-a-tus-clientes/ | B79: 2014 | C79: 2019-10-21 | D79: Consolidar | E79: G-14 | F79: =IF(E79="","",IFERROR(INDEX(Backlog!$C$2:$C$101,MATCH(E79,Backlog!$A$2:$A$101,0)),"")) -> Cómo responder comentarios negativos y atender clientes en redes sociales | G79: 301 al nuevo artículo G-14 | H79: Contenido fusionado dentro del tema destino | I79: =IF(OR(D79="Consolidar",D79="Re-redactar v2026",D79="Actualizar v2026"),IFERROR(INDEX(Backlog!$X$2:$X$101,MATCH(E79,Backlog!$A$2:$A$101,0)),""),"") -> 46499
A80: https://www.continentalmedia.com.mx/2014/05/10-errores-al-hablar-en-publico/ | B80: 2014 | C80: 2019-10-21 | D80: Re-redactar v2026 | E80: G-34 | F80: =IF(E80="","",IFERROR(INDEX(Backlog!$C$2:$C$101,MATCH(E80,Backlog!$A$2:$A$101,0)),"")) -> Cómo preparar a un vocero para entrevistas y presentaciones | G80: Publicar versión 2026; 301 de la URL antigua a la nueva (o conservar slug) | H80: Reunir contenidos de hablar en público y reuniones con clientes | I80: =IF(OR(D80="Consolidar",D80="Re-redactar v2026",D80="Actualizar v2026"),IFERROR(INDEX(Backlog!$X$2:$X$101,MATCH(E80,Backlog!$A$2:$A$101,0)),""),"") -> 46555
A81: https://www.continentalmedia.com.mx/2014/05/5-comportamientos-nocivos-en-redes-sociales/ | B81: 2014 | C81: 2019-10-21 | D81: Descartar | F81: =IF(E81="","",IFERROR(INDEX(Backlog!$C$2:$C$101,MATCH(E81,Backlog!$A$2:$A$101,0)),"")) | G81: 410, o 301 a /blog/ o a la categoría más cercana | H81: Contenido de coyuntura/curiosidad o fuera de los servicios actuales | I81: =IF(OR(D81="Consolidar",D81="Re-redactar v2026",D81="Actualizar v2026"),IFERROR(INDEX(Backlog!$X$2:$X$101,MATCH(E81,Backlog!$A$2:$A$101,0)),""),"")
A82: https://www.continentalmedia.com.mx/2014/05/8-datos-historicos-que-todo-disenador-debe-saber/ | B82: 2014 | C82: 2019-10-21 | D82: Descartar | F82: =IF(E82="","",IFERROR(INDEX(Backlog!$C$2:$C$101,MATCH(E82,Backlog!$A$2:$A$101,0)),"")) | G82: 410, o 301 a /blog/ o a la categoría más cercana | H82: Contenido de coyuntura/curiosidad o fuera de los servicios actuales | I82: =IF(OR(D82="Consolidar",D82="Re-redactar v2026",D82="Actualizar v2026"),IFERROR(INDEX(Backlog!$X$2:$X$101,MATCH(E82,Backlog!$A$2:$A$101,0)),""),"")
A83: https://www.continentalmedia.com.mx/2014/05/no-te-exprimas-el-cerebro-5-ejercicios-para-recuperar-la-creatividad/ | B83: 2014 | C83: 2019-10-21 | D83: Consolidar | E83: E-33 | F83: =IF(E83="","",IFERROR(INDEX(Backlog!$C$2:$C$101,MATCH(E83,Backlog!$A$2:$A$101,0)),"")) -> El proceso creativo en la era de la IA: cómo nacen hoy las buenas ideas | G83: 301 al nuevo artículo E-33 | H83: Contenido fusionado dentro del tema destino | I83: =IF(OR(D83="Consolidar",D83="Re-redactar v2026",D83="Actualizar v2026"),IFERROR(INDEX(Backlog!$X$2:$X$101,MATCH(E83,Backlog!$A$2:$A$101,0)),""),"") -> 46504
A84: https://www.continentalmedia.com.mx/2014/05/que-hacer-durante-una-reunion-con-un-cliente/ | B84: 2014 | C84: 2019-10-21 | D84: Consolidar | E84: G-34 | F84: =IF(E84="","",IFERROR(INDEX(Backlog!$C$2:$C$101,MATCH(E84,Backlog!$A$2:$A$101,0)),"")) -> Cómo preparar a un vocero para entrevistas y presentaciones | G84: 301 al nuevo artículo G-34 | H84: Contenido fusionado dentro del tema destino | I84: =IF(OR(D84="Consolidar",D84="Re-redactar v2026",D84="Actualizar v2026"),IFERROR(INDEX(Backlog!$X$2:$X$101,MATCH(E84,Backlog!$A$2:$A$101,0)),""),"") -> 46555
A85: https://www.continentalmedia.com.mx/2014/06/comerciales-mundial-redes-sociales/ | B85: 2014 | C85: 2019-10-22 | D85: Descartar | F85: =IF(E85="","",IFERROR(INDEX(Backlog!$C$2:$C$101,MATCH(E85,Backlog!$A$2:$A$101,0)),"")) | G85: 410, o 301 a /blog/ o a la categoría más cercana | H85: Contenido de coyuntura/curiosidad o fuera de los servicios actuales | I85: =IF(OR(D85="Consolidar",D85="Re-redactar v2026",D85="Actualizar v2026"),IFERROR(INDEX(Backlog!$X$2:$X$101,MATCH(E85,Backlog!$A$2:$A$101,0)),""),"")
A86: https://www.continentalmedia.com.mx/2014/06/empresa-lista-redes-sociales/ | B86: 2014 | C86: 2015-09-08 | D86: Re-redactar v2026 | E86: E-10 | F86: =IF(E86="","",IFERROR(INDEX(Backlog!$C$2:$C$101,MATCH(E86,Backlog!$A$2:$A$101,0)),"")) -> Alcance orgánico en redes sociales: ¿sigue valiendo la pena para tu empresa? | G86: Publicar versión 2026; 301 de la URL antigua a la nueva (o conservar slug) | H86: Datos 2026 sobre alcance orgánico vs. pauta; cuándo conviene cada uno | I86: =IF(OR(D86="Consolidar",D86="Re-redactar v2026",D86="Actualizar v2026"),IFERROR(INDEX(Backlog!$X$2:$X$101,MATCH(E86,Backlog!$A$2:$A$101,0)),""),"") -> 46378
A87: https://www.continentalmedia.com.mx/2014/06/recuperar-clientes/ | B87: 2014 | C87: 2015-09-08 | D87: Consolidar | E87: G-14 | F87: =IF(E87="","",IFERROR(INDEX(Backlog!$C$2:$C$101,MATCH(E87,Backlog!$A$2:$A$101,0)),"")) -> Cómo responder comentarios negativos y atender clientes en redes sociales | G87: 301 al nuevo artículo G-14 | H87: Contenido fusionado dentro del tema destino | I87: =IF(OR(D87="Consolidar",D87="Re-redactar v2026",D87="Actualizar v2026"),IFERROR(INDEX(Backlog!$X$2:$X$101,MATCH(E87,Backlog!$A$2:$A$101,0)),""),"") -> 46499
A88: https://www.continentalmedia.com.mx/2014/06/un-sueldo-no-es-suficiente/ | B88: 2014 | C88: 2015-09-08 | D88: Descartar | F88: =IF(E88="","",IFERROR(INDEX(Backlog!$C$2:$C$101,MATCH(E88,Backlog!$A$2:$A$101,0)),"")) | G88: 410, o 301 a /blog/ o a la categoría más cercana | H88: Contenido de coyuntura/curiosidad o fuera de los servicios actuales | I88: =IF(OR(D88="Consolidar",D88="Re-redactar v2026",D88="Actualizar v2026"),IFERROR(INDEX(Backlog!$X$2:$X$101,MATCH(E88,Backlog!$A$2:$A$101,0)),""),"")
A89: https://www.continentalmedia.com.mx/2014/07/conoces-la-manera-de-anunciarte-a-traves-de-google/ | B89: 2014 | C89: 2019-10-22 | D89: Re-redactar v2026 | E89: G-38 | F89: =IF(E89="","",IFERROR(INDEX(Backlog!$C$2:$C$101,MATCH(E89,Backlog!$A$2:$A$101,0)),"")) -> Cómo anunciarte en Google Ads desde cero | G89: Publicar versión 2026; 301 de la URL antigua a la nueva (o conservar slug) | H89: Estructura de cuenta, presupuesto y alternativas de pago | I89: =IF(OR(D89="Consolidar",D89="Re-redactar v2026",D89="Actualizar v2026"),IFERROR(INDEX(Backlog!$X$2:$X$101,MATCH(E89,Backlog!$A$2:$A$101,0)),""),"") -> 46408
A90: https://www.continentalmedia.com.mx/2014/07/estrategias-marca-twitter/ | B90: 2014 | C90: 2015-09-08 | D90: Consolidar | E90: E-14 | F90: =IF(E90="","",IFERROR(INDEX(Backlog!$C$2:$C$101,MATCH(E90,Backlog!$A$2:$A$101,0)),"")) -> Más allá de X: dónde debe estar tu marca (X, Threads, Bluesky, LinkedIn) | G90: 301 al nuevo artículo E-14 | H90: Contenido fusionado dentro del tema destino | I90: =IF(OR(D90="Consolidar",D90="Re-redactar v2026",D90="Actualizar v2026"),IFERROR(INDEX(Backlog!$X$2:$X$101,MATCH(E90,Backlog!$A$2:$A$101,0)),""),"") -> 46567
A91: https://www.continentalmedia.com.mx/2014/07/la-importancia-de-un-logotipo/ | B91: 2014 | C91: 2019-10-22 | D91: Re-redactar v2026 | E91: E-24 | F91: =IF(E91="","",IFERROR(INDEX(Backlog!$C$2:$C$101,MATCH(E91,Backlog!$A$2:$A$101,0)),"")) -> El logotipo hoy: logos adaptativos, animados y por qué importa tanto | G91: Publicar versión 2026; 301 de la URL antigua a la nueva (o conservar slug) | H91: Actualizar con tendencias de logos responsivos y motion | I91: =IF(OR(D91="Consolidar",D91="Re-redactar v2026",D91="Actualizar v2026"),IFERROR(INDEX(Backlog!$X$2:$X$101,MATCH(E91,Backlog!$A$2:$A$101,0)),""),"") -> 46455
A92: https://www.continentalmedia.com.mx/2014/08/plan-de-relaciones-publicas/ | B92: 2014 | C92: 2015-09-08 | D92: Re-redactar v2026 | E92: G-32 | F92: =IF(E92="","",IFERROR(INDEX(Backlog!$C$2:$C$101,MATCH(E92,Backlog!$A$2:$A$101,0)),"")) -> Cómo armar un plan de relaciones públicas paso a paso | G92: Publicar versión 2026; 301 de la URL antigua a la nueva (o conservar slug) | H92: Actualizar con digital PR y medición | I92: =IF(OR(D92="Consolidar",D92="Re-redactar v2026",D92="Actualizar v2026"),IFERROR(INDEX(Backlog!$X$2:$X$101,MATCH(E92,Backlog!$A$2:$A$101,0)),""),"") -> 46548
A93: https://www.continentalmedia.com.mx/2014/08/por-que-la-campana-comparte-una-coca-cola-con-ha-sido-tan-exitosa/ | B93: 2014 | C93: 2019-10-21 | D93: Consolidar | E93: E-28 | F93: =IF(E93="","",IFERROR(INDEX(Backlog!$C$2:$C$101,MATCH(E93,Backlog!$A$2:$A$101,0)),"")) -> Co-branding y alianzas de marca: casos, riesgos y lecciones | G93: 301 al nuevo artículo E-28 | H93: Contenido fusionado dentro del tema destino | I93: =IF(OR(D93="Consolidar",D93="Re-redactar v2026",D93="Actualizar v2026"),IFERROR(INDEX(Backlog!$X$2:$X$101,MATCH(E93,Backlog!$A$2:$A$101,0)),""),"") -> 46581
A94: https://www.continentalmedia.com.mx/2014/08/que-es-mejor-para-tu-empresa-una-pagina-de-facebook-o-un-sitio-web/ | B94: 2014 | C94: 2019-10-21 | D94: Re-redactar v2026 | E94: E-38 | F94: =IF(E94="","",IFERROR(INDEX(Backlog!$C$2:$C$101,MATCH(E94,Backlog!$A$2:$A$101,0)),"")) -> ¿Página de Facebook o sitio web? Por qué tu web sigue siendo tu activo principal | G94: Publicar versión 2026; 301 de la URL antigua a la nueva (o conservar slug) | H94: Argumentos 2026: propiedad de la audiencia, SEO y conversión | I94: =IF(OR(D94="Consolidar",D94="Re-redactar v2026",D94="Actualizar v2026"),IFERROR(INDEX(Backlog!$X$2:$X$101,MATCH(E94,Backlog!$A$2:$A$101,0)),""),"") -> 46343
A95: https://www.continentalmedia.com.mx/2014/09/ice-bucket-challenge/ | B95: 2014 | C95: 2019-10-21 | D95: Consolidar | E95: E-15 | F95: =IF(E95="","",IFERROR(INDEX(Backlog!$C$2:$C$101,MATCH(E95,Backlog!$A$2:$A$101,0)),"")) -> Comunidad antes que seguidores: engagement real y contenido viral con propósito | G95: 301 al nuevo artículo E-15 | H95: Contenido fusionado dentro del tema destino | I95: =IF(OR(D95="Consolidar",D95="Re-redactar v2026",D95="Actualizar v2026"),IFERROR(INDEX(Backlog!$X$2:$X$101,MATCH(E95,Backlog!$A$2:$A$101,0)),""),"") -> 46399
A96: https://www.continentalmedia.com.mx/2014/09/que-le-falta-a-tu-plan-de-negocios/ | B96: 2014 | C96: 2019-10-22 | D96: Consolidar | E96: G-01 | F96: =IF(E96="","",IFERROR(INDEX(Backlog!$C$2:$C$101,MATCH(E96,Backlog!$A$2:$A$101,0)),"")) -> Cómo crear tu plan de marketing 2027 paso a paso | G96: 301 al nuevo artículo G-01 | H96: Contenido fusionado dentro del tema destino | I96: =IF(OR(D96="Consolidar",D96="Re-redactar v2026",D96="Actualizar v2026"),IFERROR(INDEX(Backlog!$X$2:$X$101,MATCH(E96,Backlog!$A$2:$A$101,0)),""),"") -> 46314
A97: https://www.continentalmedia.com.mx/2014/10/clientes-radio-en-el-cine/ | B97: 2014 | C97: 2016-02-08 | D97: Consolidar | E97: E-45 | F97: =IF(E97="","",IFERROR(INDEX(Backlog!$C$2:$C$101,MATCH(E97,Backlog!$A$2:$A$101,0)),"")) -> Radio, TV y medios masivos en un plan de medios omnicanal 2026 | G97: 301 al nuevo artículo E-45 | H97: Contenido fusionado dentro del tema destino | I97: =IF(OR(D97="Consolidar",D97="Re-redactar v2026",D97="Actualizar v2026"),IFERROR(INDEX(Backlog!$X$2:$X$101,MATCH(E97,Backlog!$A$2:$A$101,0)),""),"") -> 46616
A98: https://www.continentalmedia.com.mx/2014/10/herramientas-marketing-digital/ | B98: 2014 | C98: 2016-02-08 | D98: Consolidar | E98: G-22 | F98: =IF(E98="","",IFERROR(INDEX(Backlog!$C$2:$C$101,MATCH(E98,Backlog!$A$2:$A$101,0)),"")) -> Herramientas de IA para marketing: cómo elegir y armar tu stack | G98: 301 al nuevo artículo G-22 | H98: Contenido fusionado dentro del tema destino | I98: =IF(OR(D98="Consolidar",D98="Re-redactar v2026",D98="Actualizar v2026"),IFERROR(INDEX(Backlog!$X$2:$X$101,MATCH(E98,Backlog!$A$2:$A$101,0)),""),"") -> 46513
A99: https://www.continentalmedia.com.mx/2014/10/marketing-360-grados/ | B99: 2014 | C99: 2016-02-08 | D99: Consolidar | E99: E-16 | F99: =IF(E99="","",IFERROR(INDEX(Backlog!$C$2:$C$101,MATCH(E99,Backlog!$A$2:$A$101,0)),"")) -> Marketing 360 en 2026: qué significa realmente y por qué sigue funcionando | G99: 301 al nuevo artículo E-16 | H99: Contenido fusionado dentro del tema destino | I99: =IF(OR(D99="Consolidar",D99="Re-redactar v2026",D99="Actualizar v2026"),IFERROR(INDEX(Backlog!$X$2:$X$101,MATCH(E99,Backlog!$A$2:$A$101,0)),""),"") -> 46329
A100: https://www.continentalmedia.com.mx/2014/11/mailing-mensajeria-negocio/ | B100: 2014 | C100: 2016-02-08 | D100: Consolidar | E100: G-42 | F100: =IF(E100="","",IFERROR(INDEX(Backlog!$C$2:$C$101,MATCH(E100,Backlog!$A$2:$A$101,0)),"")) -> Email marketing 2026: estrategia, automatizaciones y entregabilidad | G100: 301 al nuevo artículo G-42 | H100: Contenido fusionado dentro del tema destino | I100: =IF(OR(D100="Consolidar",D100="Re-redactar v2026",D100="Actualizar v2026"),IFERROR(INDEX(Backlog!$X$2:$X$101,MATCH(E100,Backlog!$A$2:$A$101,0)),""),"") -> 46569
... A111: https://www.continentalmedia.com.mx/2015/10/5-tips-para-convencer-a-tus-clientes/ | B111: 2015 | C111: 2016-02-08 | D111: Consolidar | E111: G-34 | F111: =IF(E111="","",IFERROR(INDEX(Backlog!$C$2:$C$101,MATCH(E111,Backlog!$A$2:$A$101,0)),"")) -> Cómo preparar a un vocero para entrevistas y presentaciones | G111: 301 al nuevo artículo G-34 | H111: Contenido fusionado dentro del tema destino | I111: =IF(OR(D111="Consolidar",D111="Re-redactar v2026",D111="Actualizar v2026"),IFERROR(INDEX(Backlog!$X$2:$X$101,MATCH(E111,Backlog!$A$2:$A$101,0)),""),"") -> 46555
A112: https://www.continentalmedia.com.mx/2015/11/los-5-tipos-de-personalidades-facebookeras/ | B112: 2015 | C112: 2016-02-08 | D112: Descartar | F112: =IF(E112="","",IFERROR(INDEX(Backlog!$C$2:$C$101,MATCH(E112,Backlog!$A$2:$A$101,0)),"")) | G112: 410, o 301 a /blog/ o a la categoría más cercana | H112: Contenido de coyuntura/curiosidad o fuera de los servicios actuales | I112: =IF(OR(D112="Consolidar",D112="Re-redactar v2026",D112="Actualizar v2026"),IFERROR(INDEX(Backlog!$X$2:$X$101,MATCH(E112,Backlog!$A$2:$A$101,0)),""),"")
A113: https://www.continentalmedia.com.mx/2016/02/en-que-te-beneficia-el-marketing-de-360o/ | B113: 2016 | C113: 2016-06-03 | D113: Consolidar | E113: E-16 | F113: =IF(E113="","",IFERROR(INDEX(Backlog!$C$2:$C$101,MATCH(E113,Backlog!$A$2:$A$101,0)),"")) -> Marketing 360 en 2026: qué significa realmente y por qué sigue funcionando | G113: 301 al nuevo artículo E-16 | H113: Contenido fusionado dentro del tema destino | I113: =IF(OR(D113="Consolidar",D113="Re-redactar v2026",D113="Actualizar v2026"),IFERROR(INDEX(Backlog!$X$2:$X$101,MATCH(E113,Backlog!$A$2:$A$101,0)),""),"") -> 46329
...

Sheet Cruces
A1: Desde (ID) | B1: Título desde | C1: Hacia (ID) | D1: Título hacia | E1: Tipo de cruce
A2: E-01 | B2: =IFERROR(INDEX(Backlog!$C$2:$C$101,MATCH(A2,Backlog!$A$2:$A$101,0)),"") -> IA en el marketing 2026: lo que cambió y lo que sigue siendo humano | C2: E-02 | D2: =IFERROR(INDEX(Backlog!$C$2:$C$101,MATCH(C2,Backlog!$A$2:$A$101,0)),"") -> La IA no reemplaza a tu equipo, lo multiplica: cómo trabaja una agencia en 2026 | E2: Editorial ↔ Editorial
A3: E-01 | B3: =IFERROR(INDEX(Backlog!$C$2:$C$101,MATCH(A3,Backlog!$A$2:$A$101,0)),"") -> IA en el marketing 2026: lo que cambió y lo que sigue siendo humano | C3: E-07 | D3: =IFERROR(INDEX(Backlog!$C$2:$C$101,MATCH(C3,Backlog!$A$2:$A$101,0)),"") -> De ChatGPT a los asistentes de IA: cómo evolucionó el marketing asistido | E3: Editorial ↔ Editorial
A4: E-01 | B4: =IFERROR(INDEX(Backlog!$C$2:$C$101,MATCH(A4,Backlog!$A$2:$A$101,0)),"") -> IA en el marketing 2026: lo que cambió y lo que sigue siendo humano | C4: E-09 | D4: =IFERROR(INDEX(Backlog!$C$2:$C$101,MATCH(C4,Backlog!$A$2:$A$101,0)),"") -> Tendencias de marketing 2027: lo que las marcas deben preparar desde hoy | E4: Editorial ↔ Editorial
A5: E-01 | B5: =IFERROR(INDEX(Backlog!$C$2:$C$101,MATCH(A5,Backlog!$A$2:$A$101,0)),"") -> IA en el marketing 2026: lo que cambió y lo que sigue siendo humano | C5: G-18 | D5: =IFERROR(INDEX(Backlog!$C$2:$C$101,MATCH(C5,Backlog!$A$2:$A$101,0)),"") -> 50 prompts de IA para marketing que sí funcionan | E5: Editorial ↔ Guía
A6: E-01 | B6: =IFERROR(INDEX(Backlog!$C$2:$C$101,MATCH(A6,Backlog!$A$2:$A$101,0)),"") -> IA en el marketing 2026: lo que cambió y lo que sigue siendo humano | C6: G-19 | D6: =IFERROR(INDEX(Backlog!$C$2:$C$101,MATCH(C6,Backlog!$A$2:$A$101,0)),"") -> Cómo usar IA para crear contenido sin perder tu voz de marca | E6: Editorial ↔ Guía
A7: E-01 | B7: =IFERROR(INDEX(Backlog!$C$2:$C$101,MATCH(A7,Backlog!$A$2:$A$101,0)),"") -> IA en el marketing 2026: lo que cambió y lo que sigue siendo humano | C7: G-22 | D7: =IFERROR(INDEX(Backlog!$C$2:$C$101,MATCH(C7,Backlog!$A$2:$A$101,0)),"") -> Herramientas de IA para marketing: cómo elegir y armar tu stack | E7: Editorial ↔ Guía
A8: E-02 | B8: =IFERROR(INDEX(Backlog!$C$2:$C$101,MATCH(A8,Backlog!$A$2:$A$101,0)),"") -> La IA no reemplaza a tu equipo, lo multiplica: cómo trabaja una agencia en 2026 | C8: E-04 | D8: =IFERROR(INDEX(Backlog!$C$2:$C$101,MATCH(C8,Backlog!$A$2:$A$101,0)),"") -> Agentes de IA en WhatsApp: promesas, límites y casos reales para empresas | E8: Editorial ↔ Editorial
A9: E-02 | B9: =IFERROR(INDEX(Backlog!$C$2:$C$101,MATCH(A9,Backlog!$A$2:$A$101,0)),"") -> La IA no reemplaza a tu equipo, lo multiplica: cómo trabaja una agencia en 2026 | C9: G-21 | D9: =IFERROR(INDEX(Backlog!$C$2:$C$101,MATCH(C9,Backlog!$A$2:$A$101,0)),"") -> Cómo implementar un asistente de IA en WhatsApp Business paso a paso | E9: Editorial ↔ Guía
A10: E-02 | B10: =IFERROR(INDEX(Backlog!$C$2:$C$101,MATCH(A10,Backlog!$A$2:$A$101,0)),"") -> La IA no reemplaza a tu equipo, lo multiplica: cómo trabaja una agencia en 2026 | C10: G-23 | D10: =IFERROR(INDEX(Backlog!$C$2:$C$101,MATCH(C10,Backlog!$A$2:$A$101,0)),"") -> Cómo combinar CRM, automatización y lealtad sin perder el trato humano | E10: Editorial ↔ Guía
A11: E-03 | B11: =IFERROR(INDEX(Backlog!$C$2:$C$101,MATCH(A11,Backlog!$A$2:$A$101,0)),"") -> SEO en la era de la búsqueda con IA: AI Overviews, GEO y qué hacer con tu marca | C11: E-05 | D11: =IFERROR(INDEX(Backlog!$C$2:$C$101,MATCH(C11,Backlog!$A$2:$A$101,0)),"") -> Contenido con IA sin sonar genérico: cómo conservar la voz de tu marca | E11: Editorial ↔ Editorial
A12: E-03 | B12: =IFERROR(INDEX(Backlog!$C$2:$C$101,MATCH(A12,Backlog!$A$2:$A$101,0)),"") -> SEO en la era de la búsqueda con IA: AI Overviews, GEO y qué hacer con tu marca | C12: E-11 | D12: =IFERROR(INDEX(Backlog!$C$2:$C$101,MATCH(C12,Backlog!$A$2:$A$101,0)),"") -> Social search: por qué TikTok e Instagram ya son buscadores y cómo aparecer | E12: Editorial ↔ Editorial
A13: E-03 | B13: =IFERROR(INDEX(Backlog!$C$2:$C$101,MATCH(A13,Backlog!$A$2:$A$101,0)),"") -> SEO en la era de la búsqueda con IA: AI Overviews, GEO y qué hacer con tu marca | C13: G-24 | D13: =IFERROR(INDEX(Backlog!$C$2:$C$101,MATCH(C13,Backlog!$A$2:$A$101,0)),"") -> Cómo optimizar tu contenido para buscadores con IA (GEO) | E13: Editorial ↔ Guía
... A209: G-47 | B209: =IFERROR(INDEX(Backlog!$C$2:$C$101,MATCH(A209,Backlog!$A$2:$A$101,0)),"") -> Cómo planear una sesión de fotos de producto o gastronómica | C209: G-49 | D209: =IFERROR(INDEX(Backlog!$C$2:$C$101,MATCH(C209,Backlog!$A$2:$A$101,0)),"") -> Marketing para restaurantes: redes, menú, reservaciones y reseñas | E209: Guía ↔ Guía

Sheet Pilares
A1: Código | B1: Pilar | C1: Servicio que impulsa (provisional) | D1: Editoriales | E1: Guías prácticas | F1: Total
A2: P1 | B2: Estrategia de marketing y contenidos | C2: Estrategia de marketing 360 | D2: =COUNTIFS(Backlog!$D$2:$D$101,B2,Backlog!$B$2:$B$101,"Editorial") -> 7 | E2: =COUNTIFS(Backlog!$D$2:$D$101,B2,Backlog!$B$2:$B$101,"Guía práctica") -> 8 | F2: =D2+E2 -> 15
A3: P2 | B3: Redes sociales y comunidad | C3: Gestión de redes sociales y community management | D3: =COUNTIFS(Backlog!$D$2:$D$101,B3,Backlog!$B$2:$B$101,"Editorial") -> 6 | E3: =COUNTIFS(Backlog!$D$2:$D$101,B3,Backlog!$B$2:$B$101,"Guía práctica") -> 9 | F3: =D3+E3 -> 15
A4: P3 | B4: IA aplicada al marketing | C4: IA aplicada a marketing y comunicación | D4: =COUNTIFS(Backlog!$D$2:$D$101,B4,Backlog!$B$2:$B$101,"Editorial") -> 8 | E4: =COUNTIFS(Backlog!$D$2:$D$101,B4,Backlog!$B$2:$B$101,"Guía práctica") -> 8 | F4: =D4+E4 -> 16
A5: P4 | B5: Branding, diseño y creatividad | C5: Branding, identidad y diseño gráfico | D5: =COUNTIFS(Backlog!$D$2:$D$101,B5,Backlog!$B$2:$B$101,"Editorial") -> 9 | E5: =COUNTIFS(Backlog!$D$2:$D$101,B5,Backlog!$B$2:$B$101,"Guía práctica") -> 5 | F5: =D5+E5 -> 14
A6: P5 | B6: Relaciones públicas y comunicación | C6: Relaciones públicas y comunicación corporativa | D6: =COUNTIFS(Backlog!$D$2:$D$101,B6,Backlog!$B$2:$B$101,"Editorial") -> 5 | E6: =COUNTIFS(Backlog!$D$2:$D$101,B6,Backlog!$B$2:$B$101,"Guía práctica") -> 4 | F6: =D6+E6 -> 9
A7: P6 | B7: Web, SEO y publicidad digital | C7: Diseño y desarrollo web, SEO y publicidad digital | D7: =COUNTIFS(Backlog!$D$2:$D$101,B7,Backlog!$B$2:$B$101,"Editorial") -> 5 | E7: =COUNTIFS(Backlog!$D$2:$D$101,B7,Backlog!$B$2:$B$101,"Guía práctica") -> 10 | F7: =D7+E7 -> 15
A8: P7 | B8: Video y fotografía | C8: Producción de video y fotografía | D8: =COUNTIFS(Backlog!$D$2:$D$101,B8,Backlog!$B$2:$B$101,"Editorial") -> 3 | E8: =COUNTIFS(Backlog!$D$2:$D$101,B8,Backlog!$B$2:$B$101,"Guía práctica") -> 3 | F8: =D8+E8 -> 6
A9: P8 | B9: Eventos, medios y publicidad exterior | C9: Eventos, patrocinios y medios | D9: =COUNTIFS(Backlog!$D$2:$D$101,B9,Backlog!$B$2:$B$101,"Editorial") -> 3 | E9: =COUNTIFS(Backlog!$D$2:$D$101,B9,Backlog!$B$2:$B$101,"Guía práctica") -> 1 | F9: =D9+E9 -> 4
A10: P9 | B10: Marketing por industria y mercado | C10: Marketing por industria y mercado hispano | D10: =COUNTIFS(Backlog!$D$2:$D$101,B10,Backlog!$B$2:$B$101,"Editorial") -> 4 | E10: =COUNTIFS(Backlog!$D$2:$D$101,B10,Backlog!$B$2:$B$101,"Guía práctica") -> 2 | F10: =D10+E10 -> 6
B11: Total | D11: =SUM(D2:D10) -> 50 | E11: =SUM(E2:E10) -> 50 | F11: =SUM(F2:F10) -> 100
A13: Los pilares son provisionales: la sección de servicios del sitio temporal aún no está publicada. Se infirieron del sitio nuevo (marketing digital, comunicación, diseño, RP, IA), del sitio actual (branding, community management, Google Ads, web y SEO, video, comunicados) y del portafolio.

Sheet Esquema
A1: Esquema del archivo (para carga en Claude Code)
A2: Fuente de verdad: hoja Backlog (una fila por artículo, encabezado en fila 1, sin celdas combinadas). Fechas en formato ISO yyyy-mm-dd.
A4: Columna | B4: Campo | C4: Descripción / valores
A5: A | B5: ID | C5: Identificador único. E-xx = editorial, G-xx = guía práctica. Es la llave para Cruces y Posts actuales.
A6: B | B6: Tipo | C6: Editorial | Guía práctica.
A7: C | B7: Título tentativo | C7: Título de trabajo; el H1 final se afina con la keyword validada.
A8: D | B8: Pilar | C8: Uno de los 9 pilares (hoja Pilares). Define categoría del blog.
A9: E | B9: Keyword semilla | C9: Por validar con volumen y dificultad (columnas U y V).
A10: F | B10: Intención de búsqueda | C10: Informacional, comercial, etc.
A11: G | B11: Etapa del embudo | C11: TOFU | MOFU | BOFU.
A12: H | B12: Objetivo SEO | C12: Meta de posicionamiento del tema.
A13: I | B13: Audiencia / sector | C13: Público al que se dirige.
A14: J | B14: Mercado | C14: México, EE.UU. o ambos.
A15: K | B15: Origen | C15: Re-redacción 2026 (existe artículo base en el blog actual) | Nuevo.
... A30: AA | B30: Lote | C30: Fórmula: «Lanzamiento» (8 artículos del 19/10/2026) | «Calendario semanal».
A32: Otras hojas
A33: • Resumen: indicadores, calendario mensual y notas.
A34: • Posts actuales: 188 URLs del blog actual con decisión (re-redactar, actualizar, consolidar, mantener, descartar), tema destino y fecha de activación del 301.
A35: • Cruces: pares de enlazado interno entre temas.
A36: • Pilares: los 9 pilares provisionales y su conteo de temas.
