Workbook

Sheet Resumen
A1: Inventario de URLs – continentalmedia.com.mx
A2: Fuente: sitemaps del sitio (generado con script). Fecha de corte: 14/10/2026. Solo URLs publicadas en sitemap; no confirma indexación en Google.
A4: Grupo | B4: Total URLs | C4: Con código HTTP 200 | D4: A revisar (≠200) | E4: Qué contiene
A5: Páginas | B5: =COUNTA(Páginas!A2:A1000)-0 -> 11 | C5: =COUNTIF(Páginas!E2:E1000,200) -> 9 | D5: =B5-C5 -> 2 | E5: Páginas del sitio (home, contacto, servicios, etc.)
A6: Blog | B6: =COUNTA(Blog!A2:A1000)-0 -> 188 | C6: =COUNTIF(Blog!E2:E1000,200) -> 188 | D6: =B6-C6 -> 0 | E6: Entradas del blog
A7: Portafolio | B7: =COUNTA(Portafolio!A2:A1000)-0 -> 216 | C7: =COUNTIF(Portafolio!E2:E1000,200) -> 11 | D7: =B7-C7 -> 205 | E7: Casos del portafolio
A8: Categorías | B8: =COUNTA(Categorías!A2:A1000)-0 -> 38 | C8: =COUNTIF(Categorías!E2:E1000,200) -> 12 | D8: =B8-C8 -> 26 | E8: Categorías de blog, de portafolio y testimonios
A9: Imágenes | B9: =COUNTA(Imágenes!A2:A1000)-0 -> 516 | C9: =COUNTIF(Imágenes!E2:E1000,200) -> 213 | D9: =B9-C9 -> 303 | E9: Páginas de adjuntos (una por imagen); normalmente se redirigen a su página padre
A10: Total | B10: =SUM(B5:B9) -> 969 | C10: =SUM(C5:C9) -> 433 | D10: =SUM(D5:D9) -> 536
A12: Notas
A13: • Duplicados exactos encontrados y eliminados: 0 (se comparó la URL sin mayúsculas, www, barra final ni parámetros). Lo que parecía duplicado son páginas de imágenes (hoja Imágenes) y portafolios con slug -2/-3 (columna Observaciones).
A14: • Las columnas en amarillo (Acción y URL nueva) son para llenar durante la migración.
A15: • Código HTTP ≠ 200: gran parte son errores 500 por saturación del servidor al revisar muchas URLs a la vez. Verifícalas de nuevo antes de decidir.
A16: • "Posible duplicado" = slug con sufijo -2, -3 cuyo original también existe. Revisa antes de eliminar.
A17: • Las columnas de Search Console (impresiones/clics) se quitaron porque estaban vacías; vuelve a agregarlas con el export de Rendimiento > Páginas.
A20: Tratamiento propuesto (versión de transición · 19/10/2026)
A21: Grupo | B21: 301 | C21: 404 | D21: Sin cambio | E21: Total
A22: Páginas | B22: =COUNTIFS('Mapa maestro'!$C$2:$C$970,$A22,'Mapa maestro'!$E$2:$E$970,"301") -> 5 | C22: =COUNTIFS('Mapa maestro'!$C$2:$C$970,$A22,'Mapa maestro'!$E$2:$E$970,"404") -> 5 | D22: =COUNTIFS('Mapa maestro'!$C$2:$C$970,$A22,'Mapa maestro'!$E$2:$E$970,"Sin cambio") -> 1 | E22: =SUM(B22:D22) -> 11
A23: Blog | B23: =COUNTIFS('Mapa maestro'!$C$2:$C$970,$A23,'Mapa maestro'!$E$2:$E$970,"301") -> 161 | C23: =COUNTIFS('Mapa maestro'!$C$2:$C$970,$A23,'Mapa maestro'!$E$2:$E$970,"404") -> 24 | D23: =COUNTIFS('Mapa maestro'!$C$2:$C$970,$A23,'Mapa maestro'!$E$2:$E$970,"Sin cambio") -> 1 | E23: =SUM(B23:D23) -> 186
A24: Portafolio | B24: =COUNTIFS('Mapa maestro'!$C$2:$C$970,$A24,'Mapa maestro'!$E$2:$E$970,"301") -> 216 | C24: =COUNTIFS('Mapa maestro'!$C$2:$C$970,$A24,'Mapa maestro'!$E$2:$E$970,"404") -> 0 | D24: =COUNTIFS('Mapa maestro'!$C$2:$C$970,$A24,'Mapa maestro'!$E$2:$E$970,"Sin cambio") -> 0 | E24: =SUM(B24:D24) -> 216
A25: Categorías | B25: =COUNTIFS('Mapa maestro'!$C$2:$C$970,$A25,'Mapa maestro'!$E$2:$E$970,"301") -> 38 | C25: =COUNTIFS('Mapa maestro'!$C$2:$C$970,$A25,'Mapa maestro'!$E$2:$E$970,"404") -> 0 | D25: =COUNTIFS('Mapa maestro'!$C$2:$C$970,$A25,'Mapa maestro'!$E$2:$E$970,"Sin cambio") -> 0 | E25: =SUM(B25:D25) -> 38
A26: Imágenes | B26: =COUNTIFS('Mapa maestro'!$C$2:$C$970,$A26,'Mapa maestro'!$E$2:$E$970,"301") -> 351 | C26: =COUNTIFS('Mapa maestro'!$C$2:$C$970,$A26,'Mapa maestro'!$E$2:$E$970,"404") -> 165 | D26: =COUNTIFS('Mapa maestro'!$C$2:$C$970,$A26,'Mapa maestro'!$E$2:$E$970,"Sin cambio") -> 0 | E26: =SUM(B26:D26) -> 516
A27: Total | B27: =SUM(B22:B26) -> 771 | C27: =SUM(C22:C26) -> 194 | D27: =SUM(D22:D26) -> 2 | E27: =SUM(E22:E26) -> 967
A29: Blog: qué pasa el día del corte
A30: Indicador | B30: Valor
A31: Fecha de corte (editable en hoja Destinos) | B31: =Destinos!B5 -> 46321
A32: Posts con 301 hacia un artículo | B32: =COUNTIFS('Mapa maestro'!$C$2:$C$970,"Blog",'Mapa maestro'!$F$2:$F$970,"ARTICULO") -> 158
A33: · ya van directo al artículo publicado al corte | B33: =COUNTIFS('Mapa maestro'!$C$2:$C$970,"Blog",'Mapa maestro'!$F$2:$F$970,"ARTICULO",'Mapa maestro'!$I$2:$I$970,"<="&Destinos!B5) -> 21
A34: · van provisionalmente a la categoría o a /blog/ hasta publicar su artículo | B34: =B32-B33 -> 137
A35: Posts descartados (404) | B35: =COUNTIFS('Mapa maestro'!$C$2:$C$970,"Blog",'Mapa maestro'!$E$2:$E$970,"404") -> 24
A36: Última fecha de cambio a destino final (último artículo) | B36: =MAX('Mapa maestro'!$N$2:$N$970) -> 46630
A38: Notas de la versión de transición
A39: • Hojas nuevas: Reglas (criterios), Destinos (rutas y parámetros editables) y Mapa maestro (una fila por URL, fuente para la implementación). Las columnas Acción y URL nueva de cada hoja se leen del Mapa maestro; para cambiar una decisión, editar ahí.
A40: • Host canónico y fecha de corte son supuestos (hoja Destinos). Las rutas /proyectos/, /nosotros/, anclas del home y categorías del blog son propuestas por confirmar con el sitio definitivo.
A41: • Sin datos de Search Console ni de enlaces entrantes no se puede priorizar por valor SEO real: llenar las columnas amarillas Clics y Dominios del Mapa maestro; cualquier 404 con clics o enlaces se marca solo como REVISAR.
A42: • Estados HTTP ≠ 200 del inventario (en su mayoría 500 por saturación al revisar) no cambian el tratamiento: se decide por el tipo de URL, no por el estado del día de la revisión.

Sheet Lista corta
A1: Lista corta de URLs que se atienden en el corte
A2: Criterio: páginas principales + toda URL con 2 o más clics en 16 meses (Search Console, 26-oct-2026) + los 2 posts que se conservan. Todo lo demás del mapa responde 404 con la página personalizada. Destinos y fechas se leen en vivo del Mapa maestro.
A4: # | B4: Ruta origen | C4: Grupo | D4: Clics 16m | E4: Acción final | F4: Ruta destino al corte | G4: Destino final | H4: Fecha de cambio al destino final | I4: Nota
A5: 1 | B5: ='Mapa maestro'!B42 -> /2013/04/historia-de-la-publicidad-en-mexico/ | C5: ='Mapa maestro'!C42 -> Blog | D5: =N('Mapa maestro'!Q42) -> 202 | E5: ='Mapa maestro'!U42 -> 200 · misma URL | F5: ='Mapa maestro'!K42 -> /2013/04/historia-de-la-publicidad-en-mexico/ | G5: ='Mapa maestro'!M42 -> Misma URL: se republica actualizado en el blog nuevo | H5: =IF('Mapa maestro'!N42="","",'Mapa maestro'!N42) | I5: ='Mapa maestro'!P42 -> Junto con el otro post conservado suma el 34% de los clics del sitio viejo; se conserva la ruta heredada (/AAAA/MM/slug/) en el blog nuevo.
A6: 2 | B6: ='Mapa maestro'!B81 -> /2014/02/pioneros-de-la-publicidad-en-mexico/ | C6: ='Mapa maestro'!C81 -> Blog | D6: =N('Mapa maestro'!Q81) -> 48 | E6: ='Mapa maestro'!U81 -> 200 · misma URL | F6: ='Mapa maestro'!K81 -> /2014/02/pioneros-de-la-publicidad-en-mexico/ | G6: ='Mapa maestro'!M81 -> Misma URL: se republica actualizado en el blog nuevo | H6: =IF('Mapa maestro'!N81="","",'Mapa maestro'!N81) | I6: ='Mapa maestro'!P81 -> Junto con el otro post conservado suma el 34% de los clics del sitio viejo; se conserva la ruta heredada (/AAAA/MM/slug/) en el blog nuevo.
A7: 3 | B7: ='Mapa maestro'!B135 -> /2016/11/el-poder-de-la-radio-como-medio-de-comunicacion-publicitaria/ | C7: ='Mapa maestro'!C135 -> Blog | D7: =N('Mapa maestro'!Q135) -> 24 | E7: ='Mapa maestro'!U135 -> 301 | F7: ='Mapa maestro'!K135 -> /blog/ | G7: ='Mapa maestro'!M135 -> Artículo E-45 → /blog/<slug>/ | H7: =IF('Mapa maestro'!N135="","",'Mapa maestro'!N135) -> 46616 | I7: ='Mapa maestro'!P135 -> 0
A8: 4 | B8: ='Mapa maestro'!B46 -> /2013/05/leyes-gestalt/ | C8: ='Mapa maestro'!C46 -> Blog | D8: =N('Mapa maestro'!Q46) -> 21 | E8: ='Mapa maestro'!U46 -> 301 | F8: ='Mapa maestro'!K46 -> /blog/ | G8: ='Mapa maestro'!M46 -> Artículo E-29 → /blog/<slug>/ | H8: =IF('Mapa maestro'!N46="","",'Mapa maestro'!N46) -> 46476 | I8: ='Mapa maestro'!P46 -> 0
A9: 5 | B9: ='Mapa maestro'!B5 -> /contacto/ | C9: ='Mapa maestro'!C5 -> Páginas | D9: =N('Mapa maestro'!Q5) -> 16 | E9: ='Mapa maestro'!U5 -> 301 | F9: ='Mapa maestro'!K5 -> /#contacto | G9: ='Mapa maestro'!M5 -> /#contacto | H9: =IF('Mapa maestro'!N5="","",'Mapa maestro'!N5) | I9: ='Mapa maestro'!P5 -> 0
A10: 6 | B10: ='Mapa maestro'!B350 -> /portfolio/manteleta-para-cata-de-vino/ | C10: ='Mapa maestro'!C350 -> Portafolio | D10: =N('Mapa maestro'!Q350) -> 9 | E10: ='Mapa maestro'!U350 -> 301 | F10: ='Mapa maestro'!K350 -> /proyectos/ | G10: ='Mapa maestro'!M350 -> /proyectos/ | H10: =IF('Mapa maestro'!N350="","",'Mapa maestro'!N350) | I10: ='Mapa maestro'!P350 -> 0
A11: 7 | B11: ='Mapa maestro'!B353 -> /portfolio/organigrama/ | C11: ='Mapa maestro'!C353 -> Portafolio | D11: =N('Mapa maestro'!Q353) -> 9 | E11: ='Mapa maestro'!U353 -> 301 | F11: ='Mapa maestro'!K353 -> /proyectos/ | G11: ='Mapa maestro'!M353 -> /proyectos/ | H11: =IF('Mapa maestro'!N353="","",'Mapa maestro'!N353) | I11: ='Mapa maestro'!P353 -> 0
A12: 8 | B12: ='Mapa maestro'!B120 -> /2015/08/6-secretos-para-diseñar-un-logotipo-exitoso/ | C12: ='Mapa maestro'!C120 -> Blog | D12: =N('Mapa maestro'!Q120) -> 8 | E12: ='Mapa maestro'!U120 -> 301 | F12: ='Mapa maestro'!K120 -> /blog/ | G12: ='Mapa maestro'!M120 -> Artículo G-28 → /blog/<slug>/ | H12: =IF('Mapa maestro'!N120="","",'Mapa maestro'!N120) -> 46527 | I12: ='Mapa maestro'!P120 -> 0
A13: 9 | B13: ='Mapa maestro'!B16 -> /2012/12/campanas-exitosas-del-2012/ | C13: ='Mapa maestro'!C16 -> Blog | D13: =N('Mapa maestro'!Q16) -> 7 | E13: ='Mapa maestro'!U16 -> 301 | F13: ='Mapa maestro'!K16 -> /blog/ | G13: ='Mapa maestro'!M16 -> /blog/ | H13: =IF('Mapa maestro'!N16="","",'Mapa maestro'!N16) | I13: ='Mapa maestro'!P16 -> Descartado en el backlog pero con clics (2 a 7 en 16 meses); decisión: 301 al índice del blog.
A14: 10 | B14: ='Mapa maestro'!B162 -> /2022/01/marketing-para-publico-hispano-en-eeuu/ | C14: ='Mapa maestro'!C162 -> Blog | D14: =N('Mapa maestro'!Q162) -> 7 | E14: ='Mapa maestro'!U162 -> 301 | F14: ='Mapa maestro'!K162 -> /blog/ | G14: ='Mapa maestro'!M162 -> Artículo E-47 → /blog/<slug>/ | H14: =IF('Mapa maestro'!N162="","",'Mapa maestro'!N162) -> 46350 | I14: ='Mapa maestro'!P162 -> 0
A15: 11 | B15: ='Mapa maestro'!B127 -> /2016/04/10-alternativas-de-publicidad-de-paga-en-internet/ | C15: ='Mapa maestro'!C127 -> Blog | D15: =N('Mapa maestro'!Q127) -> 6 | E15: ='Mapa maestro'!U127 -> 301 | F15: ='Mapa maestro'!K127 -> /blog/ | G15: ='Mapa maestro'!M127 -> Artículo G-38 → /blog/<slug>/ | H15: =IF('Mapa maestro'!N127="","",'Mapa maestro'!N127) -> 46408 | I15: ='Mapa maestro'!P127 -> 0
A16: 12 | B16: ='Mapa maestro'!B152 -> /2020/01/10-pasos-para-hacer-un-brief-de-redes-sociales/ | C16: ='Mapa maestro'!C152 -> Blog | D16: =N('Mapa maestro'!Q152) -> 6 | E16: ='Mapa maestro'!U152 -> 301 | F16: ='Mapa maestro'!K152 -> /blog/categoria/estrategia-de-marketing/ | G16: ='Mapa maestro'!M152 -> Artículo G-04 → /blog/<slug>/ | H16: =IF('Mapa maestro'!N152="","",'Mapa maestro'!N152) -> 46457 | I16: ='Mapa maestro'!P152 -> 0
A17: 13 | B17: ='Mapa maestro'!B423 -> /marketing/ | C17: ='Mapa maestro'!C423 -> Categorías | D17: =N('Mapa maestro'!Q423) -> 6 | E17: ='Mapa maestro'!U423 -> 301 | F17: ='Mapa maestro'!K423 -> /blog/categoria/estrategia-de-marketing/ | G17: ='Mapa maestro'!M423 -> /blog/categoria/estrategia-de-marketing/ | H17: =IF('Mapa maestro'!N423="","",'Mapa maestro'!N423) | I17: ='Mapa maestro'!P423 -> Si la categoría nueva aún no tiene artículos al corte, va a /blog/
A18: 14 | B18: ='Mapa maestro'!B309 -> /portfolio/il-veneziano-menu-de-fin-de-ano-2019/ | C18: ='Mapa maestro'!C309 -> Portafolio | D18: =N('Mapa maestro'!Q309) -> 6 | E18: ='Mapa maestro'!U309 -> 301 | F18: ='Mapa maestro'!K309 -> /proyectos/ | G18: ='Mapa maestro'!M309 -> /proyectos/ | H18: =IF('Mapa maestro'!N309="","",'Mapa maestro'!N309) | I18: ='Mapa maestro'!P309 -> 0
A19: 15 | B19: ='Mapa maestro'!B45 -> /2013/05/cuanto-valen-las-ideas/ | C19: ='Mapa maestro'!C45 -> Blog | D19: =N('Mapa maestro'!Q45) -> 5 | E19: ='Mapa maestro'!U45 -> 301 | F19: ='Mapa maestro'!K45 -> /blog/ | G19: ='Mapa maestro'!M45 -> Artículo E-33 → /blog/<slug>/ | H19: =IF('Mapa maestro'!N45="","",'Mapa maestro'!N45) -> 46504 | I19: ='Mapa maestro'!P45 -> 0
A20: 16 | B20: ='Mapa maestro'!B4 -> /agencia-de-publicidad/ | C20: ='Mapa maestro'!C4 -> Páginas | D20: =N('Mapa maestro'!Q4) -> 5 | E20: ='Mapa maestro'!U4 -> 301 | F20: ='Mapa maestro'!K4 -> / | G20: ='Mapa maestro'!M4 -> / | H20: =IF('Mapa maestro'!N4="","",'Mapa maestro'!N4) | I20: ='Mapa maestro'!P4 -> Landing con la keyword «agencia de publicidad»: reflejarla en title/H1 del home nuevo
A21: 17 | B21: ='Mapa maestro'!B12 -> /usa/ | C21: ='Mapa maestro'!C12 -> Páginas | D21: =N('Mapa maestro'!Q12) -> 5 | E21: ='Mapa maestro'!U12 -> 301 | F21: ='Mapa maestro'!K12 -> / | G21: ='Mapa maestro'!M12 -> / | H21: =IF('Mapa maestro'!N12="","",'Mapa maestro'!N12) | I21: ='Mapa maestro'!P12 -> Revisar contenido original (HTTP 500 en la revisión). Candidata a tema E-47 (consumidor hispano en EE.UU.) cuando se publique
A22: 18 | B22: ='Mapa maestro'!B104 -> /2014/08/por-que-la-campana-comparte-una-coca-cola-con-ha-sido-tan-exitosa/ | C22: ='Mapa maestro'!C104 -> Blog | D22: =N('Mapa maestro'!Q104) -> 4 | E22: ='Mapa maestro'!U104 -> 301 | F22: ='Mapa maestro'!K104 -> /blog/ | G22: ='Mapa maestro'!M104 -> Artículo E-28 → /blog/<slug>/ | H22: =IF('Mapa maestro'!N104="","",'Mapa maestro'!N104) -> 46581 | I22: ='Mapa maestro'!P104 -> 0
A23: 19 | B23: ='Mapa maestro'!B28 -> /2012/12/por-que-una-imagen-resulta-tan-poderosa/ | C23: ='Mapa maestro'!C28 -> Blog | D23: =N('Mapa maestro'!Q28) -> 3 | E23: ='Mapa maestro'!U28 -> 301 | F23: ='Mapa maestro'!K28 -> /blog/ | G23: ='Mapa maestro'!M28 -> Artículo E-20 → /blog/<slug>/ | H23: =IF('Mapa maestro'!N28="","",'Mapa maestro'!N28) -> 46427 | I23: ='Mapa maestro'!P28 -> 0
A24: 20 | B24: ='Mapa maestro'!B168 -> /2022/05/que-es-uber-one-nosotros-te-lo-explicamos/ | C24: ='Mapa maestro'!C168 -> Blog | D24: =N('Mapa maestro'!Q168) -> 3 | E24: ='Mapa maestro'!U168 -> 301 | F24: ='Mapa maestro'!K168 -> /blog/ | G24: ='Mapa maestro'!M168 -> /blog/ | H24: =IF('Mapa maestro'!N168="","",'Mapa maestro'!N168) | I24: ='Mapa maestro'!P168 -> Descartado en el backlog pero con clics (2 a 7 en 16 meses); decisión: 301 al índice del blog.
A25: 21 | B25: ='Mapa maestro'!B192 -> /2023/12/guia-de-publicidad-para-fin-de-ano/ | C25: ='Mapa maestro'!C192 -> Blog | D25: =N('Mapa maestro'!Q192) -> 3 | E25: ='Mapa maestro'!U192 -> 301 | F25: ='Mapa maestro'!K192 -> [artículo G-07] /blog/<slug>/ | G25: ='Mapa maestro'!M192 -> Artículo G-07 → /blog/<slug>/ | H25: =IF('Mapa maestro'!N192="","",'Mapa maestro'!N192) -> 46314 | I25: ='Mapa maestro'!P192 -> 0
A26: 22 | B26: ='Mapa maestro'!B10 -> /portafolio/ | C26: ='Mapa maestro'!C10 -> Páginas | D26: =N('Mapa maestro'!Q10) -> 3 | E26: ='Mapa maestro'!U10 -> 301 | F26: ='Mapa maestro'!K10 -> /proyectos/ | G26: ='Mapa maestro'!M10 -> /proyectos/ | H26: =IF('Mapa maestro'!N10="","",'Mapa maestro'!N10) | I26: ='Mapa maestro'!P10 -> 0
A27: 23 | B27: ='Mapa maestro'!B73 -> /2013/12/las-campanas-mexicanas-mas-premiadas-de-2013/ | C27: ='Mapa maestro'!C73 -> Blog | D27: =N('Mapa maestro'!Q73) -> 2 | E27: ='Mapa maestro'!U73 -> 301 | F27: ='Mapa maestro'!K73 -> /blog/ | G27: ='Mapa maestro'!M73 -> /blog/ | H27: =IF('Mapa maestro'!N73="","",'Mapa maestro'!N73) | I27: ='Mapa maestro'!P73 -> Descartado en el backlog pero con clics (2 a 7 en 16 meses); decisión: 301 al índice del blog.
A28: 24 | B28: ='Mapa maestro'!B121 -> /2015/09/la-tercera-edad-el-nicho-de-mercado-inesperado/ | C28: ='Mapa maestro'!C121 -> Blog | D28: =N('Mapa maestro'!Q121) -> 2 | E28: ='Mapa maestro'!U121 -> 301 | F28: ='Mapa maestro'!K121 -> /blog/ | G28: ='Mapa maestro'!M121 -> Artículo E-49 → /blog/<slug>/ | H28: =IF('Mapa maestro'!N121="","",'Mapa maestro'!N121) -> 46630 | I28: ='Mapa maestro'!P121 -> 0
A29: 25 | B29: ='Mapa maestro'!B137 -> /2016/12/el-patrocinio-de-eventos-una-estrategia-clave-para-tu-marca/ | C29: ='Mapa maestro'!C137 -> Blog | D29: =N('Mapa maestro'!Q137) -> 2 | E29: ='Mapa maestro'!U137 -> 301 | F29: ='Mapa maestro'!K137 -> /blog/ | G29: ='Mapa maestro'!M137 -> Artículo E-46 → /blog/<slug>/ | H29: =IF('Mapa maestro'!N137="","",'Mapa maestro'!N137) -> 46623 | I29: ='Mapa maestro'!P137 -> 0
A30: 26 | B30: ='Mapa maestro'!B148 -> /2018/03/como-hacer-un-giveaway-en-5-sencillos-pasos/ | C30: ='Mapa maestro'!C148 -> Blog | D30: =N('Mapa maestro'!Q148) -> 2 | E30: ='Mapa maestro'!U148 -> 301 | F30: ='Mapa maestro'!K148 -> /blog/categoria/redes-sociales/ | G30: ='Mapa maestro'!M148 -> Artículo G-13 → /blog/<slug>/ | H30: =IF('Mapa maestro'!N148="","",'Mapa maestro'!N148) -> 46604 | I30: ='Mapa maestro'!P148 -> 0
A31: 27 | B31: ='Mapa maestro'!B193 -> /2024/01/10-tips-para-optimizar-tus-ads-de-facebook-en-2024/ | C31: ='Mapa maestro'!C193 -> Blog | D31: =N('Mapa maestro'!Q193) -> 2 | E31: ='Mapa maestro'!U193 -> 301 | F31: ='Mapa maestro'!K193 -> /blog/ | G31: ='Mapa maestro'!M193 -> Artículo G-39 → /blog/<slug>/ | H31: =IF('Mapa maestro'!N193="","",'Mapa maestro'!N193) -> 46415 | I31: ='Mapa maestro'!P193 -> 0
A32: 28 | B32: ='Mapa maestro'!B195 -> /2025/07/como-aprovechar-la-inteligencia-artificial-en-el-marketing-6-herramientas-que-transformaran-tu-negocio/ | C32: ='Mapa maestro'!C195 -> Blog | D32: =N('Mapa maestro'!Q195) -> 2 | E32: ='Mapa maestro'!U195 -> 301 | F32: ='Mapa maestro'!K195 -> /blog/categoria/ia-aplicada-al-marketing/ | G32: ='Mapa maestro'!M195 -> Artículo G-22 → /blog/<slug>/ | H32: =IF('Mapa maestro'!N195="","",'Mapa maestro'!N195) -> 46513 | I32: ='Mapa maestro'!P195 -> Post de 2025: conviene adelantar su artículo destino en el calendario
A33: 29 | B33: ='Mapa maestro'!B421 -> /inteligencia-artificial/ | C33: ='Mapa maestro'!C421 -> Categorías | D33: =N('Mapa maestro'!Q421) -> 2 | E33: ='Mapa maestro'!U421 -> 301 | F33: ='Mapa maestro'!K421 -> /blog/categoria/ia-aplicada-al-marketing/ | G33: ='Mapa maestro'!M421 -> /blog/categoria/ia-aplicada-al-marketing/ | H33: =IF('Mapa maestro'!N421="","",'Mapa maestro'!N421) | I33: ='Mapa maestro'!P421 -> Si la categoría nueva aún no tiene artículos al corte, va a /blog/
A34: 30 | B34: ='Mapa maestro'!B8 -> /nuestros-servicios/ | C34: ='Mapa maestro'!C8 -> Páginas | D34: =N('Mapa maestro'!Q8) -> 2 | E34: ='Mapa maestro'!U8 -> 301 | F34: ='Mapa maestro'!K8 -> /#servicios | G34: ='Mapa maestro'!M8 -> /#servicios | H34: =IF('Mapa maestro'!N8="","",'Mapa maestro'!N8) | I34: ='Mapa maestro'!P8 -> 0
A35: 31 | B35: ='Mapa maestro'!B822 -> /portfolio/estanciaboca/provisa-espectacular/ | C35: ='Mapa maestro'!C822 -> Imágenes | D35: =N('Mapa maestro'!Q822) -> 2 | E35: ='Mapa maestro'!U822 -> 301 | F35: ='Mapa maestro'!K822 -> /proyectos/ | G35: ='Mapa maestro'!M822 -> /proyectos/ | H35: =IF('Mapa maestro'!N822="","",'Mapa maestro'!N822) | I35: ='Mapa maestro'!P822 -> 0
A36: 32 | B36: ='Mapa maestro'!B287 -> /portfolio/fraccionamiento-albatros-anuncio-periodico/ | C36: ='Mapa maestro'!C287 -> Portafolio | D36: =N('Mapa maestro'!Q287) -> 2 | E36: ='Mapa maestro'!U287 -> 301 | F36: ='Mapa maestro'!K287 -> /proyectos/ | G36: ='Mapa maestro'!M287 -> /proyectos/ | H36: =IF('Mapa maestro'!N287="","",'Mapa maestro'!N287) | I36: ='Mapa maestro'!P287 -> 0
A37: 33 | B37: ='Mapa maestro'!B288 -> /portfolio/fraccionamiento-albatros-fryer/ | C37: ='Mapa maestro'!C288 -> Portafolio | D37: =N('Mapa maestro'!Q288) -> 2 | E37: ='Mapa maestro'!U288 -> 301 | F37: ='Mapa maestro'!K288 -> /proyectos/ | G37: ='Mapa maestro'!M288 -> /proyectos/ | H37: =IF('Mapa maestro'!N288="","",'Mapa maestro'!N288) | I37: ='Mapa maestro'!P288 -> 0
A38: 34 | B38: ='Mapa maestro'!B297 -> /portfolio/hoja-membretada-vermara/ | C38: ='Mapa maestro'!C297 -> Portafolio | D38: =N('Mapa maestro'!Q297) -> 2 | E38: ='Mapa maestro'!U297 -> 301 | F38: ='Mapa maestro'!K297 -> /proyectos/ | G38: ='Mapa maestro'!M297 -> /proyectos/ | H38: =IF('Mapa maestro'!N297="","",'Mapa maestro'!N297) | I38: ='Mapa maestro'!P297 -> 0
A39: 35 | B39: ='Mapa maestro'!B321 -> /portfolio/la-hilacha-logotipo/ | C39: ='Mapa maestro'!C321 -> Portafolio | D39: =N('Mapa maestro'!Q321) -> 2 | E39: ='Mapa maestro'!U321 -> 301 | F39: ='Mapa maestro'!K321 -> /proyectos/ | G39: ='Mapa maestro'!M321 -> /proyectos/ | H39: =IF('Mapa maestro'!N321="","",'Mapa maestro'!N321) | I39: ='Mapa maestro'!P321 -> 0
A40: 36 | B40: ='Mapa maestro'!B333 -> /portfolio/logo-porteadores-del-centro-de-veracruz/ | C40: ='Mapa maestro'!C333 -> Portafolio | D40: =N('Mapa maestro'!Q333) -> 2 | E40: ='Mapa maestro'!U333 -> 301 | F40: ='Mapa maestro'!K333 -> /proyectos/ | G40: ='Mapa maestro'!M333 -> /proyectos/ | H40: =IF('Mapa maestro'!N333="","",'Mapa maestro'!N333) | I40: ='Mapa maestro'!P333 -> 0
A41: 37 | B41: ='Mapa maestro'!B405 -> /portfolio/triptico-cetis-15/ | C41: ='Mapa maestro'!C405 -> Portafolio | D41: =N('Mapa maestro'!Q405) -> 2 | E41: ='Mapa maestro'!U405 -> 301 | F41: ='Mapa maestro'!K405 -> /proyectos/ | G41: ='Mapa maestro'!M405 -> /proyectos/ | H41: =IF('Mapa maestro'!N405="","",'Mapa maestro'!N405) | I41: ='Mapa maestro'!P405 -> 0
A42: 38 | B42: ='Mapa maestro'!B406 -> /portfolio/valla-torneo-de-golf/ | C42: ='Mapa maestro'!C406 -> Portafolio | D42: =N('Mapa maestro'!Q406) -> 2 | E42: ='Mapa maestro'!U406 -> 301 | F42: ='Mapa maestro'!K406 -> /proyectos/ | G42: ='Mapa maestro'!M406 -> /proyectos/ | H42: =IF('Mapa maestro'!N406="","",'Mapa maestro'!N406) | I42: ='Mapa maestro'!P406 -> 0
B44: Resumen
B45: URLs en la lista corta | C45: =COUNTA(B5:B42) -> 38
B46: con redirect 301 | C46: =COUNTIF(E5:E42,"301") -> 36
B47: que se conservan (200) | C47: =COUNTIF(E5:E42,"200*") -> 2
B48: Clics de la lista sobre el total del sitio viejo | C48: =SUM(D5:D42)/SUM('Mapa maestro'!Q2:Q970) -> 0.60413793
B49: URLs del inventario que pasan a 404 | C49: =COUNTIF('Mapa maestro'!U2:U970,"404") -> 929
B50: de ellas, con clics (revisar) | C50: =COUNTIFS('Mapa maestro'!U2:U970,"404",'Mapa maestro'!Q2:Q970,">0") -> 49

Sheet Reglas
A1: Reglas de tratamiento por tipo de URL
A3: Regla | B3: Tipo de URL | C3: URLs | D3: Tratamiento | E3: Destino | F3: Por qué
A4: R-PAG-01 | B4: Home | C4: =COUNTIF('Mapa maestro'!$O$2:$O$970,A4) -> 1 | D4: Sin cambio | E4: Home nuevo (solo se normaliza host/https) | F4: Es el equivalente directo.
A5: R-PAG-02 | B5: Páginas con equivalente: contacto, nuestros-servicios, portafolio | C5: =COUNTIF('Mapa maestro'!$O$2:$O$970,A5) -> 3 | D5: 301 | E5: Sección equivalente del sitio nuevo | F5: Una página vieja → su equivalente más cercano (1 a 1).
A6: R-PAG-03 | B6: Páginas técnicas/de prueba (404-page, elementor-3504, homepage-revolution, pagina-inicial, testing-1) | C6: =COUNTIF('Mapa maestro'!$O$2:$O$970,A6) -> 5 | D6: 404 | E6: Página 404 personalizada | F6: No tienen valor SEO ni equivalente; redirigirlas al home las convertiría en soft 404.
A7: R-PAG-04 | B7: Landings sin equivalente exacto: agencia-de-publicidad, usa | C7: =COUNTIF('Mapa maestro'!$O$2:$O$970,A7) -> 2 | D7: 301 | E7: Home | F7: Revisar su contenido; si /usa/ tenía tráfico, se puede reasignar al tema E-47.
A8: R-BLOG-01 | B8: Posts con tema equivalente (re-redactar, actualizar, consolidar, mantener) | C8: =COUNTIF('Mapa maestro'!$O$2:$O$970,A8) -> 158 | D8: 301 | E8: Artículo del tema; antes de que se publique: categoría del pilar o /blog/ | F8: Hereda la señal del post al artículo que lo reemplaza; mientras tanto va al destino temático más cercano.
A9: R-BLOG-02 | B9: Posts descartados (sin valor SEO actual) | C9: =COUNTIF('Mapa maestro'!$O$2:$O$970,A9) -> 24 | D9: 404 | E9: Página 404 personalizada | F9: Evita mandar contenido no relacionado a un destino irrelevante.
A10: R-BLOG-03 | B10: Índice /blog/ | C10: =COUNTIF('Mapa maestro'!$O$2:$O$970,A10) -> 1 | D10: Sin cambio | E10: Índice del blog nuevo (misma ruta) | F10: La misma URL se conserva.
A11: R-POR-01 | B11: Piezas del portafolio | C11: =COUNTIF('Mapa maestro'!$O$2:$O$970,A11) -> 216 | D11: 301 | E11: /proyectos/ | F11: Mismo propósito (portafolio → portafolio). Requiere una página real; no un ancla del home.
A12: R-CAT-01 | B12: Categorías del blog | C12: =COUNTIF('Mapa maestro'!$O$2:$O$970,A12) -> 24 | D12: 301 | E12: Categoría del pilar equivalente (o /blog/) | F12: Temática equivalente; si la categoría aún no tiene artículos al corte, se usa /blog/.
A13: R-CAT-02 | B13: Categorías de portafolio | C13: =COUNTIF('Mapa maestro'!$O$2:$O$970,A13) -> 11 | D13: 301 | E13: /proyectos/ | F13: Mismo propósito.
A14: R-TES-01 | B14: Testimonios individuales | C14: =COUNTIF('Mapa maestro'!$O$2:$O$970,A14) -> 3 | D14: 301 | E14: Sección Testimonios | F14: Equivalente temático (solo 3 URLs).
A15: R-IMG-01 | B15: Páginas de adjuntos con padre redirigible | C15: =COUNTIF('Mapa maestro'!$O$2:$O$970,A15) -> 351 | D15: 301 | E15: Destino final de su página padre (sin cadenas) | F15: Son páginas delgadas de WordPress; siguen a su padre.
A16: R-IMG-02 | B16: Páginas de adjuntos sin padre o con padre en 404 | C16: =COUNTIF('Mapa maestro'!$O$2:$O$970,A16) -> 165 | D16: 404 | E16: Página 404 personalizada | F16: Sin contenido propio que heredar.
B17: Total | C17: =SUM(C4:C16) -> 964
A19: Reglas globales (URLs que no están en el inventario)
A20: Patrón | B20: Qué es | D20: Tratamiento | E20: Destino | F20: Nota
A21: http:// → https:// y www → host canónico | B21: Normalización de host | D21: 301 | E21: Misma ruta en el host canónico | F21: En un solo salto junto con el mapa (sin cadenas).
A22: Mayúsculas y ruta sin barra final | B22: Variantes de las URLs del mapa | D22: 301 | E22: Igual que su URL con barra final | F22: Las reglas deben ser insensibles a mayúsculas y tolerar la barra final.
A23: /feed/ · /*/feed/ · /comments/feed/ | B23: Feeds RSS de WordPress | D23: 301 | E23: /blog/feed.xml (o el feed nuevo) | F23: Conserva a los suscriptores de RSS.
A24: /sitemap_index.xml · /wp-sitemap.xml · /post-sitemap.xml · /page-sitemap.xml | B24: Sitemaps viejos | D24: 301 | E24: /sitemap.xml | F24: Google puede mostrar avisos de redirect en sitemaps viejos; es normal.
A25: /wp-content/uploads/* | B25: Archivos de imagen y PDF del sitio viejo | D25: 404 | E25: Página 404 | F25: Revisar en Search Console (imágenes) si alguno tiene tráfico y migrarlo a mano.
A26: /wp-admin/* · /wp-login.php · /xmlrpc.php · /wp-json/* | B26: Rutas técnicas de WordPress | D26: 404 | E26: Página 404 | F26: Los bots las seguirán pidiendo; no dar redirect.
A27: /tag/* · /author/* · /category/* · /page/N/ | B27: Archivos de WordPress | D27: 404 | E27: Página 404 | F27: No están en el sitemap; sin valor. /blog/page/N/ del blog nuevo conserva su ruta.
A28: Parámetros ?s= · ?p=ID · ?utm_ | B28: Búsquedas internas y enlaces cortos | D28: — | E28: Sin regla | F28: Los hosts estáticos no pueden hacer match por parámetros; el 404 sugiere a dónde ir.

Sheet Destinos
A1: Destinos del sitio nuevo y parámetros
A2: Editar solo las celdas azules/amarillas. Todo el Mapa maestro se recalcula desde aquí.
A4: Host canónico (sin barra final) | B4: https://continentalmedia.com.mx | C4: Supuesto: el sitio temporal declara el dominio sin www como canonical. Si se prefiere www, cambiar aquí y en el sitio.
A5: Fecha de corte (cambio de DNS) | B5: 46321 | C5: Supuesto editable: define qué artículos y categorías ya existen cuando se activan las redirecciones.
A8: Código | B8: Sección destino | C8: Ruta propuesta | D8: Estado de la ruta | E8: Pilar (backlog) | F8: Primera publicación | G8: ¿Existe al corte? | H8: Ruta efectiva al corte | I8: Nota
A9: HOME | B9: Inicio | C9: / | D9: Confirmada | G9: =IF(F9="",TRUE(),F9<=$B$5) -> TRUE | H9: =IF(G9,C9,$C$15) -> /
A10: SERVICIOS | B10: Servicios (sección del home) | C10: /#servicios | D10: Por confirmar | G10: =IF(F10="",TRUE(),F10<=$B$5) -> TRUE | H10: =IF(G10,C10,$C$15) -> /#servicios | I10: Ancla: Google ignora el #; para SEO cuenta la página. Alternativa: /servicios/ como página real.
A11: PROYECTOS | B11: Proyectos (página real recomendada) | C11: /proyectos/ | D11: Por crear | G11: =IF(F11="",TRUE(),F11<=$B$5) -> TRUE | H11: =IF(G11,C11,$C$15) -> /proyectos/ | I11: Recomendado: crear /proyectos/ como página real (indexable). Con ancla en el home, Google puede tratar ~230 redirects como soft 404.
A12: TESTIMONIOS | B12: Testimonios (sección del home) | C12: /#testimonios | D12: Por confirmar | G12: =IF(F12="",TRUE(),F12<=$B$5) -> TRUE | H12: =IF(G12,C12,$C$15) -> /#testimonios | I12: Solo 3 URLs; ancla del home es suficiente.
A13: NOSOTROS | B13: Nosotros | C13: /nosotros/ | D13: Por confirmar | G13: =IF(F13="",TRUE(),F13<=$B$5) -> TRUE | H13: =IF(G13,C13,$C$15) -> /nosotros/ | I13: El sitio temporal usa nosotros.html; confirmar la ruta final.
A14: CONTACTO | B14: Contacto (sección del home) | C14: /#contacto | D14: Por confirmar | G14: =IF(F14="",TRUE(),F14<=$B$5) -> TRUE | H14: =IF(G14,C14,$C$15) -> /#contacto
A15: BLOG | B15: Blog · índice | C15: /blog/ | D15: Por construir | G15: =IF(F15="",TRUE(),F15<=$B$5) -> TRUE | H15: =IF(G15,C15,$C$15) -> /blog/ | I15: Índice con la misma ruta que hoy.
A16: CAT_P1 | B16: Blog · Estrategia de marketing y contenidos | C16: /blog/categoria/estrategia-de-marketing/ | D16: Por construir | E16: Estrategia de marketing y contenidos | F16: 46314 | G16: =IF(F16="",TRUE(),F16<=$B$5) -> TRUE | H16: =IF(G16,C16,$C$15) -> /blog/categoria/estrategia-de-marketing/
A17: CAT_P2 | B17: Blog · Redes sociales y comunidad | C17: /blog/categoria/redes-sociales/ | D17: Por construir | E17: Redes sociales y comunidad | F17: 46314 | G17: =IF(F17="",TRUE(),F17<=$B$5) -> TRUE | H17: =IF(G17,C17,$C$15) -> /blog/categoria/redes-sociales/
A18: CAT_P3 | B18: Blog · IA aplicada al marketing | C18: /blog/categoria/ia-aplicada-al-marketing/ | D18: Por construir | E18: IA aplicada al marketing | F18: 46314 | G18: =IF(F18="",TRUE(),F18<=$B$5) -> TRUE | H18: =IF(G18,C18,$C$15) -> /blog/categoria/ia-aplicada-al-marketing/
A19: CAT_P4 | B19: Blog · Branding, diseño y creatividad | C19: /blog/categoria/branding-y-diseno/ | D19: Por construir | E19: Branding, diseño y creatividad | F19: 46366 | G19: =IF(F19="",TRUE(),F19<=$B$5) -> FALSE | H19: =IF(G19,C19,$C$15) -> /blog/
A20: CAT_P5 | B20: Blog · Relaciones públicas y comunicación | C20: /blog/categoria/relaciones-publicas/ | D20: Por construir | E20: Relaciones públicas y comunicación | F20: 46373 | G20: =IF(F20="",TRUE(),F20<=$B$5) -> FALSE | H20: =IF(G20,C20,$C$15) -> /blog/
A21: CAT_P6 | B21: Blog · Web, SEO y publicidad digital | C21: /blog/categoria/web-seo-y-publicidad/ | D21: Por construir | E21: Web, SEO y publicidad digital | F21: 46336 | G21: =IF(F21="",TRUE(),F21<=$B$5) -> FALSE | H21: =IF(G21,C21,$C$15) -> /blog/
A22: CAT_P7 | B22: Blog · Video y fotografía | C22: /blog/categoria/video-y-fotografia/ | D22: Por construir | E22: Video y fotografía | F22: 46532 | G22: =IF(F22="",TRUE(),F22<=$B$5) -> FALSE | H22: =IF(G22,C22,$C$15) -> /blog/
A23: CAT_P8 | B23: Blog · Eventos, medios y publicidad exterior | C23: /blog/categoria/eventos-y-medios/ | D23: Por construir | E23: Eventos, medios y publicidad exterior | F23: 46609 | G23: =IF(F23="",TRUE(),F23<=$B$5) -> FALSE | H23: =IF(G23,C23,$C$15) -> /blog/
A24: CAT_P9 | B24: Blog · Marketing por industria y mercado | C24: /blog/categoria/marketing-por-industria/ | D24: Por construir | E24: Marketing por industria y mercado | F24: 46350 | G24: =IF(F24="",TRUE(),F24<=$B$5) -> FALSE | H24: =IF(G24,C24,$C$15) -> /blog/
A25: ARTICULO | B25: Artículo del tema (slug definido al publicar) | C25: /blog/<slug>/ | D25: Por construir | G25: =IF(F25="",TRUE(),F25<=$B$5) -> TRUE | H25: =IF(G25,C25,$C$15) -> /blog/<slug>/ | I25: Cada redirect de blog apunta al artículo de su tema cuando este se publica; antes va a la categoría del pilar o a /blog/.

Sheet Mapa maestro
A1: URL origen | B1: Ruta origen | C1: Grupo | D1: Página padre (imágenes) | E1: Acción | F1: Destino lógico | G1: ID tema destino | H1: Pilar del tema | I1: Fecha publicación del tema | J1: Código HTTP | K1: Ruta destino al corte | L1: URL nueva al corte | M1: Destino final | N1: Fecha de cambio al destino final | O1: Regla | P1: Nota | Q1: Clics 16m (Search Console) | R1: Dominios que enlazan | S1: Alerta | T1: ¿Entra en la lista corta? | U1: Acción final (plan reducido)
A2: https://www.continentalmedia.com.mx/ | B2: / | C2: Páginas | E2: Sin cambio | F2: HOME | J2: =IF(E2="301",301,IF(E2="404",404,200)) -> 200 | K2: =IF($E2="404","",IF($F2="ARTICULO",IF($I2<=Destinos!$B$5,"[artículo "&$G2&"] /blog/<slug>/",IFERROR(INDEX(Destinos!$H$9:$H$25,MATCH($H2,Destinos!$E$9:$E$25,0)),Destinos!$C$15)),INDEX(Destinos!$H$9:$H$25,MATCH($F2,Destinos!$A$9:$A$25,0)))) -> / | L2: =IF($K2="","",IF(LEFT($K2,1)="/",Destinos!$B$4&$K2,$K2)) -> https://continentalmedia.com.mx/ | M2: =IF($E2="404","",IF($F2="ARTICULO","Artículo "&$G2&" → /blog/<slug>/",INDEX(Destinos!$C$9:$C$25,MATCH($F2,Destinos!$A$9:$A$25,0)))) -> / | N2: =IF(AND($E2="301",$F2="ARTICULO"),$I2,"") | O2: R-PAG-01 | P2: Equivalente directo (solo normaliza host/https) | Q2: 222 | S2: =IF(AND($E2="404",OR(N($Q2)>0,N($R2)>0)),"REVISAR: tiene clics o enlaces → pasar a 301","") | T2: =IF(OR($E2="Conservar URL",AND($E2="301",OR(N($Q2)>=2,$C2="Páginas"))),"Sí","No") -> No | U2: =IF($E2="Sin cambio","200 · sin cambio",IF($T2="Sí",IF($E2="Conservar URL","200 · misma URL","301"),"404")) -> 200 · sin cambio
A3: https://www.continentalmedia.com.mx/404-page/ | B3: /404-page/ | C3: Páginas | E3: 404 | F3: — | J3: =IF(E3="301",301,IF(E3="404",404,200)) -> 404 | K3: =IF($E3="404","",IF($F3="ARTICULO",IF($I3<=Destinos!$B$5,"[artículo "&$G3&"] /blog/<slug>/",IFERROR(INDEX(Destinos!$H$9:$H$25,MATCH($H3,Destinos!$E$9:$E$25,0)),Destinos!$C$15)),INDEX(Destinos!$H$9:$H$25,MATCH($F3,Destinos!$A$9:$A$25,0)))) | L3: =IF($K3="","",IF(LEFT($K3,1)="/",Destinos!$B$4&$K3,$K3)) | M3: =IF($E3="404","",IF($F3="ARTICULO","Artículo "&$G3&" → /blog/<slug>/",INDEX(Destinos!$C$9:$C$25,MATCH($F3,Destinos!$A$9:$A$25,0)))) | N3: =IF(AND($E3="301",$F3="ARTICULO"),$I3,"") | O3: R-PAG-03 | P3: Página técnica/de prueba | S3: =IF(AND($E3="404",OR(N($Q3)>0,N($R3)>0)),"REVISAR: tiene clics o enlaces → pasar a 301","") | T3: =IF(OR($E3="Conservar URL",AND($E3="301",OR(N($Q3)>=2,$C3="Páginas"))),"Sí","No") -> No | U3: =IF($E3="Sin cambio","200 · sin cambio",IF($T3="Sí",IF($E3="Conservar URL","200 · misma URL","301"),"404")) -> 404
A4: https://www.continentalmedia.com.mx/agencia-de-publicidad/ | B4: /agencia-de-publicidad/ | C4: Páginas | E4: 301 | F4: HOME | J4: =IF(E4="301",301,IF(E4="404",404,200)) -> 301 | K4: =IF($E4="404","",IF($F4="ARTICULO",IF($I4<=Destinos!$B$5,"[artículo "&$G4&"] /blog/<slug>/",IFERROR(INDEX(Destinos!$H$9:$H$25,MATCH($H4,Destinos!$E$9:$E$25,0)),Destinos!$C$15)),INDEX(Destinos!$H$9:$H$25,MATCH($F4,Destinos!$A$9:$A$25,0)))) -> / | L4: =IF($K4="","",IF(LEFT($K4,1)="/",Destinos!$B$4&$K4,$K4)) -> https://continentalmedia.com.mx/ | M4: =IF($E4="404","",IF($F4="ARTICULO","Artículo "&$G4&" → /blog/<slug>/",INDEX(Destinos!$C$9:$C$25,MATCH($F4,Destinos!$A$9:$A$25,0)))) -> / | N4: =IF(AND($E4="301",$F4="ARTICULO"),$I4,"") | O4: R-PAG-04 | P4: Landing con la keyword «agencia de publicidad»: reflejarla en title/H1 del home nuevo | Q4: 5 | S4: =IF(AND($E4="404",OR(N($Q4)>0,N($R4)>0)),"REVISAR: tiene clics o enlaces → pasar a 301","") | T4: =IF(OR($E4="Conservar URL",AND($E4="301",OR(N($Q4)>=2,$C4="Páginas"))),"Sí","No") -> Sí | U4: =IF($E4="Sin cambio","200 · sin cambio",IF($T4="Sí",IF($E4="Conservar URL","200 · misma URL","301"),"404")) -> 301
A5: https://www.continentalmedia.com.mx/contacto/ | B5: /contacto/ | C5: Páginas | E5: 301 | F5: CONTACTO | J5: =IF(E5="301",301,IF(E5="404",404,200)) -> 301 | K5: =IF($E5="404","",IF($F5="ARTICULO",IF($I5<=Destinos!$B$5,"[artículo "&$G5&"] /blog/<slug>/",IFERROR(INDEX(Destinos!$H$9:$H$25,MATCH($H5,Destinos!$E$9:$E$25,0)),Destinos!$C$15)),INDEX(Destinos!$H$9:$H$25,MATCH($F5,Destinos!$A$9:$A$25,0)))) -> /#contacto | L5: =IF($K5="","",IF(LEFT($K5,1)="/",Destinos!$B$4&$K5,$K5)) -> https://continentalmedia.com.mx/#contacto | M5: =IF($E5="404","",IF($F5="ARTICULO","Artículo "&$G5&" → /blog/<slug>/",INDEX(Destinos!$C$9:$C$25,MATCH($F5,Destinos!$A$9:$A$25,0)))) -> /#contacto | N5: =IF(AND($E5="301",$F5="ARTICULO"),$I5,"") | O5: R-PAG-02 | Q5: 16 | S5: =IF(AND($E5="404",OR(N($Q5)>0,N($R5)>0)),"REVISAR: tiene clics o enlaces → pasar a 301","") | T5: =IF(OR($E5="Conservar URL",AND($E5="301",OR(N($Q5)>=2,$C5="Páginas"))),"Sí","No") -> Sí | U5: =IF($E5="Sin cambio","200 · sin cambio",IF($T5="Sí",IF($E5="Conservar URL","200 · misma URL","301"),"404")) -> 301
A6: https://www.continentalmedia.com.mx/elementor-3504/ | B6: /elementor-3504/ | C6: Páginas | E6: 404 | F6: — | J6: =IF(E6="301",301,IF(E6="404",404,200)) -> 404 | K6: =IF($E6="404","",IF($F6="ARTICULO",IF($I6<=Destinos!$B$5,"[artículo "&$G6&"] /blog/<slug>/",IFERROR(INDEX(Destinos!$H$9:$H$25,MATCH($H6,Destinos!$E$9:$E$25,0)),Destinos!$C$15)),INDEX(Destinos!$H$9:$H$25,MATCH($F6,Destinos!$A$9:$A$25,0)))) | L6: =IF($K6="","",IF(LEFT($K6,1)="/",Destinos!$B$4&$K6,$K6)) | M6: =IF($E6="404","",IF($F6="ARTICULO","Artículo "&$G6&" → /blog/<slug>/",INDEX(Destinos!$C$9:$C$25,MATCH($F6,Destinos!$A$9:$A$25,0)))) | N6: =IF(AND($E6="301",$F6="ARTICULO"),$I6,"") | O6: R-PAG-03 | P6: Página técnica/de prueba | S6: =IF(AND($E6="404",OR(N($Q6)>0,N($R6)>0)),"REVISAR: tiene clics o enlaces → pasar a 301","") | T6: =IF(OR($E6="Conservar URL",AND($E6="301",OR(N($Q6)>=2,$C6="Páginas"))),"Sí","No") -> No | U6: =IF($E6="Sin cambio","200 · sin cambio",IF($T6="Sí",IF($E6="Conservar URL","200 · misma URL","301"),"404")) -> 404
A7: https://www.continentalmedia.com.mx/homepage-revolution/ | B7: /homepage-revolution/ | C7: Páginas | E7: 404 | F7: — | J7: =IF(E7="301",301,IF(E7="404",404,200)) -> 404 | K7: =IF($E7="404","",IF($F7="ARTICULO",IF($I7<=Destinos!$B$5,"[artículo "&$G7&"] /blog/<slug>/",IFERROR(INDEX(Destinos!$H$9:$H$25,MATCH($H7,Destinos!$E$9:$E$25,0)),Destinos!$C$15)),INDEX(Destinos!$H$9:$H$25,MATCH($F7,Destinos!$A$9:$A$25,0)))) | L7: =IF($K7="","",IF(LEFT($K7,1)="/",Destinos!$B$4&$K7,$K7)) | M7: =IF($E7="404","",IF($F7="ARTICULO","Artículo "&$G7&" → /blog/<slug>/",INDEX(Destinos!$C$9:$C$25,MATCH($F7,Destinos!$A$9:$A$25,0)))) | N7: =IF(AND($E7="301",$F7="ARTICULO"),$I7,"") | O7: R-PAG-03 | P7: Página técnica/de prueba | Q7: 1 | S7: =IF(AND($E7="404",OR(N($Q7)>0,N($R7)>0)),"REVISAR: tiene clics o enlaces → pasar a 301","") -> REVISAR: tiene clics o enlaces → pasar a 301 | T7: =IF(OR($E7="Conservar URL",AND($E7="301",OR(N($Q7)>=2,$C7="Páginas"))),"Sí","No") -> No | U7: =IF($E7="Sin cambio","200 · sin cambio",IF($T7="Sí",IF($E7="Conservar URL","200 · misma URL","301"),"404")) -> 404
A8: https://www.continentalmedia.com.mx/nuestros-servicios/ | B8: /nuestros-servicios/ | C8: Páginas | E8: 301 | F8: SERVICIOS | J8: =IF(E8="301",301,IF(E8="404",404,200)) -> 301 | K8: =IF($E8="404","",IF($F8="ARTICULO",IF($I8<=Destinos!$B$5,"[artículo "&$G8&"] /blog/<slug>/",IFERROR(INDEX(Destinos!$H$9:$H$25,MATCH($H8,Destinos!$E$9:$E$25,0)),Destinos!$C$15)),INDEX(Destinos!$H$9:$H$25,MATCH($F8,Destinos!$A$9:$A$25,0)))) -> /#servicios | L8: =IF($K8="","",IF(LEFT($K8,1)="/",Destinos!$B$4&$K8,$K8)) -> https://continentalmedia.com.mx/#servicios | M8: =IF($E8="404","",IF($F8="ARTICULO","Artículo "&$G8&" → /blog/<slug>/",INDEX(Destinos!$C$9:$C$25,MATCH($F8,Destinos!$A$9:$A$25,0)))) -> /#servicios | N8: =IF(AND($E8="301",$F8="ARTICULO"),$I8,"") | O8: R-PAG-02 | Q8: 2 | S8: =IF(AND($E8="404",OR(N($Q8)>0,N($R8)>0)),"REVISAR: tiene clics o enlaces → pasar a 301","") | T8: =IF(OR($E8="Conservar URL",AND($E8="301",OR(N($Q8)>=2,$C8="Páginas"))),"Sí","No") -> Sí | U8: =IF($E8="Sin cambio","200 · sin cambio",IF($T8="Sí",IF($E8="Conservar URL","200 · misma URL","301"),"404")) -> 301
A9: https://www.continentalmedia.com.mx/pagina-inicial/ | B9: /pagina-inicial/ | C9: Páginas | E9: 404 | F9: — | J9: =IF(E9="301",301,IF(E9="404",404,200)) -> 404 | K9: =IF($E9="404","",IF($F9="ARTICULO",IF($I9<=Destinos!$B$5,"[artículo "&$G9&"] /blog/<slug>/",IFERROR(INDEX(Destinos!$H$9:$H$25,MATCH($H9,Destinos!$E$9:$E$25,0)),Destinos!$C$15)),INDEX(Destinos!$H$9:$H$25,MATCH($F9,Destinos!$A$9:$A$25,0)))) | L9: =IF($K9="","",IF(LEFT($K9,1)="/",Destinos!$B$4&$K9,$K9)) | M9: =IF($E9="404","",IF($F9="ARTICULO","Artículo "&$G9&" → /blog/<slug>/",INDEX(Destinos!$C$9:$C$25,MATCH($F9,Destinos!$A$9:$A$25,0)))) | N9: =IF(AND($E9="301",$F9="ARTICULO"),$I9,"") | O9: R-PAG-03 | P9: Página técnica/de prueba | Q9: 1 | S9: =IF(AND($E9="404",OR(N($Q9)>0,N($R9)>0)),"REVISAR: tiene clics o enlaces → pasar a 301","") -> REVISAR: tiene clics o enlaces → pasar a 301 | T9: =IF(OR($E9="Conservar URL",AND($E9="301",OR(N($Q9)>=2,$C9="Páginas"))),"Sí","No") -> No | U9: =IF($E9="Sin cambio","200 · sin cambio",IF($T9="Sí",IF($E9="Conservar URL","200 · misma URL","301"),"404")) -> 404
A10: https://www.continentalmedia.com.mx/portafolio/ | B10: /portafolio/ | C10: Páginas | E10: 301 | F10: PROYECTOS | J10: =IF(E10="301",301,IF(E10="404",404,200)) -> 301 | K10: =IF($E10="404","",IF($F10="ARTICULO",IF($I10<=Destinos!$B$5,"[artículo "&$G10&"] /blog/<slug>/",IFERROR(INDEX(Destinos!$H$9:$H$25,MATCH($H10,Destinos!$E$9:$E$25,0)),Destinos!$C$15)),INDEX(Destinos!$H$9:$H$25,MATCH($F10,Destinos!$A$9:$A$25,0)))) -> /proyectos/ | L10: =IF($K10="","",IF(LEFT($K10,1)="/",Destinos!$B$4&$K10,$K10)) -> https://continentalmedia.com.mx/proyectos/ | M10: =IF($E10="404","",IF($F10="ARTICULO","Artículo "&$G10&" → /blog/<slug>/",INDEX(Destinos!$C$9:$C$25,MATCH($F10,Destinos!$A$9:$A$25,0)))) -> /proyectos/ | N10: =IF(AND($E10="301",$F10="ARTICULO"),$I10,"") | O10: R-PAG-02 | Q10: 3 | S10: =IF(AND($E10="404",OR(N($Q10)>0,N($R10)>0)),"REVISAR: tiene clics o enlaces → pasar a 301","") | T10: =IF(OR($E10="Conservar URL",AND($E10="301",OR(N($Q10)>=2,$C10="Páginas"))),"Sí","No") -> Sí | U10: =IF($E10="Sin cambio","200 · sin cambio",IF($T10="Sí",IF($E10="Conservar URL","200 · misma URL","301"),"404")) -> 301
A11: https://www.continentalmedia.com.mx/testing-1/ | B11: /testing-1/ | C11: Páginas | E11: 404 | F11: — | J11: =IF(E11="301",301,IF(E11="404",404,200)) -> 404 | K11: =IF($E11="404","",IF($F11="ARTICULO",IF($I11<=Destinos!$B$5,"[artículo "&$G11&"] /blog/<slug>/",IFERROR(INDEX(Destinos!$H$9:$H$25,MATCH($H11,Destinos!$E$9:$E$25,0)),Destinos!$C$15)),INDEX(Destinos!$H$9:$H$25,MATCH($F11,Destinos!$A$9:$A$25,0)))) | L11: =IF($K11="","",IF(LEFT($K11,1)="/",Destinos!$B$4&$K11,$K11)) | M11: =IF($E11="404","",IF($F11="ARTICULO","Artículo "&$G11&" → /blog/<slug>/",INDEX(Destinos!$C$9:$C$25,MATCH($F11,Destinos!$A$9:$A$25,0)))) | N11: =IF(AND($E11="301",$F11="ARTICULO"),$I11,"") | O11: R-PAG-03 | P11: Página técnica/de prueba | S11: =IF(AND($E11="404",OR(N($Q11)>0,N($R11)>0)),"REVISAR: tiene clics o enlaces → pasar a 301","") | T11: =IF(OR($E11="Conservar URL",AND($E11="301",OR(N($Q11)>=2,$C11="Páginas"))),"Sí","No") -> No | U11: =IF($E11="Sin cambio","200 · sin cambio",IF($T11="Sí",IF($E11="Conservar URL","200 · misma URL","301"),"404")) -> 404
A12: https://www.continentalmedia.com.mx/usa/ | B12: /usa/ | C12: Páginas | E12: 301 | F12: HOME | J12: =IF(E12="301",301,IF(E12="404",404,200)) -> 301 | K12: =IF($E12="404","",IF($F12="ARTICULO",IF($I12<=Destinos!$B$5,"[artículo "&$G12&"] /blog/<slug>/",IFERROR(INDEX(Destinos!$H$9:$H$25,MATCH($H12,Destinos!$E$9:$E$25,0)),Destinos!$C$15)),INDEX(Destinos!$H$9:$H$25,MATCH($F12,Destinos!$A$9:$A$25,0)))) -> / | L12: =IF($K12="","",IF(LEFT($K12,1)="/",Destinos!$B$4&$K12,$K12)) -> https://continentalmedia.com.mx/ | M12: =IF($E12="404","",IF($F12="ARTICULO","Artículo "&$G12&" → /blog/<slug>/",INDEX(Destinos!$C$9:$C$25,MATCH($F12,Destinos!$A$9:$A$25,0)))) -> / | N12: =IF(AND($E12="301",$F12="ARTICULO"),$I12,"") | O12: R-PAG-04 | P12: Revisar contenido original (HTTP 500 en la revisión). Candidata a tema E-47 (consumidor hispano en EE.UU.) cuando se publique | Q12: 5 | S12: =IF(AND($E12="404",OR(N($Q12)>0,N($R12)>0)),"REVISAR: tiene clics o enlaces → pasar a 301","") | T12: =IF(OR($E12="Conservar URL",AND($E12="301",OR(N($Q12)>=2,$C12="Páginas"))),"Sí","No") -> Sí | U12: =IF($E12="Sin cambio","200 · sin cambio",IF($T12="Sí",IF($E12="Conservar URL","200 · misma URL","301"),"404")) -> 301
A13: https://www.continentalmedia.com.mx/2012/08/creative-interior-design/ | B13: /2012/08/creative-interior-design/ | C13: Blog | E13: 404 | F13: — | J13: =IF(E13="301",301,IF(E13="404",404,200)) -> 404 | K13: =IF($E13="404","",IF($F13="ARTICULO",IF($I13<=Destinos!$B$5,"[artículo "&$G13&"] /blog/<slug>/",IFERROR(INDEX(Destinos!$H$9:$H$25,MATCH($H13,Destinos!$E$9:$E$25,0)),Destinos!$C$15)),INDEX(Destinos!$H$9:$H$25,MATCH($F13,Destinos!$A$9:$A$25,0)))) | L13: =IF($K13="","",IF(LEFT($K13,1)="/",Destinos!$B$4&$K13,$K13)) | M13: =IF($E13="404","",IF($F13="ARTICULO","Artículo "&$G13&" → /blog/<slug>/",INDEX(Destinos!$C$9:$C$25,MATCH($F13,Destinos!$A$9:$A$25,0)))) | N13: =IF(AND($E13="301",$F13="ARTICULO"),$I13,"") | O13: R-BLOG-02 | P13: Sin valor SEO actual; sin tema equivalente | S13: =IF(AND($E13="404",OR(N($Q13)>0,N($R13)>0)),"REVISAR: tiene clics o enlaces → pasar a 301","") | T13: =IF(OR($E13="Conservar URL",AND($E13="301",OR(N($Q13)>=2,$C13="Páginas"))),"Sí","No") -> No | U13: =IF($E13="Sin cambio","200 · sin cambio",IF($T13="Sí",IF($E13="Conservar URL","200 · misma URL","301"),"404")) -> 404
A14: https://www.continentalmedia.com.mx/2012/08/marketing-olfativo/ | B14: /2012/08/marketing-olfativo/ | C14: Blog | E14: 301 | F14: ARTICULO | G14: E-20 | H14: Branding, diseño y creatividad | I14: 46427 | J14: =IF(E14="301",301,IF(E14="404",404,200)) -> 301 | K14: =IF($E14="404","",IF($F14="ARTICULO",IF($I14<=Destinos!$B$5,"[artículo "&$G14&"] /blog/<slug>/",IFERROR(INDEX(Destinos!$H$9:$H$25,MATCH($H14,Destinos!$E$9:$E$25,0)),Destinos!$C$15)),INDEX(Destinos!$H$9:$H$25,MATCH($F14,Destinos!$A$9:$A$25,0)))) -> /blog/ | L14: =IF($K14="","",IF(LEFT($K14,1)="/",Destinos!$B$4&$K14,$K14)) -> https://continentalmedia.com.mx/blog/ | M14: =IF($E14="404","",IF($F14="ARTICULO","Artículo "&$G14&" → /blog/<slug>/",INDEX(Destinos!$C$9:$C$25,MATCH($F14,Destinos!$A$9:$A$25,0)))) -> Artículo E-20 → /blog/<slug>/ | N14: =IF(AND($E14="301",$F14="ARTICULO"),$I14,"") -> 46427 | O14: R-BLOG-01 | S14: =IF(AND($E14="404",OR(N($Q14)>0,N($R14)>0)),"REVISAR: tiene clics o enlaces → pasar a 301","") | T14: =IF(OR($E14="Conservar URL",AND($E14="301",OR(N($Q14)>=2,$C14="Páginas"))),"Sí","No") -> No | U14: =IF($E14="Sin cambio","200 · sin cambio",IF($T14="Sí",IF($E14="Conservar URL","200 · misma URL","301"),"404")) -> 404
A15: https://www.continentalmedia.com.mx/2012/12/6-razones-pymes-usar-redes-sociales/ | B15: /2012/12/6-razones-pymes-usar-redes-sociales/ | C15: Blog | E15: 301 | F15: ARTICULO | G15: E-10 | H15: Redes sociales y comunidad | I15: 46378 | J15: =IF(E15="301",301,IF(E15="404",404,200)) -> 301 | K15: =IF($E15="404","",IF($F15="ARTICULO",IF($I15<=Destinos!$B$5,"[artículo "&$G15&"] /blog/<slug>/",IFERROR(INDEX(Destinos!$H$9:$H$25,MATCH($H15,Destinos!$E$9:$E$25,0)),Destinos!$C$15)),INDEX(Destinos!$H$9:$H$25,MATCH($F15,Destinos!$A$9:$A$25,0)))) -> /blog/categoria/redes-sociales/ | L15: =IF($K15="","",IF(LEFT($K15,1)="/",Destinos!$B$4&$K15,$K15)) -> https://continentalmedia.com.mx/blog/categoria/redes-sociales/ | M15: =IF($E15="404","",IF($F15="ARTICULO","Artículo "&$G15&" → /blog/<slug>/",INDEX(Destinos!$C$9:$C$25,MATCH($F15,Destinos!$A$9:$A$25,0)))) -> Artículo E-10 → /blog/<slug>/ | N15: =IF(AND($E15="301",$F15="ARTICULO"),$I15,"") -> 46378 | O15: R-BLOG-01 | S15: =IF(AND($E15="404",OR(N($Q15)>0,N($R15)>0)),"REVISAR: tiene clics o enlaces → pasar a 301","") | T15: =IF(OR($E15="Conservar URL",AND($E15="301",OR(N($Q15)>=2,$C15="Páginas"))),"Sí","No") -> No | U15: =IF($E15="Sin cambio","200 · sin cambio",IF($T15="Sí",IF($E15="Conservar URL","200 · misma URL","301"),"404")) -> 404
A16: https://www.continentalmedia.com.mx/2012/12/campanas-exitosas-del-2012/ | B16: /2012/12/campanas-exitosas-del-2012/ | C16: Blog | E16: 301 | F16: BLOG | J16: =IF(E16="301",301,IF(E16="404",404,200)) -> 301 | K16: =IF($E16="404","",IF($F16="ARTICULO",IF($I16<=Destinos!$B$5,"[artículo "&$G16&"] /blog/<slug>/",IFERROR(INDEX(Destinos!$H$9:$H$25,MATCH($H16,Destinos!$E$9:$E$25,0)),Destinos!$C$15)),INDEX(Destinos!$H$9:$H$25,MATCH($F16,Destinos!$A$9:$A$25,0)))) -> /blog/ | L16: =IF($K16="","",IF(LEFT($K16,1)="/",Destinos!$B$4&$K16,$K16)) -> https://continentalmedia.com.mx/blog/ | M16: =IF($E16="404","",IF($F16="ARTICULO","Artículo "&$G16&" → /blog/<slug>/",INDEX(Destinos!$C$9:$C$25,MATCH($F16,Destinos!$A$9:$A$25,0)))) -> /blog/ | N16: =IF(AND($E16="301",$F16="ARTICULO"),$I16,"") | O16: R-LISTA-02 | P16: Descartado en el backlog pero con clics (2 a 7 en 16 meses); decisión: 301 al índice del blog. | Q16: 7 | S16: =IF(AND($E16="404",OR(N($Q16)>0,N($R16)>0)),"REVISAR: tiene clics o enlaces → pasar a 301","") | T16: =IF(OR($E16="Conservar URL",AND($E16="301",OR(N($Q16)>=2,$C16="Páginas"))),"Sí","No") -> Sí | U16: =IF($E16="Sin cambio","200 · sin cambio",IF($T16="Sí",IF($E16="Conservar URL","200 · misma URL","301"),"404")) -> 301
A17: https://www.continentalmedia.com.mx/2012/12/churros-creatividad/ | B17: /2012/12/churros-creatividad/ | C17: Blog | E17: 301 | F17: ARTICULO | G17: E-33 | H17: Branding, diseño y creatividad | I17: 46504 | J17: =IF(E17="301",301,IF(E17="404",404,200)) -> 301 | K17: =IF($E17="404","",IF($F17="ARTICULO",IF($I17<=Destinos!$B$5,"[artículo "&$G17&"] /blog/<slug>/",IFERROR(INDEX(Destinos!$H$9:$H$25,MATCH($H17,Destinos!$E$9:$E$25,0)),Destinos!$C$15)),INDEX(Destinos!$H$9:$H$25,MATCH($F17,Destinos!$A$9:$A$25,0)))) -> /blog/ | L17: =IF($K17="","",IF(LEFT($K17,1)="/",Destinos!$B$4&$K17,$K17)) -> https://continentalmedia.com.mx/blog/ | M17: =IF($E17="404","",IF($F17="ARTICULO","Artículo "&$G17&" → /blog/<slug>/",INDEX(Destinos!$C$9:$C$25,MATCH($F17,Destinos!$A$9:$A$25,0)))) -> Artículo E-33 → /blog/<slug>/ | N17: =IF(AND($E17="301",$F17="ARTICULO"),$I17,"") -> 46504 | O17: R-BLOG-01 | S17: =IF(AND($E17="404",OR(N($Q17)>0,N($R17)>0)),"REVISAR: tiene clics o enlaces → pasar a 301","") | T17: =IF(OR($E17="Conservar URL",AND($E17="301",OR(N($Q17)>=2,$C17="Páginas"))),"Sí","No") -> No | U17: =IF($E17="Sin cambio","200 · sin cambio",IF($T17="Sí",IF($E17="Conservar URL","200 · misma URL","301"),"404")) -> 404
A18: https://www.continentalmedia.com.mx/2012/12/conoce-el-funcionamiento-del-e-mail-marketing/ | B18: /2012/12/conoce-el-funcionamiento-del-e-mail-marketing/ | C18: Blog | E18: 301 | F18: ARTICULO | G18: G-42 | H18: Web, SEO y publicidad digital | I18: 46569 | J18: =IF(E18="301",301,IF(E18="404",404,200)) -> 301 | K18: =IF($E18="404","",IF($F18="ARTICULO",IF($I18<=Destinos!$B$5,"[artículo "&$G18&"] /blog/<slug>/",IFERROR(INDEX(Destinos!$H$9:$H$25,MATCH($H18,Destinos!$E$9:$E$25,0)),Destinos!$C$15)),INDEX(Destinos!$H$9:$H$25,MATCH($F18,Destinos!$A$9:$A$25,0)))) -> /blog/ | L18: =IF($K18="","",IF(LEFT($K18,1)="/",Destinos!$B$4&$K18,$K18)) -> https://continentalmedia.com.mx/blog/ | M18: =IF($E18="404","",IF($F18="ARTICULO","Artículo "&$G18&" → /blog/<slug>/",INDEX(Destinos!$C$9:$C$25,MATCH($F18,Destinos!$A$9:$A$25,0)))) -> Artículo G-42 → /blog/<slug>/ | N18: =IF(AND($E18="301",$F18="ARTICULO"),$I18,"") -> 46569 | O18: R-BLOG-01 | S18: =IF(AND($E18="404",OR(N($Q18)>0,N($R18)>0)),"REVISAR: tiene clics o enlaces → pasar a 301","") | T18: =IF(OR($E18="Conservar URL",AND($E18="301",OR(N($Q18)>=2,$C18="Páginas"))),"Sí","No") -> No | U18: =IF($E18="Sin cambio","200 · sin cambio",IF($T18="Sí",IF($E18="Conservar URL","200 · misma URL","301"),"404")) -> 404
A19: https://www.continentalmedia.com.mx/2012/12/es-necesario-ofrecer-una-buena-atencion-al-cliente-en-las-redes-sociales/ | B19: /2012/12/es-necesario-ofrecer-una-buena-atencion-al-cliente-en-las-redes-sociales/ | C19: Blog | E19: 301 | F19: ARTICULO | G19: G-14 | H19: Redes sociales y comunidad | I19: 46499 | J19: =IF(E19="301",301,IF(E19="404",404,200)) -> 301 | K19: =IF($E19="404","",IF($F19="ARTICULO",IF($I19<=Destinos!$B$5,"[artículo "&$G19&"] /blog/<slug>/",IFERROR(INDEX(Destinos!$H$9:$H$25,MATCH($H19,Destinos!$E$9:$E$25,0)),Destinos!$C$15)),INDEX(Destinos!$H$9:$H$25,MATCH($F19,Destinos!$A$9:$A$25,0)))) -> /blog/categoria/redes-sociales/ | L19: =IF($K19="","",IF(LEFT($K19,1)="/",Destinos!$B$4&$K19,$K19)) -> https://continentalmedia.com.mx/blog/categoria/redes-sociales/ | M19: =IF($E19="404","",IF($F19="ARTICULO","Artículo "&$G19&" → /blog/<slug>/",INDEX(Destinos!$C$9:$C$25,MATCH($F19,Destinos!$A$9:$A$25,0)))) -> Artículo G-14 → /blog/<slug>/ | N19: =IF(AND($E19="301",$F19="ARTICULO"),$I19,"") -> 46499 | O19: R-BLOG-01 | S19: =IF(AND($E19="404",OR(N($Q19)>0,N($R19)>0)),"REVISAR: tiene clics o enlaces → pasar a 301","") | T19: =IF(OR($E19="Conservar URL",AND($E19="301",OR(N($Q19)>=2,$C19="Páginas"))),"Sí","No") -> No | U19: =IF($E19="Sin cambio","200 · sin cambio",IF($T19="Sí",IF($E19="Conservar URL","200 · misma URL","301"),"404")) -> 404
A20: https://www.continentalmedia.com.mx/2012/12/inversion-publicitaria-en-medios-online/ | B20: /2012/12/inversion-publicitaria-en-medios-online/ | C20: Blog | E20: 301 | F20: ARTICULO | G20: E-45 | H20: Eventos, medios y publicidad exterior | I20: 46616 | J20: =IF(E20="301",301,IF(E20="404",404,200)) -> 301 | K20: =IF($E20="404","",IF($F20="ARTICULO",IF($I20<=Destinos!$B$5,"[artículo "&$G20&"] /blog/<slug>/",IFERROR(INDEX(Destinos!$H$9:$H$25,MATCH($H20,Destinos!$E$9:$E$25,0)),Destinos!$C$15)),INDEX(Destinos!$H$9:$H$25,MATCH($F20,Destinos!$A$9:$A$25,0)))) -> /blog/ | L20: =IF($K20="","",IF(LEFT($K20,1)="/",Destinos!$B$4&$K20,$K20)) -> https://continentalmedia.com.mx/blog/ | M20: =IF($E20="404","",IF($F20="ARTICULO","Artículo "&$G20&" → /blog/<slug>/",INDEX(Destinos!$C$9:$C$25,MATCH($F20,Destinos!$A$9:$A$25,0)))) -> Artículo E-45 → /blog/<slug>/ | N20: =IF(AND($E20="301",$F20="ARTICULO"),$I20,"") -> 46616 | O20: R-BLOG-01 | S20: =IF(AND($E20="404",OR(N($Q20)>0,N($R20)>0)),"REVISAR: tiene clics o enlaces → pasar a 301","") | T20: =IF(OR($E20="Conservar URL",AND($E20="301",OR(N($Q20)>=2,$C20="Páginas"))),"Sí","No") -> No | U20: =IF($E20="Sin cambio","200 · sin cambio",IF($T20="Sí",IF($E20="Conservar URL","200 · misma URL","301"),"404")) -> 404
A21: https://www.continentalmedia.com.mx/2012/12/las-4-r-s-de-las-redes-sociales/ | B21: /2012/12/las-4-r-s-de-las-redes-sociales/ | C21: Blog | E21: 301 | F21: ARTICULO | G21: E-15 | H21: Redes sociales y comunidad | I21: 46399 | J21: =IF(E21="301",301,IF(E21="404",404,200)) -> 301 | K21: =IF($E21="404","",IF($F21="ARTICULO",IF($I21<=Destinos!$B$5,"[artículo "&$G21&"] /blog/<slug>/",IFERROR(INDEX(Destinos!$H$9:$H$25,MATCH($H21,Destinos!$E$9:$E$25,0)),Destinos!$C$15)),INDEX(Destinos!$H$9:$H$25,MATCH($F21,Destinos!$A$9:$A$25,0)))) -> /blog/categoria/redes-sociales/ | L21: =IF($K21="","",IF(LEFT($K21,1)="/",Destinos!$B$4&$K21,$K21)) -> https://continentalmedia.com.mx/blog/categoria/redes-sociales/ | M21: =IF($E21="404","",IF($F21="ARTICULO","Artículo "&$G21&" → /blog/<slug>/",INDEX(Destinos!$C$9:$C$25,MATCH($F21,Destinos!$A$9:$A$25,0)))) -> Artículo E-15 → /blog/<slug>/ | N21: =IF(AND($E21="301",$F21="ARTICULO"),$I21,"") -> 46399 | O21: R-BLOG-01 | S21: =IF(AND($E21="404",OR(N($Q21)>0,N($R21)>0)),"REVISAR: tiene clics o enlaces → pasar a 301","") | T21: =IF(OR($E21="Conservar URL",AND($E21="301",OR(N($Q21)>=2,$C21="Páginas"))),"Sí","No") -> No | U21: =IF($E21="Sin cambio","200 · sin cambio",IF($T21="Sí",IF($E21="Conservar URL","200 · misma URL","301"),"404")) -> 404
A22: https://www.continentalmedia.com.mx/2012/12/lovemarks/ | B22: /2012/12/lovemarks/ | C22: Blog | E22: 301 | F22: ARTICULO | G22: E-26 | H22: Branding, diseño y creatividad | I22: 46574 | J22: =IF(E22="301",301,IF(E22="404",404,200)) -> 301 | K22: =IF($E22="404","",IF($F22="ARTICULO",IF($I22<=Destinos!$B$5,"[artículo "&$G22&"] /blog/<slug>/",IFERROR(INDEX(Destinos!$H$9:$H$25,MATCH($H22,Destinos!$E$9:$E$25,0)),Destinos!$C$15)),INDEX(Destinos!$H$9:$H$25,MATCH($F22,Destinos!$A$9:$A$25,0)))) -> /blog/ | L22: =IF($K22="","",IF(LEFT($K22,1)="/",Destinos!$B$4&$K22,$K22)) -> https://continentalmedia.com.mx/blog/ | M22: =IF($E22="404","",IF($F22="ARTICULO","Artículo "&$G22&" → /blog/<slug>/",INDEX(Destinos!$C$9:$C$25,MATCH($F22,Destinos!$A$9:$A$25,0)))) -> Artículo E-26 → /blog/<slug>/ | N22: =IF(AND($E22="301",$F22="ARTICULO"),$I22,"") -> 46574 | O22: R-BLOG-01 | S22: =IF(AND($E22="404",OR(N($Q22)>0,N($R22)>0)),"REVISAR: tiene clics o enlaces → pasar a 301","") | T22: =IF(OR($E22="Conservar URL",AND($E22="301",OR(N($Q22)>=2,$C22="Páginas"))),"Sí","No") -> No | U22: =IF($E22="Sin cambio","200 · sin cambio",IF($T22="Sí",IF($E22="Conservar URL","200 · misma URL","301"),"404")) -> 404
A23: https://www.continentalmedia.com.mx/2012/12/marketing-de-guerrilla/ | B23: /2012/12/marketing-de-guerrilla/ | C23: Blog | E23: 301 | F23: ARTICULO | G23: E-44 | H23: Eventos, medios y publicidad exterior | I23: 46609 | J23: =IF(E23="301",301,IF(E23="404",404,200)) -> 301 | K23: =IF($E23="404","",IF($F23="ARTICULO",IF($I23<=Destinos!$B$5,"[artículo "&$G23&"] /blog/<slug>/",IFERROR(INDEX(Destinos!$H$9:$H$25,MATCH($H23,Destinos!$E$9:$E$25,0)),Destinos!$C$15)),INDEX(Destinos!$H$9:$H$25,MATCH($F23,Destinos!$A$9:$A$25,0)))) -> /blog/ | L23: =IF($K23="","",IF(LEFT($K23,1)="/",Destinos!$B$4&$K23,$K23)) -> https://continentalmedia.com.mx/blog/ | M23: =IF($E23="404","",IF($F23="ARTICULO","Artículo "&$G23&" → /blog/<slug>/",INDEX(Destinos!$C$9:$C$25,MATCH($F23,Destinos!$A$9:$A$25,0)))) -> Artículo E-44 → /blog/<slug>/ | N23: =IF(AND($E23="301",$F23="ARTICULO"),$I23,"") -> 46609 | O23: R-BLOG-01 | S23: =IF(AND($E23="404",OR(N($Q23)>0,N($R23)>0)),"REVISAR: tiene clics o enlaces → pasar a 301","") | T23: =IF(OR($E23="Conservar URL",AND($E23="301",OR(N($Q23)>=2,$C23="Páginas"))),"Sí","No") -> No | U23: =IF($E23="Sin cambio","200 · sin cambio",IF($T23="Sí",IF($E23="Conservar URL","200 · misma URL","301"),"404")) -> 404
A24: https://www.continentalmedia.com.mx/2012/12/marketing-deportivo/ | B24: /2012/12/marketing-deportivo/ | C24: Blog | E24: 301 | F24: ARTICULO | G24: E-46 | H24: Eventos, medios y publicidad exterior | I24: 46623 | J24: =IF(E24="301",301,IF(E24="404",404,200)) -> 301 | K24: =IF($E24="404","",IF($F24="ARTICULO",IF($I24<=Destinos!$B$5,"[artículo "&$G24&"] /blog/<slug>/",IFERROR(INDEX(Destinos!$H$9:$H$25,MATCH($H24,Destinos!$E$9:$E$25,0)),Destinos!$C$15)),INDEX(Destinos!$H$9:$H$25,MATCH($F24,Destinos!$A$9:$A$25,0)))) -> /blog/ | L24: =IF($K24="","",IF(LEFT($K24,1)="/",Destinos!$B$4&$K24,$K24)) -> https://continentalmedia.com.mx/blog/ | M24: =IF($E24="404","",IF($F24="ARTICULO","Artículo "&$G24&" → /blog/<slug>/",INDEX(Destinos!$C$9:$C$25,MATCH($F24,Destinos!$A$9:$A$25,0)))) -> Artículo E-46 → /blog/<slug>/ | N24: =IF(AND($E24="301",$F24="ARTICULO"),$I24,"") -> 46623 | O24: R-BLOG-01 | S24: =IF(AND($E24="404",OR(N($Q24)>0,N($R24)>0)),"REVISAR: tiene clics o enlaces → pasar a 301","") | T24: =IF(OR($E24="Conservar URL",AND($E24="301",OR(N($Q24)>=2,$C24="Páginas"))),"Sí","No") -> No | U24: =IF($E24="Sin cambio","200 · sin cambio",IF($T24="Sí",IF($E24="Conservar URL","200 · misma URL","301"),"404")) -> 404
A25: https://www.continentalmedia.com.mx/2012/12/marketing-viral/ | B25: /2012/12/marketing-viral/ | C25: Blog | E25: 301 | F25: ARTICULO | G25: E-15 | H25: Redes sociales y comunidad | I25: 46399 | J25: =IF(E25="301",301,IF(E25="404",404,200)) -> 301 | K25: =IF($E25="404","",IF($F25="ARTICULO",IF($I25<=Destinos!$B$5,"[artículo "&$G25&"] /blog/<slug>/",IFERROR(INDEX(Destinos!$H$9:$H$25,MATCH($H25,Destinos!$E$9:$E$25,0)),Destinos!$C$15)),INDEX(Destinos!$H$9:$H$25,MATCH($F25,Destinos!$A$9:$A$25,0)))) -> /blog/categoria/redes-sociales/ | L25: =IF($K25="","",IF(LEFT($K25,1)="/",Destinos!$B$4&$K25,$K25)) -> https://continentalmedia.com.mx/blog/categoria/redes-sociales/ | M25: =IF($E25="404","",IF($F25="ARTICULO","Artículo "&$G25&" → /blog/<slug>/",INDEX(Destinos!$C$9:$C$25,MATCH($F25,Destinos!$A$9:$A$25,0)))) -> Artículo E-15 → /blog/<slug>/ | N25: =IF(AND($E25="301",$F25="ARTICULO"),$I25,"") -> 46399 | O25: R-BLOG-01 | S25: =IF(AND($E25="404",OR(N($Q25)>0,N($R25)>0)),"REVISAR: tiene clics o enlaces → pasar a 301","") | T25: =IF(OR($E25="Conservar URL",AND($E25="301",OR(N($Q25)>=2,$C25="Páginas"))),"Sí","No") -> No | U25: =IF($E25="Sin cambio","200 · sin cambio",IF($T25="Sí",IF($E25="Conservar URL","200 · misma URL","301"),"404")) -> 404
A26: https://www.continentalmedia.com.mx/2012/12/neuromarketing/ | B26: /2012/12/neuromarketing/ | C26: Blog | E26: 301 | F26: ARTICULO | G26: E-20 | H26: Branding, diseño y creatividad | I26: 46427 | J26: =IF(E26="301",301,IF(E26="404",404,200)) -> 301 | K26: =IF($E26="404","",IF($F26="ARTICULO",IF($I26<=Destinos!$B$5,"[artículo "&$G26&"] /blog/<slug>/",IFERROR(INDEX(Destinos!$H$9:$H$25,MATCH($H26,Destinos!$E$9:$E$25,0)),Destinos!$C$15)),INDEX(Destinos!$H$9:$H$25,MATCH($F26,Destinos!$A$9:$A$25,0)))) -> /blog/ | L26: =IF($K26="","",IF(LEFT($K26,1)="/",Destinos!$B$4&$K26,$K26)) -> https://continentalmedia.com.mx/blog/ | M26: =IF($E26="404","",IF($F26="ARTICULO","Artículo "&$G26&" → /blog/<slug>/",INDEX(Destinos!$C$9:$C$25,MATCH($F26,Destinos!$A$9:$A$25,0)))) -> Artículo E-20 → /blog/<slug>/ | N26: =IF(AND($E26="301",$F26="ARTICULO"),$I26,"") -> 46427 | O26: R-BLOG-01 | S26: =IF(AND($E26="404",OR(N($Q26)>0,N($R26)>0)),"REVISAR: tiene clics o enlaces → pasar a 301","") | T26: =IF(OR($E26="Conservar URL",AND($E26="301",OR(N($Q26)>=2,$C26="Páginas"))),"Sí","No") -> No | U26: =IF($E26="Sin cambio","200 · sin cambio",IF($T26="Sí",IF($E26="Conservar URL","200 · misma URL","301"),"404")) -> 404
A27: https://www.continentalmedia.com.mx/2012/12/plan-de-medios/ | B27: /2012/12/plan-de-medios/ | C27: Blog | E27: 301 | F27: ARTICULO | G27: E-45 | H27: Eventos, medios y publicidad exterior | I27: 46616 | J27: =IF(E27="301",301,IF(E27="404",404,200)) -> 301 | K27: =IF($E27="404","",IF($F27="ARTICULO",IF($I27<=Destinos!$B$5,"[artículo "&$G27&"] /blog/<slug>/",IFERROR(INDEX(Destinos!$H$9:$H$25,MATCH($H27,Destinos!$E$9:$E$25,0)),Destinos!$C$15)),INDEX(Destinos!$H$9:$H$25,MATCH($F27,Destinos!$A$9:$A$25,0)))) -> /blog/ | L27: =IF($K27="","",IF(LEFT($K27,1)="/",Destinos!$B$4&$K27,$K27)) -> https://continentalmedia.com.mx/blog/ | M27: =IF($E27="404","",IF($F27="ARTICULO","Artículo "&$G27&" → /blog/<slug>/",INDEX(Destinos!$C$9:$C$25,MATCH($F27,Destinos!$A$9:$A$25,0)))) -> Artículo E-45 → /blog/<slug>/ | N27: =IF(AND($E27="301",$F27="ARTICULO"),$I27,"") -> 46616 | O27: R-BLOG-01 | S27: =IF(AND($E27="404",OR(N($Q27)>0,N($R27)>0)),"REVISAR: tiene clics o enlaces → pasar a 301","") | T27: =IF(OR($E27="Conservar URL",AND($E27="301",OR(N($Q27)>=2,$C27="Páginas"))),"Sí","No") -> No | U27: =IF($E27="Sin cambio","200 · sin cambio",IF($T27="Sí",IF($E27="Conservar URL","200 · misma URL","301"),"404")) -> 404
A28: https://www.continentalmedia.com.mx/2012/12/por-que-una-imagen-resulta-tan-poderosa/ | B28: /2012/12/por-que-una-imagen-resulta-tan-poderosa/ | C28: Blog | E28: 301 | F28: ARTICULO | G28: E-20 | H28: Branding, diseño y creatividad | I28: 46427 | J28: =IF(E28="301",301,IF(E28="404",404,200)) -> 301 | K28: =IF($E28="404","",IF($F28="ARTICULO",IF($I28<=Destinos!$B$5,"[artículo "&$G28&"] /blog/<slug>/",IFERROR(INDEX(Destinos!$H$9:$H$25,MATCH($H28,Destinos!$E$9:$E$25,0)),Destinos!$C$15)),INDEX(Destinos!$H$9:$H$25,MATCH($F28,Destinos!$A$9:$A$25,0)))) -> /blog/ | L28: =IF($K28="","",IF(LEFT($K28,1)="/",Destinos!$B$4&$K28,$K28)) -> https://continentalmedia.com.mx/blog/ | M28: =IF($E28="404","",IF($F28="ARTICULO","Artículo "&$G28&" → /blog/<slug>/",INDEX(Destinos!$C$9:$C$25,MATCH($F28,Destinos!$A$9:$A$25,0)))) -> Artículo E-20 → /blog/<slug>/ | N28: =IF(AND($E28="301",$F28="ARTICULO"),$I28,"") -> 46427 | O28: R-BLOG-01 | Q28: 3 | S28: =IF(AND($E28="404",OR(N($Q28)>0,N($R28)>0)),"REVISAR: tiene clics o enlaces → pasar a 301","") | T28: =IF(OR($E28="Conservar URL",AND($E28="301",OR(N($Q28)>=2,$C28="Páginas"))),"Sí","No") -> Sí | U28: =IF($E28="Sin cambio","200 · sin cambio",IF($T28="Sí",IF($E28="Conservar URL","200 · misma URL","301"),"404")) -> 301
A29: https://www.continentalmedia.com.mx/2012/12/proceso-creativo/ | B29: /2012/12/proceso-creativo/ | C29: Blog | E29: 301 | F29: ARTICULO | G29: E-33 | H29: Branding, diseño y creatividad | I29: 46504 | J29: =IF(E29="301",301,IF(E29="404",404,200)) -> 301 | K29: =IF($E29="404","",IF($F29="ARTICULO",IF($I29<=Destinos!$B$5,"[artículo "&$G29&"] /blog/<slug>/",IFERROR(INDEX(Destinos!$H$9:$H$25,MATCH($H29,Destinos!$E$9:$E$25,0)),Destinos!$C$15)),INDEX(Destinos!$H$9:$H$25,MATCH($F29,Destinos!$A$9:$A$25,0)))) -> /blog/ | L29: =IF($K29="","",IF(LEFT($K29,1)="/",Destinos!$B$4&$K29,$K29)) -> https://continentalmedia.com.mx/blog/ | M29: =IF($E29="404","",IF($F29="ARTICULO","Artículo "&$G29&" → /blog/<slug>/",INDEX(Destinos!$C$9:$C$25,MATCH($F29,Destinos!$A$9:$A$25,0)))) -> Artículo E-33 → /blog/<slug>/ | N29: =IF(AND($E29="301",$F29="ARTICULO"),$I29,"") -> 46504 | O29: R-BLOG-01 | S29: =IF(AND($E29="404",OR(N($Q29)>0,N($R29)>0)),"REVISAR: tiene clics o enlaces → pasar a 301","") | T29: =IF(OR($E29="Conservar URL",AND($E29="301",OR(N($Q29)>=2,$C29="Páginas"))),"Sí","No") -> No | U29: =IF($E29="Sin cambio","200 · sin cambio",IF($T29="Sí",IF($E29="Conservar URL","200 · misma URL","301"),"404")) -> 404
A30: https://www.continentalmedia.com.mx/2012/12/publicidad-btl/ | B30: /2012/12/publicidad-btl/ | C30: Blog | E30: 301 | F30: ARTICULO | G30: E-44 | H30: Eventos, medios y publicidad exterior | I30: 46609 | J30: =IF(E30="301",301,IF(E30="404",404,200)) -> 301 | K30: =IF($E30="404","",IF($F30="ARTICULO",IF($I30<=Destinos!$B$5,"[artículo "&$G30&"] /blog/<slug>/",IFERROR(INDEX(Destinos!$H$9:$H$25,MATCH($H30,Destinos!$E$9:$E$25,0)),Destinos!$C$15)),INDEX(Destinos!$H$9:$H$25,MATCH($F30,Destinos!$A$9:$A$25,0)))) -> /blog/ | L30: =IF($K30="","",IF(LEFT($K30,1)="/",Destinos!$B$4&$K30,$K30)) -> https://continentalmedia.com.mx/blog/ | M30: =IF($E30="404","",IF($F30="ARTICULO","Artículo "&$G30&" → /blog/<slug>/",INDEX(Destinos!$C$9:$C$25,MATCH($F30,Destinos!$A$9:$A$25,0)))) -> Artículo E-44 → /blog/<slug>/ | N30: =IF(AND($E30="301",$F30="ARTICULO"),$I30,"") -> 46609 | O30: R-BLOG-01 | S30: =IF(AND($E30="404",OR(N($Q30)>0,N($R30)>0)),"REVISAR: tiene clics o enlaces → pasar a 301","") | T30: =IF(OR($E30="Conservar URL",AND($E30="301",OR(N($Q30)>=2,$C30="Páginas"))),"Sí","No") -> No | U30: =IF($E30="Sin cambio","200 · sin cambio",IF($T30="Sí",IF($E30="Conservar URL","200 · misma URL","301"),"404")) -> 404
A31: https://www.continentalmedia.com.mx/2012/12/redes-sociales-en-pymes/ | B31: /2012/12/redes-sociales-en-pymes/ | C31: Blog | E31: 301 | F31: ARTICULO | G31: E-10 | H31: Redes sociales y comunidad | I31: 46378 | J31: =IF(E31="301",301,IF(E31="404",404,200)) -> 301 | K31: =IF($E31="404","",IF($F31="ARTICULO",IF($I31<=Destinos!$B$5,"[artículo "&$G31&"] /blog/<slug>/",IFERROR(INDEX(Destinos!$H$9:$H$25,MATCH($H31,Destinos!$E$9:$E$25,0)),Destinos!$C$15)),INDEX(Destinos!$H$9:$H$25,MATCH($F31,Destinos!$A$9:$A$25,0)))) -> /blog/categoria/redes-sociales/ | L31: =IF($K31="","",IF(LEFT($K31,1)="/",Destinos!$B$4&$K31,$K31)) -> https://continentalmedia.com.mx/blog/categoria/redes-sociales/ | M31: =IF($E31="404","",IF($F31="ARTICULO","Artículo "&$G31&" → /blog/<slug>/",INDEX(Destinos!$C$9:$C$25,MATCH($F31,Destinos!$A$9:$A$25,0)))) -> Artículo E-10 → /blog/<slug>/ | N31: =IF(AND($E31="301",$F31="ARTICULO"),$I31,"") -> 46378 | O31: R-BLOG-01 | S31: =IF(AND($E31="404",OR(N($Q31)>0,N($R31)>0)),"REVISAR: tiene clics o enlaces → pasar a 301","") | T31: =IF(OR($E31="Conservar URL",AND($E31="301",OR(N($Q31)>=2,$C31="Páginas"))),"Sí","No") -> No | U31: =IF($E31="Sin cambio","200 · sin cambio",IF($T31="Sí",IF($E31="Conservar URL","200 · misma URL","301"),"404")) -> 404
A32: https://www.continentalmedia.com.mx/2012/12/relaciones-publicas/ | B32: /2012/12/relaciones-publicas/ | C32: Blog | E32: 301 | F32: ARTICULO | G32: E-30 | H32: Relaciones públicas y comunicación | I32: 46483 | J32: =IF(E32="301",301,IF(E32="404",404,200)) -> 301 | K32: =IF($E32="404","",IF($F32="ARTICULO",IF($I32<=Destinos!$B$5,"[artículo "&$G32&"] /blog/<slug>/",IFERROR(INDEX(Destinos!$H$9:$H$25,MATCH($H32,Destinos!$E$9:$E$25,0)),Destinos!$C$15)),INDEX(Destinos!$H$9:$H$25,MATCH($F32,Destinos!$A$9:$A$25,0)))) -> /blog/ | L32: =IF($K32="","",IF(LEFT($K32,1)="/",Destinos!$B$4&$K32,$K32)) -> https://continentalmedia.com.mx/blog/ | M32: =IF($E32="404","",IF($F32="ARTICULO","Artículo "&$G32&" → /blog/<slug>/",INDEX(Destinos!$C$9:$C$25,MATCH($F32,Destinos!$A$9:$A$25,0)))) -> Artículo E-30 → /blog/<slug>/ | N32: =IF(AND($E32="301",$F32="ARTICULO"),$I32,"") -> 46483 | O32: R-BLOG-01 | S32: =IF(AND($E32="404",OR(N($Q32)>0,N($R32)>0)),"REVISAR: tiene clics o enlaces → pasar a 301","") | T32: =IF(OR($E32="Conservar URL",AND($E32="301",OR(N($Q32)>=2,$C32="Páginas"))),"Sí","No") -> No | U32: =IF($E32="Sin cambio","200 · sin cambio",IF($T32="Sí",IF($E32="Conservar URL","200 · misma URL","301"),"404")) -> 404
A33: https://www.continentalmedia.com.mx/2013/01/el-social-media-no-es-una-labor-mas-de-tu-secretaria/ | B33: /2013/01/el-social-media-no-es-una-labor-mas-de-tu-secretaria/ | C33: Blog | E33: 404 | F33: — | J33: =IF(E33="301",301,IF(E33="404",404,200)) -> 404 | K33: =IF($E33="404","",IF($F33="ARTICULO",IF($I33<=Destinos!$B$5,"[artículo "&$G33&"] /blog/<slug>/",IFERROR(INDEX(Destinos!$H$9:$H$25,MATCH($H33,Destinos!$E$9:$E$25,0)),Destinos!$C$15)),INDEX(Destinos!$H$9:$H$25,MATCH($F33,Destinos!$A$9:$A$25,0)))) | L33: =IF($K33="","",IF(LEFT($K33,1)="/",Destinos!$B$4&$K33,$K33)) | M33: =IF($E33="404","",IF($F33="ARTICULO","Artículo "&$G33&" → /blog/<slug>/",INDEX(Destinos!$C$9:$C$25,MATCH($F33,Destinos!$A$9:$A$25,0)))) | N33: =IF(AND($E33="301",$F33="ARTICULO"),$I33,"") | O33: R-BLOG-02 | P33: Sin valor SEO actual; sin tema equivalente | S33: =IF(AND($E33="404",OR(N($Q33)>0,N($R33)>0)),"REVISAR: tiene clics o enlaces → pasar a 301","") | T33: =IF(OR($E33="Conservar URL",AND($E33="301",OR(N($Q33)>=2,$C33="Páginas"))),"Sí","No") -> No | U33: =IF($E33="Sin cambio","200 · sin cambio",IF($T33="Sí",IF($E33="Conservar URL","200 · misma URL","301"),"404")) -> 404
A34: https://www.continentalmedia.com.mx/2013/01/la-forma-de-hacer-marketing-en-el-2013/ | B34: /2013/01/la-forma-de-hacer-marketing-en-el-2013/ | C34: Blog | E34: 301 | F34: ARTICULO | G34: E-09 | H34: Estrategia de marketing y contenidos | I34: 46314 | J34: =IF(E34="301",301,IF(E34="404",404,200)) -> 301 | K34: =IF($E34="404","",IF($F34="ARTICULO",IF($I34<=Destinos!$B$5,"[artículo "&$G34&"] /blog/<slug>/",IFERROR(INDEX(Destinos!$H$9:$H$25,MATCH($H34,Destinos!$E$9:$E$25,0)),Destinos!$C$15)),INDEX(Destinos!$H$9:$H$25,MATCH($F34,Destinos!$A$9:$A$25,0)))) -> [artículo E-09] /blog/<slug>/ | L34: =IF($K34="","",IF(LEFT($K34,1)="/",Destinos!$B$4&$K34,$K34)) -> [artículo E-09] /blog/<slug>/ | M34: =IF($E34="404","",IF($F34="ARTICULO","Artículo "&$G34&" → /blog/<slug>/",INDEX(Destinos!$C$9:$C$25,MATCH($F34,Destinos!$A$9:$A$25,0)))) -> Artículo E-09 → /blog/<slug>/ | N34: =IF(AND($E34="301",$F34="ARTICULO"),$I34,"") -> 46314 | O34: R-BLOG-01 | S34: =IF(AND($E34="404",OR(N($Q34)>0,N($R34)>0)),"REVISAR: tiene clics o enlaces → pasar a 301","") | T34: =IF(OR($E34="Conservar URL",AND($E34="301",OR(N($Q34)>=2,$C34="Páginas"))),"Sí","No") -> No | U34: =IF($E34="Sin cambio","200 · sin cambio",IF($T34="Sí",IF($E34="Conservar URL","200 · misma URL","301"),"404")) -> 404
A35: https://www.continentalmedia.com.mx/2013/02/insight-un-concepto-que-muchos-manejan-pero-no-todos-comprenden/ | B35: /2013/02/insight-un-concepto-que-muchos-manejan-pero-no-todos-comprenden/ | C35: Blog | E35: 404 | F35: — | J35: =IF(E35="301",301,IF(E35="404",404,200)) -> 404 | K35: =IF($E35="404","",IF($F35="ARTICULO",IF($I35<=Destinos!$B$5,"[artículo "&$G35&"] /blog/<slug>/",IFERROR(INDEX(Destinos!$H$9:$H$25,MATCH($H35,Destinos!$E$9:$E$25,0)),Destinos!$C$15)),INDEX(Destinos!$H$9:$H$25,MATCH($F35,Destinos!$A$9:$A$25,0)))) | L35: =IF($K35="","",IF(LEFT($K35,1)="/",Destinos!$B$4&$K35,$K35)) | M35: =IF($E35="404","",IF($F35="ARTICULO","Artículo "&$G35&" → /blog/<slug>/",INDEX(Destinos!$C$9:$C$25,MATCH($F35,Destinos!$A$9:$A$25,0)))) | N35: =IF(AND($E35="301",$F35="ARTICULO"),$I35,"") | O35: R-BLOG-02 | P35: Sin valor SEO actual; sin tema equivalente | S35: =IF(AND($E35="404",OR(N($Q35)>0,N($R35)>0)),"REVISAR: tiene clics o enlaces → pasar a 301","") | T35: =IF(OR($E35="Conservar URL",AND($E35="301",OR(N($Q35)>=2,$C35="Páginas"))),"Sí","No") -> No | U35: =IF($E35="Sin cambio","200 · sin cambio",IF($T35="Sí",IF($E35="Conservar URL","200 · misma URL","301"),"404")) -> 404
A36: https://www.continentalmedia.com.mx/2013/03/la-publicidad-en-retrospectiva/ | B36: /2013/03/la-publicidad-en-retrospectiva/ | C36: Blog | E36: 404 | F36: — | J36: =IF(E36="301",301,IF(E36="404",404,200)) -> 404 | K36: =IF($E36="404","",IF($F36="ARTICULO",IF($I36<=Destinos!$B$5,"[artículo "&$G36&"] /blog/<slug>/",IFERROR(INDEX(Destinos!$H$9:$H$25,MATCH($H36,Destinos!$E$9:$E$25,0)),Destinos!$C$15)),INDEX(Destinos!$H$9:$H$25,MATCH($F36,Destinos!$A$9:$A$25,0)))) | L36: =IF($K36="","",IF(LEFT($K36,1)="/",Destinos!$B$4&$K36,$K36)) | M36: =IF($E36="404","",IF($F36="ARTICULO","Artículo "&$G36&" → /blog/<slug>/",INDEX(Destinos!$C$9:$C$25,MATCH($F36,Destinos!$A$9:$A$25,0)))) | N36: =IF(AND($E36="301",$F36="ARTICULO"),$I36,"") | O36: R-BLOG-02 | P36: Sin valor SEO actual; sin tema equivalente | S36: =IF(AND($E36="404",OR(N($Q36)>0,N($R36)>0)),"REVISAR: tiene clics o enlaces → pasar a 301","") | T36: =IF(OR($E36="Conservar URL",AND($E36="301",OR(N($Q36)>=2,$C36="Páginas"))),"Sí","No") -> No | U36: =IF($E36="Sin cambio","200 · sin cambio",IF($T36="Sí",IF($E36="Conservar URL","200 · misma URL","301"),"404")) -> 404
A37: https://www.continentalmedia.com.mx/2013/03/porque-invertir-en-imagen-corporativa/ | B37: /2013/03/porque-invertir-en-imagen-corporativa/ | C37: Blog | E37: 301 | F37: ARTICULO | G37: E-29 | H37: Branding, diseño y creatividad | I37: 46476 | J37: =IF(E37="301",301,IF(E37="404",404,200)) -> 301 | K37: =IF($E37="404","",IF($F37="ARTICULO",IF($I37<=Destinos!$B$5,"[artículo "&$G37&"] /blog/<slug>/",IFERROR(INDEX(Destinos!$H$9:$H$25,MATCH($H37,Destinos!$E$9:$E$25,0)),Destinos!$C$15)),INDEX(Destinos!$H$9:$H$25,MATCH($F37,Destinos!$A$9:$A$25,0)))) -> /blog/ | L37: =IF($K37="","",IF(LEFT($K37,1)="/",Destinos!$B$4&$K37,$K37)) -> https://continentalmedia.com.mx/blog/ | M37: =IF($E37="404","",IF($F37="ARTICULO","Artículo "&$G37&" → /blog/<slug>/",INDEX(Destinos!$C$9:$C$25,MATCH($F37,Destinos!$A$9:$A$25,0)))) -> Artículo E-29 → /blog/<slug>/ | N37: =IF(AND($E37="301",$F37="ARTICULO"),$I37,"") -> 46476 | O37: R-BLOG-01 | S37: =IF(AND($E37="404",OR(N($Q37)>0,N($R37)>0)),"REVISAR: tiene clics o enlaces → pasar a 301","") | T37: =IF(OR($E37="Conservar URL",AND($E37="301",OR(N($Q37)>=2,$C37="Páginas"))),"Sí","No") -> No | U37: =IF($E37="Sin cambio","200 · sin cambio",IF($T37="Sí",IF($E37="Conservar URL","200 · misma URL","301"),"404")) -> 404
A38: https://www.continentalmedia.com.mx/2013/03/tendencias-en-diseno-web-2013/ | B38: /2013/03/tendencias-en-diseno-web-2013/ | C38: Blog | E38: 301 | F38: ARTICULO | G38: E-39 | H38: Web, SEO y publicidad digital | I38: 46525 | J38: =IF(E38="301",301,IF(E38="404",404,200)) -> 301 | K38: =IF($E38="404","",IF($F38="ARTICULO",IF($I38<=Destinos!$B$5,"[artículo "&$G38&"] /blog/<slug>/",IFERROR(INDEX(Destinos!$H$9:$H$25,MATCH($H38,Destinos!$E$9:$E$25,0)),Destinos!$C$15)),INDEX(Destinos!$H$9:$H$25,MATCH($F38,Destinos!$A$9:$A$25,0)))) -> /blog/ | L38: =IF($K38="","",IF(LEFT($K38,1)="/",Destinos!$B$4&$K38,$K38)) -> https://continentalmedia.com.mx/blog/ | M38: =IF($E38="404","",IF($F38="ARTICULO","Artículo "&$G38&" → /blog/<slug>/",INDEX(Destinos!$C$9:$C$25,MATCH($F38,Destinos!$A$9:$A$25,0)))) -> Artículo E-39 → /blog/<slug>/ | N38: =IF(AND($E38="301",$F38="ARTICULO"),$I38,"") -> 46525 | O38: R-BLOG-01 | S38: =IF(AND($E38="404",OR(N($Q38)>0,N($R38)>0)),"REVISAR: tiene clics o enlaces → pasar a 301","") | T38: =IF(OR($E38="Conservar URL",AND($E38="301",OR(N($Q38)>=2,$C38="Páginas"))),"Sí","No") -> No | U38: =IF($E38="Sin cambio","200 · sin cambio",IF($T38="Sí",IF($E38="Conservar URL","200 · misma URL","301"),"404")) -> 404
A39: https://www.continentalmedia.com.mx/2013/03/un-diseno-bonito-no-lo-es-todo/ | B39: /2013/03/un-diseno-bonito-no-lo-es-todo/ | C39: Blog | E39: 301 | F39: ARTICULO | G39: E-29 | H39: Branding, diseño y creatividad | I39: 46476 | J39: =IF(E39="301",301,IF(E39="404",404,200)) -> 301 | K39: =IF($E39="404","",IF($F39="ARTICULO",IF($I39<=Destinos!$B$5,"[artículo "&$G39&"] /blog/<slug>/",IFERROR(INDEX(Destinos!$H$9:$H$25,MATCH($H39,Destinos!$E$9:$E$25,0)),Destinos!$C$15)),INDEX(Destinos!$H$9:$H$25,MATCH($F39,Destinos!$A$9:$A$25,0)))) -> /blog/ | L39: =IF($K39="","",IF(LEFT($K39,1)="/",Destinos!$B$4&$K39,$K39)) -> https://continentalmedia.com.mx/blog/ | M39: =IF($E39="404","",IF($F39="ARTICULO","Artículo "&$G39&" → /blog/<slug>/",INDEX(Destinos!$C$9:$C$25,MATCH($F39,Destinos!$A$9:$A$25,0)))) -> Artículo E-29 → /blog/<slug>/ | N39: =IF(AND($E39="301",$F39="ARTICULO"),$I39,"") -> 46476 | O39: R-BLOG-01 | S39: =IF(AND($E39="404",OR(N($Q39)>0,N($R39)>0)),"REVISAR: tiene clics o enlaces → pasar a 301","") | T39: =IF(OR($E39="Conservar URL",AND($E39="301",OR(N($Q39)>=2,$C39="Páginas"))),"Sí","No") -> No | U39: =IF($E39="Sin cambio","200 · sin cambio",IF($T39="Sí",IF($E39="Conservar URL","200 · misma URL","301"),"404")) -> 404
A40: https://www.continentalmedia.com.mx/2013/04/10-pasos-para-conseguir-mejores-ideas-creativas/ | B40: /2013/04/10-pasos-para-conseguir-mejores-ideas-creativas/ | C40: Blog | E40: 301 | F40: ARTICULO | G40: E-33 | H40: Branding, diseño y creatividad | I40: 46504 | J40: =IF(E40="301",301,IF(E40="404",404,200)) -> 301 | K40: =IF($E40="404","",IF($F40="ARTICULO",IF($I40<=Destinos!$B$5,"[artículo "&$G40&"] /blog/<slug>/",IFERROR(INDEX(Destinos!$H$9:$H$25,MATCH($H40,Destinos!$E$9:$E$25,0)),Destinos!$C$15)),INDEX(Destinos!$H$9:$H$25,MATCH($F40,Destinos!$A$9:$A$25,0)))) -> /blog/ | L40: =IF($K40="","",IF(LEFT($K40,1)="/",Destinos!$B$4&$K40,$K40)) -> https://continentalmedia.com.mx/blog/ | M40: =IF($E40="404","",IF($F40="ARTICULO","Artículo "&$G40&" → /blog/<slug>/",INDEX(Destinos!$C$9:$C$25,MATCH($F40,Destinos!$A$9:$A$25,0)))) -> Artículo E-33 → /blog/<slug>/ | N40: =IF(AND($E40="301",$F40="ARTICULO"),$I40,"") -> 46504 | O40: R-BLOG-01 | S40: =IF(AND($E40="404",OR(N($Q40)>0,N($R40)>0)),"REVISAR: tiene clics o enlaces → pasar a 301","") | T40: =IF(OR($E40="Conservar URL",AND($E40="301",OR(N($Q40)>=2,$C40="Páginas"))),"Sí","No") -> No | U40: =IF($E40="Sin cambio","200 · sin cambio",IF($T40="Sí",IF($E40="Conservar URL","200 · misma URL","301"),"404")) -> 404
A41: https://www.continentalmedia.com.mx/2013/04/decalogo-del-valor-de-las-ideas/ | B41: /2013/04/decalogo-del-valor-de-las-ideas/ | C41: Blog | E41: 301 | F41: ARTICULO | G41: E-33 | H41: Branding, diseño y creatividad | I41: 46504 | J41: =IF(E41="301",301,IF(E41="404",404,200)) -> 301 | K41: =IF($E41="404","",IF($F41="ARTICULO",IF($I41<=Destinos!$B$5,"[artículo "&$G41&"] /blog/<slug>/",IFERROR(INDEX(Destinos!$H$9:$H$25,MATCH($H41,Destinos!$E$9:$E$25,0)),Destinos!$C$15)),INDEX(Destinos!$H$9:$H$25,MATCH($F41,Destinos!$A$9:$A$25,0)))) -> /blog/ | L41: =IF($K41="","",IF(LEFT($K41,1)="/",Destinos!$B$4&$K41,$K41)) -> https://continentalmedia.com.mx/blog/ | M41: =IF($E41="404","",IF($F41="ARTICULO","Artículo "&$G41&" → /blog/<slug>/",INDEX(Destinos!$C$9:$C$25,MATCH($F41,Destinos!$A$9:$A$25,0)))) -> Artículo E-33 → /blog/<slug>/ | N41: =IF(AND($E41="301",$F41="ARTICULO"),$I41,"") -> 46504 | O41: R-BLOG-01 | S41: =IF(AND($E41="404",OR(N($Q41)>0,N($R41)>0)),"REVISAR: tiene clics o enlaces → pasar a 301","") | T41: =IF(OR($E41="Conservar URL",AND($E41="301",OR(N($Q41)>=2,$C41="Páginas"))),"Sí","No") -> No | U41: =IF($E41="Sin cambio","200 · sin cambio",IF($T41="Sí",IF($E41="Conservar URL","200 · misma URL","301"),"404")) -> 404
A42: https://www.continentalmedia.com.mx/2013/04/historia-de-la-publicidad-en-mexico/ | B42: /2013/04/historia-de-la-publicidad-en-mexico/ | C42: Blog | E42: Conservar URL | F42: MISMA | J42: 200 | K42: =B42 -> /2013/04/historia-de-la-publicidad-en-mexico/ | L42: =Destinos!$B$4&B42 -> https://continentalmedia.com.mx/2013/04/historia-de-la-publicidad-en-mexico/ | M42: Misma URL: se republica actualizado en el blog nuevo | O42: R-LISTA-01 | P42: Junto con el otro post conservado suma el 34% de los clics del sitio viejo; se conserva la ruta heredada (/AAAA/MM/slug/) en el blog nuevo. | Q42: 202 | S42: =IF(AND($E42="404",OR(N($Q42)>0,N($R42)>0)),"REVISAR: tiene clics o enlaces → pasar a 301","") | T42: =IF(OR($E42="Conservar URL",AND($E42="301",OR(N($Q42)>=2,$C42="Páginas"))),"Sí","No") -> Sí | U42: =IF($E42="Sin cambio","200 · sin cambio",IF($T42="Sí",IF($E42="Conservar URL","200 · misma URL","301"),"404")) -> 200 · misma URL
A43: https://www.continentalmedia.com.mx/2013/04/la-evolucion-de-las-redes-sociales/ | B43: /2013/04/la-evolucion-de-las-redes-sociales/ | C43: Blog | E43: 301 | F43: ARTICULO | G43: E-10 | H43: Redes sociales y comunidad | I43: 46378 | J43: =IF(E43="301",301,IF(E43="404",404,200)) -> 301 | K43: =IF($E43="404","",IF($F43="ARTICULO",IF($I43<=Destinos!$B$5,"[artículo "&$G43&"] /blog/<slug>/",IFERROR(INDEX(Destinos!$H$9:$H$25,MATCH($H43,Destinos!$E$9:$E$25,0)),Destinos!$C$15)),INDEX(Destinos!$H$9:$H$25,MATCH($F43,Destinos!$A$9:$A$25,0)))) -> /blog/categoria/redes-sociales/ | L43: =IF($K43="","",IF(LEFT($K43,1)="/",Destinos!$B$4&$K43,$K43)) -> https://continentalmedia.com.mx/blog/categoria/redes-sociales/ | M43: =IF($E43="404","",IF($F43="ARTICULO","Artículo "&$G43&" → /blog/<slug>/",INDEX(Destinos!$C$9:$C$25,MATCH($F43,Destinos!$A$9:$A$25,0)))) -> Artículo E-10 → /blog/<slug>/ | N43: =IF(AND($E43="301",$F43="ARTICULO"),$I43,"") -> 46378 | O43: R-BLOG-01 | S43: =IF(AND($E43="404",OR(N($Q43)>0,N($R43)>0)),"REVISAR: tiene clics o enlaces → pasar a 301","") | T43: =IF(OR($E43="Conservar URL",AND($E43="301",OR(N($Q43)>=2,$C43="Páginas"))),"Sí","No") -> No | U43: =IF($E43="Sin cambio","200 · sin cambio",IF($T43="Sí",IF($E43="Conservar URL","200 · misma URL","301"),"404")) -> 404
A44: https://www.continentalmedia.com.mx/2013/05/codigos-qr-una-herramienta-muy-poderosa-para-tu-empresa/ | B44: /2013/05/codigos-qr-una-herramienta-muy-poderosa-para-tu-empresa/ | C44: Blog | E44: 301 | F44: ARTICULO | G44: E-44 | H44: Eventos, medios y publicidad exterior | I44: 46609 | J44: =IF(E44="301",301,IF(E44="404",404,200)) -> 301 | K44: =IF($E44="404","",IF($F44="ARTICULO",IF($I44<=Destinos!$B$5,"[artículo "&$G44&"] /blog/<slug>/",IFERROR(INDEX(Destinos!$H$9:$H$25,MATCH($H44,Destinos!$E$9:$E$25,0)),Destinos!$C$15)),INDEX(Destinos!$H$9:$H$25,MATCH($F44,Destinos!$A$9:$A$25,0)))) -> /blog/ | L44: =IF($K44="","",IF(LEFT($K44,1)="/",Destinos!$B$4&$K44,$K44)) -> https://continentalmedia.com.mx/blog/ | M44: =IF($E44="404","",IF($F44="ARTICULO","Artículo "&$G44&" → /blog/<slug>/",INDEX(Destinos!$C$9:$C$25,MATCH($F44,Destinos!$A$9:$A$25,0)))) -> Artículo E-44 → /blog/<slug>/ | N44: =IF(AND($E44="301",$F44="ARTICULO"),$I44,"") -> 46609 | O44: R-BLOG-01 | S44: =IF(AND($E44="404",OR(N($Q44)>0,N($R44)>0)),"REVISAR: tiene clics o enlaces → pasar a 301","") | T44: =IF(OR($E44="Conservar URL",AND($E44="301",OR(N($Q44)>=2,$C44="Páginas"))),"Sí","No") -> No | U44: =IF($E44="Sin cambio","200 · sin cambio",IF($T44="Sí",IF($E44="Conservar URL","200 · misma URL","301"),"404")) -> 404
A45: https://www.continentalmedia.com.mx/2013/05/cuanto-valen-las-ideas/ | B45: /2013/05/cuanto-valen-las-ideas/ | C45: Blog | E45: 301 | F45: ARTICULO | G45: E-33 | H45: Branding, diseño y creatividad | I45: 46504 | J45: =IF(E45="301",301,IF(E45="404",404,200)) -> 301 | K45: =IF($E45="404","",IF($F45="ARTICULO",IF($I45<=Destinos!$B$5,"[artículo "&$G45&"] /blog/<slug>/",IFERROR(INDEX(Destinos!$H$9:$H$25,MATCH($H45,Destinos!$E$9:$E$25,0)),Destinos!$C$15)),INDEX(Destinos!$H$9:$H$25,MATCH($F45,Destinos!$A$9:$A$25,0)))) -> /blog/ | L45: =IF($K45="","",IF(LEFT($K45,1)="/",Destinos!$B$4&$K45,$K45)) -> https://continentalmedia.com.mx/blog/ | M45: =IF($E45="404","",IF($F45="ARTICULO","Artículo "&$G45&" → /blog/<slug>/",INDEX(Destinos!$C$9:$C$25,MATCH($F45,Destinos!$A$9:$A$25,0)))) -> Artículo E-33 → /blog/<slug>/ | N45: =IF(AND($E45="301",$F45="ARTICULO"),$I45,"") -> 46504 | O45: R-BLOG-01 | Q45: 5 | S45: =IF(AND($E45="404",OR(N($Q45)>0,N($R45)>0)),"REVISAR: tiene clics o enlaces → pasar a 301","") | T45: =IF(OR($E45="Conservar URL",AND($E45="301",OR(N($Q45)>=2,$C45="Páginas"))),"Sí","No") -> Sí | U45: =IF($E45="Sin cambio","200 · sin cambio",IF($T45="Sí",IF($E45="Conservar URL","200 · misma URL","301"),"404")) -> 301
A46: https://www.continentalmedia.com.mx/2013/05/leyes-gestalt/ | B46: /2013/05/leyes-gestalt/ | C46: Blog | E46: 301 | F46: ARTICULO | G46: E-29 | H46: Branding, diseño y creatividad | I46: 46476 | J46: =IF(E46="301",301,IF(E46="404",404,200)) -> 301 | K46: =IF($E46="404","",IF($F46="ARTICULO",IF($I46<=Destinos!$B$5,"[artículo "&$G46&"] /blog/<slug>/",IFERROR(INDEX(Destinos!$H$9:$H$25,MATCH($H46,Destinos!$E$9:$E$25,0)),Destinos!$C$15)),INDEX(Destinos!$H$9:$H$25,MATCH($F46,Destinos!$A$9:$A$25,0)))) -> /blog/ | L46: =IF($K46="","",IF(LEFT($K46,1)="/",Destinos!$B$4&$K46,$K46)) -> https://continentalmedia.com.mx/blog/ | M46: =IF($E46="404","",IF($F46="ARTICULO","Artículo "&$G46&" → /blog/<slug>/",INDEX(Destinos!$C$9:$C$25,MATCH($F46,Destinos!$A$9:$A$25,0)))) -> Artículo E-29 → /blog/<slug>/ | N46: =IF(AND($E46="301",$F46="ARTICULO"),$I46,"") -> 46476 | O46: R-BLOG-01 | Q46: 21 | S46: =IF(AND($E46="404",OR(N($Q46)>0,N($R46)>0)),"REVISAR: tiene clics o enlaces → pasar a 301","") | T46: =IF(OR($E46="Conservar URL",AND($E46="301",OR(N($Q46)>=2,$C46="Páginas"))),"Sí","No") -> Sí | U46: =IF($E46="Sin cambio","200 · sin cambio",IF($T46="Sí",IF($E46="Conservar URL","200 · misma URL","301"),"404")) -> 301
A47: https://www.continentalmedia.com.mx/2013/05/por-que-realizar-una-investigacion-de-mercados/ | B47: /2013/05/por-que-realizar-una-investigacion-de-mercados/ | C47: Blog | E47: 301 | F47: ARTICULO | G47: G-08 | H47: Estrategia de marketing y contenidos | I47: 46478 | J47: =IF(E47="301",301,IF(E47="404",404,200)) -> 301 | K47: =IF($E47="404","",IF($F47="ARTICULO",IF($I47<=Destinos!$B$5,"[artículo "&$G47&"] /blog/<slug>/",IFERROR(INDEX(Destinos!$H$9:$H$25,MATCH($H47,Destinos!$E$9:$E$25,0)),Destinos!$C$15)),INDEX(Destinos!$H$9:$H$25,MATCH($F47,Destinos!$A$9:$A$25,0)))) -> /blog/categoria/estrategia-de-marketing/ | L47: =IF($K47="","",IF(LEFT($K47,1)="/",Destinos!$B$4&$K47,$K47)) -> https://continentalmedia.com.mx/blog/categoria/estrategia-de-marketing/ | M47: =IF($E47="404","",IF($F47="ARTICULO","Artículo "&$G47&" → /blog/<slug>/",INDEX(Destinos!$C$9:$C$25,MATCH($F47,Destinos!$A$9:$A$25,0)))) -> Artículo G-08 → /blog/<slug>/ | N47: =IF(AND($E47="301",$F47="ARTICULO"),$I47,"") -> 46478 | O47: R-BLOG-01 | S47: =IF(AND($E47="404",OR(N($Q47)>0,N($R47)>0)),"REVISAR: tiene clics o enlaces → pasar a 301","") | T47: =IF(OR($E47="Conservar URL",AND($E47="301",OR(N($Q47)>=2,$C47="Páginas"))),"Sí","No") -> No | U47: =IF($E47="Sin cambio","200 · sin cambio",IF($T47="Sí",IF($E47="Conservar URL","200 · misma URL","301"),"404")) -> 404
A48: https://www.continentalmedia.com.mx/2013/06/10-sencillos-pasos-para-una-campana-publicitaria/ | B48: /2013/06/10-sencillos-pasos-para-una-campana-publicitaria/ | C48: Blog | E48: 301 | F48: ARTICULO | G48: G-04 | H48: Estrategia de marketing y contenidos | I48: 46457 | J48: =IF(E48="301",301,IF(E48="404",404,200)) -> 301 | K48: =IF($E48="404","",IF($F48="ARTICULO",IF($I48<=Destinos!$B$5,"[artículo "&$G48&"] /blog/<slug>/",IFERROR(INDEX(Destinos!$H$9:$H$25,MATCH($H48,Destinos!$E$9:$E$25,0)),Destinos!$C$15)),INDEX(Destinos!$H$9:$H$25,MATCH($F48,Destinos!$A$9:$A$25,0)))) -> /blog/categoria/estrategia-de-marketing/ | L48: =IF($K48="","",IF(LEFT($K48,1)="/",Destinos!$B$4&$K48,$K48)) -> https://continentalmedia.com.mx/blog/categoria/estrategia-de-marketing/ | M48: =IF($E48="404","",IF($F48="ARTICULO","Artículo "&$G48&" → /blog/<slug>/",INDEX(Destinos!$C$9:$C$25,MATCH($F48,Destinos!$A$9:$A$25,0)))) -> Artículo G-04 → /blog/<slug>/ | N48: =IF(AND($E48="301",$F48="ARTICULO"),$I48,"") -> 46457 | O48: R-BLOG-01 | S48: =IF(AND($E48="404",OR(N($Q48)>0,N($R48)>0)),"REVISAR: tiene clics o enlaces → pasar a 301","") | T48: =IF(OR($E48="Conservar URL",AND($E48="301",OR(N($Q48)>=2,$C48="Páginas"))),"Sí","No") -> No | U48: =IF($E48="Sin cambio","200 · sin cambio",IF($T48="Sí",IF($E48="Conservar URL","200 · misma URL","301"),"404")) -> 404
A49: https://www.continentalmedia.com.mx/2013/06/cual-es-tu-percepcion-del-color/ | B49: /2013/06/cual-es-tu-percepcion-del-color/ | C49: Blog | E49: 301 | F49: ARTICULO | G49: E-20 | H49: Branding, diseño y creatividad | I49: 46427 | J49: =IF(E49="301",301,IF(E49="404",404,200)) -> 301 | K49: =IF($E49="404","",IF($F49="ARTICULO",IF($I49<=Destinos!$B$5,"[artículo "&$G49&"] /blog/<slug>/",IFERROR(INDEX(Destinos!$H$9:$H$25,MATCH($H49,Destinos!$E$9:$E$25,0)),Destinos!$C$15)),INDEX(Destinos!$H$9:$H$25,MATCH($F49,Destinos!$A$9:$A$25,0)))) -> /blog/ | L49: =IF($K49="","",IF(LEFT($K49,1)="/",Destinos!$B$4&$K49,$K49)) -> https://continentalmedia.com.mx/blog/ | M49: =IF($E49="404","",IF($F49="ARTICULO","Artículo "&$G49&" → /blog/<slug>/",INDEX(Destinos!$C$9:$C$25,MATCH($F49,Destinos!$A$9:$A$25,0)))) -> Artículo E-20 → /blog/<slug>/ | N49: =IF(AND($E49="301",$F49="ARTICULO"),$I49,"") -> 46427 | O49: R-BLOG-01 | S49: =IF(AND($E49="404",OR(N($Q49)>0,N($R49)>0)),"REVISAR: tiene clics o enlaces → pasar a 301","") | T49: =IF(OR($E49="Conservar URL",AND($E49="301",OR(N($Q49)>=2,$C49="Páginas"))),"Sí","No") -> No | U49: =IF($E49="Sin cambio","200 · sin cambio",IF($T49="Sí",IF($E49="Conservar URL","200 · misma URL","301"),"404")) -> 404
A50: https://www.continentalmedia.com.mx/2013/06/en-politica-la-imagen-cuenta/ | B50: /2013/06/en-politica-la-imagen-cuenta/ | C50: Blog | E50: 301 | F50: ARTICULO | G50: E-32 | H50: Relaciones públicas y comunicación | I50: 46497 | J50: =IF(E50="301",301,IF(E50="404",404,200)) -> 301 | K50: =IF($E50="404","",IF($F50="ARTICULO",IF($I50<=Destinos!$B$5,"[artículo "&$G50&"] /blog/<slug>/",IFERROR(INDEX(Destinos!$H$9:$H$25,MATCH($H50,Destinos!$E$9:$E$25,0)),Destinos!$C$15)),INDEX(Destinos!$H$9:$H$25,MATCH($F50,Destinos!$A$9:$A$25,0)))) -> /blog/ | L50: =IF($K50="","",IF(LEFT($K50,1)="/",Destinos!$B$4&$K50,$K50)) -> https://continentalmedia.com.mx/blog/ | M50: =IF($E50="404","",IF($F50="ARTICULO","Artículo "&$G50&" → /blog/<slug>/",INDEX(Destinos!$C$9:$C$25,MATCH($F50,Destinos!$A$9:$A$25,0)))) -> Artículo E-32 → /blog/<slug>/ | N50: =IF(AND($E50="301",$F50="ARTICULO"),$I50,"") -> 46497 | O50: R-BLOG-01 | S50: =IF(AND($E50="404",OR(N($Q50)>0,N($R50)>0)),"REVISAR: tiene clics o enlaces → pasar a 301","") | T50: =IF(OR($E50="Conservar URL",AND($E50="301",OR(N($Q50)>=2,$C50="Páginas"))),"Sí","No") -> No | U50: =IF($E50="Sin cambio","200 · sin cambio",IF($T50="Sí",IF($E50="Conservar URL","200 · misma URL","301"),"404")) -> 404
A51: https://www.continentalmedia.com.mx/2013/06/la-necesidad-de-contar-con-un-buen-plan-de-marketing/ | B51: /2013/06/la-necesidad-de-contar-con-un-buen-plan-de-marketing/ | C51: Blog | E51: 301 | F51: ARTICULO | G51: G-01 | H51: Estrategia de marketing y contenidos | I51: 46314 | J51: =IF(E51="301",301,IF(E51="404",404,200)) -> 301 | K51: =IF($E51="404","",IF($F51="ARTICULO",IF($I51<=Destinos!$B$5,"[artículo "&$G51&"] /blog/<slug>/",IFERROR(INDEX(Destinos!$H$9:$H$25,MATCH($H51,Destinos!$E$9:$E$25,0)),Destinos!$C$15)),INDEX(Destinos!$H$9:$H$25,MATCH($F51,Destinos!$A$9:$A$25,0)))) -> [artículo G-01] /blog/<slug>/ | L51: =IF($K51="","",IF(LEFT($K51,1)="/",Destinos!$B$4&$K51,$K51)) -> [artículo G-01] /blog/<slug>/ | M51: =IF($E51="404","",IF($F51="ARTICULO","Artículo "&$G51&" → /blog/<slug>/",INDEX(Destinos!$C$9:$C$25,MATCH($F51,Destinos!$A$9:$A$25,0)))) -> Artículo G-01 → /blog/<slug>/ | N51: =IF(AND($E51="301",$F51="ARTICULO"),$I51,"") -> 46314 | O51: R-BLOG-01 | S51: =IF(AND($E51="404",OR(N($Q51)>0,N($R51)>0)),"REVISAR: tiene clics o enlaces → pasar a 301","") | T51: =IF(OR($E51="Conservar URL",AND($E51="301",OR(N($Q51)>=2,$C51="Páginas"))),"Sí","No") -> No | U51: =IF($E51="Sin cambio","200 · sin cambio",IF($T51="Sí",IF($E51="Conservar URL","200 · misma URL","301"),"404")) -> 404
A52: https://www.continentalmedia.com.mx/2013/07/acerca-del-branding-personal/ | B52: /2013/07/acerca-del-branding-personal/ | C52: Blog | E52: 301 | F52: ARTICULO | G52: E-25 | H52: Branding, diseño y creatividad | I52: 46462 | J52: =IF(E52="301",301,IF(E52="404",404,200)) -> 301 | K52: =IF($E52="404","",IF($F52="ARTICULO",IF($I52<=Destinos!$B$5,"[artículo "&$G52&"] /blog/<slug>/",IFERROR(INDEX(Destinos!$H$9:$H$25,MATCH($H52,Destinos!$E$9:$E$25,0)),Destinos!$C$15)),INDEX(Destinos!$H$9:$H$25,MATCH($F52,Destinos!$A$9:$A$25,0)))) -> /blog/ | L52: =IF($K52="","",IF(LEFT($K52,1)="/",Destinos!$B$4&$K52,$K52)) -> https://continentalmedia.com.mx/blog/ | M52: =IF($E52="404","",IF($F52="ARTICULO","Artículo "&$G52&" → /blog/<slug>/",INDEX(Destinos!$C$9:$C$25,MATCH($F52,Destinos!$A$9:$A$25,0)))) -> Artículo E-25 → /blog/<slug>/ | N52: =IF(AND($E52="301",$F52="ARTICULO"),$I52,"") -> 46462 | O52: R-BLOG-01 | S52: =IF(AND($E52="404",OR(N($Q52)>0,N($R52)>0)),"REVISAR: tiene clics o enlaces → pasar a 301","") | T52: =IF(OR($E52="Conservar URL",AND($E52="301",OR(N($Q52)>=2,$C52="Páginas"))),"Sí","No") -> No | U52: =IF($E52="Sin cambio","200 · sin cambio",IF($T52="Sí",IF($E52="Conservar URL","200 · misma URL","301"),"404")) -> 404
A53: https://www.continentalmedia.com.mx/2013/07/marketing-ecologico-una-decision-responsable/ | B53: /2013/07/marketing-ecologico-una-decision-responsable/ | C53: Blog | E53: 301 | F53: ARTICULO | G53: E-27 | H53: Branding, diseño y creatividad | I53: 46469 | J53: =IF(E53="301",301,IF(E53="404",404,200)) -> 301 | K53: =IF($E53="404","",IF($F53="ARTICULO",IF($I53<=Destinos!$B$5,"[artículo "&$G53&"] /blog/<slug>/",IFERROR(INDEX(Destinos!$H$9:$H$25,MATCH($H53,Destinos!$E$9:$E$25,0)),Destinos!$C$15)),INDEX(Destinos!$H$9:$H$25,MATCH($F53,Destinos!$A$9:$A$25,0)))) -> /blog/ | L53: =IF($K53="","",IF(LEFT($K53,1)="/",Destinos!$B$4&$K53,$K53)) -> https://continentalmedia.com.mx/blog/ | M53: =IF($E53="404","",IF($F53="ARTICULO","Artículo "&$G53&" → /blog/<slug>/",INDEX(Destinos!$C$9:$C$25,MATCH($F53,Destinos!$A$9:$A$25,0)))) -> Artículo E-27 → /blog/<slug>/ | N53: =IF(AND($E53="301",$F53="ARTICULO"),$I53,"") -> 46469 | O53: R-BLOG-01 | S53: =IF(AND($E53="404",OR(N($Q53)>0,N($R53)>0)),"REVISAR: tiene clics o enlaces → pasar a 301","") | T53: =IF(OR($E53="Conservar URL",AND($E53="301",OR(N($Q53)>=2,$C53="Páginas"))),"Sí","No") -> No | U53: =IF($E53="Sin cambio","200 · sin cambio",IF($T53="Sí",IF($E53="Conservar URL","200 · misma URL","301"),"404")) -> 404
A54: https://www.continentalmedia.com.mx/2013/07/sabes-lo-que-es-geomarketing-y-lo-que-puedes-hacer-con-el/ | B54: /2013/07/sabes-lo-que-es-geomarketing-y-lo-que-puedes-hacer-con-el/ | C54: Blog | E54: 301 | F54: ARTICULO | G54: G-37 | H54: Web, SEO y publicidad digital | I54: 46401 | J54: =IF(E54="301",301,IF(E54="404",404,200)) -> 301 | K54: =IF($E54="404","",IF($F54="ARTICULO",IF($I54<=Destinos!$B$5,"[artículo "&$G54&"] /blog/<slug>/",IFERROR(INDEX(Destinos!$H$9:$H$25,MATCH($H54,Destinos!$E$9:$E$25,0)),Destinos!$C$15)),INDEX(Destinos!$H$9:$H$25,MATCH($F54,Destinos!$A$9:$A$25,0)))) -> /blog/ | L54: =IF($K54="","",IF(LEFT($K54,1)="/",Destinos!$B$4&$K54,$K54)) -> https://continentalmedia.com.mx/blog/ | M54: =IF($E54="404","",IF($F54="ARTICULO","Artículo "&$G54&" → /blog/<slug>/",INDEX(Destinos!$C$9:$C$25,MATCH($F54,Destinos!$A$9:$A$25,0)))) -> Artículo G-37 → /blog/<slug>/ | N54: =IF(AND($E54="301",$F54="ARTICULO"),$I54,"") -> 46401 | O54: R-BLOG-01 | S54: =IF(AND($E54="404",OR(N($Q54)>0,N($R54)>0)),"REVISAR: tiene clics o enlaces → pasar a 301","") | T54: =IF(OR($E54="Conservar URL",AND($E54="301",OR(N($Q54)>=2,$C54="Páginas"))),"Sí","No") -> No | U54: =IF($E54="Sin cambio","200 · sin cambio",IF($T54="Sí",IF($E54="Conservar URL","200 · misma URL","301"),"404")) -> 404
A55: https://www.continentalmedia.com.mx/2013/07/sabes-lo-que-significa-crm/ | B55: /2013/07/sabes-lo-que-significa-crm/ | C55: Blog | E55: 301 | F55: ARTICULO | G55: G-23 | H55: IA aplicada al marketing | I55: 46611 | J55: =IF(E55="301",301,IF(E55="404",404,200)) -> 301 | K55: =IF($E55="404","",IF($F55="ARTICULO",IF($I55<=Destinos!$B$5,"[artículo "&$G55&"] /blog/<slug>/",IFERROR(INDEX(Destinos!$H$9:$H$25,MATCH($H55,Destinos!$E$9:$E$25,0)),Destinos!$C$15)),INDEX(Destinos!$H$9:$H$25,MATCH($F55,Destinos!$A$9:$A$25,0)))) -> /blog/categoria/ia-aplicada-al-marketing/ | L55: =IF($K55="","",IF(LEFT($K55,1)="/",Destinos!$B$4&$K55,$K55)) -> https://continentalmedia.com.mx/blog/categoria/ia-aplicada-al-marketing/ | M55: =IF($E55="404","",IF($F55="ARTICULO","Artículo "&$G55&" → /blog/<slug>/",INDEX(Destinos!$C$9:$C$25,MATCH($F55,Destinos!$A$9:$A$25,0)))) -> Artículo G-23 → /blog/<slug>/ | N55: =IF(AND($E55="301",$F55="ARTICULO"),$I55,"") -> 46611 | O55: R-BLOG-01 | S55: =IF(AND($E55="404",OR(N($Q55)>0,N($R55)>0)),"REVISAR: tiene clics o enlaces → pasar a 301","") | T55: =IF(OR($E55="Conservar URL",AND($E55="301",OR(N($Q55)>=2,$C55="Páginas"))),"Sí","No") -> No | U55: =IF($E55="Sin cambio","200 · sin cambio",IF($T55="Sí",IF($E55="Conservar URL","200 · misma URL","301"),"404")) -> 404
A56: https://www.continentalmedia.com.mx/2013/08/el-mundo-del-marketing-alrededor-del-vino/ | B56: /2013/08/el-mundo-del-marketing-alrededor-del-vino/ | C56: Blog | E56: 404 | F56: — | J56: =IF(E56="301",301,IF(E56="404",404,200)) -> 404 | K56: =IF($E56="404","",IF($F56="ARTICULO",IF($I56<=Destinos!$B$5,"[artículo "&$G56&"] /blog/<slug>/",IFERROR(INDEX(Destinos!$H$9:$H$25,MATCH($H56,Destinos!$E$9:$E$25,0)),Destinos!$C$15)),INDEX(Destinos!$H$9:$H$25,MATCH($F56,Destinos!$A$9:$A$25,0)))) | L56: =IF($K56="","",IF(LEFT($K56,1)="/",Destinos!$B$4&$K56,$K56)) | M56: =IF($E56="404","",IF($F56="ARTICULO","Artículo "&$G56&" → /blog/<slug>/",INDEX(Destinos!$C$9:$C$25,MATCH($F56,Destinos!$A$9:$A$25,0)))) | N56: =IF(AND($E56="301",$F56="ARTICULO"),$I56,"") | O56: R-BLOG-02 | P56: Sin valor SEO actual; sin tema equivalente | S56: =IF(AND($E56="404",OR(N($Q56)>0,N($R56)>0)),"REVISAR: tiene clics o enlaces → pasar a 301","") | T56: =IF(OR($E56="Conservar URL",AND($E56="301",OR(N($Q56)>=2,$C56="Páginas"))),"Sí","No") -> No | U56: =IF($E56="Sin cambio","200 · sin cambio",IF($T56="Sí",IF($E56="Conservar URL","200 · misma URL","301"),"404")) -> 404
A57: https://www.continentalmedia.com.mx/2013/08/packaging/ | B57: /2013/08/packaging/ | C57: Blog | E57: 301 | F57: ARTICULO | G57: E-29 | H57: Branding, diseño y creatividad | I57: 46476 | J57: =IF(E57="301",301,IF(E57="404",404,200)) -> 301 | K57: =IF($E57="404","",IF($F57="ARTICULO",IF($I57<=Destinos!$B$5,"[artículo "&$G57&"] /blog/<slug>/",IFERROR(INDEX(Destinos!$H$9:$H$25,MATCH($H57,Destinos!$E$9:$E$25,0)),Destinos!$C$15)),INDEX(Destinos!$H$9:$H$25,MATCH($F57,Destinos!$A$9:$A$25,0)))) -> /blog/ | L57: =IF($K57="","",IF(LEFT($K57,1)="/",Destinos!$B$4&$K57,$K57)) -> https://continentalmedia.com.mx/blog/ | M57: =IF($E57="404","",IF($F57="ARTICULO","Artículo "&$G57&" → /blog/<slug>/",INDEX(Destinos!$C$9:$C$25,MATCH($F57,Destinos!$A$9:$A$25,0)))) -> Artículo E-29 → /blog/<slug>/ | N57: =IF(AND($E57="301",$F57="ARTICULO"),$I57,"") -> 46476 | O57: R-BLOG-01 | S57: =IF(AND($E57="404",OR(N($Q57)>0,N($R57)>0)),"REVISAR: tiene clics o enlaces → pasar a 301","") | T57: =IF(OR($E57="Conservar URL",AND($E57="301",OR(N($Q57)>=2,$C57="Páginas"))),"Sí","No") -> No | U57: =IF($E57="Sin cambio","200 · sin cambio",IF($T57="Sí",IF($E57="Conservar URL","200 · misma URL","301"),"404")) -> 404
A58: https://www.continentalmedia.com.mx/2013/08/videojuegos-un-medio-mas-para-la-publicidad/ | B58: /2013/08/videojuegos-un-medio-mas-para-la-publicidad/ | C58: Blog | E58: 301 | F58: ARTICULO | G58: E-08 | H58: IA aplicada al marketing | I58: 46560 | J58: =IF(E58="301",301,IF(E58="404",404,200)) -> 301 | K58: =IF($E58="404","",IF($F58="ARTICULO",IF($I58<=Destinos!$B$5,"[artículo "&$G58&"] /blog/<slug>/",IFERROR(INDEX(Destinos!$H$9:$H$25,MATCH($H58,Destinos!$E$9:$E$25,0)),Destinos!$C$15)),INDEX(Destinos!$H$9:$H$25,MATCH($F58,Destinos!$A$9:$A$25,0)))) -> /blog/categoria/ia-aplicada-al-marketing/ | L58: =IF($K58="","",IF(LEFT($K58,1)="/",Destinos!$B$4&$K58,$K58)) -> https://continentalmedia.com.mx/blog/categoria/ia-aplicada-al-marketing/ | M58: =IF($E58="404","",IF($F58="ARTICULO","Artículo "&$G58&" → /blog/<slug>/",INDEX(Destinos!$C$9:$C$25,MATCH($F58,Destinos!$A$9:$A$25,0)))) -> Artículo E-08 → /blog/<slug>/ | N58: =IF(AND($E58="301",$F58="ARTICULO"),$I58,"") -> 46560 | O58: R-BLOG-01 | S58: =IF(AND($E58="404",OR(N($Q58)>0,N($R58)>0)),"REVISAR: tiene clics o enlaces → pasar a 301","") | T58: =IF(OR($E58="Conservar URL",AND($E58="301",OR(N($Q58)>=2,$C58="Páginas"))),"Sí","No") -> No | U58: =IF($E58="Sin cambio","200 · sin cambio",IF($T58="Sí",IF($E58="Conservar URL","200 · misma URL","301"),"404")) -> 404
A59: https://www.continentalmedia.com.mx/2013/09/eres-fan-de-los-gadgets-y-te-gusta-estar-conectado-a-internet-a-donde-quiera-que-vas/ | B59: /2013/09/eres-fan-de-los-gadgets-y-te-gusta-estar-conectado-a-internet-a-donde-quiera-que-vas/ | C59: Blog | E59: 404 | F59: — | J59: =IF(E59="301",301,IF(E59="404",404,200)) -> 404 | K59: =IF($E59="404","",IF($F59="ARTICULO",IF($I59<=Destinos!$B$5,"[artículo "&$G59&"] /blog/<slug>/",IFERROR(INDEX(Destinos!$H$9:$H$25,MATCH($H59,Destinos!$E$9:$E$25,0)),Destinos!$C$15)),INDEX(Destinos!$H$9:$H$25,MATCH($F59,Destinos!$A$9:$A$25,0)))) | L59: =IF($K59="","",IF(LEFT($K59,1)="/",Destinos!$B$4&$K59,$K59)) | M59: =IF($E59="404","",IF($F59="ARTICULO","Artículo "&$G59&" → /blog/<slug>/",INDEX(Destinos!$C$9:$C$25,MATCH($F59,Destinos!$A$9:$A$25,0)))) | N59: =IF(AND($E59="301",$F59="ARTICULO"),$I59,"") | O59: R-BLOG-02 | P59: Sin valor SEO actual; sin tema equivalente | S59: =IF(AND($E59="404",OR(N($Q59)>0,N($R59)>0)),"REVISAR: tiene clics o enlaces → pasar a 301","") | T59: =IF(OR($E59="Conservar URL",AND($E59="301",OR(N($Q59)>=2,$C59="Páginas"))),"Sí","No") -> No | U59: =IF($E59="Sin cambio","200 · sin cambio",IF($T59="Sí",IF($E59="Conservar URL","200 · misma URL","301"),"404")) -> 404
A60: https://www.continentalmedia.com.mx/2013/09/las-marcas-en-el-cine-casualidad-o-causalidad/ | B60: /2013/09/las-marcas-en-el-cine-casualidad-o-causalidad/ | C60: Blog | E60: 301 | F60: ARTICULO | G60: E-28 | H60: Branding, diseño y creatividad | I60: 46581 | J60: =IF(E60="301",301,IF(E60="404",404,200)) -> 301 | K60: =IF($E60="404","",IF($F60="ARTICULO",IF($I60<=Destinos!$B$5,"[artículo "&$G60&"] /blog/<slug>/",IFERROR(INDEX(Destinos!$H$9:$H$25,MATCH($H60,Destinos!$E$9:$E$25,0)),Destinos!$C$15)),INDEX(Destinos!$H$9:$H$25,MATCH($F60,Destinos!$A$9:$A$25,0)))) -> /blog/ | L60: =IF($K60="","",IF(LEFT($K60,1)="/",Destinos!$B$4&$K60,$K60)) -> https://continentalmedia.com.mx/blog/ | M60: =IF($E60="404","",IF($F60="ARTICULO","Artículo "&$G60&" → /blog/<slug>/",INDEX(Destinos!$C$9:$C$25,MATCH($F60,Destinos!$A$9:$A$25,0)))) -> Artículo E-28 → /blog/<slug>/ | N60: =IF(AND($E60="301",$F60="ARTICULO"),$I60,"") -> 46581 | O60: R-BLOG-01 | S60: =IF(AND($E60="404",OR(N($Q60)>0,N($R60)>0)),"REVISAR: tiene clics o enlaces → pasar a 301","") | T60: =IF(OR($E60="Conservar URL",AND($E60="301",OR(N($Q60)>=2,$C60="Páginas"))),"Sí","No") -> No | U60: =IF($E60="Sin cambio","200 · sin cambio",IF($T60="Sí",IF($E60="Conservar URL","200 · misma URL","301"),"404")) -> 404
A61: https://www.continentalmedia.com.mx/2013/09/no-uses-mi-marca-en-publico/ | B61: /2013/09/no-uses-mi-marca-en-publico/ | C61: Blog | E61: 404 | F61: — | J61: =IF(E61="301",301,IF(E61="404",404,200)) -> 404 | K61: =IF($E61="404","",IF($F61="ARTICULO",IF($I61<=Destinos!$B$5,"[artículo "&$G61&"] /blog/<slug>/",IFERROR(INDEX(Destinos!$H$9:$H$25,MATCH($H61,Destinos!$E$9:$E$25,0)),Destinos!$C$15)),INDEX(Destinos!$H$9:$H$25,MATCH($F61,Destinos!$A$9:$A$25,0)))) | L61: =IF($K61="","",IF(LEFT($K61,1)="/",Destinos!$B$4&$K61,$K61)) | M61: =IF($E61="404","",IF($F61="ARTICULO","Artículo "&$G61&" → /blog/<slug>/",INDEX(Destinos!$C$9:$C$25,MATCH($F61,Destinos!$A$9:$A$25,0)))) | N61: =IF(AND($E61="301",$F61="ARTICULO"),$I61,"") | O61: R-BLOG-02 | P61: Sin valor SEO actual; sin tema equivalente | S61: =IF(AND($E61="404",OR(N($Q61)>0,N($R61)>0)),"REVISAR: tiene clics o enlaces → pasar a 301","") | T61: =IF(OR($E61="Conservar URL",AND($E61="301",OR(N($Q61)>=2,$C61="Páginas"))),"Sí","No") -> No | U61: =IF($E61="Sin cambio","200 · sin cambio",IF($T61="Sí",IF($E61="Conservar URL","200 · misma URL","301"),"404")) -> 404
A62: https://www.continentalmedia.com.mx/2013/10/campanas-de-terror/ | B62: /2013/10/campanas-de-terror/ | C62: Blog | E62: 404 | F62: — | J62: =IF(E62="301",301,IF(E62="404",404,200)) -> 404 | K62: =IF($E62="404","",IF($F62="ARTICULO",IF($I62<=Destinos!$B$5,"[artículo "&$G62&"] /blog/<slug>/",IFERROR(INDEX(Destinos!$H$9:$H$25,MATCH($H62,Destinos!$E$9:$E$25,0)),Destinos!$C$15)),INDEX(Destinos!$H$9:$H$25,MATCH($F62,Destinos!$A$9:$A$25,0)))) | L62: =IF($K62="","",IF(LEFT($K62,1)="/",Destinos!$B$4&$K62,$K62)) | M62: =IF($E62="404","",IF($F62="ARTICULO","Artículo "&$G62&" → /blog/<slug>/",INDEX(Destinos!$C$9:$C$25,MATCH($F62,Destinos!$A$9:$A$25,0)))) | N62: =IF(AND($E62="301",$F62="ARTICULO"),$I62,"") | O62: R-BLOG-02 | P62: Sin valor SEO actual; sin tema equivalente | S62: =IF(AND($E62="404",OR(N($Q62)>0,N($R62)>0)),"REVISAR: tiene clics o enlaces → pasar a 301","") | T62: =IF(OR($E62="Conservar URL",AND($E62="301",OR(N($Q62)>=2,$C62="Páginas"))),"Sí","No") -> No | U62: =IF($E62="Sin cambio","200 · sin cambio",IF($T62="Sí",IF($E62="Conservar URL","200 · misma URL","301"),"404")) -> 404
A63: https://www.continentalmedia.com.mx/2013/10/crisis-de-imagen-publica-en-el-tri/ | B63: /2013/10/crisis-de-imagen-publica-en-el-tri/ | C63: Blog | E63: 301 | F63: ARTICULO | G63: E-31 | H63: Relaciones públicas y comunicación | I63: 46490 | J63: =IF(E63="301",301,IF(E63="404",404,200)) -> 301 | K63: =IF($E63="404","",IF($F63="ARTICULO",IF($I63<=Destinos!$B$5,"[artículo "&$G63&"] /blog/<slug>/",IFERROR(INDEX(Destinos!$H$9:$H$25,MATCH($H63,Destinos!$E$9:$E$25,0)),Destinos!$C$15)),INDEX(Destinos!$H$9:$H$25,MATCH($F63,Destinos!$A$9:$A$25,0)))) -> /blog/ | L63: =IF($K63="","",IF(LEFT($K63,1)="/",Destinos!$B$4&$K63,$K63)) -> https://continentalmedia.com.mx/blog/ | M63: =IF($E63="404","",IF($F63="ARTICULO","Artículo "&$G63&" → /blog/<slug>/",INDEX(Destinos!$C$9:$C$25,MATCH($F63,Destinos!$A$9:$A$25,0)))) -> Artículo E-31 → /blog/<slug>/ | N63: =IF(AND($E63="301",$F63="ARTICULO"),$I63,"") -> 46490 | O63: R-BLOG-01 | S63: =IF(AND($E63="404",OR(N($Q63)>0,N($R63)>0)),"REVISAR: tiene clics o enlaces → pasar a 301","") | T63: =IF(OR($E63="Conservar URL",AND($E63="301",OR(N($Q63)>=2,$C63="Páginas"))),"Sí","No") -> No | U63: =IF($E63="Sin cambio","200 · sin cambio",IF($T63="Sí",IF($E63="Conservar URL","200 · misma URL","301"),"404")) -> 404
A64: https://www.continentalmedia.com.mx/2013/10/google-la-red-social/ | B64: /2013/10/google-la-red-social/ | C64: Blog | E64: 301 | F64: ARTICULO | G64: E-11 | H64: Redes sociales y comunidad | I64: 46385 | J64: =IF(E64="301",301,IF(E64="404",404,200)) -> 301 | K64: =IF($E64="404","",IF($F64="ARTICULO",IF($I64<=Destinos!$B$5,"[artículo "&$G64&"] /blog/<slug>/",IFERROR(INDEX(Destinos!$H$9:$H$25,MATCH($H64,Destinos!$E$9:$E$25,0)),Destinos!$C$15)),INDEX(Destinos!$H$9:$H$25,MATCH($F64,Destinos!$A$9:$A$25,0)))) -> /blog/categoria/redes-sociales/ | L64: =IF($K64="","",IF(LEFT($K64,1)="/",Destinos!$B$4&$K64,$K64)) -> https://continentalmedia.com.mx/blog/categoria/redes-sociales/ | M64: =IF($E64="404","",IF($F64="ARTICULO","Artículo "&$G64&" → /blog/<slug>/",INDEX(Destinos!$C$9:$C$25,MATCH($F64,Destinos!$A$9:$A$25,0)))) -> Artículo E-11 → /blog/<slug>/ | N64: =IF(AND($E64="301",$F64="ARTICULO"),$I64,"") -> 46385 | O64: R-BLOG-01 | S64: =IF(AND($E64="404",OR(N($Q64)>0,N($R64)>0)),"REVISAR: tiene clics o enlaces → pasar a 301","") | T64: =IF(OR($E64="Conservar URL",AND($E64="301",OR(N($Q64)>=2,$C64="Páginas"))),"Sí","No") -> No | U64: =IF($E64="Sin cambio","200 · sin cambio",IF($T64="Sí",IF($E64="Conservar URL","200 · misma URL","301"),"404")) -> 404
A65: https://www.continentalmedia.com.mx/2013/10/marketing-digital-vs-marketing-tradicional/ | B65: /2013/10/marketing-digital-vs-marketing-tradicional/ | C65: Blog | E65: 301 | F65: ARTICULO | G65: E-17 | H65: Estrategia de marketing y contenidos | I65: 46406 | J65: =IF(E65="301",301,IF(E65="404",404,200)) -> 301 | K65: =IF($E65="404","",IF($F65="ARTICULO",IF($I65<=Destinos!$B$5,"[artículo "&$G65&"] /blog/<slug>/",IFERROR(INDEX(Destinos!$H$9:$H$25,MATCH($H65,Destinos!$E$9:$E$25,0)),Destinos!$C$15)),INDEX(Destinos!$H$9:$H$25,MATCH($F65,Destinos!$A$9:$A$25,0)))) -> /blog/categoria/estrategia-de-marketing/ | L65: =IF($K65="","",IF(LEFT($K65,1)="/",Destinos!$B$4&$K65,$K65)) -> https://continentalmedia.com.mx/blog/categoria/estrategia-de-marketing/ | M65: =IF($E65="404","",IF($F65="ARTICULO","Artículo "&$G65&" → /blog/<slug>/",INDEX(Destinos!$C$9:$C$25,MATCH($F65,Destinos!$A$9:$A$25,0)))) -> Artículo E-17 → /blog/<slug>/ | N65: =IF(AND($E65="301",$F65="ARTICULO"),$I65,"") -> 46406 | O65: R-BLOG-01 | S65: =IF(AND($E65="404",OR(N($Q65)>0,N($R65)>0)),"REVISAR: tiene clics o enlaces → pasar a 301","") | T65: =IF(OR($E65="Conservar URL",AND($E65="301",OR(N($Q65)>=2,$C65="Páginas"))),"Sí","No") -> No | U65: =IF($E65="Sin cambio","200 · sin cambio",IF($T65="Sí",IF($E65="Conservar URL","200 · misma URL","301"),"404")) -> 404
A66: https://www.continentalmedia.com.mx/2013/10/marketing-social-filantropia-o-estrategia/ | B66: /2013/10/marketing-social-filantropia-o-estrategia/ | C66: Blog | E66: 301 | F66: ARTICULO | G66: E-27 | H66: Branding, diseño y creatividad | I66: 46469 | J66: =IF(E66="301",301,IF(E66="404",404,200)) -> 301 | K66: =IF($E66="404","",IF($F66="ARTICULO",IF($I66<=Destinos!$B$5,"[artículo "&$G66&"] /blog/<slug>/",IFERROR(INDEX(Destinos!$H$9:$H$25,MATCH($H66,Destinos!$E$9:$E$25,0)),Destinos!$C$15)),INDEX(Destinos!$H$9:$H$25,MATCH($F66,Destinos!$A$9:$A$25,0)))) -> /blog/ | L66: =IF($K66="","",IF(LEFT($K66,1)="/",Destinos!$B$4&$K66,$K66)) -> https://continentalmedia.com.mx/blog/ | M66: =IF($E66="404","",IF($F66="ARTICULO","Artículo "&$G66&" → /blog/<slug>/",INDEX(Destinos!$C$9:$C$25,MATCH($F66,Destinos!$A$9:$A$25,0)))) -> Artículo E-27 → /blog/<slug>/ | N66: =IF(AND($E66="301",$F66="ARTICULO"),$I66,"") -> 46469 | O66: R-BLOG-01 | S66: =IF(AND($E66="404",OR(N($Q66)>0,N($R66)>0)),"REVISAR: tiene clics o enlaces → pasar a 301","") | T66: =IF(OR($E66="Conservar URL",AND($E66="301",OR(N($Q66)>=2,$C66="Páginas"))),"Sí","No") -> No | U66: =IF($E66="Sin cambio","200 · sin cambio",IF($T66="Sí",IF($E66="Conservar URL","200 · misma URL","301"),"404")) -> 404
A67: https://www.continentalmedia.com.mx/2013/11/calaverita-continental-media/ | B67: /2013/11/calaverita-continental-media/ | C67: Blog | E67: 404 | F67: — | J67: =IF(E67="301",301,IF(E67="404",404,200)) -> 404 | K67: =IF($E67="404","",IF($F67="ARTICULO",IF($I67<=Destinos!$B$5,"[artículo "&$G67&"] /blog/<slug>/",IFERROR(INDEX(Destinos!$H$9:$H$25,MATCH($H67,Destinos!$E$9:$E$25,0)),Destinos!$C$15)),INDEX(Destinos!$H$9:$H$25,MATCH($F67,Destinos!$A$9:$A$25,0)))) | L67: =IF($K67="","",IF(LEFT($K67,1)="/",Destinos!$B$4&$K67,$K67)) | M67: =IF($E67="404","",IF($F67="ARTICULO","Artículo "&$G67&" → /blog/<slug>/",INDEX(Destinos!$C$9:$C$25,MATCH($F67,Destinos!$A$9:$A$25,0)))) | N67: =IF(AND($E67="301",$F67="ARTICULO"),$I67,"") | O67: R-BLOG-02 | P67: Sin valor SEO actual; sin tema equivalente | S67: =IF(AND($E67="404",OR(N($Q67)>0,N($R67)>0)),"REVISAR: tiene clics o enlaces → pasar a 301","") | T67: =IF(OR($E67="Conservar URL",AND($E67="301",OR(N($Q67)>=2,$C67="Páginas"))),"Sí","No") -> No | U67: =IF($E67="Sin cambio","200 · sin cambio",IF($T67="Sí",IF($E67="Conservar URL","200 · misma URL","301"),"404")) -> 404
A68: https://www.continentalmedia.com.mx/2013/11/el-web-y-showrooming-amigos-o-enemigos-de-tu-negocio/ | B68: /2013/11/el-web-y-showrooming-amigos-o-enemigos-de-tu-negocio/ | C68: Blog | E68: 301 | F68: ARTICULO | G68: G-44 | H68: Web, SEO y publicidad digital | I68: 46625 | J68: =IF(E68="301",301,IF(E68="404",404,200)) -> 301 | K68: =IF($E68="404","",IF($F68="ARTICULO",IF($I68<=Destinos!$B$5,"[artículo "&$G68&"] /blog/<slug>/",IFERROR(INDEX(Destinos!$H$9:$H$25,MATCH($H68,Destinos!$E$9:$E$25,0)),Destinos!$C$15)),INDEX(Destinos!$H$9:$H$25,MATCH($F68,Destinos!$A$9:$A$25,0)))) -> /blog/ | L68: =IF($K68="","",IF(LEFT($K68,1)="/",Destinos!$B$4&$K68,$K68)) -> https://continentalmedia.com.mx/blog/ | M68: =IF($E68="404","",IF($F68="ARTICULO","Artículo "&$G68&" → /blog/<slug>/",INDEX(Destinos!$C$9:$C$25,MATCH($F68,Destinos!$A$9:$A$25,0)))) -> Artículo G-44 → /blog/<slug>/ | N68: =IF(AND($E68="301",$F68="ARTICULO"),$I68,"") -> 46625 | O68: R-BLOG-01 | S68: =IF(AND($E68="404",OR(N($Q68)>0,N($R68)>0)),"REVISAR: tiene clics o enlaces → pasar a 301","") | T68: =IF(OR($E68="Conservar URL",AND($E68="301",OR(N($Q68)>=2,$C68="Páginas"))),"Sí","No") -> No | U68: =IF($E68="Sin cambio","200 · sin cambio",IF($T68="Sí",IF($E68="Conservar URL","200 · misma URL","301"),"404")) -> 404
A69: https://www.continentalmedia.com.mx/2013/11/greenwashing-el-engano-verde/ | B69: /2013/11/greenwashing-el-engano-verde/ | C69: Blog | E69: 301 | F69: ARTICULO | G69: E-27 | H69: Branding, diseño y creatividad | I69: 46469 | J69: =IF(E69="301",301,IF(E69="404",404,200)) -> 301 | K69: =IF($E69="404","",IF($F69="ARTICULO",IF($I69<=Destinos!$B$5,"[artículo "&$G69&"] /blog/<slug>/",IFERROR(INDEX(Destinos!$H$9:$H$25,MATCH($H69,Destinos!$E$9:$E$25,0)),Destinos!$C$15)),INDEX(Destinos!$H$9:$H$25,MATCH($F69,Destinos!$A$9:$A$25,0)))) -> /blog/ | L69: =IF($K69="","",IF(LEFT($K69,1)="/",Destinos!$B$4&$K69,$K69)) -> https://continentalmedia.com.mx/blog/ | M69: =IF($E69="404","",IF($F69="ARTICULO","Artículo "&$G69&" → /blog/<slug>/",INDEX(Destinos!$C$9:$C$25,MATCH($F69,Destinos!$A$9:$A$25,0)))) -> Artículo E-27 → /blog/<slug>/ | N69: =IF(AND($E69="301",$F69="ARTICULO"),$I69,"") -> 46469 | O69: R-BLOG-01 | S69: =IF(AND($E69="404",OR(N($Q69)>0,N($R69)>0)),"REVISAR: tiene clics o enlaces → pasar a 301","") | T69: =IF(OR($E69="Conservar URL",AND($E69="301",OR(N($Q69)>=2,$C69="Páginas"))),"Sí","No") -> No | U69: =IF($E69="Sin cambio","200 · sin cambio",IF($T69="Sí",IF($E69="Conservar URL","200 · misma URL","301"),"404")) -> 404
A70: https://www.continentalmedia.com.mx/2013/11/no-te-pierdas-dentro-del-buen-fin/ | B70: /2013/11/no-te-pierdas-dentro-del-buen-fin/ | C70: Blog | E70: 301 | F70: ARTICULO | G70: G-07 | H70: Estrategia de marketing y contenidos | I70: 46314 | J70: =IF(E70="301",301,IF(E70="404",404,200)) -> 301 | K70: =IF($E70="404","",IF($F70="ARTICULO",IF($I70<=Destinos!$B$5,"[artículo "&$G70&"] /blog/<slug>/",IFERROR(INDEX(Destinos!$H$9:$H$25,MATCH($H70,Destinos!$E$9:$E$25,0)),Destinos!$C$15)),INDEX(Destinos!$H$9:$H$25,MATCH($F70,Destinos!$A$9:$A$25,0)))) -> [artículo G-07] /blog/<slug>/ | L70: =IF($K70="","",IF(LEFT($K70,1)="/",Destinos!$B$4&$K70,$K70)) -> [artículo G-07] /blog/<slug>/ | M70: =IF($E70="404","",IF($F70="ARTICULO","Artículo "&$G70&" → /blog/<slug>/",INDEX(Destinos!$C$9:$C$25,MATCH($F70,Destinos!$A$9:$A$25,0)))) -> Artículo G-07 → /blog/<slug>/ | N70: =IF(AND($E70="301",$F70="ARTICULO"),$I70,"") -> 46314 | O70: R-BLOG-01 | S70: =IF(AND($E70="404",OR(N($Q70)>0,N($R70)>0)),"REVISAR: tiene clics o enlaces → pasar a 301","") | T70: =IF(OR($E70="Conservar URL",AND($E70="301",OR(N($Q70)>=2,$C70="Páginas"))),"Sí","No") -> No | U70: =IF($E70="Sin cambio","200 · sin cambio",IF($T70="Sí",IF($E70="Conservar URL","200 · misma URL","301"),"404")) -> 404
A71: https://www.continentalmedia.com.mx/2013/11/realidad-aumentada-o-ciencia-ficcion/ | B71: /2013/11/realidad-aumentada-o-ciencia-ficcion/ | C71: Blog | E71: 301 | F71: ARTICULO | G71: E-08 | H71: IA aplicada al marketing | I71: 46560 | J71: =IF(E71="301",301,IF(E71="404",404,200)) -> 301 | K71: =IF($E71="404","",IF($F71="ARTICULO",IF($I71<=Destinos!$B$5,"[artículo "&$G71&"] /blog/<slug>/",IFERROR(INDEX(Destinos!$H$9:$H$25,MATCH($H71,Destinos!$E$9:$E$25,0)),Destinos!$C$15)),INDEX(Destinos!$H$9:$H$25,MATCH($F71,Destinos!$A$9:$A$25,0)))) -> /blog/categoria/ia-aplicada-al-marketing/ | L71: =IF($K71="","",IF(LEFT($K71,1)="/",Destinos!$B$4&$K71,$K71)) -> https://continentalmedia.com.mx/blog/categoria/ia-aplicada-al-marketing/ | M71: =IF($E71="404","",IF($F71="ARTICULO","Artículo "&$G71&" → /blog/<slug>/",INDEX(Destinos!$C$9:$C$25,MATCH($F71,Destinos!$A$9:$A$25,0)))) -> Artículo E-08 → /blog/<slug>/ | N71: =IF(AND($E71="301",$F71="ARTICULO"),$I71,"") -> 46560 | O71: R-BLOG-01 | S71: =IF(AND($E71="404",OR(N($Q71)>0,N($R71)>0)),"REVISAR: tiene clics o enlaces → pasar a 301","") | T71: =IF(OR($E71="Conservar URL",AND($E71="301",OR(N($Q71)>=2,$C71="Páginas"))),"Sí","No") -> No | U71: =IF($E71="Sin cambio","200 · sin cambio",IF($T71="Sí",IF($E71="Conservar URL","200 · misma URL","301"),"404")) -> 404
A72: https://www.continentalmedia.com.mx/2013/12/cuales-seran-las-tendencias-de-marketing-2014/ | B72: /2013/12/cuales-seran-las-tendencias-de-marketing-2014/ | C72: Blog | E72: 301 | F72: ARTICULO | G72: E-09 | H72: Estrategia de marketing y contenidos | I72: 46314 | J72: =IF(E72="301",301,IF(E72="404",404,200)) -> 301 | K72: =IF($E72="404","",IF($F72="ARTICULO",IF($I72<=Destinos!$B$5,"[artículo "&$G72&"] /blog/<slug>/",IFERROR(INDEX(Destinos!$H$9:$H$25,MATCH($H72,Destinos!$E$9:$E$25,0)),Destinos!$C$15)),INDEX(Destinos!$H$9:$H$25,MATCH($F72,Destinos!$A$9:$A$25,0)))) -> [artículo E-09] /blog/<slug>/ | L72: =IF($K72="","",IF(LEFT($K72,1)="/",Destinos!$B$4&$K72,$K72)) -> [artículo E-09] /blog/<slug>/ | M72: =IF($E72="404","",IF($F72="ARTICULO","Artículo "&$G72&" → /blog/<slug>/",INDEX(Destinos!$C$9:$C$25,MATCH($F72,Destinos!$A$9:$A$25,0)))) -> Artículo E-09 → /blog/<slug>/ | N72: =IF(AND($E72="301",$F72="ARTICULO"),$I72,"") -> 46314 | O72: R-BLOG-01 | S72: =IF(AND($E72="404",OR(N($Q72)>0,N($R72)>0)),"REVISAR: tiene clics o enlaces → pasar a 301","") | T72: =IF(OR($E72="Conservar URL",AND($E72="301",OR(N($Q72)>=2,$C72="Páginas"))),"Sí","No") -> No | U72: =IF($E72="Sin cambio","200 · sin cambio",IF($T72="Sí",IF($E72="Conservar URL","200 · misma URL","301"),"404")) -> 404
A73: https://www.continentalmedia.com.mx/2013/12/las-campanas-mexicanas-mas-premiadas-de-2013/ | B73: /2013/12/las-campanas-mexicanas-mas-premiadas-de-2013/ | C73: Blog | E73: 301 | F73: BLOG | J73: =IF(E73="301",301,IF(E73="404",404,200)) -> 301 | K73: =IF($E73="404","",IF($F73="ARTICULO",IF($I73<=Destinos!$B$5,"[artículo "&$G73&"] /blog/<slug>/",IFERROR(INDEX(Destinos!$H$9:$H$25,MATCH($H73,Destinos!$E$9:$E$25,0)),Destinos!$C$15)),INDEX(Destinos!$H$9:$H$25,MATCH($F73,Destinos!$A$9:$A$25,0)))) -> /blog/ | L73: =IF($K73="","",IF(LEFT($K73,1)="/",Destinos!$B$4&$K73,$K73)) -> https://continentalmedia.com.mx/blog/ | M73: =IF($E73="404","",IF($F73="ARTICULO","Artículo "&$G73&" → /blog/<slug>/",INDEX(Destinos!$C$9:$C$25,MATCH($F73,Destinos!$A$9:$A$25,0)))) -> /blog/ | N73: =IF(AND($E73="301",$F73="ARTICULO"),$I73,"") | O73: R-LISTA-02 | P73: Descartado en el backlog pero con clics (2 a 7 en 16 meses); decisión: 301 al índice del blog. | Q73: 2 | S73: =IF(AND($E73="404",OR(N($Q73)>0,N($R73)>0)),"REVISAR: tiene clics o enlaces → pasar a 301","") | T73: =IF(OR($E73="Conservar URL",AND($E73="301",OR(N($Q73)>=2,$C73="Páginas"))),"Sí","No") -> Sí | U73: =IF($E73="Sin cambio","200 · sin cambio",IF($T73="Sí",IF($E73="Conservar URL","200 · misma URL","301"),"404")) -> 301
A74: https://www.continentalmedia.com.mx/2013/12/publicidad-con-aroma-navideno/ | B74: /2013/12/publicidad-con-aroma-navideno/ | C74: Blog | E74: 301 | F74: ARTICULO | G74: G-07 | H74: Estrategia de marketing y contenidos | I74: 46314 | J74: =IF(E74="301",301,IF(E74="404",404,200)) -> 301 | K74: =IF($E74="404","",IF($F74="ARTICULO",IF($I74<=Destinos!$B$5,"[artículo "&$G74&"] /blog/<slug>/",IFERROR(INDEX(Destinos!$H$9:$H$25,MATCH($H74,Destinos!$E$9:$E$25,0)),Destinos!$C$15)),INDEX(Destinos!$H$9:$H$25,MATCH($F74,Destinos!$A$9:$A$25,0)))) -> [artículo G-07] /blog/<slug>/ | L74: =IF($K74="","",IF(LEFT($K74,1)="/",Destinos!$B$4&$K74,$K74)) -> [artículo G-07] /blog/<slug>/ | M74: =IF($E74="404","",IF($F74="ARTICULO","Artículo "&$G74&" → /blog/<slug>/",INDEX(Destinos!$C$9:$C$25,MATCH($F74,Destinos!$A$9:$A$25,0)))) -> Artículo G-07 → /blog/<slug>/ | N74: =IF(AND($E74="301",$F74="ARTICULO"),$I74,"") -> 46314 | O74: R-BLOG-01 | S74: =IF(AND($E74="404",OR(N($Q74)>0,N($R74)>0)),"REVISAR: tiene clics o enlaces → pasar a 301","") | T74: =IF(OR($E74="Conservar URL",AND($E74="301",OR(N($Q74)>=2,$C74="Páginas"))),"Sí","No") -> No | U74: =IF($E74="Sin cambio","200 · sin cambio",IF($T74="Sí",IF($E74="Conservar URL","200 · misma URL","301"),"404")) -> 404
A75: https://www.continentalmedia.com.mx/2014/01/branding-para-pymes/ | B75: /2014/01/branding-para-pymes/ | C75: Blog | E75: 404 | F75: — | J75: =IF(E75="301",301,IF(E75="404",404,200)) -> 404 | K75: =IF($E75="404","",IF($F75="ARTICULO",IF($I75<=Destinos!$B$5,"[artículo "&$G75&"] /blog/<slug>/",IFERROR(INDEX(Destinos!$H$9:$H$25,MATCH($H75,Destinos!$E$9:$E$25,0)),Destinos!$C$15)),INDEX(Destinos!$H$9:$H$25,MATCH($F75,Destinos!$A$9:$A$25,0)))) | L75: =IF($K75="","",IF(LEFT($K75,1)="/",Destinos!$B$4&$K75,$K75)) | M75: =IF($E75="404","",IF($F75="ARTICULO","Artículo "&$G75&" → /blog/<slug>/",INDEX(Destinos!$C$9:$C$25,MATCH($F75,Destinos!$A$9:$A$25,0)))) | N75: =IF(AND($E75="301",$F75="ARTICULO"),$I75,"") | O75: R-BLOG-02 | P75: Sin valor SEO actual; sin tema equivalente | S75: =IF(AND($E75="404",OR(N($Q75)>0,N($R75)>0)),"REVISAR: tiene clics o enlaces → pasar a 301","") | T75: =IF(OR($E75="Conservar URL",AND($E75="301",OR(N($Q75)>=2,$C75="Páginas"))),"Sí","No") -> No | U75: =IF($E75="Sin cambio","200 · sin cambio",IF($T75="Sí",IF($E75="Conservar URL","200 · misma URL","301"),"404")) -> 404
A76: https://www.continentalmedia.com.mx/2014/01/celebridades-marcas-y-escandalos/ | B76: /2014/01/celebridades-marcas-y-escandalos/ | C76: Blog | E76: 301 | F76: ARTICULO | G76: E-13 | H76: Redes sociales y comunidad | I76: 46392 | J76: =IF(E76="301",301,IF(E76="404",404,200)) -> 301 | K76: =IF($E76="404","",IF($F76="ARTICULO",IF($I76<=Destinos!$B$5,"[artículo "&$G76&"] /blog/<slug>/",IFERROR(INDEX(Destinos!$H$9:$H$25,MATCH($H76,Destinos!$E$9:$E$25,0)),Destinos!$C$15)),INDEX(Destinos!$H$9:$H$25,MATCH($F76,Destinos!$A$9:$A$25,0)))) -> /blog/categoria/redes-sociales/ | L76: =IF($K76="","",IF(LEFT($K76,1)="/",Destinos!$B$4&$K76,$K76)) -> https://continentalmedia.com.mx/blog/categoria/redes-sociales/ | M76: =IF($E76="404","",IF($F76="ARTICULO","Artículo "&$G76&" → /blog/<slug>/",INDEX(Destinos!$C$9:$C$25,MATCH($F76,Destinos!$A$9:$A$25,0)))) -> Artículo E-13 → /blog/<slug>/ | N76: =IF(AND($E76="301",$F76="ARTICULO"),$I76,"") -> 46392 | O76: R-BLOG-01 | S76: =IF(AND($E76="404",OR(N($Q76)>0,N($R76)>0)),"REVISAR: tiene clics o enlaces → pasar a 301","") | T76: =IF(OR($E76="Conservar URL",AND($E76="301",OR(N($Q76)>=2,$C76="Páginas"))),"Sí","No") -> No | U76: =IF($E76="Sin cambio","200 · sin cambio",IF($T76="Sí",IF($E76="Conservar URL","200 · misma URL","301"),"404")) -> 404
A77: https://www.continentalmedia.com.mx/2014/01/celebridades-y-marcas-se-llevan-bien/ | B77: /2014/01/celebridades-y-marcas-se-llevan-bien/ | C77: Blog | E77: 301 | F77: ARTICULO | G77: E-13 | H77: Redes sociales y comunidad | I77: 46392 | J77: =IF(E77="301",301,IF(E77="404",404,200)) -> 301 | K77: =IF($E77="404","",IF($F77="ARTICULO",IF($I77<=Destinos!$B$5,"[artículo "&$G77&"] /blog/<slug>/",IFERROR(INDEX(Destinos!$H$9:$H$25,MATCH($H77,Destinos!$E$9:$E$25,0)),Destinos!$C$15)),INDEX(Destinos!$H$9:$H$25,MATCH($F77,Destinos!$A$9:$A$25,0)))) -> /blog/categoria/redes-sociales/ | L77: =IF($K77="","",IF(LEFT($K77,1)="/",Destinos!$B$4&$K77,$K77)) -> https://continentalmedia.com.mx/blog/categoria/redes-sociales/ | M77: =IF($E77="404","",IF($F77="ARTICULO","Artículo "&$G77&" → /blog/<slug>/",INDEX(Destinos!$C$9:$C$25,MATCH($F77,Destinos!$A$9:$A$25,0)))) -> Artículo E-13 → /blog/<slug>/ | N77: =IF(AND($E77="301",$F77="ARTICULO"),$I77,"") -> 46392 | O77: R-BLOG-01 | S77: =IF(AND($E77="404",OR(N($Q77)>0,N($R77)>0)),"REVISAR: tiene clics o enlaces → pasar a 301","") | T77: =IF(OR($E77="Conservar URL",AND($E77="301",OR(N($Q77)>=2,$C77="Páginas"))),"Sí","No") -> No | U77: =IF($E77="Sin cambio","200 · sin cambio",IF($T77="Sí",IF($E77="Conservar URL","200 · misma URL","301"),"404")) -> 404
A78: https://www.continentalmedia.com.mx/2014/01/publicidad-discriminatoria/ | B78: /2014/01/publicidad-discriminatoria/ | C78: Blog | E78: 301 | F78: ARTICULO | G78: E-35 | H78: Relaciones públicas y comunicación | I78: 46588 | J78: =IF(E78="301",301,IF(E78="404",404,200)) -> 301 | K78: =IF($E78="404","",IF($F78="ARTICULO",IF($I78<=Destinos!$B$5,"[artículo "&$G78&"] /blog/<slug>/",IFERROR(INDEX(Destinos!$H$9:$H$25,MATCH($H78,Destinos!$E$9:$E$25,0)),Destinos!$C$15)),INDEX(Destinos!$H$9:$H$25,MATCH($F78,Destinos!$A$9:$A$25,0)))) -> /blog/ | L78: =IF($K78="","",IF(LEFT($K78,1)="/",Destinos!$B$4&$K78,$K78)) -> https://continentalmedia.com.mx/blog/ | M78: =IF($E78="404","",IF($F78="ARTICULO","Artículo "&$G78&" → /blog/<slug>/",INDEX(Destinos!$C$9:$C$25,MATCH($F78,Destinos!$A$9:$A$25,0)))) -> Artículo E-35 → /blog/<slug>/ | N78: =IF(AND($E78="301",$F78="ARTICULO"),$I78,"") -> 46588 | O78: R-BLOG-01 | S78: =IF(AND($E78="404",OR(N($Q78)>0,N($R78)>0)),"REVISAR: tiene clics o enlaces → pasar a 301","") | T78: =IF(OR($E78="Conservar URL",AND($E78="301",OR(N($Q78)>=2,$C78="Páginas"))),"Sí","No") -> No | U78: =IF($E78="Sin cambio","200 · sin cambio",IF($T78="Sí",IF($E78="Conservar URL","200 · misma URL","301"),"404")) -> 404
A79: https://www.continentalmedia.com.mx/2014/02/el-top-5-mejores-agencias-de-publicidad-en-mexico/ | B79: /2014/02/el-top-5-mejores-agencias-de-publicidad-en-mexico/ | C79: Blog | E79: 404 | F79: — | J79: =IF(E79="301",301,IF(E79="404",404,200)) -> 404 | K79: =IF($E79="404","",IF($F79="ARTICULO",IF($I79<=Destinos!$B$5,"[artículo "&$G79&"] /blog/<slug>/",IFERROR(INDEX(Destinos!$H$9:$H$25,MATCH($H79,Destinos!$E$9:$E$25,0)),Destinos!$C$15)),INDEX(Destinos!$H$9:$H$25,MATCH($F79,Destinos!$A$9:$A$25,0)))) | L79: =IF($K79="","",IF(LEFT($K79,1)="/",Destinos!$B$4&$K79,$K79)) | M79: =IF($E79="404","",IF($F79="ARTICULO","Artículo "&$G79&" → /blog/<slug>/",INDEX(Destinos!$C$9:$C$25,MATCH($F79,Destinos!$A$9:$A$25,0)))) | N79: =IF(AND($E79="301",$F79="ARTICULO"),$I79,"") | O79: R-BLOG-02 | P79: Sin valor SEO actual; sin tema equivalente | S79: =IF(AND($E79="404",OR(N($Q79)>0,N($R79)>0)),"REVISAR: tiene clics o enlaces → pasar a 301","") | T79: =IF(OR($E79="Conservar URL",AND($E79="301",OR(N($Q79)>=2,$C79="Páginas"))),"Sí","No") -> No | U79: =IF($E79="Sin cambio","200 · sin cambio",IF($T79="Sí",IF($E79="Conservar URL","200 · misma URL","301"),"404")) -> 404
A80: https://www.continentalmedia.com.mx/2014/02/estudio-de-mercado-la-clave-del-exito-de-tu-producto/ | B80: /2014/02/estudio-de-mercado-la-clave-del-exito-de-tu-producto/ | C80: Blog | E80: 301 | F80: ARTICULO | G80: G-08 | H80: Estrategia de marketing y contenidos | I80: 46478 | J80: =IF(E80="301",301,IF(E80="404",404,200)) -> 301 | K80: =IF($E80="404","",IF($F80="ARTICULO",IF($I80<=Destinos!$B$5,"[artículo "&$G80&"] /blog/<slug>/",IFERROR(INDEX(Destinos!$H$9:$H$25,MATCH($H80,Destinos!$E$9:$E$25,0)),Destinos!$C$15)),INDEX(Destinos!$H$9:$H$25,MATCH($F80,Destinos!$A$9:$A$25,0)))) -> /blog/categoria/estrategia-de-marketing/ | L80: =IF($K80="","",IF(LEFT($K80,1)="/",Destinos!$B$4&$K80,$K80)) -> https://continentalmedia.com.mx/blog/categoria/estrategia-de-marketing/ | M80: =IF($E80="404","",IF($F80="ARTICULO","Artículo "&$G80&" → /blog/<slug>/",INDEX(Destinos!$C$9:$C$25,MATCH($F80,Destinos!$A$9:$A$25,0)))) -> Artículo G-08 → /blog/<slug>/ | N80: =IF(AND($E80="301",$F80="ARTICULO"),$I80,"") -> 46478 | O80: R-BLOG-01 | S80: =IF(AND($E80="404",OR(N($Q80)>0,N($R80)>0)),"REVISAR: tiene clics o enlaces → pasar a 301","") | T80: =IF(OR($E80="Conservar URL",AND($E80="301",OR(N($Q80)>=2,$C80="Páginas"))),"Sí","No") -> No | U80: =IF($E80="Sin cambio","200 · sin cambio",IF($T80="Sí",IF($E80="Conservar URL","200 · misma URL","301"),"404")) -> 404
A81: https://www.continentalmedia.com.mx/2014/02/pioneros-de-la-publicidad-en-mexico/ | B81: /2014/02/pioneros-de-la-publicidad-en-mexico/ | C81: Blog | E81: Conservar URL | F81: MISMA | J81: 200 | K81: =B81 -> /2014/02/pioneros-de-la-publicidad-en-mexico/ | L81: =Destinos!$B$4&B81 -> https://continentalmedia.com.mx/2014/02/pioneros-de-la-publicidad-en-mexico/ | M81: Misma URL: se republica actualizado en el blog nuevo | O81: R-LISTA-01 | P81: Junto con el otro post conservado suma el 34% de los clics del sitio viejo; se conserva la ruta heredada (/AAAA/MM/slug/) en el blog nuevo. | Q81: 48 | S81: =IF(AND($E81="404",OR(N($Q81)>0,N($R81)>0)),"REVISAR: tiene clics o enlaces → pasar a 301","") | T81: =IF(OR($E81="Conservar URL",AND($E81="301",OR(N($Q81)>=2,$C81="Páginas"))),"Sí","No") -> Sí | U81: =IF($E81="Sin cambio","200 · sin cambio",IF($T81="Sí",IF($E81="Conservar URL","200 · misma URL","301"),"404")) -> 200 · misma URL
A82: https://www.continentalmedia.com.mx/2014/02/por-que-algunos-productos-fracasaron-en-el-mercado/ | B82: /2014/02/por-que-algunos-productos-fracasaron-en-el-mercado/ | C82: Blog | E82: 301 | F82: ARTICULO | G82: G-08 | H82: Estrategia de marketing y contenidos | I82: 46478 | J82: =IF(E82="301",301,IF(E82="404",404,200)) -> 301 | K82: =IF($E82="404","",IF($F82="ARTICULO",IF($I82<=Destinos!$B$5,"[artículo "&$G82&"] /blog/<slug>/",IFERROR(INDEX(Destinos!$H$9:$H$25,MATCH($H82,Destinos!$E$9:$E$25,0)),Destinos!$C$15)),INDEX(Destinos!$H$9:$H$25,MATCH($F82,Destinos!$A$9:$A$25,0)))) -> /blog/categoria/estrategia-de-marketing/ | L82: =IF($K82="","",IF(LEFT($K82,1)="/",Destinos!$B$4&$K82,$K82)) -> https://continentalmedia.com.mx/blog/categoria/estrategia-de-marketing/ | M82: =IF($E82="404","",IF($F82="ARTICULO","Artículo "&$G82&" → /blog/<slug>/",INDEX(Destinos!$C$9:$C$25,MATCH($F82,Destinos!$A$9:$A$25,0)))) -> Artículo G-08 → /blog/<slug>/ | N82: =IF(AND($E82="301",$F82="ARTICULO"),$I82,"") -> 46478 | O82: R-BLOG-01 | S82: =IF(AND($E82="404",OR(N($Q82)>0,N($R82)>0)),"REVISAR: tiene clics o enlaces → pasar a 301","") | T82: =IF(OR($E82="Conservar URL",AND($E82="301",OR(N($Q82)>=2,$C82="Páginas"))),"Sí","No") -> No | U82: =IF($E82="Sin cambio","200 · sin cambio",IF($T82="Sí",IF($E82="Conservar URL","200 · misma URL","301"),"404")) -> 404
A83: https://www.continentalmedia.com.mx/2014/03/las-5-mejores-marcas-en-redes-sociales-en-mexico/ | B83: /2014/03/las-5-mejores-marcas-en-redes-sociales-en-mexico/ | C83: Blog | E83: 301 | F83: ARTICULO | G83: E-12 | H83: Redes sociales y comunidad | I83: 46322 | J83: =IF(E83="301",301,IF(E83="404",404,200)) -> 301 | K83: =IF($E83="404","",IF($F83="ARTICULO",IF($I83<=Destinos!$B$5,"[artículo "&$G83&"] /blog/<slug>/",IFERROR(INDEX(Destinos!$H$9:$H$25,MATCH($H83,Destinos!$E$9:$E$25,0)),Destinos!$C$15)),INDEX(Destinos!$H$9:$H$25,MATCH($F83,Destinos!$A$9:$A$25,0)))) -> /blog/categoria/redes-sociales/ | L83: =IF($K83="","",IF(LEFT($K83,1)="/",Destinos!$B$4&$K83,$K83)) -> https://continentalmedia.com.mx/blog/categoria/redes-sociales/ | M83: =IF($E83="404","",IF($F83="ARTICULO","Artículo "&$G83&" → /blog/<slug>/",INDEX(Destinos!$C$9:$C$25,MATCH($F83,Destinos!$A$9:$A$25,0)))) -> Artículo E-12 → /blog/<slug>/ | N83: =IF(AND($E83="301",$F83="ARTICULO"),$I83,"") -> 46322 | O83: R-BLOG-01 | S83: =IF(AND($E83="404",OR(N($Q83)>0,N($R83)>0)),"REVISAR: tiene clics o enlaces → pasar a 301","") | T83: =IF(OR($E83="Conservar URL",AND($E83="301",OR(N($Q83)>=2,$C83="Páginas"))),"Sí","No") -> No | U83: =IF($E83="Sin cambio","200 · sin cambio",IF($T83="Sí",IF($E83="Conservar URL","200 · misma URL","301"),"404")) -> 404
A84: https://www.continentalmedia.com.mx/2014/03/por-que-es-polemica-la-publicidad-subliminal/ | B84: /2014/03/por-que-es-polemica-la-publicidad-subliminal/ | C84: Blog | E84: 301 | F84: ARTICULO | G84: E-35 | H84: Relaciones públicas y comunicación | I84: 46588 | J84: =IF(E84="301",301,IF(E84="404",404,200)) -> 301 | K84: =IF($E84="404","",IF($F84="ARTICULO",IF($I84<=Destinos!$B$5,"[artículo "&$G84&"] /blog/<slug>/",IFERROR(INDEX(Destinos!$H$9:$H$25,MATCH($H84,Destinos!$E$9:$E$25,0)),Destinos!$C$15)),INDEX(Destinos!$H$9:$H$25,MATCH($F84,Destinos!$A$9:$A$25,0)))) -> /blog/ | L84: =IF($K84="","",IF(LEFT($K84,1)="/",Destinos!$B$4&$K84,$K84)) -> https://continentalmedia.com.mx/blog/ | M84: =IF($E84="404","",IF($F84="ARTICULO","Artículo "&$G84&" → /blog/<slug>/",INDEX(Destinos!$C$9:$C$25,MATCH($F84,Destinos!$A$9:$A$25,0)))) -> Artículo E-35 → /blog/<slug>/ | N84: =IF(AND($E84="301",$F84="ARTICULO"),$I84,"") -> 46588 | O84: R-BLOG-01 | S84: =IF(AND($E84="404",OR(N($Q84)>0,N($R84)>0)),"REVISAR: tiene clics o enlaces → pasar a 301","") | T84: =IF(OR($E84="Conservar URL",AND($E84="301",OR(N($Q84)>=2,$C84="Páginas"))),"Sí","No") -> No | U84: =IF($E84="Sin cambio","200 · sin cambio",IF($T84="Sí",IF($E84="Conservar URL","200 · misma URL","301"),"404")) -> 404
A85: https://www.continentalmedia.com.mx/2014/03/que-es-el-marketing-de-influencia/ | B85: /2014/03/que-es-el-marketing-de-influencia/ | C85: Blog | E85: 301 | F85: ARTICULO | G85: E-13 | H85: Redes sociales y comunidad | I85: 46392 | J85: =IF(E85="301",301,IF(E85="404",404,200)) -> 301 | K85: =IF($E85="404","",IF($F85="ARTICULO",IF($I85<=Destinos!$B$5,"[artículo "&$G85&"] /blog/<slug>/",IFERROR(INDEX(Destinos!$H$9:$H$25,MATCH($H85,Destinos!$E$9:$E$25,0)),Destinos!$C$15)),INDEX(Destinos!$H$9:$H$25,MATCH($F85,Destinos!$A$9:$A$25,0)))) -> /blog/categoria/redes-sociales/ | L85: =IF($K85="","",IF(LEFT($K85,1)="/",Destinos!$B$4&$K85,$K85)) -> https://continentalmedia.com.mx/blog/categoria/redes-sociales/ | M85: =IF($E85="404","",IF($F85="ARTICULO","Artículo "&$G85&" → /blog/<slug>/",INDEX(Destinos!$C$9:$C$25,MATCH($F85,Destinos!$A$9:$A$25,0)))) -> Artículo E-13 → /blog/<slug>/ | N85: =IF(AND($E85="301",$F85="ARTICULO"),$I85,"") -> 46392 | O85: R-BLOG-01 | S85: =IF(AND($E85="404",OR(N($Q85)>0,N($R85)>0)),"REVISAR: tiene clics o enlaces → pasar a 301","") | T85: =IF(OR($E85="Conservar URL",AND($E85="301",OR(N($Q85)>=2,$C85="Páginas"))),"Sí","No") -> No | U85: =IF($E85="Sin cambio","200 · sin cambio",IF($T85="Sí",IF($E85="Conservar URL","200 · misma URL","301"),"404")) -> 404
A86: https://www.continentalmedia.com.mx/2014/04/10-consejos-para-el-correcto-uso-de-tu-celular/ | B86: /2014/04/10-consejos-para-el-correcto-uso-de-tu-celular/ | C86: Blog | E86: 404 | F86: — | J86: =IF(E86="301",301,IF(E86="404",404,200)) -> 404 | K86: =IF($E86="404","",IF($F86="ARTICULO",IF($I86<=Destinos!$B$5,"[artículo "&$G86&"] /blog/<slug>/",IFERROR(INDEX(Destinos!$H$9:$H$25,MATCH($H86,Destinos!$E$9:$E$25,0)),Destinos!$C$15)),INDEX(Destinos!$H$9:$H$25,MATCH($F86,Destinos!$A$9:$A$25,0)))) | L86: =IF($K86="","",IF(LEFT($K86,1)="/",Destinos!$B$4&$K86,$K86)) | M86: =IF($E86="404","",IF($F86="ARTICULO","Artículo "&$G86&" → /blog/<slug>/",INDEX(Destinos!$C$9:$C$25,MATCH($F86,Destinos!$A$9:$A$25,0)))) | N86: =IF(AND($E86="301",$F86="ARTICULO"),$I86,"") | O86: R-BLOG-02 | P86: Sin valor SEO actual; sin tema equivalente | S86: =IF(AND($E86="404",OR(N($Q86)>0,N($R86)>0)),"REVISAR: tiene clics o enlaces → pasar a 301","") | T86: =IF(OR($E86="Conservar URL",AND($E86="301",OR(N($Q86)>=2,$C86="Páginas"))),"Sí","No") -> No | U86: =IF($E86="Sin cambio","200 · sin cambio",IF($T86="Sí",IF($E86="Conservar URL","200 · misma URL","301"),"404")) -> 404
A87: https://www.continentalmedia.com.mx/2014/04/adaptate-llego-el-diseno-responsivo/ | B87: /2014/04/adaptate-llego-el-diseno-responsivo/ | C87: Blog | E87: 301 | F87: ARTICULO | G87: E-39 | H87: Web, SEO y publicidad digital | I87: 46525 | J87: =IF(E87="301",301,IF(E87="404",404,200)) -> 301 | K87: =IF($E87="404","",IF($F87="ARTICULO",IF($I87<=Destinos!$B$5,"[artículo "&$G87&"] /blog/<slug>/",IFERROR(INDEX(Destinos!$H$9:$H$25,MATCH($H87,Destinos!$E$9:$E$25,0)),Destinos!$C$15)),INDEX(Destinos!$H$9:$H$25,MATCH($F87,Destinos!$A$9:$A$25,0)))) -> /blog/ | L87: =IF($K87="","",IF(LEFT($K87,1)="/",Destinos!$B$4&$K87,$K87)) -> https://continentalmedia.com.mx/blog/ | M87: =IF($E87="404","",IF($F87="ARTICULO","Artículo "&$G87&" → /blog/<slug>/",INDEX(Destinos!$C$9:$C$25,MATCH($F87,Destinos!$A$9:$A$25,0)))) -> Artículo E-39 → /blog/<slug>/ | N87: =IF(AND($E87="301",$F87="ARTICULO"),$I87,"") -> 46525 | O87: R-BLOG-01 | S87: =IF(AND($E87="404",OR(N($Q87)>0,N($R87)>0)),"REVISAR: tiene clics o enlaces → pasar a 301","") | T87: =IF(OR($E87="Conservar URL",AND($E87="301",OR(N($Q87)>=2,$C87="Páginas"))),"Sí","No") -> No | U87: =IF($E87="Sin cambio","200 · sin cambio",IF($T87="Sí",IF($E87="Conservar URL","200 · misma URL","301"),"404")) -> 404
A88: https://www.continentalmedia.com.mx/2014/04/los-6-colores-que-mas-atraen-en-publicidad/ | B88: /2014/04/los-6-colores-que-mas-atraen-en-publicidad/ | C88: Blog | E88: 301 | F88: ARTICULO | G88: E-20 | H88: Branding, diseño y creatividad | I88: 46427 | J88: =IF(E88="301",301,IF(E88="404",404,200)) -> 301 | K88: =IF($E88="404","",IF($F88="ARTICULO",IF($I88<=Destinos!$B$5,"[artículo "&$G88&"] /blog/<slug>/",IFERROR(INDEX(Destinos!$H$9:$H$25,MATCH($H88,Destinos!$E$9:$E$25,0)),Destinos!$C$15)),INDEX(Destinos!$H$9:$H$25,MATCH($F88,Destinos!$A$9:$A$25,0)))) -> /blog/ | L88: =IF($K88="","",IF(LEFT($K88,1)="/",Destinos!$B$4&$K88,$K88)) -> https://continentalmedia.com.mx/blog/ | M88: =IF($E88="404","",IF($F88="ARTICULO","Artículo "&$G88&" → /blog/<slug>/",INDEX(Destinos!$C$9:$C$25,MATCH($F88,Destinos!$A$9:$A$25,0)))) -> Artículo E-20 → /blog/<slug>/ | N88: =IF(AND($E88="301",$F88="ARTICULO"),$I88,"") -> 46427 | O88: R-BLOG-01 | Q88: 1 | S88: =IF(AND($E88="404",OR(N($Q88)>0,N($R88)>0)),"REVISAR: tiene clics o enlaces → pasar a 301","") | T88: =IF(OR($E88="Conservar URL",AND($E88="301",OR(N($Q88)>=2,$C88="Páginas"))),"Sí","No") -> No | U88: =IF($E88="Sin cambio","200 · sin cambio",IF($T88="Sí",IF($E88="Conservar URL","200 · misma URL","301"),"404")) -> 404
A89: https://www.continentalmedia.com.mx/2014/04/marketing-de-peluche/ | B89: /2014/04/marketing-de-peluche/ | C89: Blog | E89: 404 | F89: — | J89: =IF(E89="301",301,IF(E89="404",404,200)) -> 404 | K89: =IF($E89="404","",IF($F89="ARTICULO",IF($I89<=Destinos!$B$5,"[artículo "&$G89&"] /blog/<slug>/",IFERROR(INDEX(Destinos!$H$9:$H$25,MATCH($H89,Destinos!$E$9:$E$25,0)),Destinos!$C$15)),INDEX(Destinos!$H$9:$H$25,MATCH($F89,Destinos!$A$9:$A$25,0)))) | L89: =IF($K89="","",IF(LEFT($K89,1)="/",Destinos!$B$4&$K89,$K89)) | M89: =IF($E89="404","",IF($F89="ARTICULO","Artículo "&$G89&" → /blog/<slug>/",INDEX(Destinos!$C$9:$C$25,MATCH($F89,Destinos!$A$9:$A$25,0)))) | N89: =IF(AND($E89="301",$F89="ARTICULO"),$I89,"") | O89: R-BLOG-02 | P89: Sin valor SEO actual; sin tema equivalente | Q89: 1 | S89: =IF(AND($E89="404",OR(N($Q89)>0,N($R89)>0)),"REVISAR: tiene clics o enlaces → pasar a 301","") -> REVISAR: tiene clics o enlaces → pasar a 301 | T89: =IF(OR($E89="Conservar URL",AND($E89="301",OR(N($Q89)>=2,$C89="Páginas"))),"Sí","No") -> No | U89: =IF($E89="Sin cambio","200 · sin cambio",IF($T89="Sí",IF($E89="Conservar URL","200 · misma URL","301"),"404")) -> 404
A90: https://www.continentalmedia.com.mx/2014/04/no-ahuyentes-a-tus-clientes/ | B90: /2014/04/no-ahuyentes-a-tus-clientes/ | C90: Blog | E90: 301 | F90: ARTICULO | G90: G-14 | H90: Redes sociales y comunidad | I90: 46499 | J90: =IF(E90="301",301,IF(E90="404",404,200)) -> 301 | K90: =IF($E90="404","",IF($F90="ARTICULO",IF($I90<=Destinos!$B$5,"[artículo "&$G90&"] /blog/<slug>/",IFERROR(INDEX(Destinos!$H$9:$H$25,MATCH($H90,Destinos!$E$9:$E$25,0)),Destinos!$C$15)),INDEX(Destinos!$H$9:$H$25,MATCH($F90,Destinos!$A$9:$A$25,0)))) -> /blog/categoria/redes-sociales/ | L90: =IF($K90="","",IF(LEFT($K90,1)="/",Destinos!$B$4&$K90,$K90)) -> https://continentalmedia.com.mx/blog/categoria/redes-sociales/ | M90: =IF($E90="404","",IF($F90="ARTICULO","Artículo "&$G90&" → /blog/<slug>/",INDEX(Destinos!$C$9:$C$25,MATCH($F90,Destinos!$A$9:$A$25,0)))) -> Artículo G-14 → /blog/<slug>/ | N90: =IF(AND($E90="301",$F90="ARTICULO"),$I90,"") -> 46499 | O90: R-BLOG-01 | S90: =IF(AND($E90="404",OR(N($Q90)>0,N($R90)>0)),"REVISAR: tiene clics o enlaces → pasar a 301","") | T90: =IF(OR($E90="Conservar URL",AND($E90="301",OR(N($Q90)>=2,$C90="Páginas"))),"Sí","No") -> No | U90: =IF($E90="Sin cambio","200 · sin cambio",IF($T90="Sí",IF($E90="Conservar URL","200 · misma URL","301"),"404")) -> 404
A91: https://www.continentalmedia.com.mx/2014/05/10-errores-al-hablar-en-publico/ | B91: /2014/05/10-errores-al-hablar-en-publico/ | C91: Blog | E91: 301 | F91: ARTICULO | G91: G-34 | H91: Relaciones públicas y comunicación | I91: 46555 | J91: =IF(E91="301",301,IF(E91="404",404,200)) -> 301 | K91: =IF($E91="404","",IF($F91="ARTICULO",IF($I91<=Destinos!$B$5,"[artículo "&$G91&"] /blog/<slug>/",IFERROR(INDEX(Destinos!$H$9:$H$25,MATCH($H91,Destinos!$E$9:$E$25,0)),Destinos!$C$15)),INDEX(Destinos!$H$9:$H$25,MATCH($F91,Destinos!$A$9:$A$25,0)))) -> /blog/ | L91: =IF($K91="","",IF(LEFT($K91,1)="/",Destinos!$B$4&$K91,$K91)) -> https://continentalmedia.com.mx/blog/ | M91: =IF($E91="404","",IF($F91="ARTICULO","Artículo "&$G91&" → /blog/<slug>/",INDEX(Destinos!$C$9:$C$25,MATCH($F91,Destinos!$A$9:$A$25,0)))) -> Artículo G-34 → /blog/<slug>/ | N91: =IF(AND($E91="301",$F91="ARTICULO"),$I91,"") -> 46555 | O91: R-BLOG-01 | S91: =IF(AND($E91="404",OR(N($Q91)>0,N($R91)>0)),"REVISAR: tiene clics o enlaces → pasar a 301","") | T91: =IF(OR($E91="Conservar URL",AND($E91="301",OR(N($Q91)>=2,$C91="Páginas"))),"Sí","No") -> No | U91: =IF($E91="Sin cambio","200 · sin cambio",IF($T91="Sí",IF($E91="Conservar URL","200 · misma URL","301"),"404")) -> 404
A92: https://www.continentalmedia.com.mx/2014/05/5-comportamientos-nocivos-en-redes-sociales/ | B92: /2014/05/5-comportamientos-nocivos-en-redes-sociales/ | C92: Blog | E92: 404 | F92: — | J92: =IF(E92="301",301,IF(E92="404",404,200)) -> 404 | K92: =IF($E92="404","",IF($F92="ARTICULO",IF($I92<=Destinos!$B$5,"[artículo "&$G92&"] /blog/<slug>/",IFERROR(INDEX(Destinos!$H$9:$H$25,MATCH($H92,Destinos!$E$9:$E$25,0)),Destinos!$C$15)),INDEX(Destinos!$H$9:$H$25,MATCH($F92,Destinos!$A$9:$A$25,0)))) | L92: =IF($K92="","",IF(LEFT($K92,1)="/",Destinos!$B$4&$K92,$K92)) | M92: =IF($E92="404","",IF($F92="ARTICULO","Artículo "&$G92&" → /blog/<slug>/",INDEX(Destinos!$C$9:$C$25,MATCH($F92,Destinos!$A$9:$A$25,0)))) | N92: =IF(AND($E92="301",$F92="ARTICULO"),$I92,"") | O92: R-BLOG-02 | P92: Sin valor SEO actual; sin tema equivalente | Q92: 1 | S92: =IF(AND($E92="404",OR(N($Q92)>0,N($R92)>0)),"REVISAR: tiene clics o enlaces → pasar a 301","") -> REVISAR: tiene clics o enlaces → pasar a 301 | T92: =IF(OR($E92="Conservar URL",AND($E92="301",OR(N($Q92)>=2,$C92="Páginas"))),"Sí","No") -> No | U92: =IF($E92="Sin cambio","200 · sin cambio",IF($T92="Sí",IF($E92="Conservar URL","200 · misma URL","301"),"404")) -> 404
A93: https://www.continentalmedia.com.mx/2014/05/8-datos-historicos-que-todo-disenador-debe-saber/ | B93: /2014/05/8-datos-historicos-que-todo-disenador-debe-saber/ | C93: Blog | E93: 404 | F93: — | J93: =IF(E93="301",301,IF(E93="404",404,200)) -> 404 | K93: =IF($E93="404","",IF($F93="ARTICULO",IF($I93<=Destinos!$B$5,"[artículo "&$G93&"] /blog/<slug>/",IFERROR(INDEX(Destinos!$H$9:$H$25,MATCH($H93,Destinos!$E$9:$E$25,0)),Destinos!$C$15)),INDEX(Destinos!$H$9:$H$25,MATCH($F93,Destinos!$A$9:$A$25,0)))) | L93: =IF($K93="","",IF(LEFT($K93,1)="/",Destinos!$B$4&$K93,$K93)) | M93: =IF($E93="404","",IF($F93="ARTICULO","Artículo "&$G93&" → /blog/<slug>/",INDEX(Destinos!$C$9:$C$25,MATCH($F93,Destinos!$A$9:$A$25,0)))) | N93: =IF(AND($E93="301",$F93="ARTICULO"),$I93,"") | O93: R-BLOG-02 | P93: Sin valor SEO actual; sin tema equivalente | S93: =IF(AND($E93="404",OR(N($Q93)>0,N($R93)>0)),"REVISAR: tiene clics o enlaces → pasar a 301","") | T93: =IF(OR($E93="Conservar URL",AND($E93="301",OR(N($Q93)>=2,$C93="Páginas"))),"Sí","No") -> No | U93: =IF($E93="Sin cambio","200 · sin cambio",IF($T93="Sí",IF($E93="Conservar URL","200 · misma URL","301"),"404")) -> 404
A94: https://www.continentalmedia.com.mx/2014/05/no-te-exprimas-el-cerebro-5-ejercicios-para-recuperar-la-creatividad/ | B94: /2014/05/no-te-exprimas-el-cerebro-5-ejercicios-para-recuperar-la-creatividad/ | C94: Blog | E94: 301 | F94: ARTICULO | G94: E-33 | H94: Branding, diseño y creatividad | I94: 46504 | J94: =IF(E94="301",301,IF(E94="404",404,200)) -> 301 | K94: =IF($E94="404","",IF($F94="ARTICULO",IF($I94<=Destinos!$B$5,"[artículo "&$G94&"] /blog/<slug>/",IFERROR(INDEX(Destinos!$H$9:$H$25,MATCH($H94,Destinos!$E$9:$E$25,0)),Destinos!$C$15)),INDEX(Destinos!$H$9:$H$25,MATCH($F94,Destinos!$A$9:$A$25,0)))) -> /blog/ | L94: =IF($K94="","",IF(LEFT($K94,1)="/",Destinos!$B$4&$K94,$K94)) -> https://continentalmedia.com.mx/blog/ | M94: =IF($E94="404","",IF($F94="ARTICULO","Artículo "&$G94&" → /blog/<slug>/",INDEX(Destinos!$C$9:$C$25,MATCH($F94,Destinos!$A$9:$A$25,0)))) -> Artículo E-33 → /blog/<slug>/ | N94: =IF(AND($E94="301",$F94="ARTICULO"),$I94,"") -> 46504 | O94: R-BLOG-01 | S94: =IF(AND($E94="404",OR(N($Q94)>0,N($R94)>0)),"REVISAR: tiene clics o enlaces → pasar a 301","") | T94: =IF(OR($E94="Conservar URL",AND($E94="301",OR(N($Q94)>=2,$C94="Páginas"))),"Sí","No") -> No | U94: =IF($E94="Sin cambio","200 · sin cambio",IF($T94="Sí",IF($E94="Conservar URL","200 · misma URL","301"),"404")) -> 404
A95: https://www.continentalmedia.com.mx/2014/05/que-hacer-durante-una-reunion-con-un-cliente/ | B95: /2014/05/que-hacer-durante-una-reunion-con-un-cliente/ | C95: Blog | E95: 301 | F95: ARTICULO | G95: G-34 | H95: Relaciones públicas y comunicación | I95: 46555 | J95: =IF(E95="301",301,IF(E95="404",404,200)) -> 301 | K95: =IF($E95="404","",IF($F95="ARTICULO",IF($I95<=Destinos!$B$5,"[artículo "&$G95&"] /blog/<slug>/",IFERROR(INDEX(Destinos!$H$9:$H$25,MATCH($H95,Destinos!$E$9:$E$25,0)),Destinos!$C$15)),INDEX(Destinos!$H$9:$H$25,MATCH($F95,Destinos!$A$9:$A$25,0)))) -> /blog/ | L95: =IF($K95="","",IF(LEFT($K95,1)="/",Destinos!$B$4&$K95,$K95)) -> https://continentalmedia.com.mx/blog/ | M95: =IF($E95="404","",IF($F95="ARTICULO","Artículo "&$G95&" → /blog/<slug>/",INDEX(Destinos!$C$9:$C$25,MATCH($F95,Destinos!$A$9:$A$25,0)))) -> Artículo G-34 → /blog/<slug>/ | N95: =IF(AND($E95="301",$F95="ARTICULO"),$I95,"") -> 46555 | O95: R-BLOG-01 | S95: =IF(AND($E95="404",OR(N($Q95)>0,N($R95)>0)),"REVISAR: tiene clics o enlaces → pasar a 301","") | T95: =IF(OR($E95="Conservar URL",AND($E95="301",OR(N($Q95)>=2,$C95="Páginas"))),"Sí","No") -> No | U95: =IF($E95="Sin cambio","200 · sin cambio",IF($T95="Sí",IF($E95="Conservar URL","200 · misma URL","301"),"404")) -> 404
A96: https://www.continentalmedia.com.mx/2014/06/comerciales-mundial-redes-sociales/ | B96: /2014/06/comerciales-mundial-redes-sociales/ | C96: Blog | E96: 404 | F96: — | J96: =IF(E96="301",301,IF(E96="404",404,200)) -> 404 | K96: =IF($E96="404","",IF($F96="ARTICULO",IF($I96<=Destinos!$B$5,"[artículo "&$G96&"] /blog/<slug>/",IFERROR(INDEX(Destinos!$H$9:$H$25,MATCH($H96,Destinos!$E$9:$E$25,0)),Destinos!$C$15)),INDEX(Destinos!$H$9:$H$25,MATCH($F96,Destinos!$A$9:$A$25,0)))) | L96: =IF($K96="","",IF(LEFT($K96,1)="/",Destinos!$B$4&$K96,$K96)) | M96: =IF($E96="404","",IF($F96="ARTICULO","Artículo "&$G96&" → /blog/<slug>/",INDEX(Destinos!$C$9:$C$25,MATCH($F96,Destinos!$A$9:$A$25,0)))) | N96: =IF(AND($E96="301",$F96="ARTICULO"),$I96,"") | O96: R-BLOG-02 | P96: Sin valor SEO actual; sin tema equivalente | Q96: 1 | S96: =IF(AND($E96="404",OR(N($Q96)>0,N($R96)>0)),"REVISAR: tiene clics o enlaces → pasar a 301","") -> REVISAR: tiene clics o enlaces → pasar a 301 | T96: =IF(OR($E96="Conservar URL",AND($E96="301",OR(N($Q96)>=2,$C96="Páginas"))),"Sí","No") -> No | U96: =IF($E96="Sin cambio","200 · sin cambio",IF($T96="Sí",IF($E96="Conservar URL","200 · misma URL","301"),"404")) -> 404
A97: https://www.continentalmedia.com.mx/2014/06/empresa-lista-redes-sociales/ | B97: /2014/06/empresa-lista-redes-sociales/ | C97: Blog | E97: 301 | F97: ARTICULO | G97: E-10 | H97: Redes sociales y comunidad | I97: 46378 | J97: =IF(E97="301",301,IF(E97="404",404,200)) -> 301 | K97: =IF($E97="404","",IF($F97="ARTICULO",IF($I97<=Destinos!$B$5,"[artículo "&$G97&"] /blog/<slug>/",IFERROR(INDEX(Destinos!$H$9:$H$25,MATCH($H97,Destinos!$E$9:$E$25,0)),Destinos!$C$15)),INDEX(Destinos!$H$9:$H$25,MATCH($F97,Destinos!$A$9:$A$25,0)))) -> /blog/categoria/redes-sociales/ | L97: =IF($K97="","",IF(LEFT($K97,1)="/",Destinos!$B$4&$K97,$K97)) -> https://continentalmedia.com.mx/blog/categoria/redes-sociales/ | M97: =IF($E97="404","",IF($F97="ARTICULO","Artículo "&$G97&" → /blog/<slug>/",INDEX(Destinos!$C$9:$C$25,MATCH($F97,Destinos!$A$9:$A$25,0)))) -> Artículo E-10 → /blog/<slug>/ | N97: =IF(AND($E97="301",$F97="ARTICULO"),$I97,"") -> 46378 | O97: R-BLOG-01 | S97: =IF(AND($E97="404",OR(N($Q97)>0,N($R97)>0)),"REVISAR: tiene clics o enlaces → pasar a 301","") | T97: =IF(OR($E97="Conservar URL",AND($E97="301",OR(N($Q97)>=2,$C97="Páginas"))),"Sí","No") -> No | U97: =IF($E97="Sin cambio","200 · sin cambio",IF($T97="Sí",IF($E97="Conservar URL","200 · misma URL","301"),"404")) -> 404
A98: https://www.continentalmedia.com.mx/2014/06/recuperar-clientes/ | B98: /2014/06/recuperar-clientes/ | C98: Blog | E98: 301 | F98: ARTICULO | G98: G-14 | H98: Redes sociales y comunidad | I98: 46499 | J98: =IF(E98="301",301,IF(E98="404",404,200)) -> 301 | K98: =IF($E98="404","",IF($F98="ARTICULO",IF($I98<=Destinos!$B$5,"[artículo "&$G98&"] /blog/<slug>/",IFERROR(INDEX(Destinos!$H$9:$H$25,MATCH($H98,Destinos!$E$9:$E$25,0)),Destinos!$C$15)),INDEX(Destinos!$H$9:$H$25,MATCH($F98,Destinos!$A$9:$A$25,0)))) -> /blog/categoria/redes-sociales/ | L98: =IF($K98="","",IF(LEFT($K98,1)="/",Destinos!$B$4&$K98,$K98)) -> https://continentalmedia.com.mx/blog/categoria/redes-sociales/ | M98: =IF($E98="404","",IF($F98="ARTICULO","Artículo "&$G98&" → /blog/<slug>/",INDEX(Destinos!$C$9:$C$25,MATCH($F98,Destinos!$A$9:$A$25,0)))) -> Artículo G-14 → /blog/<slug>/ | N98: =IF(AND($E98="301",$F98="ARTICULO"),$I98,"") -> 46499 | O98: R-BLOG-01 | S98: =IF(AND($E98="404",OR(N($Q98)>0,N($R98)>0)),"REVISAR: tiene clics o enlaces → pasar a 301","") | T98: =IF(OR($E98="Conservar URL",AND($E98="301",OR(N($Q98)>=2,$C98="Páginas"))),"Sí","No") -> No | U98: =IF($E98="Sin cambio","200 · sin cambio",IF($T98="Sí",IF($E98="Conservar URL","200 · misma URL","301"),"404")) -> 404
A99: https://www.continentalmedia.com.mx/2014/06/un-sueldo-no-es-suficiente/ | B99: /2014/06/un-sueldo-no-es-suficiente/ | C99: Blog | E99: 404 | F99: — | J99: =IF(E99="301",301,IF(E99="404",404,200)) -> 404 | K99: =IF($E99="404","",IF($F99="ARTICULO",IF($I99<=Destinos!$B$5,"[artículo "&$G99&"] /blog/<slug>/",IFERROR(INDEX(Destinos!$H$9:$H$25,MATCH($H99,Destinos!$E$9:$E$25,0)),Destinos!$C$15)),INDEX(Destinos!$H$9:$H$25,MATCH($F99,Destinos!$A$9:$A$25,0)))) | L99: =IF($K99="","",IF(LEFT($K99,1)="/",Destinos!$B$4&$K99,$K99)) | M99: =IF($E99="404","",IF($F99="ARTICULO","Artículo "&$G99&" → /blog/<slug>/",INDEX(Destinos!$C$9:$C$25,MATCH($F99,Destinos!$A$9:$A$25,0)))) | N99: =IF(AND($E99="301",$F99="ARTICULO"),$I99,"") | O99: R-BLOG-02 | P99: Sin valor SEO actual; sin tema equivalente | S99: =IF(AND($E99="404",OR(N($Q99)>0,N($R99)>0)),"REVISAR: tiene clics o enlaces → pasar a 301","") | T99: =IF(OR($E99="Conservar URL",AND($E99="301",OR(N($Q99)>=2,$C99="Páginas"))),"Sí","No") -> No | U99: =IF($E99="Sin cambio","200 · sin cambio",IF($T99="Sí",IF($E99="Conservar URL","200 · misma URL","301"),"404")) -> 404
A100: https://www.continentalmedia.com.mx/2014/07/conoces-la-manera-de-anunciarte-a-traves-de-google/ | B100: /2014/07/conoces-la-manera-de-anunciarte-a-traves-de-google/ | C100: Blog | E100: 301 | F100: ARTICULO | G100: G-38 | H100: Web, SEO y publicidad digital | I100: 46408 | J100: =IF(E100="301",301,IF(E100="404",404,200)) -> 301 | K100: =IF($E100="404","",IF($F100="ARTICULO",IF($I100<=Destinos!$B$5,"[artículo "&$G100&"] /blog/<slug>/",IFERROR(INDEX(Destinos!$H$9:$H$25,MATCH($H100,Destinos!$E$9:$E$25,0)),Destinos!$C$15)),INDEX(Destinos!$H$9:$H$25,MATCH($F100,Destinos!$A$9:$A$25,0)))) -> /blog/ | L100: =IF($K100="","",IF(LEFT($K100,1)="/",Destinos!$B$4&$K100,$K100)) -> https://continentalmedia.com.mx/blog/ | M100: =IF($E100="404","",IF($F100="ARTICULO","Artículo "&$G100&" → /blog/<slug>/",INDEX(Destinos!$C$9:$C$25,MATCH($F100,Destinos!$A$9:$A$25,0)))) -> Artículo G-38 → /blog/<slug>/ | N100: =IF(AND($E100="301",$F100="ARTICULO"),$I100,"") -> 46408 | O100: R-BLOG-01 | S100: =IF(AND($E100="404",OR(N($Q100)>0,N($R100)>0)),"REVISAR: tiene clics o enlaces → pasar a 301","") | T100: =IF(OR($E100="Conservar URL",AND($E100="301",OR(N($Q100)>=2,$C100="Páginas"))),"Sí","No") -> No | U100: =IF($E100="Sin cambio","200 · sin cambio",IF($T100="Sí",IF($E100="Conservar URL","200 · misma URL","301"),"404")) -> 404
...

Sheet Páginas
A1: URL | B1: Tipo | C1: Slug | D1: Última modificación | E1: Código HTTP | F1: Estado | G1: Observaciones | H1: Sugerencia | I1: Acción | J1: URL nueva
A2: https://www.continentalmedia.com.mx/ | B2: Home | C2: www.continentalmedia.com.mx | D2: 2023-03-17 | E2: 200 | F2: OK | I2: =INDEX('Mapa maestro'!$E$2:$E$970,MATCH($A2,'Mapa maestro'!$A$2:$A$970,0)) -> Sin cambio | J2: =IF(INDEX('Mapa maestro'!$E$2:$E$970,MATCH($A2,'Mapa maestro'!$A$2:$A$970,0))="404","— (404 personalizada)",INDEX('Mapa maestro'!$L$2:$L$970,MATCH($A2,'Mapa maestro'!$A$2:$A$970,0))) -> https://continentalmedia.com.mx/
A3: https://www.continentalmedia.com.mx/404-page/ | B3: Página | C3: 404-page | D3: 2014-07-17 | E3: 200 | F3: OK | G3: Página técnica/prueba | H3: Candidata a eliminar (410) | I3: =INDEX('Mapa maestro'!$E$2:$E$970,MATCH($A3,'Mapa maestro'!$A$2:$A$970,0)) -> 404 | J3: =IF(INDEX('Mapa maestro'!$E$2:$E$970,MATCH($A3,'Mapa maestro'!$A$2:$A$970,0))="404","— (404 personalizada)",INDEX('Mapa maestro'!$L$2:$L$970,MATCH($A3,'Mapa maestro'!$A$2:$A$970,0))) -> — (404 personalizada)
A4: https://www.continentalmedia.com.mx/agencia-de-publicidad/ | B4: Página | C4: agencia-de-publicidad | D4: 2023-03-17 | E4: 200 | F4: OK | I4: =INDEX('Mapa maestro'!$E$2:$E$970,MATCH($A4,'Mapa maestro'!$A$2:$A$970,0)) -> 301 | J4: =IF(INDEX('Mapa maestro'!$E$2:$E$970,MATCH($A4,'Mapa maestro'!$A$2:$A$970,0))="404","— (404 personalizada)",INDEX('Mapa maestro'!$L$2:$L$970,MATCH($A4,'Mapa maestro'!$A$2:$A$970,0))) -> https://continentalmedia.com.mx/
A5: https://www.continentalmedia.com.mx/contacto/ | B5: Página | C5: contacto | D5: 2023-03-14 | E5: 200 | F5: OK | I5: =INDEX('Mapa maestro'!$E$2:$E$970,MATCH($A5,'Mapa maestro'!$A$2:$A$970,0)) -> 301 | J5: =IF(INDEX('Mapa maestro'!$E$2:$E$970,MATCH($A5,'Mapa maestro'!$A$2:$A$970,0))="404","— (404 personalizada)",INDEX('Mapa maestro'!$L$2:$L$970,MATCH($A5,'Mapa maestro'!$A$2:$A$970,0))) -> https://continentalmedia.com.mx/#contacto
A6: https://www.continentalmedia.com.mx/elementor-3504/ | B6: Página | C6: elementor-3504 | D6: 2020-09-11 | E6: 200 | F6: OK | G6: Página técnica/prueba | H6: Candidata a eliminar (410) | I6: =INDEX('Mapa maestro'!$E$2:$E$970,MATCH($A6,'Mapa maestro'!$A$2:$A$970,0)) -> 404 | J6: =IF(INDEX('Mapa maestro'!$E$2:$E$970,MATCH($A6,'Mapa maestro'!$A$2:$A$970,0))="404","— (404 personalizada)",INDEX('Mapa maestro'!$L$2:$L$970,MATCH($A6,'Mapa maestro'!$A$2:$A$970,0))) -> — (404 personalizada)
A7: https://www.continentalmedia.com.mx/homepage-revolution/ | B7: Página | C7: homepage-revolution | D7: 2021-03-08 | E7: 200 | F7: OK | G7: Página técnica/prueba | H7: Candidata a eliminar (410) | I7: =INDEX('Mapa maestro'!$E$2:$E$970,MATCH($A7,'Mapa maestro'!$A$2:$A$970,0)) -> 404 | J7: =IF(INDEX('Mapa maestro'!$E$2:$E$970,MATCH($A7,'Mapa maestro'!$A$2:$A$970,0))="404","— (404 personalizada)",INDEX('Mapa maestro'!$L$2:$L$970,MATCH($A7,'Mapa maestro'!$A$2:$A$970,0))) -> — (404 personalizada)
A8: https://www.continentalmedia.com.mx/nuestros-servicios/ | B8: Página | C8: nuestros-servicios | D8: 2021-03-10 | E8: 200 | F8: OK | I8: =INDEX('Mapa maestro'!$E$2:$E$970,MATCH($A8,'Mapa maestro'!$A$2:$A$970,0)) -> 301 | J8: =IF(INDEX('Mapa maestro'!$E$2:$E$970,MATCH($A8,'Mapa maestro'!$A$2:$A$970,0))="404","— (404 personalizada)",INDEX('Mapa maestro'!$L$2:$L$970,MATCH($A8,'Mapa maestro'!$A$2:$A$970,0))) -> https://continentalmedia.com.mx/#servicios
A9: https://www.continentalmedia.com.mx/pagina-inicial/ | B9: Página | C9: pagina-inicial | D9: 2021-03-06 | E9: 200 | F9: OK | G9: Página técnica/prueba | H9: Candidata a eliminar (410) | I9: =INDEX('Mapa maestro'!$E$2:$E$970,MATCH($A9,'Mapa maestro'!$A$2:$A$970,0)) -> 404 | J9: =IF(INDEX('Mapa maestro'!$E$2:$E$970,MATCH($A9,'Mapa maestro'!$A$2:$A$970,0))="404","— (404 personalizada)",INDEX('Mapa maestro'!$L$2:$L$970,MATCH($A9,'Mapa maestro'!$A$2:$A$970,0))) -> — (404 personalizada)
A10: https://www.continentalmedia.com.mx/portafolio/ | B10: Página | C10: portafolio | D10: 2020-07-03 | E10: 200 | F10: OK | I10: =INDEX('Mapa maestro'!$E$2:$E$970,MATCH($A10,'Mapa maestro'!$A$2:$A$970,0)) -> 301 | J10: =IF(INDEX('Mapa maestro'!$E$2:$E$970,MATCH($A10,'Mapa maestro'!$A$2:$A$970,0))="404","— (404 personalizada)",INDEX('Mapa maestro'!$L$2:$L$970,MATCH($A10,'Mapa maestro'!$A$2:$A$970,0))) -> https://continentalmedia.com.mx/proyectos/
A11: https://www.continentalmedia.com.mx/testing-1/ | B11: Página | C11: testing-1 | D11: 2021-03-08 | E11: 500 | F11: Revisar | G11: Página técnica/prueba; HTTP 500 en la revisión (volver a verificar) | H11: Candidata a eliminar (410) | I11: =INDEX('Mapa maestro'!$E$2:$E$970,MATCH($A11,'Mapa maestro'!$A$2:$A$970,0)) -> 404 | J11: =IF(INDEX('Mapa maestro'!$E$2:$E$970,MATCH($A11,'Mapa maestro'!$A$2:$A$970,0))="404","— (404 personalizada)",INDEX('Mapa maestro'!$L$2:$L$970,MATCH($A11,'Mapa maestro'!$A$2:$A$970,0))) -> — (404 personalizada)
A12: https://www.continentalmedia.com.mx/usa/ | B12: Página | C12: usa | D12: 2022-04-22 | E12: 500 | F12: Revisar | G12: HTTP 500 en la revisión (volver a verificar) | I12: =INDEX('Mapa maestro'!$E$2:$E$970,MATCH($A12,'Mapa maestro'!$A$2:$A$970,0)) -> 301 | J12: =IF(INDEX('Mapa maestro'!$E$2:$E$970,MATCH($A12,'Mapa maestro'!$A$2:$A$970,0))="404","— (404 personalizada)",INDEX('Mapa maestro'!$L$2:$L$970,MATCH($A12,'Mapa maestro'!$A$2:$A$970,0))) -> https://continentalmedia.com.mx/

Sheet Blog
A1: URL | B1: Tipo | C1: Slug | D1: Última modificación | E1: Código HTTP | F1: Estado | G1: Observaciones | H1: Sugerencia | I1: Acción | J1: URL nueva
A2: https://www.continentalmedia.com.mx/2012/08/creative-interior-design/ | B2: Blog | C2: creative-interior-design | D2: 2019-10-29 | E2: 200 | F2: OK | I2: =INDEX('Mapa maestro'!$E$2:$E$970,MATCH($A2,'Mapa maestro'!$A$2:$A$970,0)) -> 404 | J2: =IF(INDEX('Mapa maestro'!$E$2:$E$970,MATCH($A2,'Mapa maestro'!$A$2:$A$970,0))="404","— (404 personalizada)",INDEX('Mapa maestro'!$L$2:$L$970,MATCH($A2,'Mapa maestro'!$A$2:$A$970,0))) -> — (404 personalizada)
A3: https://www.continentalmedia.com.mx/2012/08/marketing-olfativo/ | B3: Blog | C3: marketing-olfativo | D3: 2019-10-29 | E3: 200 | F3: OK | I3: =INDEX('Mapa maestro'!$E$2:$E$970,MATCH($A3,'Mapa maestro'!$A$2:$A$970,0)) -> 301 | J3: =IF(INDEX('Mapa maestro'!$E$2:$E$970,MATCH($A3,'Mapa maestro'!$A$2:$A$970,0))="404","— (404 personalizada)",INDEX('Mapa maestro'!$L$2:$L$970,MATCH($A3,'Mapa maestro'!$A$2:$A$970,0))) -> https://continentalmedia.com.mx/blog/
A4: https://www.continentalmedia.com.mx/2012/12/6-razones-pymes-usar-redes-sociales/ | B4: Blog | C4: 6-razones-pymes-usar-redes-sociales | D4: 2019-10-22 | E4: 200 | F4: OK | I4: =INDEX('Mapa maestro'!$E$2:$E$970,MATCH($A4,'Mapa maestro'!$A$2:$A$970,0)) -> 301 | J4: =IF(INDEX('Mapa maestro'!$E$2:$E$970,MATCH($A4,'Mapa maestro'!$A$2:$A$970,0))="404","— (404 personalizada)",INDEX('Mapa maestro'!$L$2:$L$970,MATCH($A4,'Mapa maestro'!$A$2:$A$970,0))) -> https://continentalmedia.com.mx/blog/categoria/redes-sociales/
A5: https://www.continentalmedia.com.mx/2012/12/campanas-exitosas-del-2012/ | B5: Blog | C5: campanas-exitosas-del-2012 | D5: 2019-10-21 | E5: 200 | F5: OK | I5: =INDEX('Mapa maestro'!$E$2:$E$970,MATCH($A5,'Mapa maestro'!$A$2:$A$970,0)) -> 301 | J5: =IF(INDEX('Mapa maestro'!$E$2:$E$970,MATCH($A5,'Mapa maestro'!$A$2:$A$970,0))="404","— (404 personalizada)",INDEX('Mapa maestro'!$L$2:$L$970,MATCH($A5,'Mapa maestro'!$A$2:$A$970,0))) -> https://continentalmedia.com.mx/blog/
A6: https://www.continentalmedia.com.mx/2012/12/churros-creatividad/ | B6: Blog | C6: churros-creatividad | D6: 2019-10-21 | E6: 200 | F6: OK | I6: =INDEX('Mapa maestro'!$E$2:$E$970,MATCH($A6,'Mapa maestro'!$A$2:$A$970,0)) -> 301 | J6: =IF(INDEX('Mapa maestro'!$E$2:$E$970,MATCH($A6,'Mapa maestro'!$A$2:$A$970,0))="404","— (404 personalizada)",INDEX('Mapa maestro'!$L$2:$L$970,MATCH($A6,'Mapa maestro'!$A$2:$A$970,0))) -> https://continentalmedia.com.mx/blog/
A7: https://www.continentalmedia.com.mx/2012/12/conoce-el-funcionamiento-del-e-mail-marketing/ | B7: Blog | C7: conoce-el-funcionamiento-del-e-mail-marketing | D7: 2019-10-22 | E7: 200 | F7: OK | I7: =INDEX('Mapa maestro'!$E$2:$E$970,MATCH($A7,'Mapa maestro'!$A$2:$A$970,0)) -> 301 | J7: =IF(INDEX('Mapa maestro'!$E$2:$E$970,MATCH($A7,'Mapa maestro'!$A$2:$A$970,0))="404","— (404 personalizada)",INDEX('Mapa maestro'!$L$2:$L$970,MATCH($A7,'Mapa maestro'!$A$2:$A$970,0))) -> https://continentalmedia.com.mx/blog/
A8: https://www.continentalmedia.com.mx/2012/12/es-necesario-ofrecer-una-buena-atencion-al-cliente-en-las-redes-sociales/ | B8: Blog | C8: es-necesario-ofrecer-una-buena-atencion-al-cliente-en-las-redes-sociales | D8: 2019-10-22 | E8: 200 | F8: OK | I8: =INDEX('Mapa maestro'!$E$2:$E$970,MATCH($A8,'Mapa maestro'!$A$2:$A$970,0)) -> 301 | J8: =IF(INDEX('Mapa maestro'!$E$2:$E$970,MATCH($A8,'Mapa maestro'!$A$2:$A$970,0))="404","— (404 personalizada)",INDEX('Mapa maestro'!$L$2:$L$970,MATCH($A8,'Mapa maestro'!$A$2:$A$970,0))) -> https://continentalmedia.com.mx/blog/categoria/redes-sociales/
A9: https://www.continentalmedia.com.mx/2012/12/inversion-publicitaria-en-medios-online/ | B9: Blog | C9: inversion-publicitaria-en-medios-online | D9: 2019-10-21 | E9: 200 | F9: OK | I9: =INDEX('Mapa maestro'!$E$2:$E$970,MATCH($A9,'Mapa maestro'!$A$2:$A$970,0)) -> 301 | J9: =IF(INDEX('Mapa maestro'!$E$2:$E$970,MATCH($A9,'Mapa maestro'!$A$2:$A$970,0))="404","— (404 personalizada)",INDEX('Mapa maestro'!$L$2:$L$970,MATCH($A9,'Mapa maestro'!$A$2:$A$970,0))) -> https://continentalmedia.com.mx/blog/
A10: https://www.continentalmedia.com.mx/2012/12/las-4-r-s-de-las-redes-sociales/ | B10: Blog | C10: las-4-r-s-de-las-redes-sociales | D10: 2019-10-21 | E10: 200 | F10: OK | I10: =INDEX('Mapa maestro'!$E$2:$E$970,MATCH($A10,'Mapa maestro'!$A$2:$A$970,0)) -> 301 | J10: =IF(INDEX('Mapa maestro'!$E$2:$E$970,MATCH($A10,'Mapa maestro'!$A$2:$A$970,0))="404","— (404 personalizada)",INDEX('Mapa maestro'!$L$2:$L$970,MATCH($A10,'Mapa maestro'!$A$2:$A$970,0))) -> https://continentalmedia.com.mx/blog/categoria/redes-sociales/
A11: https://www.continentalmedia.com.mx/2012/12/lovemarks/ | B11: Blog | C11: lovemarks | D11: 2019-10-21 | E11: 200 | F11: OK | I11: =INDEX('Mapa maestro'!$E$2:$E$970,MATCH($A11,'Mapa maestro'!$A$2:$A$970,0)) -> 301 | J11: =IF(INDEX('Mapa maestro'!$E$2:$E$970,MATCH($A11,'Mapa maestro'!$A$2:$A$970,0))="404","— (404 personalizada)",INDEX('Mapa maestro'!$L$2:$L$970,MATCH($A11,'Mapa maestro'!$A$2:$A$970,0))) -> https://continentalmedia.com.mx/blog/
A12: https://www.continentalmedia.com.mx/2012/12/marketing-de-guerrilla/ | B12: Blog | C12: marketing-de-guerrilla | D12: 2019-10-21 | E12: 200 | F12: OK | I12: =INDEX('Mapa maestro'!$E$2:$E$970,MATCH($A12,'Mapa maestro'!$A$2:$A$970,0)) -> 301 | J12: =IF(INDEX('Mapa maestro'!$E$2:$E$970,MATCH($A12,'Mapa maestro'!$A$2:$A$970,0))="404","— (404 personalizada)",INDEX('Mapa maestro'!$L$2:$L$970,MATCH($A12,'Mapa maestro'!$A$2:$A$970,0))) -> https://continentalmedia.com.mx/blog/
A13: https://www.continentalmedia.com.mx/2012/12/marketing-deportivo/ | B13: Blog | C13: marketing-deportivo | D13: 2019-10-21 | E13: 200 | F13: OK | I13: =INDEX('Mapa maestro'!$E$2:$E$970,MATCH($A13,'Mapa maestro'!$A$2:$A$970,0)) -> 301 | J13: =IF(INDEX('Mapa maestro'!$E$2:$E$970,MATCH($A13,'Mapa maestro'!$A$2:$A$970,0))="404","— (404 personalizada)",INDEX('Mapa maestro'!$L$2:$L$970,MATCH($A13,'Mapa maestro'!$A$2:$A$970,0))) -> https://continentalmedia.com.mx/blog/
... A189: https://www.continentalmedia.com.mx/blog/ | B189: Blog | C189: blog | D189: 2020-07-03 | E189: 200 | F189: OK | I189: =INDEX('Mapa maestro'!$E$2:$E$970,MATCH($A189,'Mapa maestro'!$A$2:$A$970,0)) -> Sin cambio | J189: =IF(INDEX('Mapa maestro'!$E$2:$E$970,MATCH($A189,'Mapa maestro'!$A$2:$A$970,0))="404","— (404 personalizada)",INDEX('Mapa maestro'!$L$2:$L$970,MATCH($A189,'Mapa maestro'!$A$2:$A$970,0))) -> https://continentalmedia.com.mx/blog/

Sheet Portafolio
A1: URL | B1: Tipo | C1: Slug | D1: Última modificación | E1: Código HTTP | F1: Estado | G1: Observaciones | H1: Sugerencia | I1: Acción | J1: URL nueva
A2: https://www.continentalmedia.com.mx/portfolio/2525-2/ | B2: Portafolio | C2: 2525-2 | D2: 2017-02-01 | E2: error | F2: Revisar | G2: Slug sin nombre descriptivo; HTTP error en la revisión (volver a verificar) | H2: Revisar contenido | I2: =INDEX('Mapa maestro'!$E$2:$E$970,MATCH($A2,'Mapa maestro'!$A$2:$A$970,0)) -> 301 | J2: =IF(INDEX('Mapa maestro'!$E$2:$E$970,MATCH($A2,'Mapa maestro'!$A$2:$A$970,0))="404","— (404 personalizada)",INDEX('Mapa maestro'!$L$2:$L$970,MATCH($A2,'Mapa maestro'!$A$2:$A$970,0))) -> https://continentalmedia.com.mx/proyectos/
A3: https://www.continentalmedia.com.mx/portfolio/2576-2/ | B3: Portafolio | C3: 2576-2 | D3: 2019-12-31 | E3: error | F3: Revisar | G3: Slug sin nombre descriptivo; HTTP error en la revisión (volver a verificar) | H3: Revisar contenido | I3: =INDEX('Mapa maestro'!$E$2:$E$970,MATCH($A3,'Mapa maestro'!$A$2:$A$970,0)) -> 301 | J3: =IF(INDEX('Mapa maestro'!$E$2:$E$970,MATCH($A3,'Mapa maestro'!$A$2:$A$970,0))="404","— (404 personalizada)",INDEX('Mapa maestro'!$L$2:$L$970,MATCH($A3,'Mapa maestro'!$A$2:$A$970,0))) -> https://continentalmedia.com.mx/proyectos/
A4: https://www.continentalmedia.com.mx/portfolio/3654-2/ | B4: Portafolio | C4: 3654-2 | D4: 2021-06-10 | E4: error | F4: Revisar | G4: Slug sin nombre descriptivo; HTTP error en la revisión (volver a verificar) | H4: Revisar contenido | I4: =INDEX('Mapa maestro'!$E$2:$E$970,MATCH($A4,'Mapa maestro'!$A$2:$A$970,0)) -> 301 | J4: =IF(INDEX('Mapa maestro'!$E$2:$E$970,MATCH($A4,'Mapa maestro'!$A$2:$A$970,0))="404","— (404 personalizada)",INDEX('Mapa maestro'!$L$2:$L$970,MATCH($A4,'Mapa maestro'!$A$2:$A$970,0))) -> https://continentalmedia.com.mx/proyectos/
A5: https://www.continentalmedia.com.mx/portfolio/4763-2/ | B5: Portafolio | C5: 4763-2 | D5: 2025-11-19 | E5: error | F5: Revisar | G5: Slug sin nombre descriptivo; HTTP error en la revisión (volver a verificar) | H5: Revisar contenido | I5: =INDEX('Mapa maestro'!$E$2:$E$970,MATCH($A5,'Mapa maestro'!$A$2:$A$970,0)) -> 301 | J5: =IF(INDEX('Mapa maestro'!$E$2:$E$970,MATCH($A5,'Mapa maestro'!$A$2:$A$970,0))="404","— (404 personalizada)",INDEX('Mapa maestro'!$L$2:$L$970,MATCH($A5,'Mapa maestro'!$A$2:$A$970,0))) -> https://continentalmedia.com.mx/proyectos/
A6: https://www.continentalmedia.com.mx/portfolio/adr-logotipo/ | B6: Portafolio | C6: adr-logotipo | D6: 2019-12-31 | E6: 200 | F6: OK | I6: =INDEX('Mapa maestro'!$E$2:$E$970,MATCH($A6,'Mapa maestro'!$A$2:$A$970,0)) -> 301 | J6: =IF(INDEX('Mapa maestro'!$E$2:$E$970,MATCH($A6,'Mapa maestro'!$A$2:$A$970,0))="404","— (404 personalizada)",INDEX('Mapa maestro'!$L$2:$L$970,MATCH($A6,'Mapa maestro'!$A$2:$A$970,0))) -> https://continentalmedia.com.mx/proyectos/
A7: https://www.continentalmedia.com.mx/portfolio/amalfi-blu-aplicaciones-varias/ | B7: Portafolio | C7: amalfi-blu-aplicaciones-varias | D7: 2025-03-27 | E7: 200 | F7: OK | I7: =INDEX('Mapa maestro'!$E$2:$E$970,MATCH($A7,'Mapa maestro'!$A$2:$A$970,0)) -> 301 | J7: =IF(INDEX('Mapa maestro'!$E$2:$E$970,MATCH($A7,'Mapa maestro'!$A$2:$A$970,0))="404","— (404 personalizada)",INDEX('Mapa maestro'!$L$2:$L$970,MATCH($A7,'Mapa maestro'!$A$2:$A$970,0))) -> https://continentalmedia.com.mx/proyectos/
A8: https://www.continentalmedia.com.mx/portfolio/amalfi-blu-diseno-de-logotipo/ | B8: Portafolio | C8: amalfi-blu-diseno-de-logotipo | D8: 2025-03-27 | E8: 200 | F8: OK | I8: =INDEX('Mapa maestro'!$E$2:$E$970,MATCH($A8,'Mapa maestro'!$A$2:$A$970,0)) -> 301 | J8: =IF(INDEX('Mapa maestro'!$E$2:$E$970,MATCH($A8,'Mapa maestro'!$A$2:$A$970,0))="404","— (404 personalizada)",INDEX('Mapa maestro'!$L$2:$L$970,MATCH($A8,'Mapa maestro'!$A$2:$A$970,0))) -> https://continentalmedia.com.mx/proyectos/
A9: https://www.continentalmedia.com.mx/portfolio/amalfi-blue-diseno-de-empaque/ | B9: Portafolio | C9: amalfi-blue-diseno-de-empaque | D9: 2025-03-27 | E9: 200 | F9: OK | I9: =INDEX('Mapa maestro'!$E$2:$E$970,MATCH($A9,'Mapa maestro'!$A$2:$A$970,0)) -> 301 | J9: =IF(INDEX('Mapa maestro'!$E$2:$E$970,MATCH($A9,'Mapa maestro'!$A$2:$A$970,0))="404","— (404 personalizada)",INDEX('Mapa maestro'!$L$2:$L$970,MATCH($A9,'Mapa maestro'!$A$2:$A$970,0))) -> https://continentalmedia.com.mx/proyectos/
A10: https://www.continentalmedia.com.mx/portfolio/amda-anuncio-periodico/ | B10: Portafolio | C10: amda-anuncio-periodico | D10: 2019-12-31 | E10: 200 | F10: OK | I10: =INDEX('Mapa maestro'!$E$2:$E$970,MATCH($A10,'Mapa maestro'!$A$2:$A$970,0)) -> 301 | J10: =IF(INDEX('Mapa maestro'!$E$2:$E$970,MATCH($A10,'Mapa maestro'!$A$2:$A$970,0))="404","— (404 personalizada)",INDEX('Mapa maestro'!$L$2:$L$970,MATCH($A10,'Mapa maestro'!$A$2:$A$970,0))) -> https://continentalmedia.com.mx/proyectos/
A11: https://www.continentalmedia.com.mx/portfolio/amda-imagen-y-logotipo/ | B11: Portafolio | C11: amda-imagen-y-logotipo | D11: 2019-12-31 | E11: 200 | F11: OK | I11: =INDEX('Mapa maestro'!$E$2:$E$970,MATCH($A11,'Mapa maestro'!$A$2:$A$970,0)) -> 301 | J11: =IF(INDEX('Mapa maestro'!$E$2:$E$970,MATCH($A11,'Mapa maestro'!$A$2:$A$970,0))="404","— (404 personalizada)",INDEX('Mapa maestro'!$L$2:$L$970,MATCH($A11,'Mapa maestro'!$A$2:$A$970,0))) -> https://continentalmedia.com.mx/proyectos/
A12: https://www.continentalmedia.com.mx/portfolio/amda-produccion-audiovisual/ | B12: Portafolio | C12: amda-produccion-audiovisual | D12: 2019-12-31 | E12: 200 | F12: OK | I12: =INDEX('Mapa maestro'!$E$2:$E$970,MATCH($A12,'Mapa maestro'!$A$2:$A$970,0)) -> 301 | J12: =IF(INDEX('Mapa maestro'!$E$2:$E$970,MATCH($A12,'Mapa maestro'!$A$2:$A$970,0))="404","— (404 personalizada)",INDEX('Mapa maestro'!$L$2:$L$970,MATCH($A12,'Mapa maestro'!$A$2:$A$970,0))) -> https://continentalmedia.com.mx/proyectos/
A13: https://www.continentalmedia.com.mx/portfolio/amda-revista/ | B13: Portafolio | C13: amda-revista | D13: 2019-12-31 | E13: 200 | F13: OK | I13: =INDEX('Mapa maestro'!$E$2:$E$970,MATCH($A13,'Mapa maestro'!$A$2:$A$970,0)) -> 301 | J13: =IF(INDEX('Mapa maestro'!$E$2:$E$970,MATCH($A13,'Mapa maestro'!$A$2:$A$970,0))="404","— (404 personalizada)",INDEX('Mapa maestro'!$L$2:$L$970,MATCH($A13,'Mapa maestro'!$A$2:$A$970,0))) -> https://continentalmedia.com.mx/proyectos/
A14: https://www.continentalmedia.com.mx/portfolio/andamar/ | B14: Portafolio | C14: andamar | D14: 2019-12-31 | E14: 200 | F14: OK | I14: =INDEX('Mapa maestro'!$E$2:$E$970,MATCH($A14,'Mapa maestro'!$A$2:$A$970,0)) -> 301 | J14: =IF(INDEX('Mapa maestro'!$E$2:$E$970,MATCH($A14,'Mapa maestro'!$A$2:$A$970,0))="404","— (404 personalizada)",INDEX('Mapa maestro'!$L$2:$L$970,MATCH($A14,'Mapa maestro'!$A$2:$A$970,0))) -> https://continentalmedia.com.mx/proyectos/
A15: https://www.continentalmedia.com.mx/portfolio/banner-publicitario-tgle/ | B15: Portafolio | C15: banner-publicitario-tgle | D15: 2024-11-07 | E15: 200 | F15: OK | I15: =INDEX('Mapa maestro'!$E$2:$E$970,MATCH($A15,'Mapa maestro'!$A$2:$A$970,0)) -> 301 | J15: =IF(INDEX('Mapa maestro'!$E$2:$E$970,MATCH($A15,'Mapa maestro'!$A$2:$A$970,0))="404","— (404 personalizada)",INDEX('Mapa maestro'!$L$2:$L$970,MATCH($A15,'Mapa maestro'!$A$2:$A$970,0))) -> https://continentalmedia.com.mx/proyectos/
A16: https://www.continentalmedia.com.mx/portfolio/banner-web/ | B16: Portafolio | C16: banner-web | D16: 2019-12-31 | E16: 200 | F16: OK | I16: =INDEX('Mapa maestro'!$E$2:$E$970,MATCH($A16,'Mapa maestro'!$A$2:$A$970,0)) -> 301 | J16: =IF(INDEX('Mapa maestro'!$E$2:$E$970,MATCH($A16,'Mapa maestro'!$A$2:$A$970,0))="404","— (404 personalizada)",INDEX('Mapa maestro'!$L$2:$L$970,MATCH($A16,'Mapa maestro'!$A$2:$A$970,0))) -> https://continentalmedia.com.mx/proyectos/
A17: https://www.continentalmedia.com.mx/portfolio/boca-espacio-bienes-raices-contenido-para-redes-sociales/ | B17: Portafolio | C17: boca-espacio-bienes-raices-contenido-para-redes-sociales | D17: 2026-09-14 | E17: error | F17: Revisar | G17: HTTP error en la revisión (volver a verificar) | I17: =INDEX('Mapa maestro'!$E$2:$E$970,MATCH($A17,'Mapa maestro'!$A$2:$A$970,0)) -> 301 | J17: =IF(INDEX('Mapa maestro'!$E$2:$E$970,MATCH($A17,'Mapa maestro'!$A$2:$A$970,0))="404","— (404 personalizada)",INDEX('Mapa maestro'!$L$2:$L$970,MATCH($A17,'Mapa maestro'!$A$2:$A$970,0))) -> https://continentalmedia.com.mx/proyectos/
A18: https://www.continentalmedia.com.mx/portfolio/bosque-espectacular1/ | B18: Portafolio | C18: bosque-espectacular1 | D18: 2019-12-31 | E18: error | F18: Revisar | G18: HTTP error en la revisión (volver a verificar) | I18: =INDEX('Mapa maestro'!$E$2:$E$970,MATCH($A18,'Mapa maestro'!$A$2:$A$970,0)) -> 301 | J18: =IF(INDEX('Mapa maestro'!$E$2:$E$970,MATCH($A18,'Mapa maestro'!$A$2:$A$970,0))="404","— (404 personalizada)",INDEX('Mapa maestro'!$L$2:$L$970,MATCH($A18,'Mapa maestro'!$A$2:$A$970,0))) -> https://continentalmedia.com.mx/proyectos/
A19: https://www.continentalmedia.com.mx/portfolio/bosque-residencial-san-lucas-disenos-para-redes-sociales/ | B19: Portafolio | C19: bosque-residencial-san-lucas-disenos-para-redes-sociales | D19: 2026-03-09 | E19: error | F19: Revisar | G19: HTTP error en la revisión (volver a verificar) | I19: =INDEX('Mapa maestro'!$E$2:$E$970,MATCH($A19,'Mapa maestro'!$A$2:$A$970,0)) -> 301 | J19: =IF(INDEX('Mapa maestro'!$E$2:$E$970,MATCH($A19,'Mapa maestro'!$A$2:$A$970,0))="404","— (404 personalizada)",INDEX('Mapa maestro'!$L$2:$L$970,MATCH($A19,'Mapa maestro'!$A$2:$A$970,0))) -> https://continentalmedia.com.mx/proyectos/
A20: https://www.continentalmedia.com.mx/portfolio/boxfort-diseno-de-espectacular/ | B20: Portafolio | C20: boxfort-diseno-de-espectacular | D20: 2019-12-31 | E20: error | F20: Revisar | G20: HTTP error en la revisión (volver a verificar) | I20: =INDEX('Mapa maestro'!$E$2:$E$970,MATCH($A20,'Mapa maestro'!$A$2:$A$970,0)) -> 301 | J20: =IF(INDEX('Mapa maestro'!$E$2:$E$970,MATCH($A20,'Mapa maestro'!$A$2:$A$970,0))="404","— (404 personalizada)",INDEX('Mapa maestro'!$L$2:$L$970,MATCH($A20,'Mapa maestro'!$A$2:$A$970,0))) -> https://continentalmedia.com.mx/proyectos/
A21: https://www.continentalmedia.com.mx/portfolio/boxfort-diseno-de-plana-revista/ | B21: Portafolio | C21: boxfort-diseno-de-plana-revista | D21: 2019-12-31 | E21: error | F21: Revisar | G21: HTTP error en la revisión (volver a verificar) | I21: =INDEX('Mapa maestro'!$E$2:$E$970,MATCH($A21,'Mapa maestro'!$A$2:$A$970,0)) -> 301 | J21: =IF(INDEX('Mapa maestro'!$E$2:$E$970,MATCH($A21,'Mapa maestro'!$A$2:$A$970,0))="404","— (404 personalizada)",INDEX('Mapa maestro'!$L$2:$L$970,MATCH($A21,'Mapa maestro'!$A$2:$A$970,0))) -> https://continentalmedia.com.mx/proyectos/
A22: https://www.continentalmedia.com.mx/portfolio/boxfort-doble-plana-para-revista/ | B22: Portafolio | C22: boxfort-doble-plana-para-revista | D22: 2019-12-31 | E22: error | F22: Revisar | G22: HTTP error en la revisión (volver a verificar) | I22: =INDEX('Mapa maestro'!$E$2:$E$970,MATCH($A22,'Mapa maestro'!$A$2:$A$970,0)) -> 301 | J22: =IF(INDEX('Mapa maestro'!$E$2:$E$970,MATCH($A22,'Mapa maestro'!$A$2:$A$970,0))="404","— (404 personalizada)",INDEX('Mapa maestro'!$L$2:$L$970,MATCH($A22,'Mapa maestro'!$A$2:$A$970,0))) -> https://continentalmedia.com.mx/proyectos/
A23: https://www.continentalmedia.com.mx/portfolio/boxfort-folleto/ | B23: Portafolio | C23: boxfort-folleto | D23: 2019-10-22 | E23: error | F23: Revisar | G23: HTTP error en la revisión (volver a verificar) | I23: =INDEX('Mapa maestro'!$E$2:$E$970,MATCH($A23,'Mapa maestro'!$A$2:$A$970,0)) -> 301 | J23: =IF(INDEX('Mapa maestro'!$E$2:$E$970,MATCH($A23,'Mapa maestro'!$A$2:$A$970,0))="404","— (404 personalizada)",INDEX('Mapa maestro'!$L$2:$L$970,MATCH($A23,'Mapa maestro'!$A$2:$A$970,0))) -> https://continentalmedia.com.mx/proyectos/
A24: https://www.continentalmedia.com.mx/portfolio/buen-comer-fotos/ | B24: Portafolio | C24: buen-comer-fotos | D24: 2019-12-31 | E24: error | F24: Revisar | G24: HTTP error en la revisión (volver a verificar) | I24: =INDEX('Mapa maestro'!$E$2:$E$970,MATCH($A24,'Mapa maestro'!$A$2:$A$970,0)) -> 301 | J24: =IF(INDEX('Mapa maestro'!$E$2:$E$970,MATCH($A24,'Mapa maestro'!$A$2:$A$970,0))="404","— (404 personalizada)",INDEX('Mapa maestro'!$L$2:$L$970,MATCH($A24,'Mapa maestro'!$A$2:$A$970,0))) -> https://continentalmedia.com.mx/proyectos/
A25: https://www.continentalmedia.com.mx/portfolio/buen-comer-invitacion/ | B25: Portafolio | C25: buen-comer-invitacion | D25: 2019-10-21 | E25: error | F25: Revisar | G25: HTTP error en la revisión (volver a verificar) | I25: =INDEX('Mapa maestro'!$E$2:$E$970,MATCH($A25,'Mapa maestro'!$A$2:$A$970,0)) -> 301 | J25: =IF(INDEX('Mapa maestro'!$E$2:$E$970,MATCH($A25,'Mapa maestro'!$A$2:$A$970,0))="404","— (404 personalizada)",INDEX('Mapa maestro'!$L$2:$L$970,MATCH($A25,'Mapa maestro'!$A$2:$A$970,0))) -> https://continentalmedia.com.mx/proyectos/
A26: https://www.continentalmedia.com.mx/portfolio/carrera-de-veracruzana-playera/ | B26: Portafolio | C26: carrera-de-veracruzana-playera | D26: 2017-02-01 | E26: error | F26: Revisar | G26: HTTP error en la revisión (volver a verificar) | I26: =INDEX('Mapa maestro'!$E$2:$E$970,MATCH($A26,'Mapa maestro'!$A$2:$A$970,0)) -> 301 | J26: =IF(INDEX('Mapa maestro'!$E$2:$E$970,MATCH($A26,'Mapa maestro'!$A$2:$A$970,0))="404","— (404 personalizada)",INDEX('Mapa maestro'!$L$2:$L$970,MATCH($A26,'Mapa maestro'!$A$2:$A$970,0))) -> https://continentalmedia.com.mx/proyectos/
A27: https://www.continentalmedia.com.mx/portfolio/carrera-veracruzana-2/ | B27: Portafolio | C27: carrera-veracruzana-2 | D27: 2019-12-31 | E27: error | F27: Revisar | G27: Posible duplicado de /carrera-veracruzana/; HTTP error en la revisión (volver a verificar) | H27: Revisar y consolidar con 301 | I27: =INDEX('Mapa maestro'!$E$2:$E$970,MATCH($A27,'Mapa maestro'!$A$2:$A$970,0)) -> 301 | J27: =IF(INDEX('Mapa maestro'!$E$2:$E$970,MATCH($A27,'Mapa maestro'!$A$2:$A$970,0))="404","— (404 personalizada)",INDEX('Mapa maestro'!$L$2:$L$970,MATCH($A27,'Mapa maestro'!$A$2:$A$970,0))) -> https://continentalmedia.com.mx/proyectos/
A28: https://www.continentalmedia.com.mx/portfolio/carrera-veracruzana/ | B28: Portafolio | C28: carrera-veracruzana | D28: 2017-02-01 | E28: error | F28: Revisar | G28: HTTP error en la revisión (volver a verificar) | I28: =INDEX('Mapa maestro'!$E$2:$E$970,MATCH($A28,'Mapa maestro'!$A$2:$A$970,0)) -> 301 | J28: =IF(INDEX('Mapa maestro'!$E$2:$E$970,MATCH($A28,'Mapa maestro'!$A$2:$A$970,0))="404","— (404 personalizada)",INDEX('Mapa maestro'!$L$2:$L$970,MATCH($A28,'Mapa maestro'!$A$2:$A$970,0))) -> https://continentalmedia.com.mx/proyectos/
A29: https://www.continentalmedia.com.mx/portfolio/carvimex/ | B29: Portafolio | C29: carvimex | D29: 2019-12-31 | E29: error | F29: Revisar | G29: HTTP error en la revisión (volver a verificar) | I29: =INDEX('Mapa maestro'!$E$2:$E$970,MATCH($A29,'Mapa maestro'!$A$2:$A$970,0)) -> 301 | J29: =IF(INDEX('Mapa maestro'!$E$2:$E$970,MATCH($A29,'Mapa maestro'!$A$2:$A$970,0))="404","— (404 personalizada)",INDEX('Mapa maestro'!$L$2:$L$970,MATCH($A29,'Mapa maestro'!$A$2:$A$970,0))) -> https://continentalmedia.com.mx/proyectos/
A30: https://www.continentalmedia.com.mx/portfolio/casas-bambino-espectacular/ | B30: Portafolio | C30: casas-bambino-espectacular | D30: 2019-12-31 | E30: error | F30: Revisar | G30: HTTP error en la revisión (volver a verificar) | I30: =INDEX('Mapa maestro'!$E$2:$E$970,MATCH($A30,'Mapa maestro'!$A$2:$A$970,0)) -> 301 | J30: =IF(INDEX('Mapa maestro'!$E$2:$E$970,MATCH($A30,'Mapa maestro'!$A$2:$A$970,0))="404","— (404 personalizada)",INDEX('Mapa maestro'!$L$2:$L$970,MATCH($A30,'Mapa maestro'!$A$2:$A$970,0))) -> https://continentalmedia.com.mx/proyectos/
A31: https://www.continentalmedia.com.mx/portfolio/casas-bambino-logotipo/ | B31: Portafolio | C31: casas-bambino-logotipo | D31: 2019-12-31 | E31: error | F31: Revisar | G31: HTTP error en la revisión (volver a verificar) | I31: =INDEX('Mapa maestro'!$E$2:$E$970,MATCH($A31,'Mapa maestro'!$A$2:$A$970,0)) -> 301 | J31: =IF(INDEX('Mapa maestro'!$E$2:$E$970,MATCH($A31,'Mapa maestro'!$A$2:$A$970,0))="404","— (404 personalizada)",INDEX('Mapa maestro'!$L$2:$L$970,MATCH($A31,'Mapa maestro'!$A$2:$A$970,0))) -> https://continentalmedia.com.mx/proyectos/
A32: https://www.continentalmedia.com.mx/portfolio/casas-bambino-revista-2/ | B32: Portafolio | C32: casas-bambino-revista-2 | D32: 2019-12-31 | E32: 500 | F32: Revisar | G32: Posible duplicado de /casas-bambino-revista/; HTTP 500 en la revisión (volver a verificar) | H32: Revisar y consolidar con 301 | I32: =INDEX('Mapa maestro'!$E$2:$E$970,MATCH($A32,'Mapa maestro'!$A$2:$A$970,0)) -> 301 | J32: =IF(INDEX('Mapa maestro'!$E$2:$E$970,MATCH($A32,'Mapa maestro'!$A$2:$A$970,0))="404","— (404 personalizada)",INDEX('Mapa maestro'!$L$2:$L$970,MATCH($A32,'Mapa maestro'!$A$2:$A$970,0))) -> https://continentalmedia.com.mx/proyectos/
A33: https://www.continentalmedia.com.mx/portfolio/casas-bambino-revista/ | B33: Portafolio | C33: casas-bambino-revista | D33: 2019-12-31 | E33: 500 | F33: Revisar | G33: HTTP 500 en la revisión (volver a verificar) | I33: =INDEX('Mapa maestro'!$E$2:$E$970,MATCH($A33,'Mapa maestro'!$A$2:$A$970,0)) -> 301 | J33: =IF(INDEX('Mapa maestro'!$E$2:$E$970,MATCH($A33,'Mapa maestro'!$A$2:$A$970,0))="404","— (404 personalizada)",INDEX('Mapa maestro'!$L$2:$L$970,MATCH($A33,'Mapa maestro'!$A$2:$A$970,0))) -> https://continentalmedia.com.mx/proyectos/
A34: https://www.continentalmedia.com.mx/portfolio/certificado-the-barbers-spa/ | B34: Portafolio | C34: certificado-the-barbers-spa | D34: 2017-10-27 | E34: 500 | F34: Revisar | G34: HTTP 500 en la revisión (volver a verificar) | I34: =INDEX('Mapa maestro'!$E$2:$E$970,MATCH($A34,'Mapa maestro'!$A$2:$A$970,0)) -> 301 | J34: =IF(INDEX('Mapa maestro'!$E$2:$E$970,MATCH($A34,'Mapa maestro'!$A$2:$A$970,0))="404","— (404 personalizada)",INDEX('Mapa maestro'!$L$2:$L$970,MATCH($A34,'Mapa maestro'!$A$2:$A$970,0))) -> https://continentalmedia.com.mx/proyectos/
A35: https://www.continentalmedia.com.mx/portfolio/cerveza-sur/ | B35: Portafolio | C35: cerveza-sur | D35: 2019-12-31 | E35: 500 | F35: Revisar | G35: HTTP 500 en la revisión (volver a verificar) | I35: =INDEX('Mapa maestro'!$E$2:$E$970,MATCH($A35,'Mapa maestro'!$A$2:$A$970,0)) -> 301 | J35: =IF(INDEX('Mapa maestro'!$E$2:$E$970,MATCH($A35,'Mapa maestro'!$A$2:$A$970,0))="404","— (404 personalizada)",INDEX('Mapa maestro'!$L$2:$L$970,MATCH($A35,'Mapa maestro'!$A$2:$A$970,0))) -> https://continentalmedia.com.mx/proyectos/
A36: https://www.continentalmedia.com.mx/portfolio/cetis-15-videomarketing-conociendo-cetis-15/ | B36: Portafolio | C36: cetis-15-videomarketing-conociendo-cetis-15 | D36: 2020-04-13 | E36: 500 | F36: Revisar | G36: HTTP 500 en la revisión (volver a verificar) | I36: =INDEX('Mapa maestro'!$E$2:$E$970,MATCH($A36,'Mapa maestro'!$A$2:$A$970,0)) -> 301 | J36: =IF(INDEX('Mapa maestro'!$E$2:$E$970,MATCH($A36,'Mapa maestro'!$A$2:$A$970,0))="404","— (404 personalizada)",INDEX('Mapa maestro'!$L$2:$L$970,MATCH($A36,'Mapa maestro'!$A$2:$A$970,0))) -> https://continentalmedia.com.mx/proyectos/
A37: https://www.continentalmedia.com.mx/portfolio/chevrolet-diautos-videomarketing-mes-extraordinario/ | B37: Portafolio | C37: chevrolet-diautos-videomarketing-mes-extraordinario | D37: 2020-01-07 | E37: 500 | F37: Revisar | G37: HTTP 500 en la revisión (volver a verificar) | I37: =INDEX('Mapa maestro'!$E$2:$E$970,MATCH($A37,'Mapa maestro'!$A$2:$A$970,0)) -> 301 | J37: =IF(INDEX('Mapa maestro'!$E$2:$E$970,MATCH($A37,'Mapa maestro'!$A$2:$A$970,0))="404","— (404 personalizada)",INDEX('Mapa maestro'!$L$2:$L$970,MATCH($A37,'Mapa maestro'!$A$2:$A$970,0))) -> https://continentalmedia.com.mx/proyectos/
A38: https://www.continentalmedia.com.mx/portfolio/clies-logotipo/ | B38: Portafolio | C38: clies-logotipo | D38: 2019-12-31 | E38: 500 | F38: Revisar | G38: HTTP 500 en la revisión (volver a verificar) | I38: =INDEX('Mapa maestro'!$E$2:$E$970,MATCH($A38,'Mapa maestro'!$A$2:$A$970,0)) -> 301 | J38: =IF(INDEX('Mapa maestro'!$E$2:$E$970,MATCH($A38,'Mapa maestro'!$A$2:$A$970,0))="404","— (404 personalizada)",INDEX('Mapa maestro'!$L$2:$L$970,MATCH($A38,'Mapa maestro'!$A$2:$A$970,0))) -> https://continentalmedia.com.mx/proyectos/
A39: https://www.continentalmedia.com.mx/portfolio/colegio-bilingue-baltico/ | B39: Portafolio | C39: colegio-bilingue-baltico | D39: 2019-12-31 | E39: 500 | F39: Revisar | G39: HTTP 500 en la revisión (volver a verificar) | I39: =INDEX('Mapa maestro'!$E$2:$E$970,MATCH($A39,'Mapa maestro'!$A$2:$A$970,0)) -> 301 | J39: =IF(INDEX('Mapa maestro'!$E$2:$E$970,MATCH($A39,'Mapa maestro'!$A$2:$A$970,0))="404","— (404 personalizada)",INDEX('Mapa maestro'!$L$2:$L$970,MATCH($A39,'Mapa maestro'!$A$2:$A$970,0))) -> https://continentalmedia.com.mx/proyectos/
A40: https://www.continentalmedia.com.mx/portfolio/corporativo-villalobos/ | B40: Portafolio | C40: corporativo-villalobos | D40: 2019-12-31 | E40: 500 | F40: Revisar | G40: HTTP 500 en la revisión (volver a verificar) | I40: =INDEX('Mapa maestro'!$E$2:$E$970,MATCH($A40,'Mapa maestro'!$A$2:$A$970,0)) -> 301 | J40: =IF(INDEX('Mapa maestro'!$E$2:$E$970,MATCH($A40,'Mapa maestro'!$A$2:$A$970,0))="404","— (404 personalizada)",INDEX('Mapa maestro'!$L$2:$L$970,MATCH($A40,'Mapa maestro'!$A$2:$A$970,0))) -> https://continentalmedia.com.mx/proyectos/
A41: https://www.continentalmedia.com.mx/portfolio/criver-logotipo/ | B41: Portafolio | C41: criver-logotipo | D41: 2019-12-31 | E41: 500 | F41: Revisar | G41: HTTP 500 en la revisión (volver a verificar) | I41: =INDEX('Mapa maestro'!$E$2:$E$970,MATCH($A41,'Mapa maestro'!$A$2:$A$970,0)) -> 301 | J41: =IF(INDEX('Mapa maestro'!$E$2:$E$970,MATCH($A41,'Mapa maestro'!$A$2:$A$970,0))="404","— (404 personalizada)",INDEX('Mapa maestro'!$L$2:$L$970,MATCH($A41,'Mapa maestro'!$A$2:$A$970,0))) -> https://continentalmedia.com.mx/proyectos/
A42: https://www.continentalmedia.com.mx/portfolio/criver-triptico/ | B42: Portafolio | C42: criver-triptico | D42: 2019-10-22 | E42: 500 | F42: Revisar | G42: HTTP 500 en la revisión (volver a verificar) | I42: =INDEX('Mapa maestro'!$E$2:$E$970,MATCH($A42,'Mapa maestro'!$A$2:$A$970,0)) -> 301 | J42: =IF(INDEX('Mapa maestro'!$E$2:$E$970,MATCH($A42,'Mapa maestro'!$A$2:$A$970,0))="404","— (404 personalizada)",INDEX('Mapa maestro'!$L$2:$L$970,MATCH($A42,'Mapa maestro'!$A$2:$A$970,0))) -> https://continentalmedia.com.mx/proyectos/
A43: https://www.continentalmedia.com.mx/portfolio/delfines-del-puerto-hoja/ | B43: Portafolio | C43: delfines-del-puerto-hoja | D43: 2019-12-31 | E43: 500 | F43: Revisar | G43: HTTP 500 en la revisión (volver a verificar) | I43: =INDEX('Mapa maestro'!$E$2:$E$970,MATCH($A43,'Mapa maestro'!$A$2:$A$970,0)) -> 301 | J43: =IF(INDEX('Mapa maestro'!$E$2:$E$970,MATCH($A43,'Mapa maestro'!$A$2:$A$970,0))="404","— (404 personalizada)",INDEX('Mapa maestro'!$L$2:$L$970,MATCH($A43,'Mapa maestro'!$A$2:$A$970,0))) -> https://continentalmedia.com.mx/proyectos/
A44: https://www.continentalmedia.com.mx/portfolio/delfines-del-puerto-logotipo/ | B44: Portafolio | C44: delfines-del-puerto-logotipo | D44: 2019-12-31 | E44: 500 | F44: Revisar | G44: HTTP 500 en la revisión (volver a verificar) | I44: =INDEX('Mapa maestro'!$E$2:$E$970,MATCH($A44,'Mapa maestro'!$A$2:$A$970,0)) -> 301 | J44: =IF(INDEX('Mapa maestro'!$E$2:$E$970,MATCH($A44,'Mapa maestro'!$A$2:$A$970,0))="404","— (404 personalizada)",INDEX('Mapa maestro'!$L$2:$L$970,MATCH($A44,'Mapa maestro'!$A$2:$A$970,0))) -> https://continentalmedia.com.mx/proyectos/
... A49: https://www.continentalmedia.com.mx/portfolio/diseno-de-banner-davy-johns/ | B49: Portafolio | C49: diseno-de-banner-davy-johns | D49: 2026-07-09 | E49: 500 | F49: Revisar | G49: HTTP 500 en la revisión (volver a verificar) | I49: =INDEX('Mapa maestro'!$E$2:$E$970,MATCH($A49,'Mapa maestro'!$A$2:$A$970,0)) -> 301 | J49: =IF(INDEX('Mapa maestro'!$E$2:$E$970,MATCH($A49,'Mapa maestro'!$A$2:$A$970,0))="404","— (404 personalizada)",INDEX('Mapa maestro'!$L$2:$L$970,MATCH($A49,'Mapa maestro'!$A$2:$A$970,0))) -> https://continentalmedia.com.mx/proyectos/
A50: https://www.continentalmedia.com.mx/portfolio/diseno-de-banner-salas-club-maya-2/ | B50: Portafolio | C50: diseno-de-banner-salas-club-maya-2 | D50: 2025-03-10 | E50: 500 | F50: Revisar | G50: Posible duplicado de /diseno-de-banner-salas-club-maya/; HTTP 500 en la revisión (volver a verificar) | H50: Revisar y consolidar con 301 | I50: =INDEX('Mapa maestro'!$E$2:$E$970,MATCH($A50,'Mapa maestro'!$A$2:$A$970,0)) -> 301 | J50: =IF(INDEX('Mapa maestro'!$E$2:$E$970,MATCH($A50,'Mapa maestro'!$A$2:$A$970,0))="404","— (404 personalizada)",INDEX('Mapa maestro'!$L$2:$L$970,MATCH($A50,'Mapa maestro'!$A$2:$A$970,0))) -> https://continentalmedia.com.mx/proyectos/
A51: https://www.continentalmedia.com.mx/portfolio/diseno-de-banner-salas-club-maya/ | B51: Portafolio | C51: diseno-de-banner-salas-club-maya | D51: 2025-03-03 | E51: 500 | F51: Revisar | G51: HTTP 500 en la revisión (volver a verificar) | I51: =INDEX('Mapa maestro'!$E$2:$E$970,MATCH($A51,'Mapa maestro'!$A$2:$A$970,0)) -> 301 | J51: =IF(INDEX('Mapa maestro'!$E$2:$E$970,MATCH($A51,'Mapa maestro'!$A$2:$A$970,0))="404","— (404 personalizada)",INDEX('Mapa maestro'!$L$2:$L$970,MATCH($A51,'Mapa maestro'!$A$2:$A$970,0))) -> https://continentalmedia.com.mx/proyectos/
A52: https://www.continentalmedia.com.mx/portfolio/diseno-de-flyer-copa-racquet-2025/ | B52: Portafolio | C52: diseno-de-flyer-copa-racquet-2025 | D52: 2025-12-29 | E52: 500 | F52: Revisar | G52: HTTP 500 en la revisión (volver a verificar) | I52: =INDEX('Mapa maestro'!$E$2:$E$970,MATCH($A52,'Mapa maestro'!$A$2:$A$970,0)) -> 301 | J52: =IF(INDEX('Mapa maestro'!$E$2:$E$970,MATCH($A52,'Mapa maestro'!$A$2:$A$970,0))="404","— (404 personalizada)",INDEX('Mapa maestro'!$L$2:$L$970,MATCH($A52,'Mapa maestro'!$A$2:$A$970,0))) -> https://continentalmedia.com.mx/proyectos/
A53: https://www.continentalmedia.com.mx/portfolio/diseno-de-logo-sports-lounge-by-tgle/ | B53: Portafolio | C53: diseno-de-logo-sports-lounge-by-tgle | D53: 2025-10-24 | E53: 500 | F53: Revisar | G53: HTTP 500 en la revisión (volver a verificar) | I53: =INDEX('Mapa maestro'!$E$2:$E$970,MATCH($A53,'Mapa maestro'!$A$2:$A$970,0)) -> 301 | J53: =IF(INDEX('Mapa maestro'!$E$2:$E$970,MATCH($A53,'Mapa maestro'!$A$2:$A$970,0))="404","— (404 personalizada)",INDEX('Mapa maestro'!$L$2:$L$970,MATCH($A53,'Mapa maestro'!$A$2:$A$970,0))) -> https://continentalmedia.com.mx/proyectos/
A54: https://www.continentalmedia.com.mx/portfolio/diseno-de-logotipo-assistax/ | B54: Portafolio | C54: diseno-de-logotipo-assistax | D54: 2025-11-24 | E54: 500 | F54: Revisar | G54: HTTP 500 en la revisión (volver a verificar) | I54: =INDEX('Mapa maestro'!$E$2:$E$970,MATCH($A54,'Mapa maestro'!$A$2:$A$970,0)) -> 301 | J54: =IF(INDEX('Mapa maestro'!$E$2:$E$970,MATCH($A54,'Mapa maestro'!$A$2:$A$970,0))="404","— (404 personalizada)",INDEX('Mapa maestro'!$L$2:$L$970,MATCH($A54,'Mapa maestro'!$A$2:$A$970,0))) -> https://continentalmedia.com.mx/proyectos/
A55: https://www.continentalmedia.com.mx/portfolio/diseno-de-logotipo-roncomed/ | B55: Portafolio | C55: diseno-de-logotipo-roncomed | D55: 2025-03-18 | E55: 500 | F55: Revisar | G55: HTTP 500 en la revisión (volver a verificar) | I55: =INDEX('Mapa maestro'!$E$2:$E$970,MATCH($A55,'Mapa maestro'!$A$2:$A$970,0)) -> 301 | J55: =IF(INDEX('Mapa maestro'!$E$2:$E$970,MATCH($A55,'Mapa maestro'!$A$2:$A$970,0))="404","— (404 personalizada)",INDEX('Mapa maestro'!$L$2:$L$970,MATCH($A55,'Mapa maestro'!$A$2:$A$970,0))) -> https://continentalmedia.com.mx/proyectos/
A56: https://www.continentalmedia.com.mx/portfolio/diseno-de-logotipo-torres-metal-recycling/ | B56: Portafolio | C56: diseno-de-logotipo-torres-metal-recycling | D56: 2025-12-01 | E56: 500 | F56: Revisar | G56: HTTP 500 en la revisión (volver a verificar) | I56: =INDEX('Mapa maestro'!$E$2:$E$970,MATCH($A56,'Mapa maestro'!$A$2:$A$970,0)) -> 301 | J56: =IF(INDEX('Mapa maestro'!$E$2:$E$970,MATCH($A56,'Mapa maestro'!$A$2:$A$970,0))="404","— (404 personalizada)",INDEX('Mapa maestro'!$L$2:$L$970,MATCH($A56,'Mapa maestro'!$A$2:$A$970,0))) -> https://continentalmedia.com.mx/proyectos/
A57: https://www.continentalmedia.com.mx/portfolio/diseno-de-menu-casa-romita/ | B57: Portafolio | C57: diseno-de-menu-casa-romita | D57: 2025-03-10 | E57: 500 | F57: Revisar | G57: HTTP 500 en la revisión (volver a verificar) | I57: =INDEX('Mapa maestro'!$E$2:$E$970,MATCH($A57,'Mapa maestro'!$A$2:$A$970,0)) -> 301 | J57: =IF(INDEX('Mapa maestro'!$E$2:$E$970,MATCH($A57,'Mapa maestro'!$A$2:$A$970,0))="404","— (404 personalizada)",INDEX('Mapa maestro'!$L$2:$L$970,MATCH($A57,'Mapa maestro'!$A$2:$A$970,0))) -> https://continentalmedia.com.mx/proyectos/
A58: https://www.continentalmedia.com.mx/portfolio/diseno-de-menu-salas-club-maya/ | B58: Portafolio | C58: diseno-de-menu-salas-club-maya | D58: 2025-02-24 | E58: 500 | F58: Revisar | G58: HTTP 500 en la revisión (volver a verificar) | I58: =INDEX('Mapa maestro'!$E$2:$E$970,MATCH($A58,'Mapa maestro'!$A$2:$A$970,0)) -> 301 | J58: =IF(INDEX('Mapa maestro'!$E$2:$E$970,MATCH($A58,'Mapa maestro'!$A$2:$A$970,0))="404","— (404 personalizada)",INDEX('Mapa maestro'!$L$2:$L$970,MATCH($A58,'Mapa maestro'!$A$2:$A$970,0))) -> https://continentalmedia.com.mx/proyectos/
A59: https://www.continentalmedia.com.mx/portfolio/diseno-de-menu-sports-lounge-by-tgle/ | B59: Portafolio | C59: diseno-de-menu-sports-lounge-by-tgle | D59: 2025-10-31 | E59: 500 | F59: Revisar | G59: HTTP 500 en la revisión (volver a verificar) | I59: =INDEX('Mapa maestro'!$E$2:$E$970,MATCH($A59,'Mapa maestro'!$A$2:$A$970,0)) -> 301 | J59: =IF(INDEX('Mapa maestro'!$E$2:$E$970,MATCH($A59,'Mapa maestro'!$A$2:$A$970,0))="404","— (404 personalizada)",INDEX('Mapa maestro'!$L$2:$L$970,MATCH($A59,'Mapa maestro'!$A$2:$A$970,0))) -> https://continentalmedia.com.mx/proyectos/
A60: https://www.continentalmedia.com.mx/portfolio/diseno-de-personaje-torres-metal-recycling/ | B60: Portafolio | C60: diseno-de-personaje-torres-metal-recycling | D60: 2025-12-15 | E60: 500 | F60: Revisar | G60: HTTP 500 en la revisión (volver a verificar) | I60: =INDEX('Mapa maestro'!$E$2:$E$970,MATCH($A60,'Mapa maestro'!$A$2:$A$970,0)) -> 301 | J60: =IF(INDEX('Mapa maestro'!$E$2:$E$970,MATCH($A60,'Mapa maestro'!$A$2:$A$970,0))="404","— (404 personalizada)",INDEX('Mapa maestro'!$L$2:$L$970,MATCH($A60,'Mapa maestro'!$A$2:$A$970,0))) -> https://continentalmedia.com.mx/proyectos/
A61: https://www.continentalmedia.com.mx/portfolio/diseno-de-post-kino-ranch/ | B61: Portafolio | C61: diseno-de-post-kino-ranch | D61: 2020-11-13 | E61: 500 | F61: Revisar | G61: HTTP 500 en la revisión (volver a verificar) | I61: =INDEX('Mapa maestro'!$E$2:$E$970,MATCH($A61,'Mapa maestro'!$A$2:$A$970,0)) -> 301 | J61: =IF(INDEX('Mapa maestro'!$E$2:$E$970,MATCH($A61,'Mapa maestro'!$A$2:$A$970,0))="404","— (404 personalizada)",INDEX('Mapa maestro'!$L$2:$L$970,MATCH($A61,'Mapa maestro'!$A$2:$A$970,0))) -> https://continentalmedia.com.mx/proyectos/
A62: https://www.continentalmedia.com.mx/portfolio/diseno-de-post-roca-festival-latino/ | B62: Portafolio | C62: diseno-de-post-roca-festival-latino | D62: 2024-05-17 | E62: 500 | F62: Revisar | G62: HTTP 500 en la revisión (volver a verificar) | I62: =INDEX('Mapa maestro'!$E$2:$E$970,MATCH($A62,'Mapa maestro'!$A$2:$A$970,0)) -> 301 | J62: =IF(INDEX('Mapa maestro'!$E$2:$E$970,MATCH($A62,'Mapa maestro'!$A$2:$A$970,0))="404","— (404 personalizada)",INDEX('Mapa maestro'!$L$2:$L$970,MATCH($A62,'Mapa maestro'!$A$2:$A$970,0))) -> https://continentalmedia.com.mx/proyectos/
... A99: https://www.continentalmedia.com.mx/portfolio/honda-civic/ | B99: Portafolio | C99: honda-civic | D99: 2019-12-31 | E99: 500 | F99: Revisar | G99: HTTP 500 en la revisión (volver a verificar) | I99: =INDEX('Mapa maestro'!$E$2:$E$970,MATCH($A99,'Mapa maestro'!$A$2:$A$970,0)) -> 301 | J99: =IF(INDEX('Mapa maestro'!$E$2:$E$970,MATCH($A99,'Mapa maestro'!$A$2:$A$970,0))="404","— (404 personalizada)",INDEX('Mapa maestro'!$L$2:$L$970,MATCH($A99,'Mapa maestro'!$A$2:$A$970,0))) -> https://continentalmedia.com.mx/proyectos/
A100: https://www.continentalmedia.com.mx/portfolio/honda-veracruz-2/ | B100: Portafolio | C100: honda-veracruz-2 | D100: 2017-02-01 | E100: 500 | F100: Revisar | G100: Posible duplicado de /honda-veracruz/; HTTP 500 en la revisión (volver a verificar) | H100: Revisar y consolidar con 301 | I100: =INDEX('Mapa maestro'!$E$2:$E$970,MATCH($A100,'Mapa maestro'!$A$2:$A$970,0)) -> 301 | J100: =IF(INDEX('Mapa maestro'!$E$2:$E$970,MATCH($A100,'Mapa maestro'!$A$2:$A$970,0))="404","— (404 personalizada)",INDEX('Mapa maestro'!$L$2:$L$970,MATCH($A100,'Mapa maestro'!$A$2:$A$970,0))) -> https://continentalmedia.com.mx/proyectos/
A101: https://www.continentalmedia.com.mx/portfolio/honda-veracruz/ | B101: Portafolio | C101: honda-veracruz | D101: 2019-12-31 | E101: 500 | F101: Revisar | G101: HTTP 500 en la revisión (volver a verificar) | I101: =INDEX('Mapa maestro'!$E$2:$E$970,MATCH($A101,'Mapa maestro'!$A$2:$A$970,0)) -> 301 | J101: =IF(INDEX('Mapa maestro'!$E$2:$E$970,MATCH($A101,'Mapa maestro'!$A$2:$A$970,0))="404","— (404 personalizada)",INDEX('Mapa maestro'!$L$2:$L$970,MATCH($A101,'Mapa maestro'!$A$2:$A$970,0))) -> https://continentalmedia.com.mx/proyectos/
A102: https://www.continentalmedia.com.mx/portfolio/honda/ | B102: Portafolio | C102: honda | D102: 2019-12-31 | E102: 500 | F102: Revisar | G102: HTTP 500 en la revisión (volver a verificar) | I102: =INDEX('Mapa maestro'!$E$2:$E$970,MATCH($A102,'Mapa maestro'!$A$2:$A$970,0)) -> 301 | J102: =IF(INDEX('Mapa maestro'!$E$2:$E$970,MATCH($A102,'Mapa maestro'!$A$2:$A$970,0))="404","— (404 personalizada)",INDEX('Mapa maestro'!$L$2:$L$970,MATCH($A102,'Mapa maestro'!$A$2:$A$970,0))) -> https://continentalmedia.com.mx/proyectos/
A103: https://www.continentalmedia.com.mx/portfolio/hospital-millenium-cartel/ | B103: Portafolio | C103: hospital-millenium-cartel | D103: 2020-08-18 | E103: 500 | F103: Revisar | G103: HTTP 500 en la revisión (volver a verificar) | I103: =INDEX('Mapa maestro'!$E$2:$E$970,MATCH($A103,'Mapa maestro'!$A$2:$A$970,0)) -> 301 | J103: =IF(INDEX('Mapa maestro'!$E$2:$E$970,MATCH($A103,'Mapa maestro'!$A$2:$A$970,0))="404","— (404 personalizada)",INDEX('Mapa maestro'!$L$2:$L$970,MATCH($A103,'Mapa maestro'!$A$2:$A$970,0))) -> https://continentalmedia.com.mx/proyectos/
A104: https://www.continentalmedia.com.mx/portfolio/hospital-millenium-videomarketing-atencion-medica/ | B104: Portafolio | C104: hospital-millenium-videomarketing-atencion-medica | D104: 2020-04-06 | E104: 500 | F104: Revisar | G104: HTTP 500 en la revisión (volver a verificar) | I104: =INDEX('Mapa maestro'!$E$2:$E$970,MATCH($A104,'Mapa maestro'!$A$2:$A$970,0)) -> 301 | J104: =IF(INDEX('Mapa maestro'!$E$2:$E$970,MATCH($A104,'Mapa maestro'!$A$2:$A$970,0))="404","— (404 personalizada)",INDEX('Mapa maestro'!$L$2:$L$970,MATCH($A104,'Mapa maestro'!$A$2:$A$970,0))) -> https://continentalmedia.com.mx/proyectos/
